Workbook
Name AsOf: Settings!$B$16
Name CampList: Campaign_Master!$A$2:$A$33
Name CampTypes: Campaign_Master!$B$2:$B$33
Name DaysNew: Settings!$B$22
Name DaysOld: Settings!$B$21
Name fAdSet: Fact_Data!$D$2:$D$3642
Name fCalls: Fact_Data!$S$2:$S$3642
Name fCampaign: Fact_Data!$C$2:$C$3642
Name fClicks: Fact_Data!$W$2:$W$3642
Name fConn: Fact_Data!$T$2:$T$3642
Name fContacted: Fact_Data!$Q$2:$Q$3642
Name fImpr: Fact_Data!$V$2:$V$3642
Name fLeads: Fact_Data!$O$2:$O$3642
Name fLost: Fact_Data!$R$2:$R$3642
Name fMeta: Fact_Data!$X$2:$X$3642
Name fQual: Fact_Data!$P$2:$P$3642
Name fRT: Fact_Data!$A$2:$A$3642
Name fSpend: Fact_Data!$U$2:$U$3642
Name fStatus: Fact_Data!$G$2:$G$3642
Name fType: Fact_Data!$B$2:$B$3642
Name ldCamp: Lead_Data!$I$2:$I$3628
Name ldDate: Lead_Data!$C$2:$C$3628
Name ldQual: Lead_Data!$G$2:$G$3628
Name ldStatus: Lead_Data!$F$2:$F$3628
Name ldType: Lead_Data!$H$2:$H$3628
Name LFLStart: Settings!$B$17
Name QualityStatuses: Settings!$A$4:$A$10
Name Slicer_Campaign: #N/A
Name Slicer_Campaign_Type: #N/A
Name Slicer_Lead_Month: #N/A
Name Slicer_Lead_Status: #N/A
Name Slicer_Lead_Week: #N/A
Name WinEnd: Settings!$B$15
Name WinStart: Settings!$B$14
Name fCLeads: Fact_Data!$Y$2:$Y$3642
Name fCQual: Fact_Data!$Z$2:$Z$3642
Name MetaCamps: Meta_Campaigns!$A$2:$A$29
Name Slicer_Campaign: #N/A
Name Slicer_Campaign_Type: #N/A
Name Slicer_Lead_Month: #N/A
Name Slicer_Lead_Status: #N/A
Name Slicer_Lead_Week: #N/A

Sheet Master Dashboard
B1: NATUF | Lead Quality: Old Campaigns vs New Campaigns - MASTER DASHBOARD
B2: 01-Oct-2026 to 31-Oct-2026 | CRM status as of 31-Oct-2026 | Quality Lead = Won, Token Received, Qualified, Meeting Scheduled, Meeting Conducted, Follow-Up, Details Shared | Old/New set on the Campaign_Master tab (New = Oct26 campaigns)
B4: ="QUALITY: "&TEXT(D13,"0.0%")&" of New-campaign leads are Quality leads vs "&TEXT(C13,"0.0%")&" for Old ("&TEXT((D13-C13)*100,"+0.0;-0.0;0.0")&" pp). COST: INR "&TEXT(D14,"#,##0")&" per Quality Lead for New vs INR "&TEXT(C14,"#,##0")&" for Old (cost metrics use only campaigns with Meta spend data). NOTE: New campaigns (with Meta spend data) went live "&TEXT(LFLStart,"dd-mmm")&" ("&DaysNew&" days in market vs "&DaysOld&" for Old); average lead age is "&TEXT(AsOf-AVERAGEIFS(ldDate,ldType,"New"),"0.0")&" days for New vs "&TEXT(AsOf-AVERAGEIFS(ldDate,ldType,"Old"),"0.0")&" for Old, so New statuses are still maturing." -> QUALITY: 15.0% of New-campaign leads are Quality leads vs 16.1% for Old (-1.1 pp). COST: INR 2,215 per Quality Lead for New vs INR 6,288 for Old (cost metrics use only campaigns with Meta spend data). NOTE: New campaigns (with Meta spend data) went live 08-Oct (24 days in market vs 31 for Old); average lead age is 10.5 days for New vs 17.4 for Old, so New statuses are still maturing.
B6: 1. OLD vs NEW - AT A GLANCE - NATUF
B7: Metric | C7: Old campaigns | D7: New campaigns | E7: New vs Old
B8: Ad spend (INR) | C8: =SUMIFS(fSpend,fType,"Old") -> 1301546.3 | D8: =SUMIFS(fSpend,fType,"New") -> 345559.94 | E8: =IFERROR(D8/C8-1,"-") -> -0.73450047
B9: Leads in CRM | C9: =SUMIFS(fLeads,fType,"Old") -> 1285 | D9: =SUMIFS(fLeads,fType,"New") -> 2342 | E9: =IFERROR(D9/C9-1,"-") -> 0.82256809
B10: New Leads (untouched - status = New Lead) | C10: =SUMIFS(fLeads,fType,"Old",fStatus,"New Lead") -> 227 | D10: =SUMIFS(fLeads,fType,"New",fStatus,"New Lead") -> 352 | E10: =IFERROR(D10/C10-1,"-") -> 0.55066079
B11: Cost per lead (INR) [campaigns with spend data] | C11: =IFERROR(C8/SUMIFS(fCLeads,fType,"Old"),0) -> 1012.8765 | D11: =IFERROR(D8/SUMIFS(fCLeads,fType,"New"),0) -> 358.0932 | E11: =IFERROR(D11/C11-1,"-") -> -0.64645917
B12: QUALITY LEADS | C12: =SUMIFS(fQual,fType,"Old") -> 207 | D12: =SUMIFS(fQual,fType,"New") -> 351 | E12: =IFERROR(D12/C12-1,"-") -> 0.69565217
B13: QUALITY % (quality leads / all leads) | C13: =IFERROR(C12/C9,0) -> 0.16108949 | D13: =IFERROR(D12/D9,0) -> 0.1498719 | E13: =IFERROR((D13-C13)*100,"-") -> -1.121759
B14: COST PER QUALITY LEAD (INR) [campaigns with spend data] | C14: =IFERROR(C8/SUMIFS(fCQual,fType,"Old"),0) -> 6287.6633 | D14: =IFERROR(D8/SUMIFS(fCQual,fType,"New"),0) -> 2215.1278 | E14: =IFERROR(D14/C14-1,"-") -> -0.64770254
B15: Green = New is better, red = New is worse. Rates in percentage points (pp), volumes and costs in % change. Cost per lead / per quality lead divide spend by the leads of campaigns that have Meta spend data (the EBG - In House campaigns have 1,377 CRM leads but no spend in the exports, so they are excluded from cost ratios only).
B18: 2. QUALITY PARAMETERS - Old vs New (count and % of that group's leads)
B19: Quality parameter (CRM status) | C19: Old - Quality Count | D19: Old - Quality % | E19: New - Quality Count | F19: New - Quality % | G19: New vs Old (pp)
B20: =Settings!$A$4 -> Won | C20: =SUMIFS(fLeads,fType,"Old",fStatus,$B20) -> 0 | D20: =IFERROR(C20/C$9,0) -> 0 | E20: =SUMIFS(fLeads,fType,"New",fStatus,$B20) -> 0 | F20: =IFERROR(E20/D$9,0) -> 0 | G20: =(F20-D20)*100 -> 0
B21: =Settings!$A$5 -> Token Received | C21: =SUMIFS(fLeads,fType,"Old",fStatus,$B21) -> 0 | D21: =IFERROR(C21/C$9,0) -> 0 | E21: =SUMIFS(fLeads,fType,"New",fStatus,$B21) -> 0 | F21: =IFERROR(E21/D$9,0) -> 0 | G21: =(F21-D21)*100 -> 0
B22: =Settings!$A$6 -> Qualified | C22: =SUMIFS(fLeads,fType,"Old",fStatus,$B22) -> 14 | D22: =IFERROR(C22/C$9,0) -> 0.010894942 | E22: =SUMIFS(fLeads,fType,"New",fStatus,$B22) -> 20 | F22: =IFERROR(E22/D$9,0) -> 0.0085397096 | G22: =(F22-D22)*100 -> -0.2355232
B23: =Settings!$A$7 -> Meeting Scheduled | C23: =SUMIFS(fLeads,fType,"Old",fStatus,$B23) -> 18 | D23: =IFERROR(C23/C$9,0) -> 0.014007782 | E23: =SUMIFS(fLeads,fType,"New",fStatus,$B23) -> 14 | F23: =IFERROR(E23/D$9,0) -> 0.0059777968 | G23: =(F23-D23)*100 -> -0.80299853
B24: =Settings!$A$8 -> Meeting Conducted | C24: =SUMIFS(fLeads,fType,"Old",fStatus,$B24) -> 36 | D24: =IFERROR(C24/C$9,0) -> 0.028015564 | E24: =SUMIFS(fLeads,fType,"New",fStatus,$B24) -> 15 | F24: =IFERROR(E24/D$9,0) -> 0.0064047822 | G24: =(F24-D24)*100 -> -2.1610782
B25: =Settings!$A$9 -> Follow-Up | C25: =SUMIFS(fLeads,fType,"Old",fStatus,$B25) -> 19 | D25: =IFERROR(C25/C$9,0) -> 0.014785992 | E25: =SUMIFS(fLeads,fType,"New",fStatus,$B25) -> 17 | F25: =IFERROR(E25/D$9,0) -> 0.0072587532 | G25: =(F25-D25)*100 -> -0.7527239
B26: =Settings!$A$10 -> Details Shared | C26: =SUMIFS(fLeads,fType,"Old",fStatus,$B26) -> 120 | D26: =IFERROR(C26/C$9,0) -> 0.093385214 | E26: =SUMIFS(fLeads,fType,"New",fStatus,$B26) -> 285 | F26: =IFERROR(E26/D$9,0) -> 0.12169086 | G26: =(F26-D26)*100 -> 2.8305649
B27: TOTAL QUALITY LEADS | C27: =SUM(C20:C26) -> 207 | D27: =IFERROR(C27/C$9,0) -> 0.16108949 | E27: =SUM(E20:E26) -> 351 | F27: =IFERROR(E27/D$9,0) -> 0.1498719 | G27: =(F27-D27)*100 -> -1.121759
B32: 3. CAMPAIGN WISE - quality and cost (Old campaigns first, then New; sorted by spend)
B33: Campaign Name | C33: Campaign Type (Old / New) | D33: Ad Spend (INR) | E33: Leads | F33: Quality Count | G33: Quality % | H33: Cost per Lead (INR) | I33: Cost per Quality Lead (INR) | J33: =Settings!$A$4 -> Won | K33: =Settings!$A$5 -> Token Received | L33: =Settings!$A$6 -> Qualified | M33: =Settings!$A$7 -> Meeting Scheduled | N33: =Settings!$A$8 -> Meeting Conducted | O33: =Settings!$A$9 -> Follow-Up | P33: =Settings!$A$10 -> Details Shared
B34: E_Karan_Natuf_All_07072026 | C34: =IFERROR(INDEX(CampTypes,MATCH($B34,CampList,0)),"Unattributed") -> Old | D34: =IF(COUNTIF(MetaCamps,$B34)=0,"n/a",SUMIFS(fSpend,fCampaign,$B34)) -> 277596.99 | E34: =SUMIFS(fLeads,fCampaign,$B34) -> 229 | F34: =SUMIFS(fQual,fCampaign,$B34) -> 21 | G34: =IFERROR(F34/E34,0) -> 0.091703057 | H34: =IF(OR(E34=0,COUNTIF(MetaCamps,$B34)=0),"-",D34/E34) -> 1212.2139 | I34: =IF(OR(F34=0,COUNTIF(MetaCamps,$B34)=0),"-",D34/F34) -> 13218.904 | J34: =SUMIFS(fLeads,fCampaign,$B34,fStatus,J$33) -> 0 | K34: =SUMIFS(fLeads,fCampaign,$B34,fStatus,K$33) -> 0 | L34: =SUMIFS(fLeads,fCampaign,$B34,fStatus,L$33) -> 0 | M34: =SUMIFS(fLeads,fCampaign,$B34,fStatus,M$33) -> 3 | N34: =SUMIFS(fLeads,fCampaign,$B34,fStatus,N$33) -> 2 | O34: =SUMIFS(fLeads,fCampaign,$B34,fStatus,O$33) -> 3 | P34: =SUMIFS(fLeads,fCampaign,$B34,fStatus,P$33) -> 13
B35: E_Natuf_Generic_13082026 | C35: =IFERROR(INDEX(CampTypes,MATCH($B35,CampList,0)),"Unattributed") -> Old | D35: =IF(COUNTIF(MetaCamps,$B35)=0,"n/a",SUMIFS(fSpend,fCampaign,$B35)) -> 233578.47 | E35: =SUMIFS(fLeads,fCampaign,$B35) -> 210 | F35: =SUMIFS(fQual,fCampaign,$B35) -> 40 | G35: =IFERROR(F35/E35,0) -> 0.19047619 | H35: =IF(OR(E35=0,COUNTIF(MetaCamps,$B35)=0),"-",D35/E35) -> 1112.2784 | I35: =IF(OR(F35=0,COUNTIF(MetaCamps,$B35)=0),"-",D35/F35) -> 5839.4618 | J35: =SUMIFS(fLeads,fCampaign,$B35,fStatus,J$33) -> 0 | K35: =SUMIFS(fLeads,fCampaign,$B35,fStatus,K$33) -> 0 | L35: =SUMIFS(fLeads,fCampaign,$B35,fStatus,L$33) -> 1 | M35: =SUMIFS(fLeads,fCampaign,$B35,fStatus,M$33) -> 2 | N35: =SUMIFS(fLeads,fCampaign,$B35,fStatus,N$33) -> 14 | O35: =SUMIFS(fLeads,fCampaign,$B35,fStatus,O$33) -> 3 | P35: =SUMIFS(fLeads,fCampaign,$B35,fStatus,P$33) -> 20
B36: E_Suresh_Natuf_Kiosk_07072026 | C36: =IFERROR(INDEX(CampTypes,MATCH($B36,CampList,0)),"Unattributed") -> Old | D36: =IF(COUNTIF(MetaCamps,$B36)=0,"n/a",SUMIFS(fSpend,fCampaign,$B36)) -> 232416.42 | E36: =SUMIFS(fLeads,fCampaign,$B36) -> 313 | F36: =SUMIFS(fQual,fCampaign,$B36) -> 68 | G36: =IFERROR(F36/E36,0) -> 0.2172524 | H36: =IF(OR(E36=0,COUNTIF(MetaCamps,$B36)=0),"-",D36/E36) -> 742.54447 | I36: =IF(OR(F36=0,COUNTIF(MetaCamps,$B36)=0),"-",D36/F36) -> 3417.8885 | J36: =SUMIFS(fLeads,fCampaign,$B36,fStatus,J$33) -> 0 | K36: =SUMIFS(fLeads,fCampaign,$B36,fStatus,K$33) -> 0 | L36: =SUMIFS(fLeads,fCampaign,$B36,fStatus,L$33) -> 6 | M36: =SUMIFS(fLeads,fCampaign,$B36,fStatus,M$33) -> 9 | N36: =SUMIFS(fLeads,fCampaign,$B36,fStatus,N$33) -> 8 | O36: =SUMIFS(fLeads,fCampaign,$B36,fStatus,O$33) -> 4 | P36: =SUMIFS(fLeads,fCampaign,$B36,fStatus,P$33) -> 41
B37: natuf_Kiosk_14072026_Hindi | C37: =IFERROR(INDEX(CampTypes,MATCH($B37,CampList,0)),"Unattributed") -> Old | D37: =IF(COUNTIF(MetaCamps,$B37)=0,"n/a",SUMIFS(fSpend,fCampaign,$B37)) -> 180149.88 | E37: =SUMIFS(fLeads,fCampaign,$B37) -> 382 | F37: =SUMIFS(fQual,fCampaign,$B37) -> 42 | G37: =IFERROR(F37/E37,0) -> 0.10994764 | H37: =IF(OR(E37=0,COUNTIF(MetaCamps,$B37)=0),"-",D37/E37) -> 471.59654 | I37: =IF(OR(F37=0,COUNTIF(MetaCamps,$B37)=0),"-",D37/F37) -> 4289.2829 | J37: =SUMIFS(fLeads,fCampaign,$B37,fStatus,J$33) -> 0 | K37: =SUMIFS(fLeads,fCampaign,$B37,fStatus,K$33) -> 0 | L37: =SUMIFS(fLeads,fCampaign,$B37,fStatus,L$33) -> 3 | M37: =SUMIFS(fLeads,fCampaign,$B37,fStatus,M$33) -> 2 | N37: =SUMIFS(fLeads,fCampaign,$B37,fStatus,N$33) -> 4 | O37: =SUMIFS(fLeads,fCampaign,$B37,fStatus,O$33) -> 8 | P37: =SUMIFS(fLeads,fCampaign,$B37,fStatus,P$33) -> 25
B38: E_Selva_Natuf_All_07072026 | C38: =IFERROR(INDEX(CampTypes,MATCH($B38,CampList,0)),"Unattributed") -> Old | D38: =IF(COUNTIF(MetaCamps,$B38)=0,"n/a",SUMIFS(fSpend,fCampaign,$B38)) -> 80349.25 | E38: =SUMIFS(fLeads,fCampaign,$B38) -> 46 | F38: =SUMIFS(fQual,fCampaign,$B38) -> 14 | G38: =IFERROR(F38/E38,0) -> 0.30434783 | H38: =IF(OR(E38=0,COUNTIF(MetaCamps,$B38)=0),"-",D38/E38) -> 1746.7228 | I38: =IF(OR(F38=0,COUNTIF(MetaCamps,$B38)=0),"-",D38/F38) -> 5739.2321 | J38: =SUMIFS(fLeads,fCampaign,$B38,fStatus,J$33) -> 0 | K38: =SUMIFS(fLeads,fCampaign,$B38,fStatus,K$33) -> 0 | L38: =SUMIFS(fLeads,fCampaign,$B38,fStatus,L$33) -> 2 | M38: =SUMIFS(fLeads,fCampaign,$B38,fStatus,M$33) -> 1 | N38: =SUMIFS(fLeads,fCampaign,$B38,fStatus,N$33) -> 3 | O38: =SUMIFS(fLeads,fCampaign,$B38,fStatus,O$33) -> 1 | P38: =SUMIFS(fLeads,fCampaign,$B38,fStatus,P$33) -> 7
B39: E_Natuf_MF_05092026 | C39: =IFERROR(INDEX(CampTypes,MATCH($B39,CampList,0)),"Unattributed") -> Old | D39: =IF(COUNTIF(MetaCamps,$B39)=0,"n/a",SUMIFS(fSpend,fCampaign,$B39)) -> 79772.24 | E39: =SUMIFS(fLeads,fCampaign,$B39) -> 26 | F39: =SUMIFS(fQual,fCampaign,$B39) -> 1 | G39: =IFERROR(F39/E39,0) -> 0.038461538 | H39: =IF(OR(E39=0,COUNTIF(MetaCamps,$B39)=0),"-",D39/E39) -> 3068.1631 | I39: =IF(OR(F39=0,COUNTIF(MetaCamps,$B39)=0),"-",D39/F39) -> 79772.24 | J39: =SUMIFS(fLeads,fCampaign,$B39,fStatus,J$33) -> 0 | K39: =SUMIFS(fLeads,fCampaign,$B39,fStatus,K$33) -> 0 | L39: =SUMIFS(fLeads,fCampaign,$B39,fStatus,L$33) -> 0 | M39: =SUMIFS(fLeads,fCampaign,$B39,fStatus,M$33) -> 0 | N39: =SUMIFS(fLeads,fCampaign,$B39,fStatus,N$33) -> 0 | O39: =SUMIFS(fLeads,fCampaign,$B39,fStatus,O$33) -> 0 | P39: =SUMIFS(fLeads,fCampaign,$B39,fStatus,P$33) -> 1
B40: E_Natuf_Generic_09092026 | C40: =IFERROR(INDEX(CampTypes,MATCH($B40,CampList,0)),"Unattributed") -> Old | D40: =IF(COUNTIF(MetaCamps,$B40)=0,"n/a",SUMIFS(fSpend,fCampaign,$B40)) -> 71194.81 | E40: =SUMIFS(fLeads,fCampaign,$B40) -> 8 | F40: =SUMIFS(fQual,fCampaign,$B40) -> 2 | G40: =IFERROR(F40/E40,0) -> 0.25 | H40: =IF(OR(E40=0,COUNTIF(MetaCamps,$B40)=0),"-",D40/E40) -> 8899.3512 | I40: =IF(OR(F40=0,COUNTIF(MetaCamps,$B40)=0),"-",D40/F40) -> 35597.405 | J40: =SUMIFS(fLeads,fCampaign,$B40,fStatus,J$33) -> 0 | K40: =SUMIFS(fLeads,fCampaign,$B40,fStatus,K$33) -> 0 | L40: =SUMIFS(fLeads,fCampaign,$B40,fStatus,L$33) -> 0 | M40: =SUMIFS(fLeads,fCampaign,$B40,fStatus,M$33) -> 0 | N40: =SUMIFS(fLeads,fCampaign,$B40,fStatus,N$33) -> 1 | O40: =SUMIFS(fLeads,fCampaign,$B40,fStatus,O$33) -> 0 | P40: =SUMIFS(fLeads,fCampaign,$B40,fStatus,P$33) -> 1
B41: E_Karan_Natuf_Kiosk_07072026 | C41: =IFERROR(INDEX(CampTypes,MATCH($B41,CampList,0)),"Unattributed") -> Old | D41: =IF(COUNTIF(MetaCamps,$B41)=0,"n/a",SUMIFS(fSpend,fCampaign,$B41)) -> 54540.16 | E41: =SUMIFS(fLeads,fCampaign,$B41) -> 24 | F41: =SUMIFS(fQual,fCampaign,$B41) -> 6 | G41: =IFERROR(F41/E41,0) -> 0.25 | H41: =IF(OR(E41=0,COUNTIF(MetaCamps,$B41)=0),"-",D41/E41) -> 2272.5067 | I41: =IF(OR(F41=0,COUNTIF(MetaCamps,$B41)=0),"-",D41/F41) -> 9090.0267 | J41: =SUMIFS(fLeads,fCampaign,$B41,fStatus,J$33) -> 0 | K41: =SUMIFS(fLeads,fCampaign,$B41,fStatus,K$33) -> 0 | L41: =SUMIFS(fLeads,fCampaign,$B41,fStatus,L$33) -> 1 | M41: =SUMIFS(fLeads,fCampaign,$B41,fStatus,M$33) -> 0 | N41: =SUMIFS(fLeads,fCampaign,$B41,fStatus,N$33) -> 3 | O41: =SUMIFS(fLeads,fCampaign,$B41,fStatus,O$33) -> 0 | P41: =SUMIFS(fLeads,fCampaign,$B41,fStatus,P$33) -> 2
B42: E_Natuf_Foco_10092026 | C42: =IFERROR(INDEX(CampTypes,MATCH($B42,CampList,0)),"Unattributed") -> Old | D42: =IF(COUNTIF(MetaCamps,$B42)=0,"n/a",SUMIFS(fSpend,fCampaign,$B42)) -> 46413.52 | E42: =SUMIFS(fLeads,fCampaign,$B42) -> 32 | F42: =SUMIFS(fQual,fCampaign,$B42) -> 7 | G42: =IFERROR(F42/E42,0) -> 0.21875 | H42: =IF(OR(E42=0,COUNTIF(MetaCamps,$B42)=0),"-",D42/E42) -> 1450.4225 | I42: =IF(OR(F42=0,COUNTIF(MetaCamps,$B42)=0),"-",D42/F42) -> 6630.5029 | J42: =SUMIFS(fLeads,fCampaign,$B42,fStatus,J$33) -> 0 | K42: =SUMIFS(fLeads,fCampaign,$B42,fStatus,K$33) -> 0 | L42: =SUMIFS(fLeads,fCampaign,$B42,fStatus,L$33) -> 0 | M42: =SUMIFS(fLeads,fCampaign,$B42,fStatus,M$33) -> 1 | N42: =SUMIFS(fLeads,fCampaign,$B42,fStatus,N$33) -> 1 | O42: =SUMIFS(fLeads,fCampaign,$B42,fStatus,O$33) -> 0 | P42: =SUMIFS(fLeads,fCampaign,$B42,fStatus,P$33) -> 5
B43: E_Natuf_Amazon_29092026 | C43: =IFERROR(INDEX(CampTypes,MATCH($B43,CampList,0)),"Unattributed") -> Old | D43: =IF(COUNTIF(MetaCamps,$B43)=0,"n/a",SUMIFS(fSpend,fCampaign,$B43)) -> 39121.71 | E43: =SUMIFS(fLeads,fCampaign,$B43) -> 15 | F43: =SUMIFS(fQual,fCampaign,$B43) -> 6 | G43: =IFERROR(F43/E43,0) -> 0.4 | H43: =IF(OR(E43=0,COUNTIF(MetaCamps,$B43)=0),"-",D43/E43) -> 2608.114 | I43: =IF(OR(F43=0,COUNTIF(MetaCamps,$B43)=0),"-",D43/F43) -> 6520.285 | J43: =SUMIFS(fLeads,fCampaign,$B43,fStatus,J$33) -> 0 | K43: =SUMIFS(fLeads,fCampaign,$B43,fStatus,K$33) -> 0 | L43: =SUMIFS(fLeads,fCampaign,$B43,fStatus,L$33) -> 1 | M43: =SUMIFS(fLeads,fCampaign,$B43,fStatus,M$33) -> 0 | N43: =SUMIFS(fLeads,fCampaign,$B43,fStatus,N$33) -> 0 | O43: =SUMIFS(fLeads,fCampaign,$B43,fStatus,O$33) -> 0 | P43: =SUMIFS(fLeads,fCampaign,$B43,fStatus,P$33) -> 5
B44: E_Natuf_Web_23092026 | C44: =IFERROR(INDEX(CampTypes,MATCH($B44,CampList,0)),"Unattributed") -> Old | D44: =IF(COUNTIF(MetaCamps,$B44)=0,"n/a",SUMIFS(fSpend,fCampaign,$B44)) -> 6412.86 | E44: =SUMIFS(fLeads,fCampaign,$B44) -> 0 | F44: =SUMIFS(fQual,fCampaign,$B44) -> 0 | G44: =IFERROR(F44/E44,0) -> 0 | H44: =IF(OR(E44=0,COUNTIF(MetaCamps,$B44)=0),"-",D44/E44) -> - | I44: =IF(OR(F44=0,COUNTIF(MetaCamps,$B44)=0),"-",D44/F44) -> - | J44: =SUMIFS(fLeads,fCampaign,$B44,fStatus,J$33) -> 0 | K44: =SUMIFS(fLeads,fCampaign,$B44,fStatus,K$33) -> 0 | L44: =SUMIFS(fLeads,fCampaign,$B44,fStatus,L$33) -> 0 | M44: =SUMIFS(fLeads,fCampaign,$B44,fStatus,M$33) -> 0 | N44: =SUMIFS(fLeads,fCampaign,$B44,fStatus,N$33) -> 0 | O44: =SUMIFS(fLeads,fCampaign,$B44,fStatus,O$33) -> 0 | P44: =SUMIFS(fLeads,fCampaign,$B44,fStatus,P$33) -> 0
B45: ABO | Natuf | Leads | Unit Franchise | India | Oct26 | V1 | C45: =IFERROR(INDEX(CampTypes,MATCH($B45,CampList,0)),"Unattributed") -> New | D45: =IF(COUNTIF(MetaCamps,$B45)=0,"n/a",SUMIFS(fSpend,fCampaign,$B45)) -> 264151.59 | E45: =SUMIFS(fLeads,fCampaign,$B45) -> 817 | F45: =SUMIFS(fQual,fCampaign,$B45) -> 149 | G45: =IFERROR(F45/E45,0) -> 0.18237454 | H45: =IF(OR(E45=0,COUNTIF(MetaCamps,$B45)=0),"-",D45/E45) -> 323.31896 | I45: =IF(OR(F45=0,COUNTIF(MetaCamps,$B45)=0),"-",D45/F45) -> 1772.8295 | J45: =SUMIFS(fLeads,fCampaign,$B45,fStatus,J$33) -> 0 | K45: =SUMIFS(fLeads,fCampaign,$B45,fStatus,K$33) -> 0 | L45: =SUMIFS(fLeads,fCampaign,$B45,fStatus,L$33) -> 14 | M45: =SUMIFS(fLeads,fCampaign,$B45,fStatus,M$33) -> 4 | N45: =SUMIFS(fLeads,fCampaign,$B45,fStatus,N$33) -> 5 | O45: =SUMIFS(fLeads,fCampaign,$B45,fStatus,O$33) -> 2 | P45: =SUMIFS(fLeads,fCampaign,$B45,fStatus,P$33) -> 124
... B50: EBG - In House | ABO | Natuf | Leads | Master Franchise | India | Oct26 | V1 | C50: =IFERROR(INDEX(CampTypes,MATCH($B50,CampList,0)),"Unattributed") -> New | D50: =IF(COUNTIF(MetaCamps,$B50)=0,"n/a",SUMIFS(fSpend,fCampaign,$B50)) -> n/a | E50: =SUMIFS(fLeads,fCampaign,$B50) -> 42 | F50: =SUMIFS(fQual,fCampaign,$B50) -> 0 | G50: =IFERROR(F50/E50,0) -> 0 | H50: =IF(OR(E50=0,COUNTIF(MetaCamps,$B50)=0),"-",D50/E50) -> - | I50: =IF(OR(F50=0,COUNTIF(MetaCamps,$B50)=0),"-",D50/F50) -> - | J50: =SUMIFS(fLeads,fCampaign,$B50,fStatus,J$33) -> 0 | K50: =SUMIFS(fLeads,fCampaign,$B50,fStatus,K$33) -> 0 | L50: =SUMIFS(fLeads,fCampaign,$B50,fStatus,L$33) -> 0 | M50: =SUMIFS(fLeads,fCampaign,$B50,fStatus,M$33) -> 0 | N50: =SUMIFS(fLeads,fCampaign,$B50,fStatus,N$33) -> 0 | O50: =SUMIFS(fLeads,fCampaign,$B50,fStatus,O$33) -> 0 | P50: =SUMIFS(fLeads,fCampaign,$B50,fStatus,P$33) -> 0
B52: TOTAL - OLD CAMPAIGNS | D52: =SUMIFS(fSpend,fType,"Old") -> 1301546.3 | E52: =SUMIFS(fLeads,fType,"Old") -> 1285 | F52: =SUMIFS(fQual,fType,"Old") -> 207 | G52: =IFERROR(F52/E52,0) -> 0.16108949 | H52: =IF(SUMIFS(fCLeads,fType,"Old")=0,"-",D52/SUMIFS(fCLeads,fType,"Old")) -> 1012.8765 | I52: =IF(SUMIFS(fCQual,fType,"Old")=0,"-",D52/SUMIFS(fCQual,fType,"Old")) -> 6287.6633 | J52: =SUMIFS(fLeads,fType,"Old",fStatus,J$33) -> 0 | K52: =SUMIFS(fLeads,fType,"Old",fStatus,K$33) -> 0 | L52: =SUMIFS(fLeads,fType,"Old",fStatus,L$33) -> 14 | M52: =SUMIFS(fLeads,fType,"Old",fStatus,M$33) -> 18 | N52: =SUMIFS(fLeads,fType,"Old",fStatus,N$33) -> 36 | O52: =SUMIFS(fLeads,fType,"Old",fStatus,O$33) -> 19 | P52: =SUMIFS(fLeads,fType,"Old",fStatus,P$33) -> 120
B53: TOTAL - NEW CAMPAIGNS | D53: =SUMIFS(fSpend,fType,"New") -> 345559.94 | E53: =SUMIFS(fLeads,fType,"New") -> 2342 | F53: =SUMIFS(fQual,fType,"New") -> 351 | G53: =IFERROR(F53/E53,0) -> 0.1498719 | H53: =IF(SUMIFS(fCLeads,fType,"New")=0,"-",D53/SUMIFS(fCLeads,fType,"New")) -> 358.0932 | I53: =IF(SUMIFS(fCQual,fType,"New")=0,"-",D53/SUMIFS(fCQual,fType,"New")) -> 2215.1278 | J53: =SUMIFS(fLeads,fType,"New",fStatus,J$33) -> 0 | K53: =SUMIFS(fLeads,fType,"New",fStatus,K$33) -> 0 | L53: =SUMIFS(fLeads,fType,"New",fStatus,L$33) -> 20 | M53: =SUMIFS(fLeads,fType,"New",fStatus,M$33) -> 14 | N53: =SUMIFS(fLeads,fType,"New",fStatus,N$33) -> 15 | O53: =SUMIFS(fLeads,fType,"New",fStatus,O$33) -> 17 | P53: =SUMIFS(fLeads,fType,"New",fStatus,P$33) -> 285
B54: GRAND TOTAL (all Natuf campaigns) | D54: =SUM(fSpend) -> 1647106.2 | E54: =SUM(fLeads) -> 3627 | F54: =SUM(fQual) -> 558 | G54: =IFERROR(F54/E54,0) -> 0.15384615 | H54: =IF(SUM(fCLeads)=0,"-",D54/SUM(fCLeads)) -> 732.04722 | I54: =IF(SUM(fCQual)=0,"-",D54/SUM(fCQual)) -> 4537.4828 | J54: =SUMIFS(fLeads,fStatus,J$33) -> 0 | K54: =SUMIFS(fLeads,fStatus,K$33) -> 0 | L54: =SUMIFS(fLeads,fStatus,L$33) -> 34 | M54: =SUMIFS(fLeads,fStatus,M$33) -> 32 | N54: =SUMIFS(fLeads,fStatus,N$33) -> 51 | O54: =SUMIFS(fLeads,fStatus,O$33) -> 36 | P54: =SUMIFS(fLeads,fStatus,P$33) -> 405
B56: Quality parameters (right-hand columns) are the lead counts per CRM status; their sum equals Quality Count. Cost = ad spend / leads (or quality leads) of campaigns with Meta spend data; "n/a" = campaign not in the Meta exports (EBG - In House ad account), "-" = no leads / no quality leads. Unattributed = CRM leads with no campaign tag.

Sheet Master Pivot
B1: NATUF | Lead Quality: Old Campaigns vs New Campaigns - MASTER PIVOT (interactive)
B2: 01-Oct-2026 to 31-Oct-2026 | CRM status as of 31-Oct-2026 | Quality Lead = Won, Token Received, Qualified, Meeting Scheduled, Meeting Conducted, Follow-Up, Details Shared | Click any slicer button to filter every table (Ctrl+click = multi-select)
B3: Jump to > | C3: Headline | D3: Status funnel | E3: Campaign | F3: Quality table
B4: FILTERS (slicers) - click a button to filter the three pivot tables below; Ctrl+click = multi-select. Spend cannot be split by status / month / week, so it shows "-" when those are used. Cost per lead / per quality lead use only campaigns with Meta spend data (EBG - In House campaigns have no spend in the exports).
B24: 1. HEADLINE - Old vs New campaigns (all key metrics)
C25: Campaign Type
B26: Values | C26: Old | D26: New | E26: Grand Total
B27: Spend (₹) | C27: 1301546.3 | D27: 345559.94 | E27: 1647106.2
B28: Leads | C28: 1285 | D28: 2342 | E28: 3627
B29: Cost per Lead (₹) | C29: 1012.8765 | D29: 358.0932 | E29: 732.04722
B30: Contacted % | C30: 0.8233463 | D30: 0.84970111 | E30: 0.84036394
B31: Quality Leads | C31: 207 | D31: 351 | E31: 558
B32: Quality % | C32: 0.16108949 | D32: 0.1498719 | E32: 0.15384615
B33: Quality % of Contacted | C33: 0.19565217 | D33: 0.17638191 | E33: 0.18307087
B34: Cost per Quality Lead (₹) | C34: 6287.6633 | D34: 2215.1278 | E34: 4537.4828
B38: 2. LEAD STATUS FUNNEL - number of leads by status
B39: Record Type | C39: Lead
B41: Leads | C41: Campaign Type
B42: Lead Status | C42: Old | D42: New | E42: Grand Total
B43: Qualified | C43: 14 | D43: 20 | E43: 34
B44: Meeting Scheduled | C44: 18 | D44: 14 | E44: 32
B45: Meeting Conducted | C45: 36 | D45: 15 | E45: 51
B46: Follow-Up | C46: 19 | D46: 17 | E46: 36
B47: Details Shared | C47: 120 | D47: 285 | E47: 405
B48: Connected | C48: 217 | D48: 341 | E48: 558
B49: Attempt 1 | C49: 210 | D49: 639 | E49: 849
B50: Attempt 2 | C50: 117 | D50: 184 | E50: 301
B51: Attempt 3 | C51: 21 | D51: 56 | E51: 77
B52: Attempt 4 | C52: 25 | D52: 24 | E52: 49
B53: Attempt 5 | C53: 13 | D53: 20 | E53: 33
B54: New Lead | C54: 227 | D54: 352 | E54: 579
B55: Nurture | C55: 3 | D55: 5 | E55: 8
B56: Meeting Conducted but NOT QUALIFIED | C56: 1 | E56: 1
B57: Lost | C57: 243 | D57: 370 | E57: 613
B58: Negotiation | C58: 1 | E58: 1
B59: Grand Total | C59: 1285 | D59: 2342 | E59: 3627
B63: 3. LEAD STATUS FUNNEL - % of each campaign type's leads
B64: Record Type | C64: Lead
B66: Leads | C66: Campaign Type
B67: Lead Status | C67: Old | D67: New | E67: Grand Total
B68: Qualified | C68: 0.010894942 | D68: 0.0085397096 | E68: 0.0093741384
B69: Meeting Scheduled | C69: 0.014007782 | D69: 0.0059777968 | E69: 0.0088227185
B70: Meeting Conducted | C70: 0.028015564 | D70: 0.0064047822 | E70: 0.014061208
B71: Follow-Up | C71: 0.014785992 | D71: 0.0072587532 | E71: 0.0099255583
B72: Details Shared | C72: 0.093385214 | D72: 0.12169086 | E72: 0.11166253
B73: Connected | C73: 0.1688716 | D73: 0.14560205 | E73: 0.15384615
B74: Attempt 1 | C74: 0.16342412 | D74: 0.27284372 | E74: 0.23407775
B75: Attempt 2 | C75: 0.091050584 | D75: 0.078565329 | E75: 0.082988696
B76: Attempt 3 | C76: 0.016342412 | D76: 0.023911187 | E76: 0.021229666
B77: Attempt 4 | C77: 0.019455253 | D77: 0.010247652 | E77: 0.013509788
B78: Attempt 5 | C78: 0.010116732 | D78: 0.0085397096 | E78: 0.0090984285
B79: New Lead | C79: 0.1766537 | D79: 0.15029889 | E79: 0.15963606
... B84: Grand Total | C84: 1 | D84: 1 | E84: 1
B88: 3. CAMPAIGN WISE - spend, leads and lead quality
C89: Values
B90: Campaign Type / Campaign | C90: Spend (₹) | D90: Leads | E90: Cost per Lead (₹) | F90: Quality Leads | G90: Quality % | H90: Cost per Quality Lead (₹)
B91: Old | C91: 1301546.3 | D91: 1285 | E91: 1012.8765 | F91: 207 | G91: 0.16108949 | H91: 6287.6633
B92: E_Karan_Natuf_All_07072026 | C92: 277596.99 | D92: 229 | E92: 1212.2139 | F92: 21 | G92: 0.091703057 | H92: 13218.904
B93: E_Natuf_Generic_13082026 | C93: 233578.47 | D93: 210 | E93: 1112.2784 | F93: 40 | G93: 0.19047619 | H93: 5839.4618
B94: E_Suresh_Natuf_Kiosk_07072026 | C94: 232416.42 | D94: 313 | E94: 742.54447 | F94: 68 | G94: 0.2172524 | H94: 3417.8885
B95: natuf_Kiosk_14072026_Hindi | C95: 180149.88 | D95: 382 | E95: 471.59654 | F95: 42 | G95: 0.10994764 | H95: 4289.2829
B96: E_Selva_Natuf_All_07072026 | C96: 80349.25 | D96: 46 | E96: 1746.7228 | F96: 14 | G96: 0.30434783 | H96: 5739.2321
B97: E_Natuf_MF_05092026 | C97: 79772.24 | D97: 26 | E97: 3068.1631 | F97: 1 | G97: 0.038461538 | H97: 79772.24
B98: E_Natuf_Generic_09092026 | C98: 71194.81 | D98: 8 | E98: 8899.3512 | F98: 2 | G98: 0.25 | H98: 35597.405
B99: E_Karan_Natuf_Kiosk_07072026 | C99: 54540.16 | D99: 24 | E99: 2272.5067 | F99: 6 | G99: 0.25 | H99: 9090.0267
B100: E_Natuf_Foco_10092026 | C100: 46413.52 | D100: 32 | E100: 1450.4225 | F100: 7 | G100: 0.21875 | H100: 6630.5029
B101: E_Natuf_Amazon_29092026 | C101: 39121.71 | D101: 15 | E101: 2608.114 | F101: 6 | G101: 0.4 | H101: 6520.285
B102: E_Natuf_Web_23092026 | C102: 6412.86 | D102: 0 | E102: - | F102: 0 | G102: - | H102: -
B103: New | C103: 345559.94 | D103: 2342 | E103: 358.0932 | F103: 351 | G103: 0.1498719 | H103: 2215.1278
B104: ABO | Natuf | Leads | Unit Franchise | India | Oct26 | V1 | C104: 264151.59 | D104: 817 | E104: 323.31896 | F104: 149 | G104: 0.18237454 | H104: 1772.8295
B105: ABO | Natuf | Leads | Master Franchise | India | Oct26 | V1 | C105: 55861.63 | D105: 148 | E105: 377.44345 | F105: 7 | G105: 0.047297297 | H105: 7980.2329
B106: Natuf | ABO | WhatsApp | Unit Franchise | India | Oct26 | V1 | C106: 25546.72 | D106: 0 | E106: - | F106: 0 | G106: - | H106: -
B107: EBG - In House | ABO | Natuf | Leads | Unit Franchise | India | Oct26 | V1 | C107: 0 | D107: 1262 | E107: - | F107: 193 | G107: 0.15293185 | H107: -
B108: Natuf | In House | ABO | | WhatsApp | Unit Franchise | India | Oct26 | V1 | C108: 0 | D108: 73 | E108: - | F108: 2 | G108: 0.02739726 | H108: -
B109: EBG - In House | ABO | Natuf | Leads | Master Franchise | India | Oct26 | V1 | C109: 0 | D109: 42 | E109: - | F109: 0 | G109: 0 | H109: -
B110: Grand Total | C110: 1647106.2 | D110: 3627 | E110: 732.04722 | F110: 558 | G110: 0.15384615 | H110: 4537.4828
B114: 4. QUALITY TABLE - Campaign Name, Campaign Type, Quality Parameter, Quality % and Quality Count
B115: Campaign Name | C115: Campaign Type (Old / New) | D115: Quality Parameter | E115: Quality % | F115: Quality Count | G115: Campaign Leads | H115: Campaign Spend (INR)
B116: ALL OLD CAMPAIGNS (combined) | C116: Old | D116: =Settings!$A$4 -> Won | E116: =IFERROR(F116/G116,0) -> 0 | F116: =SUMIFS(fLeads,fType,$C116,fStatus,$D116) -> 0 | G116: =SUMIFS(fLeads,fType,$C116) -> 1285 | H116: =SUMIFS(fSpend,fType,$C116) -> 1301546.3
B117: ALL OLD CAMPAIGNS (combined) | C117: Old | D117: =Settings!$A$5 -> Token Received | E117: =IFERROR(F117/G117,0) -> 0 | F117: =SUMIFS(fLeads,fType,$C117,fStatus,$D117) -> 0 | G117: =SUMIFS(fLeads,fType,$C117) -> 1285 | H117: =SUMIFS(fSpend,fType,$C117) -> 1301546.3
B118: ALL OLD CAMPAIGNS (combined) | C118: Old | D118: =Settings!$A$6 -> Qualified | E118: =IFERROR(F118/G118,0) -> 0.010894942 | F118: =SUMIFS(fLeads,fType,$C118,fStatus,$D118) -> 14 | G118: =SUMIFS(fLeads,fType,$C118) -> 1285 | H118: =SUMIFS(fSpend,fType,$C118) -> 1301546.3
B119: ALL OLD CAMPAIGNS (combined) | C119: Old | D119: =Settings!$A$7 -> Meeting Scheduled | E119: =IFERROR(F119/G119,0) -> 0.014007782 | F119: =SUMIFS(fLeads,fType,$C119,fStatus,$D119) -> 18 | G119: =SUMIFS(fLeads,fType,$C119) -> 1285 | H119: =SUMIFS(fSpend,fType,$C119) -> 1301546.3
B120: ALL OLD CAMPAIGNS (combined) | C120: Old | D120: =Settings!$A$8 -> Meeting Conducted | E120: =IFERROR(F120/G120,0) -> 0.028015564 | F120: =SUMIFS(fLeads,fType,$C120,fStatus,$D120) -> 36 | G120: =SUMIFS(fLeads,fType,$C120) -> 1285 | H120: =SUMIFS(fSpend,fType,$C120) -> 1301546.3
B121: ALL OLD CAMPAIGNS (combined) | C121: Old | D121: =Settings!$A$9 -> Follow-Up | E121: =IFERROR(F121/G121,0) -> 0.014785992 | F121: =SUMIFS(fLeads,fType,$C121,fStatus,$D121) -> 19 | G121: =SUMIFS(fLeads,fType,$C121) -> 1285 | H121: =SUMIFS(fSpend,fType,$C121) -> 1301546.3
B122: ALL OLD CAMPAIGNS (combined) | C122: Old | D122: =Settings!$A$10 -> Details Shared | E122: =IFERROR(F122/G122,0) -> 0.093385214 | F122: =SUMIFS(fLeads,fType,$C122,fStatus,$D122) -> 120 | G122: =SUMIFS(fLeads,fType,$C122) -> 1285 | H122: =SUMIFS(fSpend,fType,$C122) -> 1301546.3
B123: ALL OLD CAMPAIGNS (combined) | C123: Old | D123: TOTAL QUALITY LEADS | E123: =IFERROR(F123/G123,0) -> 0.16108949 | F123: =SUMIFS(fQual,fType,$C123) -> 207 | G123: =SUMIFS(fLeads,fType,$C123) -> 1285 | H123: =SUMIFS(fSpend,fType,$C123) -> 1301546.3
B124: ALL NEW CAMPAIGNS (combined) | C124: New | D124: =Settings!$A$4 -> Won | E124: =IFERROR(F124/G124,0) -> 0 | F124: =SUMIFS(fLeads,fType,$C124,fStatus,$D124) -> 0 | G124: =SUMIFS(fLeads,fType,$C124) -> 2342 | H124: =SUMIFS(fSpend,fType,$C124) -> 345559.94
B125: ALL NEW CAMPAIGNS (combined) | C125: New | D125: =Settings!$A$5 -> Token Received | E125: =IFERROR(F125/G125,0) -> 0 | F125: =SUMIFS(fLeads,fType,$C125,fStatus,$D125) -> 0 | G125: =SUMIFS(fLeads,fType,$C125) -> 2342 | H125: =SUMIFS(fSpend,fType,$C125) -> 345559.94
B126: ALL NEW CAMPAIGNS (combined) | C126: New | D126: =Settings!$A$6 -> Qualified | E126: =IFERROR(F126/G126,0) -> 0.0085397096 | F126: =SUMIFS(fLeads,fType,$C126,fStatus,$D126) -> 20 | G126: =SUMIFS(fLeads,fType,$C126) -> 2342 | H126: =SUMIFS(fSpend,fType,$C126) -> 345559.94
B127: ALL NEW CAMPAIGNS (combined) | C127: New | D127: =Settings!$A$7 -> Meeting Scheduled | E127: =IFERROR(F127/G127,0) -> 0.0059777968 | F127: =SUMIFS(fLeads,fType,$C127,fStatus,$D127) -> 14 | G127: =SUMIFS(fLeads,fType,$C127) -> 2342 | H127: =SUMIFS(fSpend,fType,$C127) -> 345559.94
B128: ALL NEW CAMPAIGNS (combined) | C128: New | D128: =Settings!$A$8 -> Meeting Conducted | E128: =IFERROR(F128/G128,0) -> 0.0064047822 | F128: =SUMIFS(fLeads,fType,$C128,fStatus,$D128) -> 15 | G128: =SUMIFS(fLeads,fType,$C128) -> 2342 | H128: =SUMIFS(fSpend,fType,$C128) -> 345559.94
B129: ALL NEW CAMPAIGNS (combined) | C129: New | D129: =Settings!$A$9 -> Follow-Up | E129: =IFERROR(F129/G129,0) -> 0.0072587532 | F129: =SUMIFS(fLeads,fType,$C129,fStatus,$D129) -> 17 | G129: =SUMIFS(fLeads,fType,$C129) -> 2342 | H129: =SUMIFS(fSpend,fType,$C129) -> 345559.94
B130: ALL NEW CAMPAIGNS (combined) | C130: New | D130: =Settings!$A$10 -> Details Shared | E130: =IFERROR(F130/G130,0) -> 0.12169086 | F130: =SUMIFS(fLeads,fType,$C130,fStatus,$D130) -> 285 | G130: =SUMIFS(fLeads,fType,$C130) -> 2342 | H130: =SUMIFS(fSpend,fType,$C130) -> 345559.94
B131: ALL NEW CAMPAIGNS (combined) | C131: New | D131: TOTAL QUALITY LEADS | E131: =IFERROR(F131/G131,0) -> 0.1498719 | F131: =SUMIFS(fQual,fType,$C131) -> 351 | G131: =SUMIFS(fLeads,fType,$C131) -> 2342 | H131: =SUMIFS(fSpend,fType,$C131) -> 345559.94
B132: E_Karan_Natuf_All_07072026 | C132: =IFERROR(INDEX(CampTypes,MATCH($B132,CampList,0)),"Unattributed") -> Old | D132: =Settings!$A$4 -> Won | E132: =IFERROR(F132/G132,0) -> 0 | F132: =SUMIFS(fLeads,fCampaign,$B132,fStatus,$D132) -> 0 | G132: =SUMIFS(fLeads,fCampaign,$B132) -> 229 | H132: =IF(COUNTIF(MetaCamps,$B132)=0,"n/a",SUMIFS(fSpend,fCampaign,$B132)) -> 277596.99
B133: E_Karan_Natuf_All_07072026 | C133: =IFERROR(INDEX(CampTypes,MATCH($B133,CampList,0)),"Unattributed") -> Old | D133: =Settings!$A$5 -> Token Received | E133: =IFERROR(F133/G133,0) -> 0 | F133: =SUMIFS(fLeads,fCampaign,$B133,fStatus,$D133) -> 0 | G133: =SUMIFS(fLeads,fCampaign,$B133) -> 229 | H133: =IF(COUNTIF(MetaCamps,$B133)=0,"n/a",SUMIFS(fSpend,fCampaign,$B133)) -> 277596.99
B134: E_Karan_Natuf_All_07072026 | C134: =IFERROR(INDEX(CampTypes,MATCH($B134,CampList,0)),"Unattributed") -> Old | D134: =Settings!$A$6 -> Qualified | E134: =IFERROR(F134/G134,0) -> 0 | F134: =SUMIFS(fLeads,fCampaign,$B134,fStatus,$D134) -> 0 | G134: =SUMIFS(fLeads,fCampaign,$B134) -> 229 | H134: =IF(COUNTIF(MetaCamps,$B134)=0,"n/a",SUMIFS(fSpend,fCampaign,$B134)) -> 277596.99
B135: E_Karan_Natuf_All_07072026 | C135: =IFERROR(INDEX(CampTypes,MATCH($B135,CampList,0)),"Unattributed") -> Old | D135: =Settings!$A$7 -> Meeting Scheduled | E135: =IFERROR(F135/G135,0) -> 0.013100437 | F135: =SUMIFS(fLeads,fCampaign,$B135,fStatus,$D135) -> 3 | G135: =SUMIFS(fLeads,fCampaign,$B135) -> 229 | H135: =IF(COUNTIF(MetaCamps,$B135)=0,"n/a",SUMIFS(fSpend,fCampaign,$B135)) -> 277596.99
B136: E_Karan_Natuf_All_07072026 | C136: =IFERROR(INDEX(CampTypes,MATCH($B136,CampList,0)),"Unattributed") -> Old | D136: =Settings!$A$8 -> Meeting Conducted | E136: =IFERROR(F136/G136,0) -> 0.0087336245 | F136: =SUMIFS(fLeads,fCampaign,$B136,fStatus,$D136) -> 2 | G136: =SUMIFS(fLeads,fCampaign,$B136) -> 229 | H136: =IF(COUNTIF(MetaCamps,$B136)=0,"n/a",SUMIFS(fSpend,fCampaign,$B136)) -> 277596.99
B137: E_Karan_Natuf_All_07072026 | C137: =IFERROR(INDEX(CampTypes,MATCH($B137,CampList,0)),"Unattributed") -> Old | D137: =Settings!$A$9 -> Follow-Up | E137: =IFERROR(F137/G137,0) -> 0.013100437 | F137: =SUMIFS(fLeads,fCampaign,$B137,fStatus,$D137) -> 3 | G137: =SUMIFS(fLeads,fCampaign,$B137) -> 229 | H137: =IF(COUNTIF(MetaCamps,$B137)=0,"n/a",SUMIFS(fSpend,fCampaign,$B137)) -> 277596.99
...

Sheet Executive Summary
A1: Natuf - Old vs New Campaigns: Lead Quality Comparison
A2: Period 01-Oct-2026 to 31-Oct-2026 | CRM status as of 31-Oct-2026 | Quality Lead = Won, Token Received, Qualified, Meeting Scheduled, Meeting Conducted, Follow-Up, Details Shared | All figures are live formulas on the Fact_Data / Lead_Data tabs
A4: KEY TAKEAWAYS
A5: SCALE - Old campaigns (window 31 days) spent ₹1,301,546 and generated 1,285 CRM leads. New campaigns (live 24 days, from 08-Oct) spent ₹345,560 on campaigns with Meta spend data and generated 2,342 CRM leads (1,377 of them from EBG - In House campaigns whose spend is not in the exports).
A6: COST - Cost per lead (campaigns with spend data): Old ₹1,013 vs New ₹358 (-65%). Cost per Quality Lead: Old ₹6,288 vs New ₹2,215 (-65%).
A7: QUALITY RATE - Quality leads are 16.1% of Old leads vs 15.0% of New leads (-1.1 pp). Counting only leads already worked (status other than 'New Lead'): Old 19.6% vs New 17.6%.
A8: LIKE-FOR-LIKE - 352 New-campaign leads (15.0%) are still un-actioned ('New Lead') vs 227 (17.7%) for Old. On leads created in the same window (08-Oct to 31-Oct), quality is 15.0% for New vs 13.7% for Old (+1.3 pp) - the fairest like-for-like view.
A9: DEEP FUNNEL - Won / Token / Qualified / Meeting Scheduled / Meeting Conducted: Old 68 (5.3% of leads) vs New 49 (2.1%). Lost: Old 18.9% vs New 15.8%.
A10: NOTE - ₹31,960 of spend sits on 2 campaign(s) with Meta spend but no CRM leads (web landing-page / WhatsApp-conversation campaigns: E_Natuf_Web_23092026, Natuf | ABO | WhatsApp | Unit Franchise | India | Oct26 | V1). It is kept in spend, so CPL / CPQL for that group are slightly overstated.
A11: DATA SCOPE - LeadData_October2026 holds 28,939 rows (28,937 unique leads, all brands); 3,627 belong to Natuf campaigns (used here). 35 Natuf-brand rows are excluded and 57 Natuf-campaign leads tagged to other brands are listed on XBrand_Leads - see Reconciliation / Notes.
A13: 1. HEADLINE KPIs (Old vs New)
A14: Metric | B14: Old | C14: New | D14: Total (all Natuf) | E14: New vs Old | F14: Definition
A15: Ad spend (INR) | B15: =SUMIFS(fSpend,fType,B$14) -> 1301546.3 | C15: =SUMIFS(fSpend,fType,C$14) -> 345559.94 | D15: =SUM(fSpend) -> 1647106.2 | E15: =IFERROR(C15/B15-1,"-") -> -0.73450047 | F15: Meta amount spent (campaign file = sum of ad sets).
A16: Impressions | B16: =SUMIFS(fImpr,fType,B$14) -> 1771115 | C16: =SUMIFS(fImpr,fType,C$14) -> 2355759 | D16: =SUM(fImpr) -> 4126874 | E16: =IFERROR(C16/B16-1,"-") -> 0.3300994 | F16: Meta impressions.
A17: Link clicks | B17: =SUMIFS(fClicks,fType,B$14) -> 20173 | C17: =SUMIFS(fClicks,fType,C$14) -> 14032 | D17: =SUM(fClicks) -> 34205 | E17: =IFERROR(C17/B17-1,"-") -> -0.30441679 | F17: Meta link clicks.
A18: CTR (link) | B18: =IFERROR(B17/B16,0) -> 0.01139 | C18: =IFERROR(C17/C16,0) -> 0.0059564667 | D18: =IFERROR(D17/D16,0) -> 0.0082883558 | E18: =IFERROR((C18-B18)*100,"-") -> -0.54335334 | F18: Link clicks / impressions.
A19: CPM (INR) | B19: =IFERROR(B15/B16*1000,0) -> 734.87397 | C19: =IFERROR(C15/C16*1000,0) -> 146.68731 | D19: =IFERROR(D15/D16*1000,0) -> 399.11716 | E19: =IFERROR(C19/B19-1,"-") -> -0.80039121 | F19: Spend per 1,000 impressions.
A20: CPC - link (INR) | B20: =IFERROR(B15/B17,0) -> 64.519224 | C20: =IFERROR(C15/C17,0) -> 24.626564 | D20: =IFERROR(D15/D17,0) -> 48.153961 | E20: =IFERROR(C20/B20-1,"-") -> -0.61830658 | F20: Spend per link click.
A21: Meta-reported results (lead forms + WhatsApp conversations) | B21: =SUMIFS(fMeta,fType,B$14) -> 1602 | C21: =SUMIFS(fMeta,fType,C$14) -> 2556 | D21: =SUM(fMeta) -> 4158 | E21: =IFERROR(C21/B21-1,"-") -> 0.59550562 | F21: Meta "Results": instant-form leads and WhatsApp conversations started. Web landing-page-views are excluded.
A22: Cost per Meta result (INR) | B22: =IFERROR(B15/B21,0) -> 812.45088 | C22: =IFERROR(C15/C21,0) -> 135.19559 | D22: =IFERROR(D15/D21,0) -> 396.12945 | E22: =IFERROR(C22/B22-1,"-") -> -0.83359536 | F22: Spend / Meta results (spend of the web landing-page campaign included in spend).
A23: CRM leads (Natuf campaigns) | B23: =SUMIFS(fLeads,fType,B$14) -> 1285 | C23: =SUMIFS(fLeads,fType,C$14) -> 2342 | D23: =SUM(fLeads) -> 3627 | E23: =IFERROR(C23/B23-1,"-") -> 0.82256809 | F23: Lead records in the CRM attributed to the campaigns (recovered via ad-set name where the CRM campaign was blank).
A24: CRM capture rate (CRM leads of Meta campaigns / Meta results) | B24: =IFERROR(SUMIFS(fCLeads,fType,B$14)/B21,0) -> 0.80212235 | C24: =IFERROR(SUMIFS(fCLeads,fType,C$14)/C21,0) -> 0.37754304 | D24: =IFERROR(SUM(fCLeads)/D21,0) -> 0.54112554 | E24: =IFERROR((C24-B24)*100,"-") -> -42.457931 | F24: How much of what Meta reports reached the CRM pipeline (leads of EBG - In House campaigns excluded: no Meta data).
A25: Cost per CRM lead - CPL (INR) | B25: =IFERROR(B15/SUMIFS(fCLeads,fType,B$14),0) -> 1012.8765 | C25: =IFERROR(C15/SUMIFS(fCLeads,fType,C$14),0) -> 358.0932 | D25: =IFERROR(D15/SUM(fCLeads),0) -> 732.04722 | E25: =IFERROR(C25/B25-1,"-") -> -0.64645917 | F25: Ad spend / CRM leads of campaigns that have Meta spend data.
A26: Contacted leads | B26: =SUMIFS(fContacted,fType,B$14) -> 1058 | C26: =SUMIFS(fContacted,fType,C$14) -> 1990 | D26: =SUM(fContacted) -> 3048 | E26: =IFERROR(C26/B26-1,"-") -> 0.88090737 | F26: Leads whose status is anything other than "New Lead".
A27: Contacted % | B27: =IFERROR(B26/B23,0) -> 0.8233463 | C27: =IFERROR(C26/C23,0) -> 0.84970111 | D27: =IFERROR(D26/D23,0) -> 0.84036394 | E27: =IFERROR((C27-B27)*100,"-") -> 2.6354807 | F27: Contacted / CRM leads (indicates sales follow-up speed).
A28: Calls per lead | B28: =IFERROR(SUMIFS(fCalls,fType,B$14)/B23,0) -> 2.9027237 | C28: =IFERROR(SUMIFS(fCalls,fType,C$14)/C23,0) -> 1.9355252 | D28: =IFERROR(SUM(fCalls)/D23,0) -> 2.2781913 | E28: =IFERROR(C28/B28-1,"-") -> -0.33320379 | F28: Total calls made / CRM leads.
A29: Call connect rate | B29: =IFERROR(SUMIFS(fConn,fType,B$14)/SUMIFS(fCalls,fType,B$14),0) -> 0.43485255 | C29: =IFERROR(SUMIFS(fConn,fType,C$14)/SUMIFS(fCalls,fType,C$14),0) -> 0.46878447 | D29: =IFERROR(SUM(fConn)/SUM(fCalls),0) -> 0.45346726 | E29: =IFERROR((C29-B29)*100,"-") -> 3.3931923 | F29: Connected calls / total calls.
A30: QUALITY LEADS | B30: =SUMIFS(fQual,fType,B$14) -> 207 | C30: =SUMIFS(fQual,fType,C$14) -> 351 | D30: =SUM(fQual) -> 558 | E30: =IFERROR(C30/B30-1,"-") -> 0.69565217 | F30: Status in {Won, Token Received, Qualified, Meeting Scheduled, Meeting Conducted, Follow-Up, Details Shared}.
A31: Quality % (of all leads) | B31: =IFERROR(B30/B23,0) -> 0.16108949 | C31: =IFERROR(C30/C23,0) -> 0.1498719 | D31: =IFERROR(D30/D23,0) -> 0.15384615 | E31: =IFERROR((C31-B31)*100,"-") -> -1.121759 | F31: Quality leads / CRM leads.
A32: Quality % of contacted leads | B32: =IFERROR(B30/B26,0) -> 0.19565217 | C32: =IFERROR(C30/C26,0) -> 0.17638191 | D32: =IFERROR(D30/D26,0) -> 0.18307087 | E32: =IFERROR((C32-B32)*100,"-") -> -1.9270264 | F32: Quality leads / contacted leads - removes the effect of leads not yet worked.
A33: COST PER QUALITY LEAD - CPQL (INR) | B33: =IFERROR(B15/SUMIFS(fCQual,fType,B$14),0) -> 6287.6633 | C33: =IFERROR(C15/SUMIFS(fCQual,fType,C$14),0) -> 2215.1278 | D33: =IFERROR(D15/SUM(fCQual),0) -> 4537.4828 | E33: =IFERROR(C33/B33-1,"-") -> -0.64770254 | F33: Ad spend / quality leads of campaigns that have Meta spend data.
A34: Lost leads | B34: =SUMIFS(fLost,fType,B$14) -> 243 | C34: =SUMIFS(fLost,fType,C$14) -> 370 | D34: =SUM(fLost) -> 613 | E34: =IFERROR(C34/B34-1,"-") -> 0.52263374 | F34: Status = Lost.
A35: Lost % | B35: =IFERROR(B34/B23,0) -> 0.18910506 | C35: =IFERROR(C34/C23,0) -> 0.15798463 | D35: =IFERROR(D34/D23,0) -> 0.1690102 | E35: =IFERROR((C35-B35)*100,"-") -> -3.112043 | F35: Lost / CRM leads.
A36: Un-actioned leads (status "New Lead") | B36: =COUNTIFS(ldType,B$14,ldStatus,"New Lead") -> 227 | C36: =COUNTIFS(ldType,C$14,ldStatus,"New Lead") -> 352 | D36: =COUNTIFS(ldStatus,"New Lead") -> 579 | E36: =IFERROR(C36/B36-1,"-") -> 0.55066079 | F36: Leads not yet touched by sales as of 31-Oct.
A37: Un-actioned % | B37: =IFERROR(B36/B23,0) -> 0.1766537 | C37: =IFERROR(C36/C23,0) -> 0.15029889 | D37: =IFERROR(D36/D23,0) -> 0.15963606 | E37: =IFERROR((C37-B37)*100,"-") -> -2.6354807 | F37: Higher = quality rate still immature.
A38: Days in market (in window) | B38: =DaysOld -> 31 | C38: =DaysNew -> 24 | D38: ="" | F38: Settings tab. Old: 01-Oct to 31-Oct; New (campaigns with Meta data): 08-Oct to 31-Oct.
A39: Avg daily ad spend (INR) | B39: =IFERROR(B15/B38,0) -> 41985.365 | C39: =IFERROR(C15/C38,0) -> 14398.331 | D39: ="" | E39: =IFERROR(C39/B39-1,"-") -> -0.6570631 | F39: Spend / days in market.
A40: Avg daily CRM leads | B40: =IFERROR(B23/B38,0) -> 41.451613 | C40: =IFERROR(C23/C38,0) -> 97.583333 | D40: ="" | E40: =IFERROR(C40/B40-1,"-") -> 1.3541505 | F40: CRM leads / days in market.
A41: Avg daily quality leads | B41: =IFERROR(B30/B38,0) -> 6.6774194 | C41: =IFERROR(C30/C38,0) -> 14.625 | D41: ="" | E41: =IFERROR(C41/B41-1,"-") -> 1.1902174 | F41: Quality leads / days in market (New is still maturing).
A42: New vs Old: relative change for volumes / costs, percentage-point (pp) change for rates. Green = New better, red = New worse (colour only on rate and cost metrics). "Total (all Natuf)" also contains Unattributed leads.
A44: 2. LEAD STATUS FUNNEL (count and % of leads)
A45: Lead status | B45: Old - leads | C45: New - leads | D45: Old - % of leads | E45: New - % of leads | F45: Quality status? / New vs Old (pp)
A46: Won | B46: =COUNTIFS(ldType,"Old",ldStatus,$A46) -> 0 | C46: =COUNTIFS(ldType,"New",ldStatus,$A46) -> 0 | D46: =IFERROR(B46/B$64,0) -> 0 | E46: =IFERROR(C46/C$64,0) -> 0 | F46: =IF(ISNUMBER(MATCH($A46,QualityStatuses,0)),"Quality | ","")&TEXT((E46-D46)*100,"+0.0;-0.0;0.0")&" pp" -> Quality | 0.0 pp
A47: Token Received | B47: =COUNTIFS(ldType,"Old",ldStatus,$A47) -> 0 | C47: =COUNTIFS(ldType,"New",ldStatus,$A47) -> 0 | D47: =IFERROR(B47/B$64,0) -> 0 | E47: =IFERROR(C47/C$64,0) -> 0 | F47: =IF(ISNUMBER(MATCH($A47,QualityStatuses,0)),"Quality | ","")&TEXT((E47-D47)*100,"+0.0;-0.0;0.0")&" pp" -> Quality | 0.0 pp
A48: Qualified | B48: =COUNTIFS(ldType,"Old",ldStatus,$A48) -> 14 | C48: =COUNTIFS(ldType,"New",ldStatus,$A48) -> 20 | D48: =IFERROR(B48/B$64,0) -> 0.010894942 | E48: =IFERROR(C48/C$64,0) -> 0.0085397096 | F48: =IF(ISNUMBER(MATCH($A48,QualityStatuses,0)),"Quality | ","")&TEXT((E48-D48)*100,"+0.0;-0.0;0.0")&" pp" -> Quality | -0.2 pp
A49: Meeting Scheduled | B49: =COUNTIFS(ldType,"Old",ldStatus,$A49) -> 18 | C49: =COUNTIFS(ldType,"New",ldStatus,$A49) -> 14 | D49: =IFERROR(B49/B$64,0) -> 0.014007782 | E49: =IFERROR(C49/C$64,0) -> 0.0059777968 | F49: =IF(ISNUMBER(MATCH($A49,QualityStatuses,0)),"Quality | ","")&TEXT((E49-D49)*100,"+0.0;-0.0;0.0")&" pp" -> Quality | -0.8 pp
A50: Meeting Conducted | B50: =COUNTIFS(ldType,"Old",ldStatus,$A50) -> 36 | C50: =COUNTIFS(ldType,"New",ldStatus,$A50) -> 15 | D50: =IFERROR(B50/B$64,0) -> 0.028015564 | E50: =IFERROR(C50/C$64,0) -> 0.0064047822 | F50: =IF(ISNUMBER(MATCH($A50,QualityStatuses,0)),"Quality | ","")&TEXT((E50-D50)*100,"+0.0;-0.0;0.0")&" pp" -> Quality | -2.2 pp
A51: Follow-Up | B51: =COUNTIFS(ldType,"Old",ldStatus,$A51) -> 19 | C51: =COUNTIFS(ldType,"New",ldStatus,$A51) -> 17 | D51: =IFERROR(B51/B$64,0) -> 0.014785992 | E51: =IFERROR(C51/C$64,0) -> 0.0072587532 | F51: =IF(ISNUMBER(MATCH($A51,QualityStatuses,0)),"Quality | ","")&TEXT((E51-D51)*100,"+0.0;-0.0;0.0")&" pp" -> Quality | -0.8 pp
A52: Details Shared | B52: =COUNTIFS(ldType,"Old",ldStatus,$A52) -> 120 | C52: =COUNTIFS(ldType,"New",ldStatus,$A52) -> 285 | D52: =IFERROR(B52/B$64,0) -> 0.093385214 | E52: =IFERROR(C52/C$64,0) -> 0.12169086 | F52: =IF(ISNUMBER(MATCH($A52,QualityStatuses,0)),"Quality | ","")&TEXT((E52-D52)*100,"+0.0;-0.0;0.0")&" pp" -> Quality | +2.8 pp
A53: Connected | B53: =COUNTIFS(ldType,"Old",ldStatus,$A53) -> 217 | C53: =COUNTIFS(ldType,"New",ldStatus,$A53) -> 341 | D53: =IFERROR(B53/B$64,0) -> 0.1688716 | E53: =IFERROR(C53/C$64,0) -> 0.14560205 | F53: =IF(ISNUMBER(MATCH($A53,QualityStatuses,0)),"Quality | ","")&TEXT((E53-D53)*100,"+0.0;-0.0;0.0")&" pp" -> -2.3 pp
A54: Attempt 1 | B54: =COUNTIFS(ldType,"Old",ldStatus,$A54) -> 210 | C54: =COUNTIFS(ldType,"New",ldStatus,$A54) -> 639 | D54: =IFERROR(B54/B$64,0) -> 0.16342412 | E54: =IFERROR(C54/C$64,0) -> 0.27284372 | F54: =IF(ISNUMBER(MATCH($A54,QualityStatuses,0)),"Quality | ","")&TEXT((E54-D54)*100,"+0.0;-0.0;0.0")&" pp" -> +10.9 pp
A55: Attempt 2 | B55: =COUNTIFS(ldType,"Old",ldStatus,$A55) -> 117 | C55: =COUNTIFS(ldType,"New",ldStatus,$A55) -> 184 | D55: =IFERROR(B55/B$64,0) -> 0.091050584 | E55: =IFERROR(C55/C$64,0) -> 0.078565329 | F55: =IF(ISNUMBER(MATCH($A55,QualityStatuses,0)),"Quality | ","")&TEXT((E55-D55)*100,"+0.0;-0.0;0.0")&" pp" -> -1.2 pp
A56: Attempt 3 | B56: =COUNTIFS(ldType,"Old",ldStatus,$A56) -> 21 | C56: =COUNTIFS(ldType,"New",ldStatus,$A56) -> 56 | D56: =IFERROR(B56/B$64,0) -> 0.016342412 | E56: =IFERROR(C56/C$64,0) -> 0.023911187 | F56: =IF(ISNUMBER(MATCH($A56,QualityStatuses,0)),"Quality | ","")&TEXT((E56-D56)*100,"+0.0;-0.0;0.0")&" pp" -> +0.8 pp
A57: Attempt 4 | B57: =COUNTIFS(ldType,"Old",ldStatus,$A57) -> 25 | C57: =COUNTIFS(ldType,"New",ldStatus,$A57) -> 24 | D57: =IFERROR(B57/B$64,0) -> 0.019455253 | E57: =IFERROR(C57/C$64,0) -> 0.010247652 | F57: =IF(ISNUMBER(MATCH($A57,QualityStatuses,0)),"Quality | ","")&TEXT((E57-D57)*100,"+0.0;-0.0;0.0")&" pp" -> -0.9 pp
... A63: Negotiation | B63: =COUNTIFS(ldType,"Old",ldStatus,$A63) -> 1 | C63: =COUNTIFS(ldType,"New",ldStatus,$A63) -> 0 | D63: =IFERROR(B63/B$64,0) -> 0.00077821012 | E63: =IFERROR(C63/C$64,0) -> 0 | F63: =IF(ISNUMBER(MATCH($A63,QualityStatuses,0)),"Quality | ","")&TEXT((E63-D63)*100,"+0.0;-0.0;0.0")&" pp" -> -0.1 pp
A64: Total (Old / New leads) | B64: =SUM(B46:B63) -> 1285 | C64: =SUM(C46:C63) -> 2342 | D64: =SUM(D46:D63) -> 1 | E64: =SUM(E46:E63) -> 1
A65: Total leads here exclude the 0 Unattributed leads. Rows highlighted green in the status column are Quality statuses.
A67: 3. LIKE-FOR-LIKE COHORT - leads created on/after the Like-for-like start date (Settings; here 08-Oct-2026)
A68: Metric | B68: Old | C68: New | E68: New vs Old | F68: Why it matters
A69: Leads created in cohort | B69: =COUNTIFS(ldType,B$67,ldDate,">="&LFLStart) -> 0 | C69: =COUNTIFS(ldType,C$67,ldDate,">="&LFLStart) -> 0 | E69: =IFERROR(C69/B69-1,"-") -> - | F69: Both groups have the same maximum lead age (24 days).
A70: Contacted leads | B70: =COUNTIFS(ldType,B$67,ldDate,">="&LFLStart,ldStatus,"<>New Lead") -> 0 | C70: =COUNTIFS(ldType,C$67,ldDate,">="&LFLStart,ldStatus,"<>New Lead") -> 0 | E70: =IFERROR(C70/B70-1,"-") -> -
A71: Contacted % | B71: =IFERROR(B70/B69,0) -> 0 | C71: =IFERROR(C70/C69,0) -> 0 | E71: =IFERROR((C71-B71)*100,"-") -> 0 | F71: Sales follow-up speed on the same-age leads.
A72: Quality leads | B72: =COUNTIFS(ldType,B$67,ldDate,">="&LFLStart,ldQual,"Quality Lead") -> 0 | C72: =COUNTIFS(ldType,C$67,ldDate,">="&LFLStart,ldQual,"Quality Lead") -> 0 | E72: =IFERROR(C72/B72-1,"-") -> -
A73: Quality % (of leads) | B73: =IFERROR(B72/B69,0) -> 0 | C73: =IFERROR(C72/C69,0) -> 0 | E73: =IFERROR((C73-B73)*100,"-") -> 0 | F73: Fairest quality comparison: removes lead-age bias.
A74: Quality % of contacted | B74: =IFERROR(B72/B70,0) -> 0 | C74: =IFERROR(C72/C70,0) -> 0 | E74: =IFERROR((C74-B74)*100,"-") -> 0
A76: 4. CAMPAIGN SCORECARD
A77: Campaign | B77: Type | C77: Ad spend (INR) | D77: Meta results | E77: CRM leads | F77: Quality leads | G77: Quality % | H77: CPL (INR) | I77: CPQL (INR) | J77: Contacted %
A78: E_Karan_Natuf_All_07072026 | B78: =IFERROR(INDEX(CampTypes,MATCH(A78,CampList,0)),"") -> Old | C78: =IF(COUNTIF(MetaCamps,$A78)=0,"n/a",SUMIFS(fSpend,fCampaign,$A78)) -> 277596.99 | D78: =SUMIFS(fMeta,fCampaign,$A78) -> 289 | E78: =SUMIFS(fLeads,fCampaign,$A78) -> 229 | F78: =SUMIFS(fQual,fCampaign,$A78) -> 21 | G78: =IFERROR(F78/E78,0) -> 0.091703057 | H78: =IF(COUNTIF(MetaCamps,$A78)=0,"n/a",IFERROR(C78/E78,0)) -> 1212.2139 | I78: =IF(COUNTIF(MetaCamps,$A78)=0,"n/a",IFERROR(C78/F78,0)) -> 13218.904 | J78: =IFERROR(SUMIFS(fContacted,fCampaign,$A78)/E78,0) -> 0.72052402
A79: E_Natuf_Generic_13082026 | B79: =IFERROR(INDEX(CampTypes,MATCH(A79,CampList,0)),"") -> Old | C79: =IF(COUNTIF(MetaCamps,$A79)=0,"n/a",SUMIFS(fSpend,fCampaign,$A79)) -> 233578.47 | D79: =SUMIFS(fMeta,fCampaign,$A79) -> 245 | E79: =SUMIFS(fLeads,fCampaign,$A79) -> 210 | F79: =SUMIFS(fQual,fCampaign,$A79) -> 40 | G79: =IFERROR(F79/E79,0) -> 0.19047619 | H79: =IF(COUNTIF(MetaCamps,$A79)=0,"n/a",IFERROR(C79/E79,0)) -> 1112.2784 | I79: =IF(COUNTIF(MetaCamps,$A79)=0,"n/a",IFERROR(C79/F79,0)) -> 5839.4618 | J79: =IFERROR(SUMIFS(fContacted,fCampaign,$A79)/E79,0) -> 0.86190476
A80: E_Suresh_Natuf_Kiosk_07072026 | B80: =IFERROR(INDEX(CampTypes,MATCH(A80,CampList,0)),"") -> Old | C80: =IF(COUNTIF(MetaCamps,$A80)=0,"n/a",SUMIFS(fSpend,fCampaign,$A80)) -> 232416.42 | D80: =SUMIFS(fMeta,fCampaign,$A80) -> 360 | E80: =SUMIFS(fLeads,fCampaign,$A80) -> 313 | F80: =SUMIFS(fQual,fCampaign,$A80) -> 68 | G80: =IFERROR(F80/E80,0) -> 0.2172524 | H80: =IF(COUNTIF(MetaCamps,$A80)=0,"n/a",IFERROR(C80/E80,0)) -> 742.54447 | I80: =IF(COUNTIF(MetaCamps,$A80)=0,"n/a",IFERROR(C80/F80,0)) -> 3417.8885 | J80: =IFERROR(SUMIFS(fContacted,fCampaign,$A80)/E80,0) -> 0.85303514
A81: natuf_Kiosk_14072026_Hindi | B81: =IFERROR(INDEX(CampTypes,MATCH(A81,CampList,0)),"") -> Old | C81: =IF(COUNTIF(MetaCamps,$A81)=0,"n/a",SUMIFS(fSpend,fCampaign,$A81)) -> 180149.88 | D81: =SUMIFS(fMeta,fCampaign,$A81) -> 438 | E81: =SUMIFS(fLeads,fCampaign,$A81) -> 382 | F81: =SUMIFS(fQual,fCampaign,$A81) -> 42 | G81: =IFERROR(F81/E81,0) -> 0.10994764 | H81: =IF(COUNTIF(MetaCamps,$A81)=0,"n/a",IFERROR(C81/E81,0)) -> 471.59654 | I81: =IF(COUNTIF(MetaCamps,$A81)=0,"n/a",IFERROR(C81/F81,0)) -> 4289.2829 | J81: =IFERROR(SUMIFS(fContacted,fCampaign,$A81)/E81,0) -> 0.79842932
A82: E_Selva_Natuf_All_07072026 | B82: =IFERROR(INDEX(CampTypes,MATCH(A82,CampList,0)),"") -> Old | C82: =IF(COUNTIF(MetaCamps,$A82)=0,"n/a",SUMIFS(fSpend,fCampaign,$A82)) -> 80349.25 | D82: =SUMIFS(fMeta,fCampaign,$A82) -> 71 | E82: =SUMIFS(fLeads,fCampaign,$A82) -> 46 | F82: =SUMIFS(fQual,fCampaign,$A82) -> 14 | G82: =IFERROR(F82/E82,0) -> 0.30434783 | H82: =IF(COUNTIF(MetaCamps,$A82)=0,"n/a",IFERROR(C82/E82,0)) -> 1746.7228 | I82: =IF(COUNTIF(MetaCamps,$A82)=0,"n/a",IFERROR(C82/F82,0)) -> 5739.2321 | J82: =IFERROR(SUMIFS(fContacted,fCampaign,$A82)/E82,0) -> 1
A83: E_Natuf_MF_05092026 | B83: =IFERROR(INDEX(CampTypes,MATCH(A83,CampList,0)),"") -> Old | C83: =IF(COUNTIF(MetaCamps,$A83)=0,"n/a",SUMIFS(fSpend,fCampaign,$A83)) -> 79772.24 | D83: =SUMIFS(fMeta,fCampaign,$A83) -> 30 | E83: =SUMIFS(fLeads,fCampaign,$A83) -> 26 | F83: =SUMIFS(fQual,fCampaign,$A83) -> 1 | G83: =IFERROR(F83/E83,0) -> 0.038461538 | H83: =IF(COUNTIF(MetaCamps,$A83)=0,"n/a",IFERROR(C83/E83,0)) -> 3068.1631 | I83: =IF(COUNTIF(MetaCamps,$A83)=0,"n/a",IFERROR(C83/F83,0)) -> 79772.24 | J83: =IFERROR(SUMIFS(fContacted,fCampaign,$A83)/E83,0) -> 0.92307692
A84: E_Natuf_Generic_09092026 | B84: =IFERROR(INDEX(CampTypes,MATCH(A84,CampList,0)),"") -> Old | C84: =IF(COUNTIF(MetaCamps,$A84)=0,"n/a",SUMIFS(fSpend,fCampaign,$A84)) -> 71194.81 | D84: =SUMIFS(fMeta,fCampaign,$A84) -> 77 | E84: =SUMIFS(fLeads,fCampaign,$A84) -> 8 | F84: =SUMIFS(fQual,fCampaign,$A84) -> 2 | G84: =IFERROR(F84/E84,0) -> 0.25 | H84: =IF(COUNTIF(MetaCamps,$A84)=0,"n/a",IFERROR(C84/E84,0)) -> 8899.3512 | I84: =IF(COUNTIF(MetaCamps,$A84)=0,"n/a",IFERROR(C84/F84,0)) -> 35597.405 | J84: =IFERROR(SUMIFS(fContacted,fCampaign,$A84)/E84,0) -> 1
A85: E_Karan_Natuf_Kiosk_07072026 | B85: =IFERROR(INDEX(CampTypes,MATCH(A85,CampList,0)),"") -> Old | C85: =IF(COUNTIF(MetaCamps,$A85)=0,"n/a",SUMIFS(fSpend,fCampaign,$A85)) -> 54540.16 | D85: =SUMIFS(fMeta,fCampaign,$A85) -> 30 | E85: =SUMIFS(fLeads,fCampaign,$A85) -> 24 | F85: =SUMIFS(fQual,fCampaign,$A85) -> 6 | G85: =IFERROR(F85/E85,0) -> 0.25 | H85: =IF(COUNTIF(MetaCamps,$A85)=0,"n/a",IFERROR(C85/E85,0)) -> 2272.5067 | I85: =IF(COUNTIF(MetaCamps,$A85)=0,"n/a",IFERROR(C85/F85,0)) -> 9090.0267 | J85: =IFERROR(SUMIFS(fContacted,fCampaign,$A85)/E85,0) -> 0.625
A86: E_Natuf_Foco_10092026 | B86: =IFERROR(INDEX(CampTypes,MATCH(A86,CampList,0)),"") -> Old | C86: =IF(COUNTIF(MetaCamps,$A86)=0,"n/a",SUMIFS(fSpend,fCampaign,$A86)) -> 46413.52 | D86: =SUMIFS(fMeta,fCampaign,$A86) -> 40 | E86: =SUMIFS(fLeads,fCampaign,$A86) -> 32 | F86: =SUMIFS(fQual,fCampaign,$A86) -> 7 | G86: =IFERROR(F86/E86,0) -> 0.21875 | H86: =IF(COUNTIF(MetaCamps,$A86)=0,"n/a",IFERROR(C86/E86,0)) -> 1450.4225 | I86: =IF(COUNTIF(MetaCamps,$A86)=0,"n/a",IFERROR(C86/F86,0)) -> 6630.5029 | J86: =IFERROR(SUMIFS(fContacted,fCampaign,$A86)/E86,0) -> 1
A87: E_Natuf_Amazon_29092026 | B87: =IFERROR(INDEX(CampTypes,MATCH(A87,CampList,0)),"") -> Old | C87: =IF(COUNTIF(MetaCamps,$A87)=0,"n/a",SUMIFS(fSpend,fCampaign,$A87)) -> 39121.71 | D87: =SUMIFS(fMeta,fCampaign,$A87) -> 22 | E87: =SUMIFS(fLeads,fCampaign,$A87) -> 15 | F87: =SUMIFS(fQual,fCampaign,$A87) -> 6 | G87: =IFERROR(F87/E87,0) -> 0.4 | H87: =IF(COUNTIF(MetaCamps,$A87)=0,"n/a",IFERROR(C87/E87,0)) -> 2608.114 | I87: =IF(COUNTIF(MetaCamps,$A87)=0,"n/a",IFERROR(C87/F87,0)) -> 6520.285 | J87: =IFERROR(SUMIFS(fContacted,fCampaign,$A87)/E87,0) -> 1
A88: E_Natuf_Web_23092026 | B88: =IFERROR(INDEX(CampTypes,MATCH(A88,CampList,0)),"") -> Old | C88: =IF(COUNTIF(MetaCamps,$A88)=0,"n/a",SUMIFS(fSpend,fCampaign,$A88)) -> 6412.86 | D88: =SUMIFS(fMeta,fCampaign,$A88) -> 0 | E88: =SUMIFS(fLeads,fCampaign,$A88) -> 0 | F88: =SUMIFS(fQual,fCampaign,$A88) -> 0 | G88: =IFERROR(F88/E88,0) -> 0 | H88: =IF(COUNTIF(MetaCamps,$A88)=0,"n/a",IFERROR(C88/E88,0)) -> 0 | I88: =IF(COUNTIF(MetaCamps,$A88)=0,"n/a",IFERROR(C88/F88,0)) -> 0 | J88: =IFERROR(SUMIFS(fContacted,fCampaign,$A88)/E88,0) -> 0
A89: ABO | Natuf | Leads | Unit Franchise | India | Oct26 | V1 | B89: =IFERROR(INDEX(CampTypes,MATCH(A89,CampList,0)),"") -> New | C89: =IF(COUNTIF(MetaCamps,$A89)=0,"n/a",SUMIFS(fSpend,fCampaign,$A89)) -> 264151.59 | D89: =SUMIFS(fMeta,fCampaign,$A89) -> 2102 | E89: =SUMIFS(fLeads,fCampaign,$A89) -> 817 | F89: =SUMIFS(fQual,fCampaign,$A89) -> 149 | G89: =IFERROR(F89/E89,0) -> 0.18237454 | H89: =IF(COUNTIF(MetaCamps,$A89)=0,"n/a",IFERROR(C89/E89,0)) -> 323.31896 | I89: =IF(COUNTIF(MetaCamps,$A89)=0,"n/a",IFERROR(C89/F89,0)) -> 1772.8295 | J89: =IFERROR(SUMIFS(fContacted,fCampaign,$A89)/E89,0) -> 0.71481028
... A94: EBG - In House | ABO | Natuf | Leads | Master Franchise | India | Oct26 | V1 | B94: =IFERROR(INDEX(CampTypes,MATCH(A94,CampList,0)),"") -> New | C94: =IF(COUNTIF(MetaCamps,$A94)=0,"n/a",SUMIFS(fSpend,fCampaign,$A94)) -> n/a | D94: =SUMIFS(fMeta,fCampaign,$A94) -> 0 | E94: =SUMIFS(fLeads,fCampaign,$A94) -> 42 | F94: =SUMIFS(fQual,fCampaign,$A94) -> 0 | G94: =IFERROR(F94/E94,0) -> 0 | H94: =IF(COUNTIF(MetaCamps,$A94)=0,"n/a",IFERROR(C94/E94,0)) -> n/a | I94: =IF(COUNTIF(MetaCamps,$A94)=0,"n/a",IFERROR(C94/F94,0)) -> n/a | J94: =IFERROR(SUMIFS(fContacted,fCampaign,$A94)/E94,0) -> 0.83333333
A95: TOTAL | C95: =SUM(C78:C94) -> 1647106.2 | D95: =SUM(D78:D94) -> 4158 | E95: =SUM(E78:E94) -> 3627 | F95: =SUM(F78:F94) -> 558 | G95: =IFERROR(F95/E95,0) -> 0.15384615 | H95: =IFERROR(C95/SUM(fCLeads),0) -> 732.04722 | I95: =IFERROR(C95/SUM(fCQual),0) -> 4537.4828 | J95: =IFERROR(SUM(fContacted)/E95,0) -> 0.84036394
A96: Note: "n/a" = campaign not present in the Meta exports (EBG - In House ad account): its leads/quality are counted, its spend is unknown. Total CPL / CPQL divide total spend by the leads / quality leads of campaigns that have spend data. Web landing-page campaigns report page views, not leads.
A99: Chart data (linked to the tables above) | B99: Old | C99: New
A100: Contacted % | B100: =B27 -> 0.8233463 | C100: =C27 -> 0.84970111
A101: Quality % (of leads) | B101: =B31 -> 0.16108949 | C101: =C31 -> 0.1498719
A102: Quality % of contacted | B102: =B32 -> 0.19565217 | C102: =C32 -> 0.17638191
A103: Lost % | B103: =B35 -> 0.18910506 | C103: =C35 -> 0.15798463
A105: Cost metrics (INR) | B105: Old | C105: New
A106: Cost per lead (CPL) | B106: =B25 -> 1012.8765 | C106: =C25 -> 358.0932
A107: Cost per quality lead (CPQL) | B107: =B33 -> 6287.6633 | C107: =C33 -> 2215.1278

Sheet Reconciliation
A1: Reconciliation & Data Integrity Checks
A2: Source figures are computed directly from the raw files provided (pandas, independent of the workbook); report figures are live formulas on the workbook tabs. Status = OK when difference is zero.
A4: # | B4: Check | C4: Source file value | D4: Report value | E4: Difference | F4: Status | G4: Comment
A5: 1 | B5: CRM rows in LeadData_October2026.csv (all brands) = duplicate rows + in-scope + excluded + cross-brand + other-brand records | C5: 28939 | D5: =2+COUNTA(Lead_Data!A2:A3628)+COUNTA(Excluded_Leads!A2:A36)+COUNTA(XBrand_Leads!A2:A58)+25218 -> 28939 | E5: =ROUND(D5-C5,2) -> 0 | F5: =IF(ABS(E5)<=0.005,"OK","SEE NOTE") -> OK | G5: 28,939 rows: 2 duplicate Lead id rows removed + 3,627 Natuf-campaign leads + 35 excluded Natuf-brand rows + 57 cross-brand + 25,218 other-brand records
A6: 2 | B6: In-scope leads = Old + New + Unattributed | C6: 3627 | D6: =COUNTIF(ldType,"Old")+COUNTIF(ldType,"New")+COUNTIF(ldType,"Unattributed") -> 3627 | E6: =ROUND(D6-C6,2) -> 0 | F6: =IF(ABS(E6)<=0.005,"OK","SEE NOTE") -> OK | G6: Every in-scope lead is classified
A7: 3 | B7: Fact_Data lead rows = Lead_Data rows | C7: 3627 | D7: =COUNTIF(fRT,"Lead") -> 3627 | E7: =ROUND(D7-C7,2) -> 0 | F7: =IF(ABS(E7)<=0.005,"OK","SEE NOTE") -> OK | G7: Pivot source table vs lead list
A8: 4 | B8: Fact_Data quality leads = Lead_Data quality leads | C8: 558 | D8: =COUNTIF(ldQual,"Quality Lead") -> 558 | E8: =ROUND(D8-C8,2) -> 0 | F8: =IF(ABS(E8)<=0.005,"OK","SEE NOTE") -> OK | G8: Quality = status in the Settings list
A9: 5 | B9: Quality-status records among all Natuf-brand rows in the CRM file = in-scope + excluded | C9: 558 | D9: =COUNTIF(ldQual,"Quality Lead")+COUNTIF(Excluded_Leads!H2:H36,"Yes") -> 558 | E9: =ROUND(D9-C9,2) -> 0 | F9: =IF(ABS(E9)<=0.005,"OK","SEE NOTE") -> OK | G9: Every quality record of the brand is accounted for
A10: 6 | B10: Leads with no campaign tag kept as Unattributed | C10: 0 | D10: =COUNTIF(ldType,"Unattributed") -> 0 | E10: =ROUND(D10-C10,2) -> 0 | F10: =IF(ABS(E10)<=0.005,"OK","SEE NOTE") -> OK | G10: Paid / WhatsApp-API leads with campaign blank - shown as Unattributed, not forced into Old/New
A11: 7 | B11: Bulk / manual (Excel) uploads with no campaign - excluded | C11: 34 | D11: =COUNTIF(Excluded_Leads!I2:I36,"No campaign*") -> 34 | E11: =ROUND(D11-C11,2) -> 0 | F11: =IF(ABS(E11)<=0.005,"OK","SEE NOTE") -> OK | G11: Not campaign leads (lead source = Excel)
A12: 8 | B12: Ad spend: campaign file total (INR) | C12: 1647106.2 | D12: =SUM(fSpend) -> 1647106.2 | E12: =ROUND(D12-C12,2) -> 0 | F12: =IF(ABS(E12)<=0.005,"OK","SEE NOTE") -> OK | G12: Fact_Data spend rows (one per campaign) sum to the Meta campaign file
A13: 9 | B13: Ad spend: ad-set file total (INR) | C13: 1647106.2 | D13: =SUM(fSpend) -> 1647106.2 | E13: =ROUND(D13-C13,2) -> 0 | F13: =IF(ABS(E13)<=0.005,"OK","SEE NOTE") -> OK | G13: Campaign file = ad-set file = report
A14: 10 | B14: Ad spend: sum of ad sets mapped to campaigns vs campaign file (Campaign_Master total difference) | C14: 0 | D14: =Campaign_Master!J34 -> 0 | E14: =ROUND(D14-C14,2) -> 0 | F14: =IF(ABS(E14)<=0.005,"OK","SEE NOTE") -> OK | G14: Inferred ad-set to campaign mapping reproduces every campaign total exactly (spend, impressions, results)
A15: 11 | B15: Impressions: campaign file total | C15: 4126874 | D15: =SUM(fImpr) -> 4126874 | E15: =ROUND(D15-C15,2) -> 0 | F15: =IF(ABS(E15)<=0.005,"OK","SEE NOTE") -> OK
A16: 12 | B16: Link clicks: campaign file total | C16: 34205 | D16: =SUM(fClicks) -> 34205 | E16: =ROUND(D16-C16,2) -> 0 | F16: =IF(ABS(E16)<=0.005,"OK","SEE NOTE") -> OK | G16: Report uses campaign-file clicks (the ad-set export sums to 0 more in places)
A17: 13 | B17: Meta lead-type results (campaign file, excl. landing-page-view campaigns) | C17: 4158 | D17: =SUM(fMeta) -> 4158 | E17: =ROUND(D17-C17,2) -> 0 | F17: =IF(ABS(E17)<=0.005,"OK","SEE NOTE") -> OK | G17: Web campaigns report landing page views, not leads
A18: 14 | B18: Ad-level file spend (INR) vs campaign file | C18: 1647106.2 | D18: 1641571.9 | E18: =ROUND(D18-C18,2) -> -5534.4 | F18: INFO | G18: Ad-level export may miss deleted / archived ads and repeats ad names across ad sets - ad-level spend is NOT used; spend is reported at campaign level
A19: 15 | B19: Dashboard grand-total leads = Lead_Data leads | C19: 3627 | D19: ='Master Dashboard'!E54 -> 3627 | E19: =ROUND(D19-C19,2) -> 0 | F19: =IF(ABS(E19)<=0.005,"OK","SEE NOTE") -> OK | G19: Dashboard ties to the lead list
A20: 16 | B20: Leads created outside the reporting window (01-Oct to 31-Oct) | C20: 0 | D20: =COUNTIF(ldDate,"<"&WinStart)+COUNTIF(ldDate,">"&WinEnd) -> 0 | E20: =ROUND(D20-C20,2) -> 0 | F20: =IF(ABS(E20)<=0.005,"OK","SEE NOTE") -> OK | G20: Lead export covers exactly the window
A21: 17 | B21: Natuf-campaign leads tagged to OTHER brands in CRM (listed, not counted) | C21: 57 | D21: =COUNTA(XBrand_Leads!A2:A58) -> 57 | E21: =ROUND(D21-C21,2) -> 0 | F21: =IF(ABS(E21)<=0.005,"OK","SEE NOTE") -> OK | G21: Reported separately on XBrand_Leads; their status belongs to another brand pipeline
A23: LEAD FLOW - from raw file to report
B24: Rows in LeadData_October2026.csv (all brands) | C24: 28939
B25: less: duplicate Lead id rows (same lead exported twice) | C25: 2
B26: less: other brands' records (not a Natuf brand and not on a Natuf campaign) | C26: 25218
B27: less: Natuf-brand rows excluded (bulk upload / other-brand campaign) | C27: 35
B28: less: Natuf-campaign leads tagged to other brands (XBrand_Leads) | C28: 57
B29: Natuf-campaign leads used in the report (total) | C29: 3627
B30: of which Old campaigns | C30: 1285
B31: of which New campaigns | C31: 2342
B32: of which Unattributed | C32: 0
B33: memo: New-campaign leads from EBG - In House campaigns (no Meta spend data) | C33: 1377
B35: No separate Lead Center export was supplied for this period; LeadData_October2026.csv (CRM export, one row per Lead id) is the single lead source. The previous reports' Lead Center reconciliation and Performance-Report cross-checks are therefore not repeated.

Sheet Notes
B1: Notes, Definitions & Assumptions - Natuf
B3: HOW TO READ THIS WORKBOOK
B4: • Master Dashboard: the one-page management view (formula-driven): Old vs New headline KPIs, quality parameters, and a campaign-wise table with type, spend, leads, quality count, quality %, CPL and CPQL. Master Pivot: real PivotTables + slicers (Campaign Type, Campaign, Lead Status, Month, Week) plus the Campaign x Quality Parameter table at the bottom. Meta spend cannot be split by status / month / week, so spend shows as "-" when those slicers are used.
B5: • Executive Summary: takeaways, Old-vs-New KPI table, status funnel, same-age cohort and campaign scorecard - all live formulas.
B6: • Reconciliation: every figure tied back to the raw files. Campaign_Master: Old/New classification (editable). Data tabs: Fact_Data (pivot source), Lead_Data, Excluded_Leads, XBrand_Leads, Meta_* (raw Meta exports), Settings.
B7: DEFINITIONS
B8: • Quality Lead = lead whose CRM Status is one of: Won, Token Received, Qualified, Meeting Scheduled, Meeting Conducted, Follow-Up, Details Shared (editable on Settings). "Meeting Conducted but NOT QUALIFIED" is not a quality status.
B9: • Old / New: a campaign is NEW if its name carries 'Oct26' - the new October-2026 campaign structure (ABO campaigns in the Kustard ad account and the 'EBG - In House ... Oct26' campaigns in the In-House ad account). Every other campaign is Old. Editable on Campaign_Master.
B10: • CRM leads = lead records in the CRM (one row per Lead id). Contacted = status other than "New Lead". Quality % = Quality leads / CRM leads. CPL = ad spend / CRM leads. CPQL = ad spend / Quality leads.
B11: • Meta results = instant-form leads (leadgen) plus WhatsApp conversations started. Web landing-page campaigns report landing page views (not leads) - excluded from results but their spend is included in spend.
B12: DATA TREATMENT & FINDINGS
B13: • REPORTING WINDOW: the Meta exports (campaigns, ad sets, ads) and LeadData_October2026.csv cover 01-Oct-2026 to 31-Oct-2026 only (the CRM export was taken on 31-Oct, last lead created 31-Oct 12:56). September is not in the supplied files, so this report compares Old vs New on October data; it is not cumulative with the earlier 01-Sep to 18-Oct report.
... B23: • Phone numbers are masked and names / e-mails are not included in this workbook.

Sheet Campaign_Master
A1: Campaign | B1: Campaign Type (EDITABLE: Old / New) | C1: Basis for classification | D1: Meta delivery | E1: Result type | F1: Budget (INR/day) | G1: Earliest ad-set start | H1: Spend - campaign file (INR) | I1: Spend - sum of ad sets (INR) | J1: Difference | K1: CRM leads (in report) | L1: Quality leads | M1: Spend data
A2: GenY-Natuf-LeadGen-10032026 | B2: Old | C2: Old: all campaigns other than the Oct26 campaigns are Old | D2: inactive | F2: ad set budget | H2: =SUMIFS(Meta_Campaigns!$G$2:$G$29,Meta_Campaigns!$A$2:$A$29,A2) -> 0 | I2: =SUMIFS(Meta_AdSets!$G$2:$G$93,Meta_AdSets!$B$2:$B$93,A2) -> 0 | J2: =ROUND(H2-I2,2) -> 0 | K2: =SUMIFS(fLeads,fCampaign,A2) -> 0 | L2: =SUMIFS(fQual,fCampaign,A2) -> 0 | M2: =IF(COUNTIF(MetaCamps,A2)>0,"In Meta export","NOT in Meta export (spend n/a)") -> In Meta export
A3: E_Karan_Natuf_Kiosk_07072026 | B3: Old | C3: Old: all campaigns other than the Oct26 campaigns are Old | D3: inactive | E3: leadgen.other | F3: 5000 | G3: 46210 | H3: =SUMIFS(Meta_Campaigns!$G$2:$G$29,Meta_Campaigns!$A$2:$A$29,A3) -> 54540.16 | I3: =SUMIFS(Meta_AdSets!$G$2:$G$93,Meta_AdSets!$B$2:$B$93,A3) -> 54540.16 | J3: =ROUND(H3-I3,2) -> 0 | K3: =SUMIFS(fLeads,fCampaign,A3) -> 24 | L3: =SUMIFS(fQual,fCampaign,A3) -> 6 | M3: =IF(COUNTIF(MetaCamps,A3)>0,"In Meta export","NOT in Meta export (spend n/a)") -> In Meta export
A4: E_Suresh_Natuf_Kiosk_07072026 | B4: Old | C4: Old: all campaigns other than the Oct26 campaigns are Old | D4: inactive | E4: leadgen.other | F4: 10000 | G4: 46211 | H4: =SUMIFS(Meta_Campaigns!$G$2:$G$29,Meta_Campaigns!$A$2:$A$29,A4) -> 232416.42 | I4: =SUMIFS(Meta_AdSets!$G$2:$G$93,Meta_AdSets!$B$2:$B$93,A4) -> 232416.42 | J4: =ROUND(H4-I4,2) -> 0 | K4: =SUMIFS(fLeads,fCampaign,A4) -> 313 | L4: =SUMIFS(fQual,fCampaign,A4) -> 68 | M4: =IF(COUNTIF(MetaCamps,A4)>0,"In Meta export","NOT in Meta export (spend n/a)") -> In Meta export
A5: E_Aryan_Natuf_Kiosk_07072026 | B5: Old | C5: Old: all campaigns other than the Oct26 campaigns are Old | D5: inactive | F5: 12000 | H5: =SUMIFS(Meta_Campaigns!$G$2:$G$29,Meta_Campaigns!$A$2:$A$29,A5) -> 0 | I5: =SUMIFS(Meta_AdSets!$G$2:$G$93,Meta_AdSets!$B$2:$B$93,A5) -> 0 | J5: =ROUND(H5-I5,2) -> 0 | K5: =SUMIFS(fLeads,fCampaign,A5) -> 0 | L5: =SUMIFS(fQual,fCampaign,A5) -> 0 | M5: =IF(COUNTIF(MetaCamps,A5)>0,"In Meta export","NOT in Meta export (spend n/a)") -> In Meta export
A6: E_Selva_Natuf_Kiosk_07072026 | B6: Old | C6: Old: all campaigns other than the Oct26 campaigns are Old | D6: inactive | F6: 3000 | H6: =SUMIFS(Meta_Campaigns!$G$2:$G$29,Meta_Campaigns!$A$2:$A$29,A6) -> 0 | I6: =SUMIFS(Meta_AdSets!$G$2:$G$93,Meta_AdSets!$B$2:$B$93,A6) -> 0 | J6: =ROUND(H6-I6,2) -> 0 | K6: =SUMIFS(fLeads,fCampaign,A6) -> 0 | L6: =SUMIFS(fQual,fCampaign,A6) -> 0 | M6: =IF(COUNTIF(MetaCamps,A6)>0,"In Meta export","NOT in Meta export (spend n/a)") -> In Meta export
A7: E_Karan_Natuf_All_07072026 | B7: Old | C7: Old: all campaigns other than the Oct26 campaigns are Old | D7: inactive | E7: leadgen.other | F7: 15000 | G7: 46210 | H7: =SUMIFS(Meta_Campaigns!$G$2:$G$29,Meta_Campaigns!$A$2:$A$29,A7) -> 277596.99 | I7: =SUMIFS(Meta_AdSets!$G$2:$G$93,Meta_AdSets!$B$2:$B$93,A7) -> 277596.99 | J7: =ROUND(H7-I7,2) -> 0 | K7: =SUMIFS(fLeads,fCampaign,A7) -> 229 | L7: =SUMIFS(fQual,fCampaign,A7) -> 21 | M7: =IF(COUNTIF(MetaCamps,A7)>0,"In Meta export","NOT in Meta export (spend n/a)") -> In Meta export
A8: E_Aryan_Natuf_All_07072026 | B8: Old | C8: Old: all campaigns other than the Oct26 campaigns are Old | D8: inactive | F8: 5000 | H8: =SUMIFS(Meta_Campaigns!$G$2:$G$29,Meta_Campaigns!$A$2:$A$29,A8) -> 0 | I8: =SUMIFS(Meta_AdSets!$G$2:$G$93,Meta_AdSets!$B$2:$B$93,A8) -> 0 | J8: =ROUND(H8-I8,2) -> 0 | K8: =SUMIFS(fLeads,fCampaign,A8) -> 0 | L8: =SUMIFS(fQual,fCampaign,A8) -> 0 | M8: =IF(COUNTIF(MetaCamps,A8)>0,"In Meta export","NOT in Meta export (spend n/a)") -> In Meta export
A9: E_Selva_Natuf_All_07072026 | B9: Old | C9: Old: all campaigns other than the Oct26 campaigns are Old | D9: inactive | E9: leadgen.other | F9: 10000 | G9: 46211 | H9: =SUMIFS(Meta_Campaigns!$G$2:$G$29,Meta_Campaigns!$A$2:$A$29,A9) -> 80349.25 | I9: =SUMIFS(Meta_AdSets!$G$2:$G$93,Meta_AdSets!$B$2:$B$93,A9) -> 80349.25 | J9: =ROUND(H9-I9,2) -> 0 | K9: =SUMIFS(fLeads,fCampaign,A9) -> 46 | L9: =SUMIFS(fQual,fCampaign,A9) -> 14 | M9: =IF(COUNTIF(MetaCamps,A9)>0,"In Meta export","NOT in Meta export (spend n/a)") -> In Meta export
A10: E_Suresh_Natuf_All_07072026 | B10: Old | C10: Old: all campaigns other than the Oct26 campaigns are Old | D10: inactive | F10: 3000 | H10: =SUMIFS(Meta_Campaigns!$G$2:$G$29,Meta_Campaigns!$A$2:$A$29,A10) -> 0 | I10: =SUMIFS(Meta_AdSets!$G$2:$G$93,Meta_AdSets!$B$2:$B$93,A10) -> 0 | J10: =ROUND(H10-I10,2) -> 0 | K10: =SUMIFS(fLeads,fCampaign,A10) -> 0 | L10: =SUMIFS(fQual,fCampaign,A10) -> 0 | M10: =IF(COUNTIF(MetaCamps,A10)>0,"In Meta export","NOT in Meta export (spend n/a)") -> In Meta export
A11: E_Natuf_Kiosk_07072026- WC-Priyanka | B11: Old | C11: Old: all campaigns other than the Oct26 campaigns are Old | D11: inactive | F11: 2000 | H11: =SUMIFS(Meta_Campaigns!$G$2:$G$29,Meta_Campaigns!$A$2:$A$29,A11) -> 0 | I11: =SUMIFS(Meta_AdSets!$G$2:$G$93,Meta_AdSets!$B$2:$B$93,A11) -> 0 | J11: =ROUND(H11-I11,2) -> 0 | K11: =SUMIFS(fLeads,fCampaign,A11) -> 0 | L11: =SUMIFS(fQual,fCampaign,A11) -> 0 | M11: =IF(COUNTIF(MetaCamps,A11)>0,"In Meta export","NOT in Meta export (spend n/a)") -> In Meta export
A12: natuf_Kiosk_14072026_Hindi | B12: Old | C12: Old: all campaigns other than the Oct26 campaigns are Old | D12: inactive | E12: leadgen.other | F12: 10000 | G12: 46217 | H12: =SUMIFS(Meta_Campaigns!$G$2:$G$29,Meta_Campaigns!$A$2:$A$29,A12) -> 180149.88 | I12: =SUMIFS(Meta_AdSets!$G$2:$G$93,Meta_AdSets!$B$2:$B$93,A12) -> 180149.88 | J12: =ROUND(H12-I12,2) -> 0 | K12: =SUMIFS(fLeads,fCampaign,A12) -> 382 | L12: =SUMIFS(fQual,fCampaign,A12) -> 42 | M12: =IF(COUNTIF(MetaCamps,A12)>0,"In Meta export","NOT in Meta export (spend n/a)") -> In Meta export
A13: natuf_Kiosk_14072026 – WC | B13: Old | C13: Old: all campaigns other than the Oct26 campaigns are Old | D13: inactive | F13: 1000 | H13: =SUMIFS(Meta_Campaigns!$G$2:$G$29,Meta_Campaigns!$A$2:$A$29,A13) -> 0 | I13: =SUMIFS(Meta_AdSets!$G$2:$G$93,Meta_AdSets!$B$2:$B$93,A13) -> 0 | J13: =ROUND(H13-I13,2) -> 0 | K13: =SUMIFS(fLeads,fCampaign,A13) -> 0 | L13: =SUMIFS(fQual,fCampaign,A13) -> 0 | M13: =IF(COUNTIF(MetaCamps,A13)>0,"In Meta export","NOT in Meta export (spend n/a)") -> In Meta export
A14: E_Natuf_Kiosk_07072026- WC – Telugu | B14: Old | C14: Old: all campaigns other than the Oct26 campaigns are Old | D14: inactive | F14: 1000 | H14: =SUMIFS(Meta_Campaigns!$G$2:$G$29,Meta_Campaigns!$A$2:$A$29,A14) -> 0 | I14: =SUMIFS(Meta_AdSets!$G$2:$G$93,Meta_AdSets!$B$2:$B$93,A14) -> 0 | J14: =ROUND(H14-I14,2) -> 0 | K14: =SUMIFS(fLeads,fCampaign,A14) -> 0 | L14: =SUMIFS(fQual,fCampaign,A14) -> 0 | M14: =IF(COUNTIF(MetaCamps,A14)>0,"In Meta export","NOT in Meta export (spend n/a)") -> In Meta export
A15: Natuf_Carpo_Gift_Usha | B15: Old | C15: Old: all campaigns other than the Oct26 campaigns are Old | D15: inactive | F15: 2000 | H15: =SUMIFS(Meta_Campaigns!$G$2:$G$29,Meta_Campaigns!$A$2:$A$29,A15) -> 0 | I15: =SUMIFS(Meta_AdSets!$G$2:$G$93,Meta_AdSets!$B$2:$B$93,A15) -> 0 | J15: =ROUND(H15-I15,2) -> 0 | K15: =SUMIFS(fLeads,fCampaign,A15) -> 0 | L15: =SUMIFS(fQual,fCampaign,A15) -> 0 | M15: =IF(COUNTIF(MetaCamps,A15)>0,"In Meta export","NOT in Meta export (spend n/a)") -> In Meta export
A16: E_Natuf_Kiosk_10082026 | B16: Old | C16: Old: all campaigns other than the Oct26 campaigns are Old | D16: inactive | F16: 5000 | H16: =SUMIFS(Meta_Campaigns!$G$2:$G$29,Meta_Campaigns!$A$2:$A$29,A16) -> 0 | I16: =SUMIFS(Meta_AdSets!$G$2:$G$93,Meta_AdSets!$B$2:$B$93,A16) -> 0 | J16: =ROUND(H16-I16,2) -> 0 | K16: =SUMIFS(fLeads,fCampaign,A16) -> 0 | L16: =SUMIFS(fQual,fCampaign,A16) -> 0 | M16: =IF(COUNTIF(MetaCamps,A16)>0,"In Meta export","NOT in Meta export (spend n/a)") -> In Meta export
A17: E_Natuf_Generic_13082026 | B17: Old | C17: Old: all campaigns other than the Oct26 campaigns are Old | D17: inactive | E17: leadgen.other | F17: ad set budget | G17: 46247 | H17: =SUMIFS(Meta_Campaigns!$G$2:$G$29,Meta_Campaigns!$A$2:$A$29,A17) -> 233578.47 | I17: =SUMIFS(Meta_AdSets!$G$2:$G$93,Meta_AdSets!$B$2:$B$93,A17) -> 233578.47 | J17: =ROUND(H17-I17,2) -> 0 | K17: =SUMIFS(fLeads,fCampaign,A17) -> 210 | L17: =SUMIFS(fQual,fCampaign,A17) -> 40 | M17: =IF(COUNTIF(MetaCamps,A17)>0,"In Meta export","NOT in Meta export (spend n/a)") -> In Meta export
A18: E_Natuf_MF_05092026 | B18: Old | C18: Old: all campaigns other than the Oct26 campaigns are Old | D18: inactive | E18: leadgen.other | F18: 5000 | G18: 46270 | H18: =SUMIFS(Meta_Campaigns!$G$2:$G$29,Meta_Campaigns!$A$2:$A$29,A18) -> 79772.24 | I18: =SUMIFS(Meta_AdSets!$G$2:$G$93,Meta_AdSets!$B$2:$B$93,A18) -> 79772.24 | J18: =ROUND(H18-I18,2) -> 0 | K18: =SUMIFS(fLeads,fCampaign,A18) -> 26 | L18: =SUMIFS(fQual,fCampaign,A18) -> 1 | M18: =IF(COUNTIF(MetaCamps,A18)>0,"In Meta export","NOT in Meta export (spend n/a)") -> In Meta export
A19: E_Natuf_Generic_09092026 | B19: Old | C19: Old: all campaigns other than the Oct26 campaigns are Old | D19: inactive | E19: leadgen.other | F19: ad set budget | G19: 46275 | H19: =SUMIFS(Meta_Campaigns!$G$2:$G$29,Meta_Campaigns!$A$2:$A$29,A19) -> 71194.81 | I19: =SUMIFS(Meta_AdSets!$G$2:$G$93,Meta_AdSets!$B$2:$B$93,A19) -> 71194.81 | J19: =ROUND(H19-I19,2) -> 0 | K19: =SUMIFS(fLeads,fCampaign,A19) -> 8 | L19: =SUMIFS(fQual,fCampaign,A19) -> 2 | M19: =IF(COUNTIF(MetaCamps,A19)>0,"In Meta export","NOT in Meta export (spend n/a)") -> In Meta export
A20: E_Natuf_Foco_10092026 | B20: Old | C20: Old: all campaigns other than the Oct26 campaigns are Old | D20: inactive | E20: leadgen.other | F20: ad set budget | G20: 46276 | H20: =SUMIFS(Meta_Campaigns!$G$2:$G$29,Meta_Campaigns!$A$2:$A$29,A20) -> 46413.52 | I20: =SUMIFS(Meta_AdSets!$G$2:$G$93,Meta_AdSets!$B$2:$B$93,A20) -> 46413.52 | J20: =ROUND(H20-I20,2) -> 0 | K20: =SUMIFS(fLeads,fCampaign,A20) -> 32 | L20: =SUMIFS(fQual,fCampaign,A20) -> 7 | M20: =IF(COUNTIF(MetaCamps,A20)>0,"In Meta export","NOT in Meta export (spend n/a)") -> In Meta export
A21: E_Natuf_Web_23092026 | B21: Old | C21: Old: all campaigns other than the Oct26 campaigns are Old | D21: inactive | E21: omni_landing_page_view | F21: 500 | G21: 46288 | H21: =SUMIFS(Meta_Campaigns!$G$2:$G$29,Meta_Campaigns!$A$2:$A$29,A21) -> 6412.86 | I21: =SUMIFS(Meta_AdSets!$G$2:$G$93,Meta_AdSets!$B$2:$B$93,A21) -> 6412.86 | J21: =ROUND(H21-I21,2) -> 0 | K21: =SUMIFS(fLeads,fCampaign,A21) -> 0 | L21: =SUMIFS(fQual,fCampaign,A21) -> 0 | M21: =IF(COUNTIF(MetaCamps,A21)>0,"In Meta export","NOT in Meta export (spend n/a)") -> In Meta export
A22: E_Natuf_Amazon_29092026 | B22: Old | C22: Old: all campaigns other than the Oct26 campaigns are Old | D22: inactive | E22: leadgen.other | F22: 5000 | G22: 46294 | H22: =SUMIFS(Meta_Campaigns!$G$2:$G$29,Meta_Campaigns!$A$2:$A$29,A22) -> 39121.71 | I22: =SUMIFS(Meta_AdSets!$G$2:$G$93,Meta_AdSets!$B$2:$B$93,A22) -> 39121.71 | J22: =ROUND(H22-I22,2) -> 0 | K22: =SUMIFS(fLeads,fCampaign,A22) -> 15 | L22: =SUMIFS(fQual,fCampaign,A22) -> 6 | M22: =IF(COUNTIF(MetaCamps,A22)>0,"In Meta export","NOT in Meta export (spend n/a)") -> In Meta export
A23: ABO | Natuf | Leads | Unit Franchise | India | Oct26 | V1 | B23: New | C23: New: campaign name carries 'Oct26' (new Oct-2026 campaign structure, as defined by the business) | D23: active | E23: leadgen.other | F23: ad set budget | G23: 46303 | H23: =SUMIFS(Meta_Campaigns!$G$2:$G$29,Meta_Campaigns!$A$2:$A$29,A23) -> 264151.59 | I23: =SUMIFS(Meta_AdSets!$G$2:$G$93,Meta_AdSets!$B$2:$B$93,A23) -> 264151.59 | J23: =ROUND(H23-I23,2) -> 0 | K23: =SUMIFS(fLeads,fCampaign,A23) -> 817 | L23: =SUMIFS(fQual,fCampaign,A23) -> 149 | M23: =IF(COUNTIF(MetaCamps,A23)>0,"In Meta export","NOT in Meta export (spend n/a)") -> In Meta export
A24: EBG - In House | ABO | Natuf Website | Leads | Unit Franchise | India | Oct26 | V1 - Copy | B24: New | C24: New: campaign name carries 'Oct26' (new Oct-2026 campaign structure, as defined by the business) | D24: inactive | F24: ad set budget | H24: =SUMIFS(Meta_Campaigns!$G$2:$G$29,Meta_Campaigns!$A$2:$A$29,A24) -> 0 | I24: =SUMIFS(Meta_AdSets!$G$2:$G$93,Meta_AdSets!$B$2:$B$93,A24) -> 0 | J24: =ROUND(H24-I24,2) -> 0 | K24: =SUMIFS(fLeads,fCampaign,A24) -> 0 | L24: =SUMIFS(fQual,fCampaign,A24) -> 0 | M24: =IF(COUNTIF(MetaCamps,A24)>0,"In Meta export","NOT in Meta export (spend n/a)") -> In Meta export
A25: Natuf | ABO | WhatsApp | Unit Franchise | India | Oct26 | V1 | B25: New | C25: New: campaign name carries 'Oct26' (new Oct-2026 campaign structure, as defined by the business) | D25: active | E25: onsite_conversion.messaging_conversation_started_7d | F25: ad set budget | G25: 46312 | H25: =SUMIFS(Meta_Campaigns!$G$2:$G$29,Meta_Campaigns!$A$2:$A$29,A25) -> 25546.72 | I25: =SUMIFS(Meta_AdSets!$G$2:$G$93,Meta_AdSets!$B$2:$B$93,A25) -> 25546.72 | J25: =ROUND(H25-I25,2) -> 0 | K25: =SUMIFS(fLeads,fCampaign,A25) -> 0 | L25: =SUMIFS(fQual,fCampaign,A25) -> 0 | M25: =IF(COUNTIF(MetaCamps,A25)>0,"In Meta export","NOT in Meta export (spend n/a)") -> In Meta export
A26: ABO | Natuf | Leads | Master Franchise | India | Oct26 | V1 | B26: New | C26: New: campaign name carries 'Oct26' (new Oct-2026 campaign structure, as defined by the business) | D26: active | E26: leadgen.other | F26: ad set budget | G26: 46314 | H26: =SUMIFS(Meta_Campaigns!$G$2:$G$29,Meta_Campaigns!$A$2:$A$29,A26) -> 55861.63 | I26: =SUMIFS(Meta_AdSets!$G$2:$G$93,Meta_AdSets!$B$2:$B$93,A26) -> 55861.63 | J26: =ROUND(H26-I26,2) -> 0 | K26: =SUMIFS(fLeads,fCampaign,A26) -> 148 | L26: =SUMIFS(fQual,fCampaign,A26) -> 7 | M26: =IF(COUNTIF(MetaCamps,A26)>0,"In Meta export","NOT in Meta export (spend n/a)") -> In Meta export
A27: GenY-Natuf-LeadGen-09-04-26 | B27: Old | C27: Old: all campaigns other than the Oct26 campaigns are Old | D27: inactive | F27: ad set budget | H27: =SUMIFS(Meta_Campaigns!$G$2:$G$29,Meta_Campaigns!$A$2:$A$29,A27) -> 0 | I27: =SUMIFS(Meta_AdSets!$G$2:$G$93,Meta_AdSets!$B$2:$B$93,A27) -> 0 | J27: =ROUND(H27-I27,2) -> 0 | K27: =SUMIFS(fLeads,fCampaign,A27) -> 0 | L27: =SUMIFS(fQual,fCampaign,A27) -> 0 | M27: =IF(COUNTIF(MetaCamps,A27)>0,"In Meta export","NOT in Meta export (spend n/a)") -> In Meta export
A28: GenY-Natuf-LeadGen-09-04-26 –IF | B28: Old | C28: Old: all campaigns other than the Oct26 campaigns are Old | D28: inactive | F28: ad set budget | H28: =SUMIFS(Meta_Campaigns!$G$2:$G$29,Meta_Campaigns!$A$2:$A$29,A28) -> 0 | I28: =SUMIFS(Meta_AdSets!$G$2:$G$93,Meta_AdSets!$B$2:$B$93,A28) -> 0 | J28: =ROUND(H28-I28,2) -> 0 | K28: =SUMIFS(fLeads,fCampaign,A28) -> 0 | L28: =SUMIFS(fQual,fCampaign,A28) -> 0 | M28: =IF(COUNTIF(MetaCamps,A28)>0,"In Meta export","NOT in Meta export (spend n/a)") -> In Meta export
A29: GenY-Natuf-MasterFranchise-LeadGen-050526 | B29: Old | C29: Old: all campaigns other than the Oct26 campaigns are Old | D29: inactive | F29: ad set budget | H29: =SUMIFS(Meta_Campaigns!$G$2:$G$29,Meta_Campaigns!$A$2:$A$29,A29) -> 0 | I29: =SUMIFS(Meta_AdSets!$G$2:$G$93,Meta_AdSets!$B$2:$B$93,A29) -> 0 | J29: =ROUND(H29-I29,2) -> 0 | K29: =SUMIFS(fLeads,fCampaign,A29) -> 0 | L29: =SUMIFS(fQual,fCampaign,A29) -> 0 | M29: =IF(COUNTIF(MetaCamps,A29)>0,"In Meta export","NOT in Meta export (spend n/a)") -> In Meta export
A30: EBG - In House | ABO | Natuf | Leads | Master Franchise | India | Oct26 | V1 | B30: New | C30: New: campaign name carries 'Oct26' (new Oct-2026 campaign structure, as defined by the business) | D30: not in Meta export | H30: =SUMIFS(Meta_Campaigns!$G$2:$G$29,Meta_Campaigns!$A$2:$A$29,A30) -> 0 | I30: =SUMIFS(Meta_AdSets!$G$2:$G$93,Meta_AdSets!$B$2:$B$93,A30) -> 0 | J30: =ROUND(H30-I30,2) -> 0 | K30: =SUMIFS(fLeads,fCampaign,A30) -> 42 | L30: =SUMIFS(fQual,fCampaign,A30) -> 0 | M30: =IF(COUNTIF(MetaCamps,A30)>0,"In Meta export","NOT in Meta export (spend n/a)") -> NOT in Meta export (spend n/a)
A31: EBG - In House | ABO | Natuf | Leads | Unit Franchise | India | Oct26 | V1 | B31: New | C31: New: campaign name carries 'Oct26' (new Oct-2026 campaign structure, as defined by the business) | D31: not in Meta export | H31: =SUMIFS(Meta_Campaigns!$G$2:$G$29,Meta_Campaigns!$A$2:$A$29,A31) -> 0 | I31: =SUMIFS(Meta_AdSets!$G$2:$G$93,Meta_AdSets!$B$2:$B$93,A31) -> 0 | J31: =ROUND(H31-I31,2) -> 0 | K31: =SUMIFS(fLeads,fCampaign,A31) -> 1262 | L31: =SUMIFS(fQual,fCampaign,A31) -> 193 | M31: =IF(COUNTIF(MetaCamps,A31)>0,"In Meta export","NOT in Meta export (spend n/a)") -> NOT in Meta export (spend n/a)
A32: Natuf | In House | ABO | | WhatsApp | Unit Franchise | India | Oct26 | V1 | B32: New | C32: New: campaign name carries 'Oct26' (new Oct-2026 campaign structure, as defined by the business) | D32: not in Meta export | H32: =SUMIFS(Meta_Campaigns!$G$2:$G$29,Meta_Campaigns!$A$2:$A$29,A32) -> 0 | I32: =SUMIFS(Meta_AdSets!$G$2:$G$93,Meta_AdSets!$B$2:$B$93,A32) -> 0 | J32: =ROUND(H32-I32,2) -> 0 | K32: =SUMIFS(fLeads,fCampaign,A32) -> 73 | L32: =SUMIFS(fQual,fCampaign,A32) -> 2 | M32: =IF(COUNTIF(MetaCamps,A32)>0,"In Meta export","NOT in Meta export (spend n/a)") -> NOT in Meta export (spend n/a)
A33: (Unattributed) | B33: Unattributed | C33: No campaign tag in CRM (WhatsApp-API lead with blank campaign) - not forced into Old/New | D33: n/a | H33: =SUMIFS(Meta_Campaigns!$G$2:$G$29,Meta_Campaigns!$A$2:$A$29,A33) -> 0 | I33: =SUMIFS(Meta_AdSets!$G$2:$G$93,Meta_AdSets!$B$2:$B$93,A33) -> 0 | J33: =ROUND(H33-I33,2) -> 0 | K33: =SUMIFS(fLeads,fCampaign,A33) -> 0 | L33: =SUMIFS(fQual,fCampaign,A33) -> 0 | M33: =IF(COUNTIF(MetaCamps,A33)>0,"In Meta export","NOT in Meta export (spend n/a)") -> NOT in Meta export (spend n/a)
A34: TOTAL | H34: =SUM(H2:H33) -> 1647106.2 | I34: =SUM(I2:I33) -> 1647106.2 | J34: =SUM(J2:J33) -> 0 | K34: =SUM(K2:K33) -> 3627 | L34: =SUM(L2:L33) -> 558
A36: Rule: a campaign is NEW if its name carries 'Oct26' (the new Oct-2026 structure: 'ABO | ... | Oct26' in the Kustard ad account and 'EBG - In House | ... | Oct26' in the In-House ad account). All other campaigns are OLD. Change column B and press Data > Refresh All. EBG - In House campaigns have CRM leads but NO Meta spend in the exports provided, so their cost is shown as n/a.

Sheet Fact_Data
A1: Record Type | B1: Campaign Type | C1: Campaign | D1: Ad Set | E1: Ad | F1: CRM Brand | G1: Lead Status | H1: Lead Quality | I1: Lead Month | J1: Lead Week | K1: Team Manager | L1: Lead Source | M1: Attribution Method | N1: Lead ID | O1: Lead Count | P1: Quality Count | Q1: Contacted Count | R1: Lost Count | S1: Calls Count | T1: Connected Calls | U1: Spend INR | V1: Impressions | W1: Link Clicks | X1: Meta Results Count | Y1: Costed Lead Count | Z1: Costed Quality Count
A2: Lead | B2: =IFERROR(INDEX(CampTypes,MATCH(C2,CampList,0)),"Unattributed") -> New | C2: ABO | Natuf | Leads | Unit Franchise | India | Oct26 | V1 | D2: Natuf | Broad | Tier1 + Growth Cities | Oct26 | V1 | E2: Natuf | Reel | Brand Ambassador | Heard Of Owning A Cafe | V1 | F2: In House Natuf | G2: New Lead | H2: =IF(ISNUMBER(MATCH(G2,QualityStatuses,0)),"Quality Lead","Non-Quality Lead") -> Non-Quality Lead | I2: 2026-10 | J2: Wk of 2026-10-26 | K2: Vikas Pathak | L2: Facebook | M2: Direct (campaign tagged in CRM) | N2: 6ae597f7b26a2f65d10a4408 | O2: 1 | P2: =IF(A2="Lead",IF(ISNUMBER(MATCH(G2,QualityStatuses,0)),1,0),0) -> 0 | Q2: =IF(A2="Lead",IF(G2="New Lead",0,1),0) -> 0 | R2: =IF(A2="Lead",IF(G2="Lost",1,0),0) -> 0 | S2: 0 | T2: 0 | U2: 0 | V2: 0 | W2: 0 | X2: 0 | Y2: =IF(AND(A2="Lead",COUNTIF(MetaCamps,C2)>0),1,0) -> 1 | Z2: =IF(Y2=1,P2,0) -> 0
A3: Lead | B3: =IFERROR(INDEX(CampTypes,MATCH(C3,CampList,0)),"Unattributed") -> New | C3: ABO | Natuf | Leads | Master Franchise | India | Oct26 | V1 | D3: Natuf | Broad | Tier1 + Growth Cities | Oct26 | V1 | E3: Natuf | Static | Become A Levantine Food | V1 | F3: Natuf_MF | G3: New Lead | H3: =IF(ISNUMBER(MATCH(G3,QualityStatuses,0)),"Quality Lead","Non-Quality Lead") -> Non-Quality Lead | I3: 2026-10 | J3: Wk of 2026-10-26 | K3: Marshal Malbari | L3: Facebook | M3: Direct (campaign tagged in CRM) | N3: 6ae597ab99edaed0c5aab4b9 | O3: 1 | P3: =IF(A3="Lead",IF(ISNUMBER(MATCH(G3,QualityStatuses,0)),1,0),0) -> 0 | Q3: =IF(A3="Lead",IF(G3="New Lead",0,1),0) -> 0 | R3: =IF(A3="Lead",IF(G3="Lost",1,0),0) -> 0 | S3: 0 | T3: 0 | U3: 0 | V3: 0 | W3: 0 | X3: 0 | Y3: =IF(AND(A3="Lead",COUNTIF(MetaCamps,C3)>0),1,0) -> 1 | Z3: =IF(Y3=1,P3,0) -> 0
A4: Lead | B4: =IFERROR(INDEX(CampTypes,MATCH(C4,CampList,0)),"Unattributed") -> New | C4: ABO | Natuf | Leads | Unit Franchise | India | Oct26 | V1 | D4: Natuf | LAL 1% | India | Jul26 | V1 | E4: Natuf | Reel | Brand Ambassador | Heard Of Owning A Cafe | V1 | F4: In House Natuf | G4: New Lead | H4: =IF(ISNUMBER(MATCH(G4,QualityStatuses,0)),"Quality Lead","Non-Quality Lead") -> Non-Quality Lead | I4: 2026-10 | J4: Wk of 2026-10-26 | K4: (Unassigned) | L4: Facebook | M4: Direct (campaign tagged in CRM) | N4: 6ae59561315f55f2fd4319c5 | O4: 1 | P4: =IF(A4="Lead",IF(ISNUMBER(MATCH(G4,QualityStatuses,0)),1,0),0) -> 0 | Q4: =IF(A4="Lead",IF(G4="New Lead",0,1),0) -> 0 | R4: =IF(A4="Lead",IF(G4="Lost",1,0),0) -> 0 | S4: 0 | T4: 0 | U4: 0 | V4: 0 | W4: 0 | X4: 0 | Y4: =IF(AND(A4="Lead",COUNTIF(MetaCamps,C4)>0),1,0) -> 1 | Z4: =IF(Y4=1,P4,0) -> 0
A5: Lead | B5: =IFERROR(INDEX(CampTypes,MATCH(C5,CampList,0)),"Unattributed") -> New | C5: ABO | Natuf | Leads | Unit Franchise | India | Oct26 | V1 | D5: Natuf | Business Owners | Tier1 + Growth Cities | Oct26 | V1 | E5: Natuf | Reel | Brand Ambassador | Heard Of Owning A Cafe | V1 | F5: In House Natuf | G5: New Lead | H5: =IF(ISNUMBER(MATCH(G5,QualityStatuses,0)),"Quality Lead","Non-Quality Lead") -> Non-Quality Lead | I5: 2026-10 | J5: Wk of 2026-10-26 | K5: Marshal Malbari | L5: Facebook | M5: Direct (campaign tagged in CRM) | N5: 6ae59349481a67e46c03f3ae | O5: 1 | P5: =IF(A5="Lead",IF(ISNUMBER(MATCH(G5,QualityStatuses,0)),1,0),0) -> 0 | Q5: =IF(A5="Lead",IF(G5="New Lead",0,1),0) -> 0 | R5: =IF(A5="Lead",IF(G5="Lost",1,0),0) -> 0 | S5: 0 | T5: 0 | U5: 0 | V5: 0 | W5: 0 | X5: 0 | Y5: =IF(AND(A5="Lead",COUNTIF(MetaCamps,C5)>0),1,0) -> 1 | Z5: =IF(Y5=1,P5,0) -> 0
A6: Lead | B6: =IFERROR(INDEX(CampTypes,MATCH(C6,CampList,0)),"Unattributed") -> New | C6: ABO | Natuf | Leads | Unit Franchise | India | Oct26 | V1 | D6: Natuf | Business Owners | Tier1 + Growth Cities | Oct26 | V1 | E6: Natuf | Reel | Brand Ambassador | Heard Of Owning A Cafe | V1 | F6: In House Natuf | G6: New Lead | H6: =IF(ISNUMBER(MATCH(G6,QualityStatuses,0)),"Quality Lead","Non-Quality Lead") -> Non-Quality Lead | I6: 2026-10 | J6: Wk of 2026-10-26 | K6: (Unassigned) | L6: Facebook | M6: Direct (campaign tagged in CRM) | N6: 6ae58f6ead9b3f10ed1ee1f8 | O6: 1 | P6: =IF(A6="Lead",IF(ISNUMBER(MATCH(G6,QualityStatuses,0)),1,0),0) -> 0 | Q6: =IF(A6="Lead",IF(G6="New Lead",0,1),0) -> 0 | R6: =IF(A6="Lead",IF(G6="Lost",1,0),0) -> 0 | S6: 0 | T6: 0 | U6: 0 | V6: 0 | W6: 0 | X6: 0 | Y6: =IF(AND(A6="Lead",COUNTIF(MetaCamps,C6)>0),1,0) -> 1 | Z6: =IF(Y6=1,P6,0) -> 0
A7: Lead | B7: =IFERROR(INDEX(CampTypes,MATCH(C7,CampList,0)),"Unattributed") -> New | C7: ABO | Natuf | Leads | Unit Franchise | India | Oct26 | V1 | D7: Natuf | Investors | Tier1 + Growth Cities | Oct26 | V1 | E7: Natuf | Reel | Brand Ambassador | Heard Of Owning A Cafe | V1 | F7: In House Natuf | G7: New Lead | H7: =IF(ISNUMBER(MATCH(G7,QualityStatuses,0)),"Quality Lead","Non-Quality Lead") -> Non-Quality Lead | I7: 2026-10 | J7: Wk of 2026-10-26 | K7: Marshal Malbari | L7: Facebook | M7: Direct (campaign tagged in CRM) | N7: 6ae58f56a3c40b362d514506 | O7: 1 | P7: =IF(A7="Lead",IF(ISNUMBER(MATCH(G7,QualityStatuses,0)),1,0),0) -> 0 | Q7: =IF(A7="Lead",IF(G7="New Lead",0,1),0) -> 0 | R7: =IF(A7="Lead",IF(G7="Lost",1,0),0) -> 0 | S7: 0 | T7: 0 | U7: 0 | V7: 0 | W7: 0 | X7: 0 | Y7: =IF(AND(A7="Lead",COUNTIF(MetaCamps,C7)>0),1,0) -> 1 | Z7: =IF(Y7=1,P7,0) -> 0
A8: Lead | B8: =IFERROR(INDEX(CampTypes,MATCH(C8,CampList,0)),"Unattributed") -> New | C8: ABO | Natuf | Leads | Unit Franchise | India | Oct26 | V1 | D8: Natuf | Investors | Tier1 + Growth Cities | Oct26 | V1 | E8: Natuf | Reel | Brand Ambassador | Heard Of Owning A Cafe | V1 | F8: In House Natuf | G8: New Lead | H8: =IF(ISNUMBER(MATCH(G8,QualityStatuses,0)),"Quality Lead","Non-Quality Lead") -> Non-Quality Lead | I8: 2026-10 | J8: Wk of 2026-10-26 | K8: (Unassigned) | L8: Facebook | M8: Direct (campaign tagged in CRM) | N8: 6ae58effd0aa4b0328d1c585 | O8: 1 | P8: =IF(A8="Lead",IF(ISNUMBER(MATCH(G8,QualityStatuses,0)),1,0),0) -> 0 | Q8: =IF(A8="Lead",IF(G8="New Lead",0,1),0) -> 0 | R8: =IF(A8="Lead",IF(G8="Lost",1,0),0) -> 0 | S8: 0 | T8: 0 | U8: 0 | V8: 0 | W8: 0 | X8: 0 | Y8: =IF(AND(A8="Lead",COUNTIF(MetaCamps,C8)>0),1,0) -> 1 | Z8: =IF(Y8=1,P8,0) -> 0
A9: Lead | B9: =IFERROR(INDEX(CampTypes,MATCH(C9,CampList,0)),"Unattributed") -> New | C9: ABO | Natuf | Leads | Unit Franchise | India | Oct26 | V1 | D9: Natuf | Broad | Tier1 + Growth Cities | Oct26 | V1 | E9: Natuf | Reel | Brand Ambassador | Heard Of Owning A Cafe | V1 | F9: In House Natuf | G9: New Lead | H9: =IF(ISNUMBER(MATCH(G9,QualityStatuses,0)),"Quality Lead","Non-Quality Lead") -> Non-Quality Lead | I9: 2026-10 | J9: Wk of 2026-10-26 | K9: (Unassigned) | L9: Facebook | M9: Direct (campaign tagged in CRM) | N9: 6ae58ee221cda82dfed326df | O9: 1 | P9: =IF(A9="Lead",IF(ISNUMBER(MATCH(G9,QualityStatuses,0)),1,0),0) -> 0 | Q9: =IF(A9="Lead",IF(G9="New Lead",0,1),0) -> 0 | R9: =IF(A9="Lead",IF(G9="Lost",1,0),0) -> 0 | S9: 0 | T9: 0 | U9: 0 | V9: 0 | W9: 0 | X9: 0 | Y9: =IF(AND(A9="Lead",COUNTIF(MetaCamps,C9)>0),1,0) -> 1 | Z9: =IF(Y9=1,P9,0) -> 0
A10: Lead | B10: =IFERROR(INDEX(CampTypes,MATCH(C10,CampList,0)),"Unattributed") -> New | C10: ABO | Natuf | Leads | Unit Franchise | India | Oct26 | V1 | D10: Natuf | Broad | Tier1 + Growth Cities | Oct26 | V1 | E10: Natuf | Reel | Brand Ambassador | Heard Of Owning A Cafe | V1 | F10: In House Natuf | G10: Attempt 1 | H10: =IF(ISNUMBER(MATCH(G10,QualityStatuses,0)),"Quality Lead","Non-Quality Lead") -> Non-Quality Lead | I10: 2026-10 | J10: Wk of 2026-10-26 | K10: Vikas Pathak | L10: Facebook | M10: Direct (campaign tagged in CRM) | N10: 6ae58d3adb91a7cf96deb9cf | O10: 1 | P10: =IF(A10="Lead",IF(ISNUMBER(MATCH(G10,QualityStatuses,0)),1,0),0) -> 0 | Q10: =IF(A10="Lead",IF(G10="New Lead",0,1),0) -> 1 | R10: =IF(A10="Lead",IF(G10="Lost",1,0),0) -> 0 | S10: 1 | T10: 0 | U10: 0 | V10: 0 | W10: 0 | X10: 0 | Y10: =IF(AND(A10="Lead",COUNTIF(MetaCamps,C10)>0),1,0) -> 1 | Z10: =IF(Y10=1,P10,0) -> 0
A11: Lead | B11: =IFERROR(INDEX(CampTypes,MATCH(C11,CampList,0)),"Unattributed") -> New | C11: ABO | Natuf | Leads | Master Franchise | India | Oct26 | V1 | D11: Natuf | LAL 1% | India | Jul26 | V1 | E11: Natuf | Static | Become A Levantine Food | V1 | F11: Natuf_MF | G11: New Lead | H11: =IF(ISNUMBER(MATCH(G11,QualityStatuses,0)),"Quality Lead","Non-Quality Lead") -> Non-Quality Lead | I11: 2026-10 | J11: Wk of 2026-10-26 | K11: Shivam Kumar | L11: Facebook | M11: Direct (campaign tagged in CRM) | N11: 6ae58b5dc80e9a3a8ca338fa | O11: 1 | P11: =IF(A11="Lead",IF(ISNUMBER(MATCH(G11,QualityStatuses,0)),1,0),0) -> 0 | Q11: =IF(A11="Lead",IF(G11="New Lead",0,1),0) -> 0 | R11: =IF(A11="Lead",IF(G11="Lost",1,0),0) -> 0 | S11: 0 | T11: 0 | U11: 0 | V11: 0 | W11: 0 | X11: 0 | Y11: =IF(AND(A11="Lead",COUNTIF(MetaCamps,C11)>0),1,0) -> 1 | Z11: =IF(Y11=1,P11,0) -> 0
A12: Lead | B12: =IFERROR(INDEX(CampTypes,MATCH(C12,CampList,0)),"Unattributed") -> New | C12: ABO | Natuf | Leads | Unit Franchise | India | Oct26 | V1 | D12: Natuf | Investors | Tier1 + Growth Cities | Oct26 | V1 | E12: Natuf | Reel | Brand Ambassador | Heard Of Owning A Cafe | V1 | F12: In House Natuf | G12: New Lead | H12: =IF(ISNUMBER(MATCH(G12,QualityStatuses,0)),"Quality Lead","Non-Quality Lead") -> Non-Quality Lead | I12: 2026-10 | J12: Wk of 2026-10-26 | K12: (Unassigned) | L12: Facebook | M12: Direct (campaign tagged in CRM) | N12: 6ae5894b252750c50e8a30e2 | O12: 1 | P12: =IF(A12="Lead",IF(ISNUMBER(MATCH(G12,QualityStatuses,0)),1,0),0) -> 0 | Q12: =IF(A12="Lead",IF(G12="New Lead",0,1),0) -> 0 | R12: =IF(A12="Lead",IF(G12="Lost",1,0),0) -> 0 | S12: 0 | T12: 0 | U12: 0 | V12: 0 | W12: 0 | X12: 0 | Y12: =IF(AND(A12="Lead",COUNTIF(MetaCamps,C12)>0),1,0) -> 1 | Z12: =IF(Y12=1,P12,0) -> 0
A13: Lead | B13: =IFERROR(INDEX(CampTypes,MATCH(C13,CampList,0)),"Unattributed") -> New | C13: ABO | Natuf | Leads | Unit Franchise | India | Oct26 | V1 | D13: Natuf | Broad | Tier1 + Growth Cities | Oct26 | V1 | E13: Natuf | Reel | Brand Ambassador | Heard Of Owning A Cafe | V1 | F13: In House Natuf | G13: Attempt 1 | H13: =IF(ISNUMBER(MATCH(G13,QualityStatuses,0)),"Quality Lead","Non-Quality Lead") -> Non-Quality Lead | I13: 2026-10 | J13: Wk of 2026-10-26 | K13: Vikas Pathak | L13: Facebook | M13: Direct (campaign tagged in CRM) | N13: 6ae587d98135cd63e5061f00 | O13: 1 | P13: =IF(A13="Lead",IF(ISNUMBER(MATCH(G13,QualityStatuses,0)),1,0),0) -> 0 | Q13: =IF(A13="Lead",IF(G13="New Lead",0,1),0) -> 1 | R13: =IF(A13="Lead",IF(G13="Lost",1,0),0) -> 0 | S13: 1 | T13: 0 | U13: 0 | V13: 0 | W13: 0 | X13: 0 | Y13: =IF(AND(A13="Lead",COUNTIF(MetaCamps,C13)>0),1,0) -> 1 | Z13: =IF(Y13=1,P13,0) -> 0
... A3628: Lead | B3628: =IFERROR(INDEX(CampTypes,MATCH(C3628,CampList,0)),"Unattributed") -> Old | C3628: E_Suresh_Natuf_Kiosk_07072026 | D3628: E_Suresh_Natuf_Kiosk_07072026_Adset5 | E3628: E_Hindi_Suresh_Natuf_Kiosk_07072026_Adset5_ad3 – Copy 2 | F3628: Natuf | G3628: Attempt 1 | H3628: =IF(ISNUMBER(MATCH(G3628,QualityStatuses,0)),"Quality Lead","Non-Quality Lead") -> Non-Quality Lead | I3628: 2026-10 | J3628: Wk of 2026-09-28 | K3628: Tejaswini Tarigopula | L3628: Facebook | M3628: Direct (campaign tagged in CRM) | N3628: 6abd55b450b9d169a360a76e | O3628: 1 | P3628: =IF(A3628="Lead",IF(ISNUMBER(MATCH(G3628,QualityStatuses,0)),1,0),0) -> 0 | Q3628: =IF(A3628="Lead",IF(G3628="New Lead",0,1),0) -> 1 | R3628: =IF(A3628="Lead",IF(G3628="Lost",1,0),0) -> 0 | S3628: 0 | T3628: 0 | U3628: 0 | V3628: 0 | W3628: 0 | X3628: 0 | Y3628: =IF(AND(A3628="Lead",COUNTIF(MetaCamps,C3628)>0),1,0) -> 1 | Z3628: =IF(Y3628=1,P3628,0) -> 0
A3629: Spend | B3629: =IFERROR(INDEX(CampTypes,MATCH(C3629,CampList,0)),"Unattributed") -> Old | C3629: E_Karan_Natuf_Kiosk_07072026 | D3629: (campaign level) | E3629: (n/a - spend) | F3629: (n/a - spend) | G3629: (n/a - spend) | H3629: (n/a - spend) | I3629: (n/a - spend) | J3629: (n/a - spend) | K3629: (n/a - spend) | L3629: (n/a - spend) | M3629: (n/a - spend) | N3629: (n/a - spend) | O3629: 0 | P3629: =IF(A3629="Lead",IF(ISNUMBER(MATCH(G3629,QualityStatuses,0)),1,0),0) -> 0 | Q3629: =IF(A3629="Lead",IF(G3629="New Lead",0,1),0) -> 0 | R3629: =IF(A3629="Lead",IF(G3629="Lost",1,0),0) -> 0 | S3629: 0 | T3629: 0 | U3629: =SUMIFS(Meta_Campaigns!$G$2:$G$29,Meta_Campaigns!$A$2:$A$29,$C3629) -> 54540.16 | V3629: =SUMIFS(Meta_Campaigns!$F$2:$F$29,Meta_Campaigns!$A$2:$A$29,$C3629) -> 37281 | W3629: =SUMIFS(Meta_Campaigns!$H$2:$H$29,Meta_Campaigns!$A$2:$A$29,$C3629) -> 444 | X3629: =SUMIFS(Meta_Campaigns!$P$2:$P$29,Meta_Campaigns!$A$2:$A$29,$C3629) -> 30 | Y3629: =IF(AND(A3629="Lead",COUNTIF(MetaCamps,C3629)>0),1,0) -> 0 | Z3629: =IF(Y3629=1,P3629,0) -> 0
A3630: Spend | B3630: =IFERROR(INDEX(CampTypes,MATCH(C3630,CampList,0)),"Unattributed") -> Old | C3630: E_Suresh_Natuf_Kiosk_07072026 | D3630: (campaign level) | E3630: (n/a - spend) | F3630: (n/a - spend) | G3630: (n/a - spend) | H3630: (n/a - spend) | I3630: (n/a - spend) | J3630: (n/a - spend) | K3630: (n/a - spend) | L3630: (n/a - spend) | M3630: (n/a - spend) | N3630: (n/a - spend) | O3630: 0 | P3630: =IF(A3630="Lead",IF(ISNUMBER(MATCH(G3630,QualityStatuses,0)),1,0),0) -> 0 | Q3630: =IF(A3630="Lead",IF(G3630="New Lead",0,1),0) -> 0 | R3630: =IF(A3630="Lead",IF(G3630="Lost",1,0),0) -> 0 | S3630: 0 | T3630: 0 | U3630: =SUMIFS(Meta_Campaigns!$G$2:$G$29,Meta_Campaigns!$A$2:$A$29,$C3630) -> 232416.42 | V3630: =SUMIFS(Meta_Campaigns!$F$2:$F$29,Meta_Campaigns!$A$2:$A$29,$C3630) -> 210455 | W3630: =SUMIFS(Meta_Campaigns!$H$2:$H$29,Meta_Campaigns!$A$2:$A$29,$C3630) -> 2446 | X3630: =SUMIFS(Meta_Campaigns!$P$2:$P$29,Meta_Campaigns!$A$2:$A$29,$C3630) -> 360 | Y3630: =IF(AND(A3630="Lead",COUNTIF(MetaCamps,C3630)>0),1,0) -> 0 | Z3630: =IF(Y3630=1,P3630,0) -> 0
A3631: Spend | B3631: =IFERROR(INDEX(CampTypes,MATCH(C3631,CampList,0)),"Unattributed") -> Old | C3631: E_Karan_Natuf_All_07072026 | D3631: (campaign level) | E3631: (n/a - spend) | F3631: (n/a - spend) | G3631: (n/a - spend) | H3631: (n/a - spend) | I3631: (n/a - spend) | J3631: (n/a - spend) | K3631: (n/a - spend) | L3631: (n/a - spend) | M3631: (n/a - spend) | N3631: (n/a - spend) | O3631: 0 | P3631: =IF(A3631="Lead",IF(ISNUMBER(MATCH(G3631,QualityStatuses,0)),1,0),0) -> 0 | Q3631: =IF(A3631="Lead",IF(G3631="New Lead",0,1),0) -> 0 | R3631: =IF(A3631="Lead",IF(G3631="Lost",1,0),0) -> 0 | S3631: 0 | T3631: 0 | U3631: =SUMIFS(Meta_Campaigns!$G$2:$G$29,Meta_Campaigns!$A$2:$A$29,$C3631) -> 277596.99 | V3631: =SUMIFS(Meta_Campaigns!$F$2:$F$29,Meta_Campaigns!$A$2:$A$29,$C3631) -> 164085 | W3631: =SUMIFS(Meta_Campaigns!$H$2:$H$29,Meta_Campaigns!$A$2:$A$29,$C3631) -> 1632 | X3631: =SUMIFS(Meta_Campaigns!$P$2:$P$29,Meta_Campaigns!$A$2:$A$29,$C3631) -> 289 | Y3631: =IF(AND(A3631="Lead",COUNTIF(MetaCamps,C3631)>0),1,0) -> 0 | Z3631: =IF(Y3631=1,P3631,0) -> 0
A3632: Spend | B3632: =IFERROR(INDEX(CampTypes,MATCH(C3632,CampList,0)),"Unattributed") -> Old | C3632: E_Selva_Natuf_All_07072026 | D3632: (campaign level) | E3632: (n/a - spend) | F3632: (n/a - spend) | G3632: (n/a - spend) | H3632: (n/a - spend) | I3632: (n/a - spend) | J3632: (n/a - spend) | K3632: (n/a - spend) | L3632: (n/a - spend) | M3632: (n/a - spend) | N3632: (n/a - spend) | O3632: 0 | P3632: =IF(A3632="Lead",IF(ISNUMBER(MATCH(G3632,QualityStatuses,0)),1,0),0) -> 0 | Q3632: =IF(A3632="Lead",IF(G3632="New Lead",0,1),0) -> 0 | R3632: =IF(A3632="Lead",IF(G3632="Lost",1,0),0) -> 0 | S3632: 0 | T3632: 0 | U3632: =SUMIFS(Meta_Campaigns!$G$2:$G$29,Meta_Campaigns!$A$2:$A$29,$C3632) -> 80349.25 | V3632: =SUMIFS(Meta_Campaigns!$F$2:$F$29,Meta_Campaigns!$A$2:$A$29,$C3632) -> 78881 | W3632: =SUMIFS(Meta_Campaigns!$H$2:$H$29,Meta_Campaigns!$A$2:$A$29,$C3632) -> 806 | X3632: =SUMIFS(Meta_Campaigns!$P$2:$P$29,Meta_Campaigns!$A$2:$A$29,$C3632) -> 71 | Y3632: =IF(AND(A3632="Lead",COUNTIF(MetaCamps,C3632)>0),1,0) -> 0 | Z3632: =IF(Y3632=1,P3632,0) -> 0
A3633: Spend | B3633: =IFERROR(INDEX(CampTypes,MATCH(C3633,CampList,0)),"Unattributed") -> Old | C3633: natuf_Kiosk_14072026_Hindi | D3633: (campaign level) | E3633: (n/a - spend) | F3633: (n/a - spend) | G3633: (n/a - spend) | H3633: (n/a - spend) | I3633: (n/a - spend) | J3633: (n/a - spend) | K3633: (n/a - spend) | L3633: (n/a - spend) | M3633: (n/a - spend) | N3633: (n/a - spend) | O3633: 0 | P3633: =IF(A3633="Lead",IF(ISNUMBER(MATCH(G3633,QualityStatuses,0)),1,0),0) -> 0 | Q3633: =IF(A3633="Lead",IF(G3633="New Lead",0,1),0) -> 0 | R3633: =IF(A3633="Lead",IF(G3633="Lost",1,0),0) -> 0 | S3633: 0 | T3633: 0 | U3633: =SUMIFS(Meta_Campaigns!$G$2:$G$29,Meta_Campaigns!$A$2:$A$29,$C3633) -> 180149.88 | V3633: =SUMIFS(Meta_Campaigns!$F$2:$F$29,Meta_Campaigns!$A$2:$A$29,$C3633) -> 419595 | W3633: =SUMIFS(Meta_Campaigns!$H$2:$H$29,Meta_Campaigns!$A$2:$A$29,$C3633) -> 3627 | X3633: =SUMIFS(Meta_Campaigns!$P$2:$P$29,Meta_Campaigns!$A$2:$A$29,$C3633) -> 438 | Y3633: =IF(AND(A3633="Lead",COUNTIF(MetaCamps,C3633)>0),1,0) -> 0 | Z3633: =IF(Y3633=1,P3633,0) -> 0
A3634: Spend | B3634: =IFERROR(INDEX(CampTypes,MATCH(C3634,CampList,0)),"Unattributed") -> Old | C3634: E_Natuf_Generic_13082026 | D3634: (campaign level) | E3634: (n/a - spend) | F3634: (n/a - spend) | G3634: (n/a - spend) | H3634: (n/a - spend) | I3634: (n/a - spend) | J3634: (n/a - spend) | K3634: (n/a - spend) | L3634: (n/a - spend) | M3634: (n/a - spend) | N3634: (n/a - spend) | O3634: 0 | P3634: =IF(A3634="Lead",IF(ISNUMBER(MATCH(G3634,QualityStatuses,0)),1,0),0) -> 0 | Q3634: =IF(A3634="Lead",IF(G3634="New Lead",0,1),0) -> 0 | R3634: =IF(A3634="Lead",IF(G3634="Lost",1,0),0) -> 0 | S3634: 0 | T3634: 0 | U3634: =SUMIFS(Meta_Campaigns!$G$2:$G$29,Meta_Campaigns!$A$2:$A$29,$C3634) -> 233578.47 | V3634: =SUMIFS(Meta_Campaigns!$F$2:$F$29,Meta_Campaigns!$A$2:$A$29,$C3634) -> 243248 | W3634: =SUMIFS(Meta_Campaigns!$H$2:$H$29,Meta_Campaigns!$A$2:$A$29,$C3634) -> 2722 | X3634: =SUMIFS(Meta_Campaigns!$P$2:$P$29,Meta_Campaigns!$A$2:$A$29,$C3634) -> 245 | Y3634: =IF(AND(A3634="Lead",COUNTIF(MetaCamps,C3634)>0),1,0) -> 0 | Z3634: =IF(Y3634=1,P3634,0) -> 0
A3635: Spend | B3635: =IFERROR(INDEX(CampTypes,MATCH(C3635,CampList,0)),"Unattributed") -> Old | C3635: E_Natuf_MF_05092026 | D3635: (campaign level) | E3635: (n/a - spend) | F3635: (n/a - spend) | G3635: (n/a - spend) | H3635: (n/a - spend) | I3635: (n/a - spend) | J3635: (n/a - spend) | K3635: (n/a - spend) | L3635: (n/a - spend) | M3635: (n/a - spend) | N3635: (n/a - spend) | O3635: 0 | P3635: =IF(A3635="Lead",IF(ISNUMBER(MATCH(G3635,QualityStatuses,0)),1,0),0) -> 0 | Q3635: =IF(A3635="Lead",IF(G3635="New Lead",0,1),0) -> 0 | R3635: =IF(A3635="Lead",IF(G3635="Lost",1,0),0) -> 0 | S3635: 0 | T3635: 0 | U3635: =SUMIFS(Meta_Campaigns!$G$2:$G$29,Meta_Campaigns!$A$2:$A$29,$C3635) -> 79772.24 | V3635: =SUMIFS(Meta_Campaigns!$F$2:$F$29,Meta_Campaigns!$A$2:$A$29,$C3635) -> 130721 | W3635: =SUMIFS(Meta_Campaigns!$H$2:$H$29,Meta_Campaigns!$A$2:$A$29,$C3635) -> 1050 | X3635: =SUMIFS(Meta_Campaigns!$P$2:$P$29,Meta_Campaigns!$A$2:$A$29,$C3635) -> 30 | Y3635: =IF(AND(A3635="Lead",COUNTIF(MetaCamps,C3635)>0),1,0) -> 0 | Z3635: =IF(Y3635=1,P3635,0) -> 0
A3636: Spend | B3636: =IFERROR(INDEX(CampTypes,MATCH(C3636,CampList,0)),"Unattributed") -> Old | C3636: E_Natuf_Generic_09092026 | D3636: (campaign level) | E3636: (n/a - spend) | F3636: (n/a - spend) | G3636: (n/a - spend) | H3636: (n/a - spend) | I3636: (n/a - spend) | J3636: (n/a - spend) | K3636: (n/a - spend) | L3636: (n/a - spend) | M3636: (n/a - spend) | N3636: (n/a - spend) | O3636: 0 | P3636: =IF(A3636="Lead",IF(ISNUMBER(MATCH(G3636,QualityStatuses,0)),1,0),0) -> 0 | Q3636: =IF(A3636="Lead",IF(G3636="New Lead",0,1),0) -> 0 | R3636: =IF(A3636="Lead",IF(G3636="Lost",1,0),0) -> 0 | S3636: 0 | T3636: 0 | U3636: =SUMIFS(Meta_Campaigns!$G$2:$G$29,Meta_Campaigns!$A$2:$A$29,$C3636) -> 71194.81 | V3636: =SUMIFS(Meta_Campaigns!$F$2:$F$29,Meta_Campaigns!$A$2:$A$29,$C3636) -> 136362 | W3636: =SUMIFS(Meta_Campaigns!$H$2:$H$29,Meta_Campaigns!$A$2:$A$29,$C3636) -> 1618 | X3636: =SUMIFS(Meta_Campaigns!$P$2:$P$29,Meta_Campaigns!$A$2:$A$29,$C3636) -> 77 | Y3636: =IF(AND(A3636="Lead",COUNTIF(MetaCamps,C3636)>0),1,0) -> 0 | Z3636: =IF(Y3636=1,P3636,0) -> 0
A3637: Spend | B3637: =IFERROR(INDEX(CampTypes,MATCH(C3637,CampList,0)),"Unattributed") -> Old | C3637: E_Natuf_Foco_10092026 | D3637: (campaign level) | E3637: (n/a - spend) | F3637: (n/a - spend) | G3637: (n/a - spend) | H3637: (n/a - spend) | I3637: (n/a - spend) | J3637: (n/a - spend) | K3637: (n/a - spend) | L3637: (n/a - spend) | M3637: (n/a - spend) | N3637: (n/a - spend) | O3637: 0 | P3637: =IF(A3637="Lead",IF(ISNUMBER(MATCH(G3637,QualityStatuses,0)),1,0),0) -> 0 | Q3637: =IF(A3637="Lead",IF(G3637="New Lead",0,1),0) -> 0 | R3637: =IF(A3637="Lead",IF(G3637="Lost",1,0),0) -> 0 | S3637: 0 | T3637: 0 | U3637: =SUMIFS(Meta_Campaigns!$G$2:$G$29,Meta_Campaigns!$A$2:$A$29,$C3637) -> 46413.52 | V3637: =SUMIFS(Meta_Campaigns!$F$2:$F$29,Meta_Campaigns!$A$2:$A$29,$C3637) -> 94401 | W3637: =SUMIFS(Meta_Campaigns!$H$2:$H$29,Meta_Campaigns!$A$2:$A$29,$C3637) -> 722 | X3637: =SUMIFS(Meta_Campaigns!$P$2:$P$29,Meta_Campaigns!$A$2:$A$29,$C3637) -> 40 | Y3637: =IF(AND(A3637="Lead",COUNTIF(MetaCamps,C3637)>0),1,0) -> 0 | Z3637: =IF(Y3637=1,P3637,0) -> 0
A3638: Spend | B3638: =IFERROR(INDEX(CampTypes,MATCH(C3638,CampList,0)),"Unattributed") -> Old | C3638: E_Natuf_Web_23092026 | D3638: (campaign level) | E3638: (n/a - spend) | F3638: (n/a - spend) | G3638: (n/a - spend) | H3638: (n/a - spend) | I3638: (n/a - spend) | J3638: (n/a - spend) | K3638: (n/a - spend) | L3638: (n/a - spend) | M3638: (n/a - spend) | N3638: (n/a - spend) | O3638: 0 | P3638: =IF(A3638="Lead",IF(ISNUMBER(MATCH(G3638,QualityStatuses,0)),1,0),0) -> 0 | Q3638: =IF(A3638="Lead",IF(G3638="New Lead",0,1),0) -> 0 | R3638: =IF(A3638="Lead",IF(G3638="Lost",1,0),0) -> 0 | S3638: 0 | T3638: 0 | U3638: =SUMIFS(Meta_Campaigns!$G$2:$G$29,Meta_Campaigns!$A$2:$A$29,$C3638) -> 6412.86 | V3638: =SUMIFS(Meta_Campaigns!$F$2:$F$29,Meta_Campaigns!$A$2:$A$29,$C3638) -> 189828 | W3638: =SUMIFS(Meta_Campaigns!$H$2:$H$29,Meta_Campaigns!$A$2:$A$29,$C3638) -> 4334 | X3638: =SUMIFS(Meta_Campaigns!$P$2:$P$29,Meta_Campaigns!$A$2:$A$29,$C3638) -> 0 | Y3638: =IF(AND(A3638="Lead",COUNTIF(MetaCamps,C3638)>0),1,0) -> 0 | Z3638: =IF(Y3638=1,P3638,0) -> 0
A3639: Spend | B3639: =IFERROR(INDEX(CampTypes,MATCH(C3639,CampList,0)),"Unattributed") -> Old | C3639: E_Natuf_Amazon_29092026 | D3639: (campaign level) | E3639: (n/a - spend) | F3639: (n/a - spend) | G3639: (n/a - spend) | H3639: (n/a - spend) | I3639: (n/a - spend) | J3639: (n/a - spend) | K3639: (n/a - spend) | L3639: (n/a - spend) | M3639: (n/a - spend) | N3639: (n/a - spend) | O3639: 0 | P3639: =IF(A3639="Lead",IF(ISNUMBER(MATCH(G3639,QualityStatuses,0)),1,0),0) -> 0 | Q3639: =IF(A3639="Lead",IF(G3639="New Lead",0,1),0) -> 0 | R3639: =IF(A3639="Lead",IF(G3639="Lost",1,0),0) -> 0 | S3639: 0 | T3639: 0 | U3639: =SUMIFS(Meta_Campaigns!$G$2:$G$29,Meta_Campaigns!$A$2:$A$29,$C3639) -> 39121.71 | V3639: =SUMIFS(Meta_Campaigns!$F$2:$F$29,Meta_Campaigns!$A$2:$A$29,$C3639) -> 66258 | W3639: =SUMIFS(Meta_Campaigns!$H$2:$H$29,Meta_Campaigns!$A$2:$A$29,$C3639) -> 772 | X3639: =SUMIFS(Meta_Campaigns!$P$2:$P$29,Meta_Campaigns!$A$2:$A$29,$C3639) -> 22 | Y3639: =IF(AND(A3639="Lead",COUNTIF(MetaCamps,C3639)>0),1,0) -> 0 | Z3639: =IF(Y3639=1,P3639,0) -> 0
A3640: Spend | B3640: =IFERROR(INDEX(CampTypes,MATCH(C3640,CampList,0)),"Unattributed") -> New | C3640: ABO | Natuf | Leads | Unit Franchise | India | Oct26 | V1 | D3640: (campaign level) | E3640: (n/a - spend) | F3640: (n/a - spend) | G3640: (n/a - spend) | H3640: (n/a - spend) | I3640: (n/a - spend) | J3640: (n/a - spend) | K3640: (n/a - spend) | L3640: (n/a - spend) | M3640: (n/a - spend) | N3640: (n/a - spend) | O3640: 0 | P3640: =IF(A3640="Lead",IF(ISNUMBER(MATCH(G3640,QualityStatuses,0)),1,0),0) -> 0 | Q3640: =IF(A3640="Lead",IF(G3640="New Lead",0,1),0) -> 0 | R3640: =IF(A3640="Lead",IF(G3640="Lost",1,0),0) -> 0 | S3640: 0 | T3640: 0 | U3640: =SUMIFS(Meta_Campaigns!$G$2:$G$29,Meta_Campaigns!$A$2:$A$29,$C3640) -> 264151.59 | V3640: =SUMIFS(Meta_Campaigns!$F$2:$F$29,Meta_Campaigns!$A$2:$A$29,$C3640) -> 2158611 | W3640: =SUMIFS(Meta_Campaigns!$H$2:$H$29,Meta_Campaigns!$A$2:$A$29,$C3640) -> 12758 | X3640: =SUMIFS(Meta_Campaigns!$P$2:$P$29,Meta_Campaigns!$A$2:$A$29,$C3640) -> 2102 | Y3640: =IF(AND(A3640="Lead",COUNTIF(MetaCamps,C3640)>0),1,0) -> 0 | Z3640: =IF(Y3640=1,P3640,0) -> 0
... A3642: Spend | B3642: =IFERROR(INDEX(CampTypes,MATCH(C3642,CampList,0)),"Unattributed") -> New | C3642: ABO | Natuf | Leads | Master Franchise | India | Oct26 | V1 | D3642: (campaign level) | E3642: (n/a - spend) | F3642: (n/a - spend) | G3642: (n/a - spend) | H3642: (n/a - spend) | I3642: (n/a - spend) | J3642: (n/a - spend) | K3642: (n/a - spend) | L3642: (n/a - spend) | M3642: (n/a - spend) | N3642: (n/a - spend) | O3642: 0 | P3642: =IF(A3642="Lead",IF(ISNUMBER(MATCH(G3642,QualityStatuses,0)),1,0),0) -> 0 | Q3642: =IF(A3642="Lead",IF(G3642="New Lead",0,1),0) -> 0 | R3642: =IF(A3642="Lead",IF(G3642="Lost",1,0),0) -> 0 | S3642: 0 | T3642: 0 | U3642: =SUMIFS(Meta_Campaigns!$G$2:$G$29,Meta_Campaigns!$A$2:$A$29,$C3642) -> 55861.63 | V3642: =SUMIFS(Meta_Campaigns!$F$2:$F$29,Meta_Campaigns!$A$2:$A$29,$C3642) -> 117446 | W3642: =SUMIFS(Meta_Campaigns!$H$2:$H$29,Meta_Campaigns!$A$2:$A$29,$C3642) -> 788 | X3642: =SUMIFS(Meta_Campaigns!$P$2:$P$29,Meta_Campaigns!$A$2:$A$29,$C3642) -> 188 | Y3642: =IF(AND(A3642="Lead",COUNTIF(MetaCamps,C3642)>0),1,0) -> 0 | Z3642: =IF(Y3642=1,P3642,0) -> 0

Sheet Lead_Data
A1: Lead ID | B1: Created On | C1: Created Date | D1: Lead Month | E1: Lead Week | F1: Lead Status | G1: Lead Quality | H1: Campaign Type | I1: Campaign (clean) | J1: Campaign (as in CRM) | K1: Attribution Method | L1: Ad Set (clean) | M1: Ad Set (as in CRM) | N1: Ad (as in CRM) | O1: CRM Brand | P1: Lead Source | Q1: Team Manager | R1: Assignee | S1: Lost Reason | T1: City | U1: State | V1: Calls Count | W1: Connected Calls | X1: Phone (masked) | Y1: Last Modified On
A2: 6ae597f7b26a2f65d10a4408 | B2: 46326.539 | C2: 46326 | D2: 2026-10 | E2: Wk of 2026-10-26 | F2: New Lead | G2: =IF(ISNUMBER(MATCH(F2,QualityStatuses,0)),"Quality Lead","Non-Quality Lead") -> Non-Quality Lead | H2: =IFERROR(INDEX(CampTypes,MATCH(I2,CampList,0)),"Unattributed") -> New | I2: ABO | Natuf | Leads | Unit Franchise | India | Oct26 | V1 | J2: ABO | Natuf | Leads | Unit Franchise | India | Oct26 | V1 | K2: Direct (campaign tagged in CRM) | L2: Natuf | Broad | Tier1 + Growth Cities | Oct26 | V1 | M2: Natuf | Broad | Tier1 + Growth Cities | Oct26 | V1 | N2: Natuf | Reel | Brand Ambassador | Heard Of Owning A Cafe | V1 | O2: In House Natuf | P2: Facebook | Q2: Vikas Pathak | R2: Anish kaundal | S2: - | T2: Surat | V2: 0 | W2: 0 | X2: XXXXXX7285 | Y2: 46326.539
A3: 6ae597ab99edaed0c5aab4b9 | B3: 46326.538 | C3: 46326 | D3: 2026-10 | E3: Wk of 2026-10-26 | F3: New Lead | G3: =IF(ISNUMBER(MATCH(F3,QualityStatuses,0)),"Quality Lead","Non-Quality Lead") -> Non-Quality Lead | H3: =IFERROR(INDEX(CampTypes,MATCH(I3,CampList,0)),"Unattributed") -> New | I3: ABO | Natuf | Leads | Master Franchise | India | Oct26 | V1 | J3: ABO | Natuf | Leads | Master Franchise | India | Oct26 | V1 | K3: Direct (campaign tagged in CRM) | L3: Natuf | Broad | Tier1 + Growth Cities | Oct26 | V1 | M3: Natuf | Broad | Tier1 + Growth Cities | Oct26 | V1 | N3: Natuf | Static | Become A Levantine Food | V1 | O3: Natuf_MF | P3: Facebook | Q3: Marshal Malbari | R3: Tanishq A | S3: - | T3: Vadodara | V3: 0 | W3: 0 | X3: XXXXXX1657 | Y3: 46326.538
A4: 6ae59561315f55f2fd4319c5 | B4: 46326.531 | C4: 46326 | D4: 2026-10 | E4: Wk of 2026-10-26 | F4: New Lead | G4: =IF(ISNUMBER(MATCH(F4,QualityStatuses,0)),"Quality Lead","Non-Quality Lead") -> Non-Quality Lead | H4: =IFERROR(INDEX(CampTypes,MATCH(I4,CampList,0)),"Unattributed") -> New | I4: ABO | Natuf | Leads | Unit Franchise | India | Oct26 | V1 | J4: ABO | Natuf | Leads | Unit Franchise | India | Oct26 | V1 | K4: Direct (campaign tagged in CRM) | L4: Natuf | LAL 1% | India | Jul26 | V1 | M4: Natuf | LAL 1% | India | Jul26 | V1 | N4: Natuf | Reel | Brand Ambassador | Heard Of Owning A Cafe | V1 | O4: In House Natuf | P4: Facebook | Q4: (Unassigned) | R4: Omkar Navge | S4: - | T4: Srinagar | V4: 0 | W4: 0 | X4: XXXXXX5286 | Y4: 46326.531
A5: 6ae59349481a67e46c03f3ae | B5: 46326.525 | C5: 46326 | D5: 2026-10 | E5: Wk of 2026-10-26 | F5: New Lead | G5: =IF(ISNUMBER(MATCH(F5,QualityStatuses,0)),"Quality Lead","Non-Quality Lead") -> Non-Quality Lead | H5: =IFERROR(INDEX(CampTypes,MATCH(I5,CampList,0)),"Unattributed") -> New | I5: ABO | Natuf | Leads | Unit Franchise | India | Oct26 | V1 | J5: ABO | Natuf | Leads | Unit Franchise | India | Oct26 | V1 | K5: Direct (campaign tagged in CRM) | L5: Natuf | Business Owners | Tier1 + Growth Cities | Oct26 | V1 | M5: Natuf | Business Owners | Tier1 + Growth Cities | Oct26 | V1 | N5: Natuf | Reel | Brand Ambassador | Heard Of Owning A Cafe | V1 | O5: In House Natuf | P5: Facebook | Q5: Marshal Malbari | R5: Drishti Lodhia | S5: - | T5: Raipur | V5: 0 | W5: 0 | X5: XXXXXX9660 | Y5: 46326.525
A6: 6ae58f6ead9b3f10ed1ee1f8 | B6: 46326.513 | C6: 46326 | D6: 2026-10 | E6: Wk of 2026-10-26 | F6: New Lead | G6: =IF(ISNUMBER(MATCH(F6,QualityStatuses,0)),"Quality Lead","Non-Quality Lead") -> Non-Quality Lead | H6: =IFERROR(INDEX(CampTypes,MATCH(I6,CampList,0)),"Unattributed") -> New | I6: ABO | Natuf | Leads | Unit Franchise | India | Oct26 | V1 | J6: ABO | Natuf | Leads | Unit Franchise | India | Oct26 | V1 | K6: Direct (campaign tagged in CRM) | L6: Natuf | Business Owners | Tier1 + Growth Cities | Oct26 | V1 | M6: Natuf | Business Owners | Tier1 + Growth Cities | Oct26 | V1 | N6: Natuf | Reel | Brand Ambassador | Heard Of Owning A Cafe | V1 | O6: In House Natuf | P6: Facebook | Q6: (Unassigned) | R6: Omkar Navge | S6: - | T6: jaipur | V6: 0 | W6: 0 | X6: XXXXXX7989 | Y6: 46326.52
A7: 6ae58f56a3c40b362d514506 | B7: 46326.513 | C7: 46326 | D7: 2026-10 | E7: Wk of 2026-10-26 | F7: New Lead | G7: =IF(ISNUMBER(MATCH(F7,QualityStatuses,0)),"Quality Lead","Non-Quality Lead") -> Non-Quality Lead | H7: =IFERROR(INDEX(CampTypes,MATCH(I7,CampList,0)),"Unattributed") -> New | I7: ABO | Natuf | Leads | Unit Franchise | India | Oct26 | V1 | J7: ABO | Natuf | Leads | Unit Franchise | India | Oct26 | V1 | K7: Direct (campaign tagged in CRM) | L7: Natuf | Investors | Tier1 + Growth Cities | Oct26 | V1 | M7: Natuf | Investors | Tier1 + Growth Cities | Oct26 | V1 | N7: Natuf | Reel | Brand Ambassador | Heard Of Owning A Cafe | V1 | O7: In House Natuf | P7: Facebook | Q7: Marshal Malbari | R7: Shubham Menon | S7: - | T7: Nagpur | V7: 0 | W7: 0 | X7: XXXXXX9250 | Y7: 46326.52
A8: 6ae58effd0aa4b0328d1c585 | B8: 46326.512 | C8: 46326 | D8: 2026-10 | E8: Wk of 2026-10-26 | F8: New Lead | G8: =IF(ISNUMBER(MATCH(F8,QualityStatuses,0)),"Quality Lead","Non-Quality Lead") -> Non-Quality Lead | H8: =IFERROR(INDEX(CampTypes,MATCH(I8,CampList,0)),"Unattributed") -> New | I8: ABO | Natuf | Leads | Unit Franchise | India | Oct26 | V1 | J8: ABO | Natuf | Leads | Unit Franchise | India | Oct26 | V1 | K8: Direct (campaign tagged in CRM) | L8: Natuf | Investors | Tier1 + Growth Cities | Oct26 | V1 | M8: Natuf | Investors | Tier1 + Growth Cities | Oct26 | V1 | N8: Natuf | Reel | Brand Ambassador | Heard Of Owning A Cafe | V1 | O8: In House Natuf | P8: Facebook | Q8: (Unassigned) | R8: Omkar Navge | S8: - | T8: New Delhi | V8: 0 | W8: 0 | X8: XXXXXX9615 | Y8: 46326.52
A9: 6ae58ee221cda82dfed326df | B9: 46326.512 | C9: 46326 | D9: 2026-10 | E9: Wk of 2026-10-26 | F9: New Lead | G9: =IF(ISNUMBER(MATCH(F9,QualityStatuses,0)),"Quality Lead","Non-Quality Lead") -> Non-Quality Lead | H9: =IFERROR(INDEX(CampTypes,MATCH(I9,CampList,0)),"Unattributed") -> New | I9: ABO | Natuf | Leads | Unit Franchise | India | Oct26 | V1 | J9: ABO | Natuf | Leads | Unit Franchise | India | Oct26 | V1 | K9: Direct (campaign tagged in CRM) | L9: Natuf | Broad | Tier1 + Growth Cities | Oct26 | V1 | M9: Natuf | Broad | Tier1 + Growth Cities | Oct26 | V1 | N9: Natuf | Reel | Brand Ambassador | Heard Of Owning A Cafe | V1 | O9: In House Natuf | P9: Facebook | Q9: (Unassigned) | R9: Omkar Navge | S9: - | T9: Pune | V9: 0 | W9: 0 | X9: XXXXXX8532 | Y9: 46326.52
A10: 6ae58d3adb91a7cf96deb9cf | B10: 46326.507 | C10: 46326 | D10: 2026-10 | E10: Wk of 2026-10-26 | F10: Attempt 1 | G10: =IF(ISNUMBER(MATCH(F10,QualityStatuses,0)),"Quality Lead","Non-Quality Lead") -> Non-Quality Lead | H10: =IFERROR(INDEX(CampTypes,MATCH(I10,CampList,0)),"Unattributed") -> New | I10: ABO | Natuf | Leads | Unit Franchise | India | Oct26 | V1 | J10: ABO | Natuf | Leads | Unit Franchise | India | Oct26 | V1 | K10: Direct (campaign tagged in CRM) | L10: Natuf | Broad | Tier1 + Growth Cities | Oct26 | V1 | M10: Natuf | Broad | Tier1 + Growth Cities | Oct26 | V1 | N10: Natuf | Reel | Brand Ambassador | Heard Of Owning A Cafe | V1 | O10: In House Natuf | P10: Facebook | Q10: Vikas Pathak | R10: Hriday Jindal | S10: - | T10: Jadugoda | V10: 1 | W10: 0 | X10: XXXXXX3193 | Y10: 46326.535
A11: 6ae58b5dc80e9a3a8ca338fa | B11: 46326.501 | C11: 46326 | D11: 2026-10 | E11: Wk of 2026-10-26 | F11: New Lead | G11: =IF(ISNUMBER(MATCH(F11,QualityStatuses,0)),"Quality Lead","Non-Quality Lead") -> Non-Quality Lead | H11: =IFERROR(INDEX(CampTypes,MATCH(I11,CampList,0)),"Unattributed") -> New | I11: ABO | Natuf | Leads | Master Franchise | India | Oct26 | V1 | J11: ABO | Natuf | Leads | Master Franchise | India | Oct26 | V1 | K11: Direct (campaign tagged in CRM) | L11: Natuf | LAL 1% | India | Jul26 | V1 | M11: Natuf | LAL 1% | India | Jul26 | V1 | N11: Natuf | Static | Become A Levantine Food | V1 | O11: Natuf_MF | P11: Facebook | Q11: Shivam Kumar | R11: Nagaraju Mandala | S11: - | T11: Bathinda | V11: 0 | W11: 0 | X11: XXXXXX0099 | Y11: 46326.52
A12: 6ae5894b252750c50e8a30e2 | B12: 46326.495 | C12: 46326 | D12: 2026-10 | E12: Wk of 2026-10-26 | F12: New Lead | G12: =IF(ISNUMBER(MATCH(F12,QualityStatuses,0)),"Quality Lead","Non-Quality Lead") -> Non-Quality Lead | H12: =IFERROR(INDEX(CampTypes,MATCH(I12,CampList,0)),"Unattributed") -> New | I12: ABO | Natuf | Leads | Unit Franchise | India | Oct26 | V1 | J12: ABO | Natuf | Leads | Unit Franchise | India | Oct26 | V1 | K12: Direct (campaign tagged in CRM) | L12: Natuf | Investors | Tier1 + Growth Cities | Oct26 | V1 | M12: Natuf | Investors | Tier1 + Growth Cities | Oct26 | V1 | N12: Natuf | Reel | Brand Ambassador | Heard Of Owning A Cafe | V1 | O12: In House Natuf | P12: Facebook | Q12: (Unassigned) | R12: Omkar Navge | S12: - | T12: Hyderabad | V12: 0 | W12: 0 | X12: XXXXXX9825 | Y12: 46326.52
A13: 6ae587d98135cd63e5061f00 | B13: 46326.491 | C13: 46326 | D13: 2026-10 | E13: Wk of 2026-10-26 | F13: Attempt 1 | G13: =IF(ISNUMBER(MATCH(F13,QualityStatuses,0)),"Quality Lead","Non-Quality Lead") -> Non-Quality Lead | H13: =IFERROR(INDEX(CampTypes,MATCH(I13,CampList,0)),"Unattributed") -> New | I13: ABO | Natuf | Leads | Unit Franchise | India | Oct26 | V1 | J13: ABO | Natuf | Leads | Unit Franchise | India | Oct26 | V1 | K13: Direct (campaign tagged in CRM) | L13: Natuf | Broad | Tier1 + Growth Cities | Oct26 | V1 | M13: Natuf | Broad | Tier1 + Growth Cities | Oct26 | V1 | N13: Natuf | Reel | Brand Ambassador | Heard Of Owning A Cafe | V1 | O13: In House Natuf | P13: Facebook | Q13: Vikas Pathak | R13: Karan | S13: - | T13: Patna | V13: 1 | W13: 0 | X13: XXXXXX3571 | Y13: 46326.535
... A47: 6ae53fb2c63618b46b74d079 | B47: 46326.277 | C47: 46326 | D47: 2026-10 | E47: Wk of 2026-10-26 | F47: Lost | G47: =IF(ISNUMBER(MATCH(F47,QualityStatuses,0)),"Quality Lead","Non-Quality Lead") -> Non-Quality Lead | H47: =IFERROR(INDEX(CampTypes,MATCH(I47,CampList,0)),"Unattributed") -> New | I47: ABO | Natuf | Leads | Master Franchise | India | Oct26 | V1 | J47: ABO | Natuf | Leads | Master Franchise | India | Oct26 | V1 | K47: Direct (campaign tagged in CRM) | L47: Natuf | Broad | Tier1 + Growth Cities | Oct26 | V1 | M47: Natuf | Broad | Tier1 + Growth Cities | Oct26 | V1 | N47: Natuf | Static | Become A Levantine Food | V1 | O47: Natuf_MF | P47: Facebook | Q47: Marshal Malbari | R47: Rudresh Thorat | S47: Junk | T47: 6 | V47: 1 | W47: 1 | X47: XXXXXX7364 | Y47: 46326.52
A48: 6ae53c5abd0b6ad51bc29a73 | B48: 46326.267 | C48: 46326 | D48: 2026-10 | E48: Wk of 2026-10-26 | F48: Details Shared | G48: =IF(ISNUMBER(MATCH(F48,QualityStatuses,0)),"Quality Lead","Non-Quality Lead") -> Quality Lead | H48: =IFERROR(INDEX(CampTypes,MATCH(I48,CampList,0)),"Unattributed") -> New | I48: ABO | Natuf | Leads | Unit Franchise | India | Oct26 | V1 | J48: ABO | Natuf | Leads | Unit Franchise | India | Oct26 | V1 | K48: Direct (campaign tagged in CRM) | L48: Natuf | LAL 1% | India | Jul26 | V1 | M48: Natuf | LAL 1% | India | Jul26 | V1 | N48: Natuf | Reel | Brand Ambassador | Heard Of Owning A Cafe | V1 | O48: In House Natuf | P48: Facebook | Q48: Marshal Malbari | R48: Rudresh Thorat | S48: - | T48: Bahraich | U48: uttar_pradesh_(₹3_cr) | V48: 3 | W48: 2 | X48: XXXXXX5424 | Y48: 46326.502
A49: 6ae537e069599a4e0e6c8402 | B49: 46326.254 | C49: 46326 | D49: 2026-10 | E49: Wk of 2026-10-26 | F49: New Lead | G49: =IF(ISNUMBER(MATCH(F49,QualityStatuses,0)),"Quality Lead","Non-Quality Lead") -> Non-Quality Lead | H49: =IFERROR(INDEX(CampTypes,MATCH(I49,CampList,0)),"Unattributed") -> New | I49: ABO | Natuf | Leads | Unit Franchise | India | Oct26 | V1 | J49: ABO | Natuf | Leads | Unit Franchise | India | Oct26 | V1 | K49: Direct (campaign tagged in CRM) | L49: Natuf | Investors | Tier1 + Growth Cities | Oct26 | V1 | M49: Natuf | Investors | Tier1 + Growth Cities | Oct26 | V1 | N49: Natuf | Reel | Brand Ambassador | Heard Of Owning A Cafe | V1 | O49: In House Natuf | P49: Facebook | Q49: (Unassigned) | R49: Omkar Navge | S49: - | T49: Gopalganj | V49: 0 | W49: 0 | X49: XXXXXX5346 | Y49: 46326.52
A50: 6ae50d4d8b0ca8414d183a03 | B50: 46326.128 | C50: 46326 | D50: 2026-10 | E50: Wk of 2026-10-26 | F50: Attempt 1 | G50: =IF(ISNUMBER(MATCH(F50,QualityStatuses,0)),"Quality Lead","Non-Quality Lead") -> Non-Quality Lead | H50: =IFERROR(INDEX(CampTypes,MATCH(I50,CampList,0)),"Unattributed") -> New | I50: ABO | Natuf | Leads | Unit Franchise | India | Oct26 | V1 | J50: ABO | Natuf | Leads | Unit Franchise | India | Oct26 | V1 | K50: Direct (campaign tagged in CRM) | L50: Natuf | Business Owners | Tier1 + Growth Cities | Oct26 | V1 | M50: Natuf | Business Owners | Tier1 + Growth Cities | Oct26 | V1 | N50: Natuf | Reel | Brand Ambassador | Heard Of Owning A Cafe | V1 | O50: In House Natuf | P50: Facebook | Q50: Vikas Pathak | R50: Hriday Jindal | S50: - | T50: Lucknow | V50: 2 | W50: 0 | X50: XXXXXX3921 | Y50: 46326.52
A51: 6ae502f06a214b40e456e010 | B51: 46326.097 | C51: 46326 | D51: 2026-10 | E51: Wk of 2026-10-26 | F51: New Lead | G51: =IF(ISNUMBER(MATCH(F51,QualityStatuses,0)),"Quality Lead","Non-Quality Lead") -> Non-Quality Lead | H51: =IFERROR(INDEX(CampTypes,MATCH(I51,CampList,0)),"Unattributed") -> New | I51: ABO | Natuf | Leads | Master Franchise | India | Oct26 | V1 | J51: ABO | Natuf | Leads | Master Franchise | India | Oct26 | V1 | K51: Direct (campaign tagged in CRM) | L51: Natuf | Business Owners | Tier1 + Growth Cities | Oct26 | V1 | M51: Natuf | Business Owners | Tier1 + Growth Cities | Oct26 | V1 | N51: Natuf | Static | Become A Levantine Food | V1 | O51: Natuf_MF | P51: Facebook | Q51: Marshal Malbari | R51: Rinkita Virvani | S51: - | T51: आशान | V51: 0 | W51: 0 | X51: XXXXXX6073 | Y51: 46326.52
A52: 6ae4f9deabc693318c229008 | B52: 46326.07 | C52: 46326 | D52: 2026-10 | E52: Wk of 2026-10-26 | F52: New Lead | G52: =IF(ISNUMBER(MATCH(F52,QualityStatuses,0)),"Quality Lead","Non-Quality Lead") -> Non-Quality Lead | H52: =IFERROR(INDEX(CampTypes,MATCH(I52,CampList,0)),"Unattributed") -> New | I52: ABO | Natuf | Leads | Unit Franchise | India | Oct26 | V1 | J52: ABO | Natuf | Leads | Unit Franchise | India | Oct26 | V1 | K52: Direct (campaign tagged in CRM) | L52: Natuf | Business Owners | Tier1 + Growth Cities | Oct26 | V1 | M52: Natuf | Business Owners | Tier1 + Growth Cities | Oct26 | V1 | N52: Natuf | Reel | Brand Ambassador | Heard Of Owning A Cafe | V1 | O52: In House Natuf | P52: Facebook | Q52: (Unassigned) | R52: Omkar Navge | S52: - | T52: Noida | V52: 0 | W52: 0 | X52: XXXXXX0570 | Y52: 46326.52
A53: 6ae4f7ee8ea12fb2c39069fb | B53: 46326.065 | C53: 46326 | D53: 2026-10 | E53: Wk of 2026-10-26 | F53: Details Shared | G53: =IF(ISNUMBER(MATCH(F53,QualityStatuses,0)),"Quality Lead","Non-Quality Lead") -> Quality Lead | H53: =IFERROR(INDEX(CampTypes,MATCH(I53,CampList,0)),"Unattributed") -> New | I53: ABO | Natuf | Leads | Master Franchise | India | Oct26 | V1 | J53: ABO | Natuf | Leads | Master Franchise | India | Oct26 | V1 | K53: Direct (campaign tagged in CRM) | L53: Natuf | LAL 1% | India | Jul26 | V1 | M53: Natuf | LAL 1% | India | Jul26 | V1 | N53: Natuf | Static | Become A Levantine Food | V1 | O53: Natuf_MF | P53: Facebook | Q53: Marshal Malbari | R53: Pammi Roy | S53: - | T53: Osmanabad | V53: 1 | W53: 1 | X53: XXXXXX9895 | Y53: 46326.52
A54: 6ae4f537c0cb08f341dd357f | B54: 46326.056 | C54: 46326 | D54: 2026-10 | E54: Wk of 2026-10-26 | F54: Details Shared | G54: =IF(ISNUMBER(MATCH(F54,QualityStatuses,0)),"Quality Lead","Non-Quality Lead") -> Quality Lead | H54: =IFERROR(INDEX(CampTypes,MATCH(I54,CampList,0)),"Unattributed") -> New | I54: ABO | Natuf | Leads | Unit Franchise | India | Oct26 | V1 | J54: ABO | Natuf | Leads | Unit Franchise | India | Oct26 | V1 | K54: Direct (campaign tagged in CRM) | L54: Natuf | Investors | Tier1 + Growth Cities | Oct26 | V1 | M54: Natuf | Investors | Tier1 + Growth Cities | Oct26 | V1 | N54: Natuf | Reel | Brand Ambassador | Heard Of Owning A Cafe | V1 | O54: In House Natuf | P54: Facebook | Q54: Vikas Pathak | R54: Karan | S54: - | T54: Doddabalapura | V54: 1 | W54: 1 | X54: XXXXXX5634 | Y54: 46326.533
A55: 6ae4f453be920aaa70f3a1a4 | B55: 46326.054 | C55: 46326 | D55: 2026-10 | E55: Wk of 2026-10-26 | F55: Attempt 1 | G55: =IF(ISNUMBER(MATCH(F55,QualityStatuses,0)),"Quality Lead","Non-Quality Lead") -> Non-Quality Lead | H55: =IFERROR(INDEX(CampTypes,MATCH(I55,CampList,0)),"Unattributed") -> New | I55: ABO | Natuf | Leads | Unit Franchise | India | Oct26 | V1 | J55: ABO | Natuf | Leads | Unit Franchise | India | Oct26 | V1 | K55: Direct (campaign tagged in CRM) | L55: Natuf | Broad | Tier1 + Growth Cities | Oct26 | V1 | M55: Natuf | Broad | Tier1 + Growth Cities | Oct26 | V1 | N55: Natuf | Reel | Brand Ambassador | Heard Of Owning A Cafe | V1 | O55: In House Natuf | P55: Facebook | Q55: Vikas Pathak | R55: Anish kaundal | S55: - | T55: Hyderabad | V55: 1 | W55: 1 | X55: XXXXXX0005 | Y55: 46326.53
A56: 6ae4f4436e0f4585fe2247a9 | B56: 46326.054 | C56: 46326 | D56: 2026-10 | E56: Wk of 2026-10-26 | F56: New Lead | G56: =IF(ISNUMBER(MATCH(F56,QualityStatuses,0)),"Quality Lead","Non-Quality Lead") -> Non-Quality Lead | H56: =IFERROR(INDEX(CampTypes,MATCH(I56,CampList,0)),"Unattributed") -> New | I56: ABO | Natuf | Leads | Master Franchise | India | Oct26 | V1 | J56: ABO | Natuf | Leads | Master Franchise | India | Oct26 | V1 | K56: Direct (campaign tagged in CRM) | L56: Natuf | Broad | Tier1 + Growth Cities | Oct26 | V1 | M56: Natuf | Broad | Tier1 + Growth Cities | Oct26 | V1 | N56: Natuf | Static | Become A Levantine Food | V1 | O56: Natuf_MF | P56: Facebook | Q56: Marshal Malbari | R56: Drishti Lodhia | S56: - | T56: Ramesh | V56: 0 | W56: 0 | X56: XXXXXX9485 | Y56: 46326.52
A57: 6ae4f244c22f91a27cf9b10a | B57: 46326.048 | C57: 46326 | D57: 2026-10 | E57: Wk of 2026-10-26 | F57: New Lead | G57: =IF(ISNUMBER(MATCH(F57,QualityStatuses,0)),"Quality Lead","Non-Quality Lead") -> Non-Quality Lead | H57: =IFERROR(INDEX(CampTypes,MATCH(I57,CampList,0)),"Unattributed") -> New | I57: ABO | Natuf | Leads | Unit Franchise | India | Oct26 | V1 | J57: ABO | Natuf | Leads | Unit Franchise | India | Oct26 | V1 | K57: Direct (campaign tagged in CRM) | L57: Natuf | Investors | Tier1 + Growth Cities | Oct26 | V1 | M57: Natuf | Investors | Tier1 + Growth Cities | Oct26 | V1 | N57: Natuf | Reel | Brand Ambassador | Heard Of Owning A Cafe | V1 | O57: In House Natuf | P57: Facebook | Q57: (Unassigned) | R57: Omkar Navge | S57: - | T57: Hyderabad | V57: 0 | W57: 0 | X57: XXXXXX4560 | Y57: 46326.52
A58: 6ae4eed6fd2eb58fb1024396 | B58: 46326.038 | C58: 46326 | D58: 2026-10 | E58: Wk of 2026-10-26 | F58: New Lead | G58: =IF(ISNUMBER(MATCH(F58,QualityStatuses,0)),"Quality Lead","Non-Quality Lead") -> Non-Quality Lead | H58: =IFERROR(INDEX(CampTypes,MATCH(I58,CampList,0)),"Unattributed") -> New | I58: ABO | Natuf | Leads | Unit Franchise | India | Oct26 | V1 | J58: ABO | Natuf | Leads | Unit Franchise | India | Oct26 | V1 | K58: Direct (campaign tagged in CRM) | L58: Natuf | Business Owners | Tier1 + Growth Cities | Oct26 | V1 | M58: Natuf | Business Owners | Tier1 + Growth Cities | Oct26 | V1 | N58: Natuf | Reel | Brand Ambassador | Heard Of Owning A Cafe | V1 | O58: In House Natuf | P58: Facebook | Q58: Marshal Malbari | R58: Rinkita Virvani | S58: - | T58: Nouda | V58: 0 | W58: 0 | X58: XXXXXX0829 | Y58: 46326.52
A59: 6ae4ee9ffd2eb58fb1024357 | B59: 46326.037 | C59: 46326 | D59: 2026-10 | E59: Wk of 2026-10-26 | F59: New Lead | G59: =IF(ISNUMBER(MATCH(F59,QualityStatuses,0)),"Quality Lead","Non-Quality Lead") -> Non-Quality Lead | H59: =IFERROR(INDEX(CampTypes,MATCH(I59,CampList,0)),"Unattributed") -> New | I59: ABO | Natuf | Leads | Unit Franchise | India | Oct26 | V1 | J59: ABO | Natuf | Leads | Unit Franchise | India | Oct26 | V1 | K59: Direct (campaign tagged in CRM) | L59: Natuf | Investors | Tier1 + Growth Cities | Oct26 | V1 | M59: Natuf | Investors | Tier1 + Growth Cities | Oct26 | V1 | N59: Natuf | Reel | Brand Ambassador | Heard Of Owning A Cafe | V1 | O59: In House Natuf | P59: Facebook | Q59: (Unassigned) | R59: Omkar Navge | S59: - | T59: Ahmedabad | V59: 0 | W59: 0 | X59: XXXXXX8899 | Y59: 46326.52
A60: 6ae4ee95ac07bde7b9bcd37e | B60: 46326.037 | C60: 46326 | D60: 2026-10 | E60: Wk of 2026-10-26 | F60: Attempt 1 | G60: =IF(ISNUMBER(MATCH(F60,QualityStatuses,0)),"Quality Lead","Non-Quality Lead") -> Non-Quality Lead | H60: =IFERROR(INDEX(CampTypes,MATCH(I60,CampList,0)),"Unattributed") -> New | I60: ABO | Natuf | Leads | Unit Franchise | India | Oct26 | V1 | J60: ABO | Natuf | Leads | Unit Franchise | India | Oct26 | V1 | K60: Direct (campaign tagged in CRM) | L60: Natuf | Broad | Tier1 + Growth Cities | Oct26 | V1 | M60: Natuf | Broad | Tier1 + Growth Cities | Oct26 | V1 | N60: Natuf | Reel | Brand Ambassador | Heard Of Owning A Cafe | V1 | O60: In House Natuf | P60: Facebook | Q60: Marshal Malbari | R60: Pammi Roy | S60: - | T60: Pondicherry | V60: 1 | W60: 0 | X60: XXXXXX8582 | Y60: 46326.52
... A386: 6ae216c31b25b79660b9c544 | B386: 46323.88 | C386: 46323 | D386: 2026-10 | E386: Wk of 2026-10-26 | F386: Attempt 2 | G386: =IF(ISNUMBER(MATCH(F386,QualityStatuses,0)),"Quality Lead","Non-Quality Lead") -> Non-Quality Lead | H386: =IFERROR(INDEX(CampTypes,MATCH(I386,CampList,0)),"Unattributed") -> New | I386: ABO | Natuf | Leads | Unit Franchise | India | Oct26 | V1 | J386: ABO | Natuf | Leads | Unit Franchise | India | Oct26 | V1 | K386: Direct (campaign tagged in CRM) | L386: Natuf | LAL 1% | India | Jul26 | V1 | M386: Natuf | LAL 1% | India | Jul26 | V1 | N386: Natuf | Reel | Brand Ambassador | Heard Of Owning A Cafe | V1 | O386: In House Natuf | P386: Facebook | Q386: Vikas Pathak | R386: Anish kaundal | S386: - | T386: Noida, India | V386: 2 | W386: 0 | X386: XXXXXX0370 | Y386: 46326.52
A387: 6ae2111d7365aa841f80e147 | B387: 46323.864 | C387: 46323 | D387: 2026-10 | E387: Wk of 2026-10-26 | F387: Attempt 1 | G387: =IF(ISNUMBER(MATCH(F387,QualityStatuses,0)),"Quality Lead","Non-Quality Lead") -> Non-Quality Lead | H387: =IFERROR(INDEX(CampTypes,MATCH(I387,CampList,0)),"Unattributed") -> New | I387: ABO | Natuf | Leads | Unit Franchise | India | Oct26 | V1 | J387: ABO | Natuf | Leads | Unit Franchise | India | Oct26 | V1 | K387: Direct (campaign tagged in CRM) | L387: Natuf | Broad | Tier1 + Growth Cities | Oct26 | V1 | M387: Natuf | Broad | Tier1 + Growth Cities | Oct26 | V1 | N387: Natuf | Reel | Brand Ambassador | Heard Of Owning A Cafe | V1 | O387: In House Natuf | P387: Facebook | Q387: Omkar Navge | R387: Somya | S387: - | T387: Navimumbai | U387: maharashtra_(₹3_cr) | V387: 1 | W387: 0 | X387: XXXXXX4280 | Y387: 46325.626
A388: 6ae210fab199d8558f305e32 | B388: 46323.863 | C388: 46323 | D388: 2026-10 | E388: Wk of 2026-10-26 | F388: Attempt 1 | G388: =IF(ISNUMBER(MATCH(F388,QualityStatuses,0)),"Quality Lead","Non-Quality Lead") -> Non-Quality Lead | H388: =IFERROR(INDEX(CampTypes,MATCH(I388,CampList,0)),"Unattributed") -> New | I388: ABO | Natuf | Leads | Unit Franchise | India | Oct26 | V1 | J388: ABO | Natuf | Leads | Unit Franchise | India | Oct26 | V1 | K388: Direct (campaign tagged in CRM) | L388: Natuf | Business Owners | Tier1 + Growth Cities | Oct26 | V1 | M388: Natuf | Business Owners | Tier1 + Growth Cities | Oct26 | V1 | N388: Natuf | Reel | Brand Ambassador | Heard Of Owning A Cafe | V1 | O388: In House Natuf | P388: Facebook | Q388: Omkar Navge | R388: Jasmine | S388: - | T388: Delhi | V388: 1 | W388: 1 | X388: XXXXXX9529 | Y388: 46326.52
A389: 6ae210c667de21eb71b87d69 | B389: 46323.863 | C389: 46323 | D389: 2026-10 | E389: Wk of 2026-10-26 | F389: Attempt 1 | G389: =IF(ISNUMBER(MATCH(F389,QualityStatuses,0)),"Quality Lead","Non-Quality Lead") -> Non-Quality Lead | H389: =IFERROR(INDEX(CampTypes,MATCH(I389,CampList,0)),"Unattributed") -> New | I389: ABO | Natuf | Leads | Unit Franchise | India | Oct26 | V1 | J389: ABO | Natuf | Leads | Unit Franchise | India | Oct26 | V1 | K389: Direct (campaign tagged in CRM) | L389: Natuf | Business Owners | Tier1 + Growth Cities | Oct26 | V1 | M389: Natuf | Business Owners | Tier1 + Growth Cities | Oct26 | V1 | N389: Natuf | Reel | Brand Ambassador | Heard Of Owning A Cafe | V1 | O389: In House Natuf | P389: Facebook | Q389: Omkar Navge | R389: Jasmine | S389: - | T389: Nairobi | V389: 1 | W389: 0 | X389: XXXXXX9148 | Y389: 46326.52
A390: 6ae20f211ba72ba336c2b7f3 | B390: 46323.858 | C390: 46323 | D390: 2026-10 | E390: Wk of 2026-10-26 | F390: Attempt 2 | G390: =IF(ISNUMBER(MATCH(F390,QualityStatuses,0)),"Quality Lead","Non-Quality Lead") -> Non-Quality Lead | H390: =IFERROR(INDEX(CampTypes,MATCH(I390,CampList,0)),"Unattributed") -> New | I390: ABO | Natuf | Leads | Unit Franchise | India | Oct26 | V1 | J390: ABO | Natuf | Leads | Unit Franchise | India | Oct26 | V1 | K390: Direct (campaign tagged in CRM) | L390: Natuf | Broad | Tier1 + Growth Cities | Oct26 | V1 | M390: Natuf | Broad | Tier1 + Growth Cities | Oct26 | V1 | N390: Natuf | Reel | Brand Ambassador | Heard Of Owning A Cafe | V1 | O390: In House Natuf | P390: Facebook | Q390: Vikas Pathak | R390: Hriday Jindal | S390: - | T390: Ranchi | V390: 2 | W390: 0 | X390: XXXXXX5222 | Y390: 46326.52
A391: 6ae20ef2ba3f72ebb12a4f31 | B391: 46323.857 | C391: 46323 | D391: 2026-10 | E391: Wk of 2026-10-26 | F391: Details Shared | G391: =IF(ISNUMBER(MATCH(F391,QualityStatuses,0)),"Quality Lead","Non-Quality Lead") -> Quality Lead | H391: =IFERROR(INDEX(CampTypes,MATCH(I391,CampList,0)),"Unattributed") -> New | I391: ABO | Natuf | Leads | Unit Franchise | India | Oct26 | V1 | J391: ABO | Natuf | Leads | Unit Franchise | India | Oct26 | V1 | K391: Direct (campaign tagged in CRM) | L391: Natuf | LAL 1% | India | Jul26 | V1 | M391: Natuf | LAL 1% | India | Jul26 | V1 | N391: Natuf | Reel | Brand Ambassador | Heard Of Owning A Cafe | V1 | O391: In House Natuf | P391: Facebook | Q391: Omkar Navge | R391: Jasmine | S391: - | T391: Shilllong | V391: 2 | W391: 2 | X391: XXXXXX3018 | Y391: 46326.52
A392: 6ae20d59546f36c5b2ded0a9 | B392: 46323.852 | C392: 46323 | D392: 2026-10 | E392: Wk of 2026-10-26 | F392: Details Shared | G392: =IF(ISNUMBER(MATCH(F392,QualityStatuses,0)),"Quality Lead","Non-Quality Lead") -> Quality Lead | H392: =IFERROR(INDEX(CampTypes,MATCH(I392,CampList,0)),"Unattributed") -> New | I392: ABO | Natuf | Leads | Unit Franchise | India | Oct26 | V1 | J392: ABO | Natuf | Leads | Unit Franchise | India | Oct26 | V1 | K392: Direct (campaign tagged in CRM) | L392: Natuf | Investors | Tier1 + Growth Cities | Oct26 | V1 | M392: Natuf | Investors | Tier1 + Growth Cities | Oct26 | V1 | N392: Natuf | Reel | Brand Ambassador | Heard Of Owning A Cafe | V1 | O392: In House Natuf | P392: Facebook | Q392: Vikas Pathak | R392: Karan | S392: - | T392: Sohna | V392: 2 | W392: 2 | X392: XXXXXX9772 | Y392: 46326.52
A393: 6ae20cbb607f6717c9816060 | B393: 46323.851 | C393: 46323 | D393: 2026-10 | E393: Wk of 2026-10-26 | F393: Connected | G393: =IF(ISNUMBER(MATCH(F393,QualityStatuses,0)),"Quality Lead","Non-Quality Lead") -> Non-Quality Lead | H393: =IFERROR(INDEX(CampTypes,MATCH(I393,CampList,0)),"Unattributed") -> New | I393: ABO | Natuf | Leads | Unit Franchise | India | Oct26 | V1 | J393: ABO | Natuf | Leads | Unit Franchise | India | Oct26 | V1 | K393: Direct (campaign tagged in CRM) | L393: Natuf | Broad | Tier1 + Growth Cities | Oct26 | V1 | M393: Natuf | Broad | Tier1 + Growth Cities | Oct26 | V1 | N393: Natuf | Reel | Brand Ambassador | Heard Of Owning A Cafe | V1 | O393: In House Natuf | P393: Facebook | Q393: Vikas Pathak | R393: Anish kaundal | S393: - | T393: Noida | V393: 4 | W393: 3 | X393: XXXXXX3337 | Y393: 46326.52
A394: 6ae20a6b4a1a3e5dc13b01f0 | B394: 46323.844 | C394: 46323 | D394: 2026-10 | E394: Wk of 2026-10-26 | F394: Attempt 1 | G394: =IF(ISNUMBER(MATCH(F394,QualityStatuses,0)),"Quality Lead","Non-Quality Lead") -> Non-Quality Lead | H394: =IFERROR(INDEX(CampTypes,MATCH(I394,CampList,0)),"Unattributed") -> New | I394: ABO | Natuf | Leads | Unit Franchise | India | Oct26 | V1 | J394: ABO | Natuf | Leads | Unit Franchise | India | Oct26 | V1 | K394: Direct (campaign tagged in CRM) | L394: Natuf | LAL 1% | India | Jul26 | V1 | M394: Natuf | LAL 1% | India | Jul26 | V1 | N394: Natuf | Reel | Brand Ambassador | Heard Of Owning A Cafe | V1 | O394: In House Natuf | P394: Facebook | Q394: Omkar Navge | R394: Shambhavi | S394: - | T394: silchar | V394: 1 | W394: 0 | X394: XXXXXX3558 | Y394: 46326.52
A395: 6ae209d5a5b6558ee62f77c7 | B395: 46323.842 | C395: 46323 | D395: 2026-10 | E395: Wk of 2026-10-26 | F395: Attempt 1 | G395: =IF(ISNUMBER(MATCH(F395,QualityStatuses,0)),"Quality Lead","Non-Quality Lead") -> Non-Quality Lead | H395: =IFERROR(INDEX(CampTypes,MATCH(I395,CampList,0)),"Unattributed") -> New | I395: ABO | Natuf | Leads | Master Franchise | India | Oct26 | V1 | J395: ABO | Natuf | Leads | Master Franchise | India | Oct26 | V1 | K395: Direct (campaign tagged in CRM) | L395: Natuf | Investors | Tier1 + Growth Cities | Oct26 | V1 | M395: Natuf | Investors | Tier1 + Growth Cities | Oct26 | V1 | N395: Natuf | Static | Lead Your State With | V1 | O395: Natuf_MF | P395: Facebook | Q395: Marshal Malbari | R395: Tanishq A | S395: - | T395: Sendhwa | V395: 1 | W395: 0 | X395: XXXXXX7832 | Y395: 46326.52
A396: 6ae207c9609f78b72ae0a620 | B396: 46323.836 | C396: 46323 | D396: 2026-10 | E396: Wk of 2026-10-26 | F396: Attempt 1 | G396: =IF(ISNUMBER(MATCH(F396,QualityStatuses,0)),"Quality Lead","Non-Quality Lead") -> Non-Quality Lead | H396: =IFERROR(INDEX(CampTypes,MATCH(I396,CampList,0)),"Unattributed") -> New | I396: ABO | Natuf | Leads | Unit Franchise | India | Oct26 | V1 | J396: ABO | Natuf | Leads | Unit Franchise | India | Oct26 | V1 | K396: Direct (campaign tagged in CRM) | L396: Natuf | Investors | Tier1 + Growth Cities | Oct26 | V1 | M396: Natuf | Investors | Tier1 + Growth Cities | Oct26 | V1 | N396: Natuf | Reel | Brand Ambassador | Heard Of Owning A Cafe | V1 | O396: In House Natuf | P396: Facebook | Q396: Omkar Navge | R396: Shambhavi | S396: - | T396: udaipur Rajasthan | V396: 2 | W396: 1 | X396: XXXXXX0183 | Y396: 46326.52
A397: 6ae2074d41652ba312cc7190 | B397: 46323.835 | C397: 46323 | D397: 2026-10 | E397: Wk of 2026-10-26 | F397: Attempt 1 | G397: =IF(ISNUMBER(MATCH(F397,QualityStatuses,0)),"Quality Lead","Non-Quality Lead") -> Non-Quality Lead | H397: =IFERROR(INDEX(CampTypes,MATCH(I397,CampList,0)),"Unattributed") -> New | I397: ABO | Natuf | Leads | Unit Franchise | India | Oct26 | V1 | J397: ABO | Natuf | Leads | Unit Franchise | India | Oct26 | V1 | K397: Direct (campaign tagged in CRM) | L397: Natuf | Investors | Tier1 + Growth Cities | Oct26 | V1 | M397: Natuf | Investors | Tier1 + Growth Cities | Oct26 | V1 | N397: Natuf | Reel | Brand Ambassador | Heard Of Owning A Cafe | V1 | O397: In House Natuf | P397: Facebook | Q397: Marshal Malbari | R397: Shubham Menon | S397: - | T397: Patna | V397: 2 | W397: 0 | X397: XXXXXX5947 | Y397: 46326.52
A398: 6ae2019f4944c39e33b70527 | B398: 46323.818 | C398: 46323 | D398: 2026-10 | E398: Wk of 2026-10-26 | F398: Attempt 1 | G398: =IF(ISNUMBER(MATCH(F398,QualityStatuses,0)),"Quality Lead","Non-Quality Lead") -> Non-Quality Lead | H398: =IFERROR(INDEX(CampTypes,MATCH(I398,CampList,0)),"Unattributed") -> New | I398: ABO | Natuf | Leads | Unit Franchise | India | Oct26 | V1 | J398: ABO | Natuf | Leads | Unit Franchise | India | Oct26 | V1 | K398: Direct (campaign tagged in CRM) | L398: Natuf | LAL 1% | India | Jul26 | V1 | M398: Natuf | LAL 1% | India | Jul26 | V1 | N398: Natuf | Reel | Brand Ambassador | Heard Of Owning A Cafe | V1 | O398: In House Natuf | P398: Facebook | Q398: Omkar Navge | R398: Somya | S398: - | T398: Kannur | V398: 1 | W398: 0 | X398: XXXXXX0812 | Y398: 46326.52
A399: 6ae201116d7be33a54bcabea | B399: 46323.816 | C399: 46323 | D399: 2026-10 | E399: Wk of 2026-10-26 | F399: Attempt 1 | G399: =IF(ISNUMBER(MATCH(F399,QualityStatuses,0)),"Quality Lead","Non-Quality Lead") -> Non-Quality Lead | H399: =IFERROR(INDEX(CampTypes,MATCH(I399,CampList,0)),"Unattributed") -> New | I399: ABO | Natuf | Leads | Master Franchise | India | Oct26 | V1 | J399: ABO | Natuf | Leads | Master Franchise | India | Oct26 | V1 | K399: Direct (campaign tagged in CRM) | L399: Natuf | Business Owners | Tier1 + Growth Cities | Oct26 | V1 | M399: Natuf | Business Owners | Tier1 + Growth Cities | Oct26 | V1 | N399: Natuf | Static | Become A Levantine Food | V1 | O399: Natuf_MF | P399: Facebook | Q399: Marshal Malbari | R399: Tanishq A | S399: - | T399: Bhubaneswar | V399: 2 | W399: 0 | X399: XXXXXX0180 | Y399: 46326.52
... A740: 6adefde2e874a1f5befb2adb | B740: 46321.531 | C740: 46321 | D740: 2026-10 | E740: Wk of 2026-10-26 | F740: Attempt 1 | G740: =IF(ISNUMBER(MATCH(F740,QualityStatuses,0)),"Quality Lead","Non-Quality Lead") -> Non-Quality Lead | H740: =IFERROR(INDEX(CampTypes,MATCH(I740,CampList,0)),"Unattributed") -> New | I740: ABO | Natuf | Leads | Master Franchise | India | Oct26 | V1 | J740: ABO | Natuf | Leads | Master Franchise | India | Oct26 | V1 | K740: Direct (campaign tagged in CRM) | L740: Natuf | Investors | Tier1 + Growth Cities | Oct26 | V1 | M740: Natuf | Investors | Tier1 + Growth Cities | Oct26 | V1 | N740: Natuf | Static | Become A Levantine Food | V1 | O740: Natuf_MF | P740: Facebook | Q740: Tejaswini Tarigopula | R740: Rima Paul | S740: - | T740: Jamshedpur | V740: 2 | W740: 0 | X740: XXXXXX3241 | Y740: 46326.52
A741: 6adefd1c858430c985e92cac | B741: 46321.529 | C741: 46321 | D741: 2026-10 | E741: Wk of 2026-10-26 | F741: Connected | G741: =IF(ISNUMBER(MATCH(F741,QualityStatuses,0)),"Quality Lead","Non-Quality Lead") -> Non-Quality Lead | H741: =IFERROR(INDEX(CampTypes,MATCH(I741,CampList,0)),"Unattributed") -> New | I741: ABO | Natuf | Leads | Unit Franchise | India | Oct26 | V1 | J741: ABO | Natuf | Leads | Unit Franchise | India | Oct26 | V1 | K741: Direct (campaign tagged in CRM) | L741: Natuf | LAL 1% | India | Jul26 | V1 | M741: Natuf | LAL 1% | India | Jul26 | V1 | N741: Natuf | Reel | Brand Ambassador | Heard Of Owning A Cafe | V1 | O741: In House Natuf | P741: Facebook | Q741: Tejaswini Tarigopula | R741: Sai Charan | S741: - | T741: Navi Mumbai (New Mumbai) | U741: uttar_pradesh_(₹3_cr) | V741: 3 | W741: 3 | X741: XXXXXX2252 | Y741: 46324.598
A742: 6adef450a9655ebfcc4cfa62 | B742: 46321.503 | C742: 46321 | D742: 2026-10 | E742: Wk of 2026-10-26 | F742: Follow-Up | G742: =IF(ISNUMBER(MATCH(F742,QualityStatuses,0)),"Quality Lead","Non-Quality Lead") -> Quality Lead | H742: =IFERROR(INDEX(CampTypes,MATCH(I742,CampList,0)),"Unattributed") -> Old | I742: E_Karan_Natuf_All_07072026 | J742: E_Karan_Natuf_All_07072026 | K742: Direct (campaign tagged in CRM) | L742: E_Karan_Natuf_Sign_07072026_Adset3 | M742: E_Karan_Natuf_Sign_07072026_Adset3 | N742: E_Karan_Natuf_Sign_07072026_Adset2_Ad1 | O742: Natuf | P742: Facebook | Q742: Omkar Navge | R742: Somya | S742: - | T742: Raipur | U742: chhattisgarh_(₹1.5_cr) | V742: 2 | W742: 2 | X742: XXXXXX9664 | Y742: 46322.731
A743: 6adc6685304536018e706f33 | B743: 46319.566 | C743: 46319 | D743: 2026-10 | E743: Wk of 2026-10-19 | F743: Attempt 1 | G743: =IF(ISNUMBER(MATCH(F743,QualityStatuses,0)),"Quality Lead","Non-Quality Lead") -> Non-Quality Lead | H743: =IFERROR(INDEX(CampTypes,MATCH(I743,CampList,0)),"Unattributed") -> New | I743: ABO | Natuf | Leads | Unit Franchise | India | Oct26 | V1 | J743: ABO | Natuf | Leads | Unit Franchise | India | Oct26 | V1 | K743: Direct (campaign tagged in CRM) | L743: Natuf | Investors | Tier1 + Growth Cities | Oct26 | V1 | M743: Natuf | Investors | Tier1 + Growth Cities | Oct26 | V1 | N743: Natuf | Reel | Brand Ambassador | Heard Of Owning A Cafe | V1 | O743: In House Natuf | P743: Facebook | Q743: Omkar Navge | R743: Somya | S743: - | T743: New Delhi | V743: 1 | W743: 0 | X743: XXXXXX2839 | Y743: 46326.52
A744: 6adc651ad19d675a5c8c5a1a | B744: 46319.561 | C744: 46319 | D744: 2026-10 | E744: Wk of 2026-10-19 | F744: Connected | G744: =IF(ISNUMBER(MATCH(F744,QualityStatuses,0)),"Quality Lead","Non-Quality Lead") -> Non-Quality Lead | H744: =IFERROR(INDEX(CampTypes,MATCH(I744,CampList,0)),"Unattributed") -> New | I744: ABO | Natuf | Leads | Unit Franchise | India | Oct26 | V1 | J744: ABO | Natuf | Leads | Unit Franchise | India | Oct26 | V1 | K744: Direct (campaign tagged in CRM) | L744: Natuf | Investors | Tier1 + Growth Cities | Oct26 | V1 | M744: Natuf | Investors | Tier1 + Growth Cities | Oct26 | V1 | N744: Natuf | Reel | Brand Ambassador | Heard Of Owning A Cafe | V1 | O744: In House Natuf | P744: Facebook | Q744: Tejaswini Tarigopula | R744: Prabhudatta Pattanaik | S744: - | T744: ujjain | V744: 2 | W744: 1 | X744: XXXXXX3110 | Y744: 46326.52
A745: 6adc640a29c088fb644b3945 | B745: 46319.558 | C745: 46319 | D745: 2026-10 | E745: Wk of 2026-10-19 | F745: Connected | G745: =IF(ISNUMBER(MATCH(F745,QualityStatuses,0)),"Quality Lead","Non-Quality Lead") -> Non-Quality Lead | H745: =IFERROR(INDEX(CampTypes,MATCH(I745,CampList,0)),"Unattributed") -> New | I745: ABO | Natuf | Leads | Unit Franchise | India | Oct26 | V1 | J745: ABO | Natuf | Leads | Unit Franchise | India | Oct26 | V1 | K745: Direct (campaign tagged in CRM) | L745: Natuf | LAL 1% | India | Jul26 | V1 | M745: Natuf | LAL 1% | India | Jul26 | V1 | N745: Natuf | Reel | Brand Ambassador | Heard Of Owning A Cafe | V1 | O745: In House Natuf | P745: Facebook | Q745: Omkar Navge | R745: Somya | S745: - | T745: jaipur | V745: 1 | W745: 1 | X745: XXXXXX7163 | Y745: 46326.52
A746: 6adc63ef5acab979c1259e27 | B746: 46319.558 | C746: 46319 | D746: 2026-10 | E746: Wk of 2026-10-19 | F746: Connected | G746: =IF(ISNUMBER(MATCH(F746,QualityStatuses,0)),"Quality Lead","Non-Quality Lead") -> Non-Quality Lead | H746: =IFERROR(INDEX(CampTypes,MATCH(I746,CampList,0)),"Unattributed") -> New | I746: ABO | Natuf | Leads | Unit Franchise | India | Oct26 | V1 | J746: ABO | Natuf | Leads | Unit Franchise | India | Oct26 | V1 | K746: Direct (campaign tagged in CRM) | L746: Natuf | Investors | Tier1 + Growth Cities | Oct26 | V1 | M746: Natuf | Investors | Tier1 + Growth Cities | Oct26 | V1 | N746: Natuf | Reel | Brand Ambassador | Heard Of Owning A Cafe | V1 | O746: In House Natuf | P746: Facebook | Q746: Tejaswini Tarigopula | R746: Arjuman Vidya Sagar | S746: - | T746: Ahemdabad | V746: 1 | W746: 1 | X746: XXXXXX9838 | Y746: 46326.52
A747: 6adc638117793c419df97eab | B747: 46319.557 | C747: 46319 | D747: 2026-10 | E747: Wk of 2026-10-19 | F747: Attempt 1 | G747: =IF(ISNUMBER(MATCH(F747,QualityStatuses,0)),"Quality Lead","Non-Quality Lead") -> Non-Quality Lead | H747: =IFERROR(INDEX(CampTypes,MATCH(I747,CampList,0)),"Unattributed") -> New | I747: ABO | Natuf | Leads | Unit Franchise | India | Oct26 | V1 | J747: ABO | Natuf | Leads | Unit Franchise | India | Oct26 | V1 | K747: Direct (campaign tagged in CRM) | L747: Natuf | LAL 1% | India | Jul26 | V1 | M747: Natuf | LAL 1% | India | Jul26 | V1 | N747: Natuf | Reel | Brand Ambassador | Heard Of Owning A Cafe | V1 | O747: In House Natuf | P747: Facebook | Q747: Omkar Navge | R747: Somya | S747: - | T747: Kolkata | V747: 1 | W747: 0 | X747: XXXXXX3555 | Y747: 46326.52
A748: 6adc623875d1a246c037bed8 | B748: 46319.553 | C748: 46319 | D748: 2026-10 | E748: Wk of 2026-10-19 | F748: Details Shared | G748: =IF(ISNUMBER(MATCH(F748,QualityStatuses,0)),"Quality Lead","Non-Quality Lead") -> Quality Lead | H748: =IFERROR(INDEX(CampTypes,MATCH(I748,CampList,0)),"Unattributed") -> New | I748: ABO | Natuf | Leads | Master Franchise | India | Oct26 | V1 | J748: ABO | Natuf | Leads | Master Franchise | India | Oct26 | V1 | K748: Direct (campaign tagged in CRM) | L748: Natuf | LAL 1% | India | Jul26 | V1 | M748: Natuf | LAL 1% | India | Jul26 | V1 | N748: Natuf | Static | Become A Levantine Food | V1 | O748: Natuf_MF | P748: Facebook | Q748: Tejaswini Tarigopula | R748: Prabhudatta Pattanaik | S748: - | T748: Dewas | V748: 1 | W748: 1 | X748: XXXXXX2803 | Y748: 46326.52
A749: 6adc6010e5977ff980841fc9 | B749: 46319.546 | C749: 46319 | D749: 2026-10 | E749: Wk of 2026-10-19 | F749: Lost | G749: =IF(ISNUMBER(MATCH(F749,QualityStatuses,0)),"Quality Lead","Non-Quality Lead") -> Non-Quality Lead | H749: =IFERROR(INDEX(CampTypes,MATCH(I749,CampList,0)),"Unattributed") -> New | I749: ABO | Natuf | Leads | Master Franchise | India | Oct26 | V1 | J749: ABO | Natuf | Leads | Master Franchise | India | Oct26 | V1 | K749: Direct (campaign tagged in CRM) | L749: Natuf | Business Owners | Tier1 + Growth Cities | Oct26 | V1 | M749: Natuf | Business Owners | Tier1 + Growth Cities | Oct26 | V1 | N749: Natuf | Static | Become A Levantine Food | V1 | O749: Natuf_MF | P749: Facebook | Q749: Tejaswini Tarigopula | R749: Prabhudatta Pattanaik | S749: Junk | T749: Gadakana | V749: 1 | W749: 1 | X749: XXXXXX5074 | Y749: 46326.52
A750: 6adc5e80d19d675a5c8c5338 | B750: 46319.542 | C750: 46319 | D750: 2026-10 | E750: Wk of 2026-10-19 | F750: Details Shared | G750: =IF(ISNUMBER(MATCH(F750,QualityStatuses,0)),"Quality Lead","Non-Quality Lead") -> Quality Lead | H750: =IFERROR(INDEX(CampTypes,MATCH(I750,CampList,0)),"Unattributed") -> New | I750: ABO | Natuf | Leads | Unit Franchise | India | Oct26 | V1 | J750: ABO | Natuf | Leads | Unit Franchise | India | Oct26 | V1 | K750: Direct (campaign tagged in CRM) | L750: Natuf | LAL 1% | India | Jul26 | V1 | M750: Natuf | LAL 1% | India | Jul26 | V1 | N750: Natuf | Reel | Brand Ambassador | Heard Of Owning A Cafe | V1 | O750: In House Natuf | P750: Facebook | Q750: Vikas Pathak | R750: Hriday Jindal | S750: - | T750: Bengaluru | V750: 2 | W750: 2 | X750: XXXXXX5823 | Y750: 46326.52
A751: 6adc5b539f9dca9c6411b98a | B751: 46319.532 | C751: 46319 | D751: 2026-10 | E751: Wk of 2026-10-19 | F751: Lost | G751: =IF(ISNUMBER(MATCH(F751,QualityStatuses,0)),"Quality Lead","Non-Quality Lead") -> Non-Quality Lead | H751: =IFERROR(INDEX(CampTypes,MATCH(I751,CampList,0)),"Unattributed") -> New | I751: ABO | Natuf | Leads | Master Franchise | India | Oct26 | V1 | J751: ABO | Natuf | Leads | Master Franchise | India | Oct26 | V1 | K751: Direct (campaign tagged in CRM) | L751: Natuf | Investors | Tier1 + Growth Cities | Oct26 | V1 | M751: Natuf | Investors | Tier1 + Growth Cities | Oct26 | V1 | N751: Natuf | Static | Become A Levantine Food | V1 | O751: Natuf_MF | P751: Facebook | Q751: Tejaswini Tarigopula | R751: Prabhudatta Pattanaik | S751: Junk | T751: Kajal | V751: 1 | W751: 1 | X751: XXXXXX8602 | Y751: 46326.52
A752: 6adc5a72599621e9d4e1af2d | B752: 46319.53 | C752: 46319 | D752: 2026-10 | E752: Wk of 2026-10-19 | F752: Attempt 1 | G752: =IF(ISNUMBER(MATCH(F752,QualityStatuses,0)),"Quality Lead","Non-Quality Lead") -> Non-Quality Lead | H752: =IFERROR(INDEX(CampTypes,MATCH(I752,CampList,0)),"Unattributed") -> New | I752: ABO | Natuf | Leads | Unit Franchise | India | Oct26 | V1 | J752: ABO | Natuf | Leads | Unit Franchise | India | Oct26 | V1 | K752: Direct (campaign tagged in CRM) | L752: Natuf | Business Owners | Tier1 + Growth Cities | Oct26 | V1 | M752: Natuf | Business Owners | Tier1 + Growth Cities | Oct26 | V1 | N752: Natuf | Reel | Brand Ambassador | Heard Of Owning A Cafe | V1 | O752: In House Natuf | P752: Facebook | Q752: Omkar Navge | R752: Somya | S752: - | T752: Pune | V752: 1 | W752: 0 | X752: XXXXXX9678 | Y752: 46326.52
A753: 6adc592cb2e9433652533c9d | B753: 46319.526 | C753: 46319 | D753: 2026-10 | E753: Wk of 2026-10-19 | F753: Details Shared | G753: =IF(ISNUMBER(MATCH(F753,QualityStatuses,0)),"Quality Lead","Non-Quality Lead") -> Quality Lead | H753: =IFERROR(INDEX(CampTypes,MATCH(I753,CampList,0)),"Unattributed") -> New | I753: ABO | Natuf | Leads | Unit Franchise | India | Oct26 | V1 | J753: ABO | Natuf | Leads | Unit Franchise | India | Oct26 | V1 | K753: Direct (campaign tagged in CRM) | L753: Natuf | LAL 1% | India | Jul26 | V1 | M753: Natuf | LAL 1% | India | Jul26 | V1 | N753: Natuf | Reel | Brand Ambassador | Heard Of Owning A Cafe | V1 | O753: In House Natuf | P753: Facebook | Q753: Vikas Pathak | R753: Karan | S753: - | T753: Kolkata | V753: 2 | W753: 1 | X753: XXXXXX5549 | Y753: 46326.52
A754: 6adc58fbd79dfc1a8260c6c8 | B754: 46319.525 | C754: 46319 | D754: 2026-10 | E754: Wk of 2026-10-19 | F754: Attempt 1 | G754: =IF(ISNUMBER(MATCH(F754,QualityStatuses,0)),"Quality Lead","Non-Quality Lead") -> Non-Quality Lead | H754: =IFERROR(INDEX(CampTypes,MATCH(I754,CampList,0)),"Unattributed") -> New | I754: ABO | Natuf | Leads | Master Franchise | India | Oct26 | V1 | J754: ABO | Natuf | Leads | Master Franchise | India | Oct26 | V1 | K754: Direct (campaign tagged in CRM) | L754: Natuf | LAL 1% | India | Jul26 | V1 | M754: Natuf | LAL 1% | India | Jul26 | V1 | N754: Natuf | Static | Become A Levantine Food | V1 | O754: Natuf_MF | P754: Facebook | Q754: Tejaswini Tarigopula | R754: Rima Paul | S754: - | T754: Ratla | V754: 3 | W754: 1 | X754: XXXXXX0572 | Y754: 46326.52
... A858: 6adb7c8f4ff3ea4ba8596eac | B858: 46318.872 | C858: 46318 | D858: 2026-10 | E858: Wk of 2026-10-19 | F858: New Lead | G858: =IF(ISNUMBER(MATCH(F858,QualityStatuses,0)),"Quality Lead","Non-Quality Lead") -> Non-Quality Lead | H858: =IFERROR(INDEX(CampTypes,MATCH(I858,CampList,0)),"Unattributed") -> New | I858: ABO | Natuf | Leads | Unit Franchise | India | Oct26 | V1 | J858: ABO | Natuf | Leads | Unit Franchise | India | Oct26 | V1 | K858: Direct (campaign tagged in CRM) | L858: Natuf | Broad | Tier1 + Growth Cities | Oct26 | V1 | M858: Natuf | Broad | Tier1 + Growth Cities | Oct26 | V1 | N858: Natuf | Reel | Brand Ambassador | Heard Of Owning A Cafe | V1 | O858: In House Natuf | P858: Facebook | Q858: (Unassigned) | R858: Omkar Navge | S858: - | T858: Cuddalore | V858: 0 | W858: 0 | X858: XXXXXX9059 | Y858: 46326.52
A859: 6adb79f0280feb4c19a76c96 | B859: 46318.865 | C859: 46318 | D859: 2026-10 | E859: Wk of 2026-10-19 | F859: Attempt 2 | G859: =IF(ISNUMBER(MATCH(F859,QualityStatuses,0)),"Quality Lead","Non-Quality Lead") -> Non-Quality Lead | H859: =IFERROR(INDEX(CampTypes,MATCH(I859,CampList,0)),"Unattributed") -> Old | I859: E_Natuf_Generic_13082026 | J859: E_Natuf_Generic_13082026 | K859: Direct (campaign tagged in CRM) | L859: E_Natuf_Generic_13082026_Adset1 | M859: E_Natuf_Generic_13082026_Adset1 | N859: E_Natuf_Generic_13082026_Adset1_Ad1 | O859: Natuf | P859: Facebook | Q859: Tejaswini Tarigopula | R859: Sai Charan | S859: - | T859: Nashik | U859: maharashtra_(₹3_cr) | V859: 3 | W859: 0 | X859: XXXXXX3083 | Y859: 46322.663
A860: 6adb79ed4ff3ea4ba8596bd2 | B860: 46318.865 | C860: 46318 | D860: 2026-10 | E860: Wk of 2026-10-19 | F860: Details Shared | G860: =IF(ISNUMBER(MATCH(F860,QualityStatuses,0)),"Quality Lead","Non-Quality Lead") -> Quality Lead | H860: =IFERROR(INDEX(CampTypes,MATCH(I860,CampList,0)),"Unattributed") -> New | I860: ABO | Natuf | Leads | Unit Franchise | India | Oct26 | V1 | J860: ABO | Natuf | Leads | Unit Franchise | India | Oct26 | V1 | K860: Direct (campaign tagged in CRM) | L860: Natuf | Broad | Tier1 + Growth Cities | Oct26 | V1 | M860: Natuf | Broad | Tier1 + Growth Cities | Oct26 | V1 | N860: Natuf | Reel | Brand Ambassador | Heard Of Owning A Cafe | V1 | O860: In House Natuf | P860: Facebook | Q860: Vikas Pathak | R860: Anish kaundal | S860: - | T860: Bareja | V860: 6 | W860: 1 | X860: XXXXXX9116 | Y860: 46326.52
A861: 6adb7786e2e6b2734d0ab523 | B861: 46318.857 | C861: 46318 | D861: 2026-10 | E861: Wk of 2026-10-19 | F861: Attempt 1 | G861: =IF(ISNUMBER(MATCH(F861,QualityStatuses,0)),"Quality Lead","Non-Quality Lead") -> Non-Quality Lead | H861: =IFERROR(INDEX(CampTypes,MATCH(I861,CampList,0)),"Unattributed") -> New | I861: ABO | Natuf | Leads | Unit Franchise | India | Oct26 | V1 | J861: ABO | Natuf | Leads | Unit Franchise | India | Oct26 | V1 | K861: Direct (campaign tagged in CRM) | L861: Natuf | Broad | Tier1 + Growth Cities | Oct26 | V1 | M861: Natuf | Broad | Tier1 + Growth Cities | Oct26 | V1 | N861: Natuf | Reel | Brand Ambassador | Heard Of Owning A Cafe | V1 | O861: In House Natuf | P861: Facebook | Q861: Tejaswini Tarigopula | R861: Rima Paul | S861: - | T861: Vadodara | V861: 1 | W861: 0 | X861: XXXXXX6406 | Y861: 46326.52
A862: 6adb767f9a1de2887534177f | B862: 46318.854 | C862: 46318 | D862: 2026-10 | E862: Wk of 2026-10-19 | F862: New Lead | G862: =IF(ISNUMBER(MATCH(F862,QualityStatuses,0)),"Quality Lead","Non-Quality Lead") -> Non-Quality Lead | H862: =IFERROR(INDEX(CampTypes,MATCH(I862,CampList,0)),"Unattributed") -> New | I862: ABO | Natuf | Leads | Unit Franchise | India | Oct26 | V1 | J862: ABO | Natuf | Leads | Unit Franchise | India | Oct26 | V1 | K862: Direct (campaign tagged in CRM) | L862: Natuf | Business Owners | Tier1 + Growth Cities | Oct26 | V1 | M862: Natuf | Business Owners | Tier1 + Growth Cities | Oct26 | V1 | N862: Natuf | Reel | Brand Ambassador | Heard Of Owning A Cafe | V1 | O862: In House Natuf | P862: Facebook | Q862: (Unassigned) | R862: Omkar Navge | S862: - | T862: Bhubaneswar | V862: 0 | W862: 0 | X862: XXXXXX5515 | Y862: 46326.52
A863: 6adb7562fbf79fd239c1bdc8 | B863: 46318.851 | C863: 46318 | D863: 2026-10 | E863: Wk of 2026-10-19 | F863: Attempt 1 | G863: =IF(ISNUMBER(MATCH(F863,QualityStatuses,0)),"Quality Lead","Non-Quality Lead") -> Non-Quality Lead | H863: =IFERROR(INDEX(CampTypes,MATCH(I863,CampList,0)),"Unattributed") -> New | I863: ABO | Natuf | Leads | Unit Franchise | India | Oct26 | V1 | J863: ABO | Natuf | Leads | Unit Franchise | India | Oct26 | V1 | K863: Direct (campaign tagged in CRM) | L863: Natuf | Broad | Tier1 + Growth Cities | Oct26 | V1 | M863: Natuf | Broad | Tier1 + Growth Cities | Oct26 | V1 | N863: Natuf | Reel | Brand Ambassador | Heard Of Owning A Cafe | V1 | O863: In House Natuf | P863: Facebook | Q863: Tejaswini Tarigopula | R863: Shivani Sharma | S863: - | T863: Palwal | V863: 1 | W863: 0 | X863: XXXXXX1867 | Y863: 46326.52
A864: 6adb74cb0f63874ae543b9da | B864: 46318.849 | C864: 46318 | D864: 2026-10 | E864: Wk of 2026-10-19 | F864: New Lead | G864: =IF(ISNUMBER(MATCH(F864,QualityStatuses,0)),"Quality Lead","Non-Quality Lead") -> Non-Quality Lead | H864: =IFERROR(INDEX(CampTypes,MATCH(I864,CampList,0)),"Unattributed") -> New | I864: ABO | Natuf | Leads | Unit Franchise | India | Oct26 | V1 | J864: ABO | Natuf | Leads | Unit Franchise | India | Oct26 | V1 | K864: Direct (campaign tagged in CRM) | L864: Natuf | Investors | Tier1 + Growth Cities | Oct26 | V1 | M864: Natuf | Investors | Tier1 + Growth Cities | Oct26 | V1 | N864: Natuf | Reel | Brand Ambassador | Heard Of Owning A Cafe | V1 | O864: In House Natuf | P864: Facebook | Q864: (Unassigned) | R864: Omkar Navge | S864: - | T864: Pune | V864: 0 | W864: 0 | X864: XXXXXX9773 | Y864: 46326.52
A865: 6adb71146775edc566a9d7ba | B865: 46318.838 | C865: 46318 | D865: 2026-10 | E865: Wk of 2026-10-19 | F865: Attempt 3 | G865: =IF(ISNUMBER(MATCH(F865,QualityStatuses,0)),"Quality Lead","Non-Quality Lead") -> Non-Quality Lead | H865: =IFERROR(INDEX(CampTypes,MATCH(I865,CampList,0)),"Unattributed") -> New | I865: ABO | Natuf | Leads | Unit Franchise | India | Oct26 | V1 | J865: ABO | Natuf | Leads | Unit Franchise | India | Oct26 | V1 | K865: Direct (campaign tagged in CRM) | L865: Natuf | Business Owners | Tier1 + Growth Cities | Oct26 | V1 | M865: Natuf | Business Owners | Tier1 + Growth Cities | Oct26 | V1 | N865: Natuf | Reel | Brand Ambassador | Heard Of Owning A Cafe | V1 | O865: In House Natuf | P865: Facebook | Q865: Tejaswini Tarigopula | R865: Shivamani | S865: - | T865: Noida | V865: 3 | W865: 3 | X865: XXXXXX4340 | Y865: 46326.52
A866: 6adb6db8f5b5a25241addc61 | B866: 46318.828 | C866: 46318 | D866: 2026-10 | E866: Wk of 2026-10-19 | F866: New Lead | G866: =IF(ISNUMBER(MATCH(F866,QualityStatuses,0)),"Quality Lead","Non-Quality Lead") -> Non-Quality Lead | H866: =IFERROR(INDEX(CampTypes,MATCH(I866,CampList,0)),"Unattributed") -> New | I866: ABO | Natuf | Leads | Unit Franchise | India | Oct26 | V1 | J866: ABO | Natuf | Leads | Unit Franchise | India | Oct26 | V1 | K866: Direct (campaign tagged in CRM) | L866: Natuf | LAL 1% | India | Jul26 | V1 | M866: Natuf | LAL 1% | India | Jul26 | V1 | N866: Natuf | Reel | Brand Ambassador | Heard Of Owning A Cafe | V1 | O866: In House Natuf | P866: Facebook | Q866: (Unassigned) | R866: Omkar Navge | S866: - | T866: Jabalpur | V866: 0 | W866: 0 | X866: XXXXXX8391 | Y866: 46326.52
A867: 6adb69eb16ae0b5376905871 | B867: 46318.817 | C867: 46318 | D867: 2026-10 | E867: Wk of 2026-10-19 | F867: Connected | G867: =IF(ISNUMBER(MATCH(F867,QualityStatuses,0)),"Quality Lead","Non-Quality Lead") -> Non-Quality Lead | H867: =IFERROR(INDEX(CampTypes,MATCH(I867,CampList,0)),"Unattributed") -> New | I867: ABO | Natuf | Leads | Unit Franchise | India | Oct26 | V1 | J867: ABO | Natuf | Leads | Unit Franchise | India | Oct26 | V1 | K867: Direct (campaign tagged in CRM) | L867: Natuf | Broad | Tier1 + Growth Cities | Oct26 | V1 | M867: Natuf | Broad | Tier1 + Growth Cities | Oct26 | V1 | N867: Natuf | Reel | Brand Ambassador | Heard Of Owning A Cafe | V1 | O867: In House Natuf | P867: Facebook | Q867: Tejaswini Tarigopula | R867: Sai Charan | S867: - | T867: Indore | V867: 2 | W867: 1 | X867: XXXXXX0733 | Y867: 46326.52
A868: 6adb69889c789a9080644d80 | B868: 46318.816 | C868: 46318 | D868: 2026-10 | E868: Wk of 2026-10-19 | F868: New Lead | G868: =IF(ISNUMBER(MATCH(F868,QualityStatuses,0)),"Quality Lead","Non-Quality Lead") -> Non-Quality Lead | H868: =IFERROR(INDEX(CampTypes,MATCH(I868,CampList,0)),"Unattributed") -> New | I868: ABO | Natuf | Leads | Unit Franchise | India | Oct26 | V1 | J868: ABO | Natuf | Leads | Unit Franchise | India | Oct26 | V1 | K868: Direct (campaign tagged in CRM) | L868: Natuf | LAL 1% | India | Jul26 | V1 | M868: Natuf | LAL 1% | India | Jul26 | V1 | N868: Natuf | Reel | Brand Ambassador | Heard Of Owning A Cafe | V1 | O868: In House Natuf | P868: Facebook | Q868: (Unassigned) | R868: Omkar Navge | S868: - | T868: sant ravidas nagar | V868: 0 | W868: 0 | X868: XXXXXX4687 | Y868: 46326.52
A869: 6adb68f741fffdc87686e30d | B869: 46318.814 | C869: 46318 | D869: 2026-10 | E869: Wk of 2026-10-19 | F869: Connected | G869: =IF(ISNUMBER(MATCH(F869,QualityStatuses,0)),"Quality Lead","Non-Quality Lead") -> Non-Quality Lead | H869: =IFERROR(INDEX(CampTypes,MATCH(I869,CampList,0)),"Unattributed") -> New | I869: ABO | Natuf | Leads | Unit Franchise | India | Oct26 | V1 | J869: ABO | Natuf | Leads | Unit Franchise | India | Oct26 | V1 | K869: Direct (campaign tagged in CRM) | L869: Natuf | Broad | Tier1 + Growth Cities | Oct26 | V1 | M869: Natuf | Broad | Tier1 + Growth Cities | Oct26 | V1 | N869: Natuf | Reel | Brand Ambassador | Heard Of Owning A Cafe | V1 | O869: In House Natuf | P869: Facebook | Q869: Tejaswini Tarigopula | R869: Prabhudatta Pattanaik | S869: - | T869: Chennai | V869: 2 | W869: 1 | X869: XXXXXX6313 | Y869: 46326.52
A870: 6adb687fa87210d6b7b388ce | B870: 46318.813 | C870: 46318 | D870: 2026-10 | E870: Wk of 2026-10-19 | F870: New Lead | G870: =IF(ISNUMBER(MATCH(F870,QualityStatuses,0)),"Quality Lead","Non-Quality Lead") -> Non-Quality Lead | H870: =IFERROR(INDEX(CampTypes,MATCH(I870,CampList,0)),"Unattributed") -> New | I870: ABO | Natuf | Leads | Unit Franchise | India | Oct26 | V1 | J870: ABO | Natuf | Leads | Unit Franchise | India | Oct26 | V1 | K870: Direct (campaign tagged in CRM) | L870: Natuf | LAL 1% | India | Jul26 | V1 | M870: Natuf | LAL 1% | India | Jul26 | V1 | N870: Natuf | Reel | Brand Ambassador | Heard Of Owning A Cafe | V1 | O870: In House Natuf | P870: Facebook | Q870: (Unassigned) | R870: Omkar Navge | S870: - | T870: Purulia | V870: 0 | W870: 0 | X870: XXXXXX2701 | Y870: 46326.52
A871: 6adb67d09c789a9080644c36 | B871: 46318.811 | C871: 46318 | D871: 2026-10 | E871: Wk of 2026-10-19 | F871: Attempt 1 | G871: =IF(ISNUMBER(MATCH(F871,QualityStatuses,0)),"Quality Lead","Non-Quality Lead") -> Non-Quality Lead | H871: =IFERROR(INDEX(CampTypes,MATCH(I871,CampList,0)),"Unattributed") -> New | I871: ABO | Natuf | Leads | Master Franchise | India | Oct26 | V1 | J871: ABO | Natuf | Leads | Master Franchise | India | Oct26 | V1 | K871: Direct (campaign tagged in CRM) | L871: Natuf | Investors | Tier1 + Growth Cities | Oct26 | V1 | M871: Natuf | Investors | Tier1 + Growth Cities | Oct26 | V1 | N871: Natuf | Static | Become A Levantine Food | V1 | O871: Natuf_MF | P871: Facebook | Q871: Tejaswini Tarigopula | R871: Rima Paul | S871: - | T871: Sehore | V871: 1 | W871: 0 | X871: XXXXXX1905 | Y871: 46326.52
... A1607: 6ad611a5441864890cffeba8 | B1607: 46314.763 | C1607: 46314 | D1607: 2026-10 | E1607: Wk of 2026-10-19 | F1607: Attempt 1 | G1607: =IF(ISNUMBER(MATCH(F1607,QualityStatuses,0)),"Quality Lead","Non-Quality Lead") -> Non-Quality Lead | H1607: =IFERROR(INDEX(CampTypes,MATCH(I1607,CampList,0)),"Unattributed") -> New | I1607: EBG - In House | ABO | Natuf | Leads | Unit Franchise | India | Oct26 | V1 | J1607: EBG - In House | ABO | Natuf | Leads | Unit Franchise | India | Oct26 | V1 | K1607: Direct (campaign tagged in CRM) | L1607: Natuf | Broad | Tier1 + Growth Cities | Oct26 | V1 | M1607: Natuf | Broad | Tier1 + Growth Cities | Oct26 | V1 | N1607: Natuf | Reel | Brand Ambassador | Heard Of Owning A Cafe | V1 | O1607: In House Natuf | P1607: Facebook | Q1607: Tejaswini Tarigopula | R1607: Shivamani | S1607: - | T1607: Bangalore | V1607: 1 | W1607: 0 | X1607: XXXXXX1812 | Y1607: 46326.52
A1608: 6ad60ea9737d7cb1079e6702 | B1608: 46314.754 | C1608: 46314 | D1608: 2026-10 | E1608: Wk of 2026-10-19 | F1608: New Lead | G1608: =IF(ISNUMBER(MATCH(F1608,QualityStatuses,0)),"Quality Lead","Non-Quality Lead") -> Non-Quality Lead | H1608: =IFERROR(INDEX(CampTypes,MATCH(I1608,CampList,0)),"Unattributed") -> New | I1608: Natuf | In House | ABO | | WhatsApp | Unit Franchise | India | Oct26 | V1 | J1608: Natuf | In House | ABO | | WhatsApp | Unit Franchise | India | Oct26 | V1 | K1608: Direct (campaign tagged in CRM) | L1608: _ | M1608: _ | N1608: _ | O1608: In House Natuf | P1608: Whatsapp Cloud API | Q1608: (Unassigned) | R1608: (Unassigned) | S1608: - | T1608: - | U1608: - | V1608: 0 | W1608: 0 | X1608: XXXXXX9838 | Y1608: 46314.769
A1609: 6ad60e956dfc0575807ecdbc | B1609: 46314.754 | C1609: 46314 | D1609: 2026-10 | E1609: Wk of 2026-10-19 | F1609: Attempt 1 | G1609: =IF(ISNUMBER(MATCH(F1609,QualityStatuses,0)),"Quality Lead","Non-Quality Lead") -> Non-Quality Lead | H1609: =IFERROR(INDEX(CampTypes,MATCH(I1609,CampList,0)),"Unattributed") -> New | I1609: EBG - In House | ABO | Natuf | Leads | Unit Franchise | India | Oct26 | V1 | J1609: EBG - In House | ABO | Natuf | Leads | Unit Franchise | India | Oct26 | V1 | K1609: Direct (campaign tagged in CRM) | L1609: Natuf | Investors | Tier1 + Growth Cities | Oct26 | V1 | M1609: Natuf | Investors | Tier1 + Growth Cities | Oct26 | V1 | N1609: Natuf | Reel | Brand Ambassador | Heard Of Owning A Cafe | V1 | O1609: In House Natuf | P1609: Facebook | Q1609: Tejaswini Tarigopula | R1609: Rima Paul | S1609: - | T1609: jalgaon | V1609: 1 | W1609: 1 | X1609: XXXXXX7973 | Y1609: 46326.52
A1610: 6ad60cd6b3384bff603d4497 | B1610: 46314.749 | C1610: 46314 | D1610: 2026-10 | E1610: Wk of 2026-10-19 | F1610: New Lead | G1610: =IF(ISNUMBER(MATCH(F1610,QualityStatuses,0)),"Quality Lead","Non-Quality Lead") -> Non-Quality Lead | H1610: =IFERROR(INDEX(CampTypes,MATCH(I1610,CampList,0)),"Unattributed") -> Old | I1610: E_Karan_Natuf_All_07072026 | J1610: E_Karan_Natuf_All_07072026 | K1610: Direct (campaign tagged in CRM) | L1610: E_Karan_Natuf_Sign_07072026_Adset3 | M1610: E_Karan_Natuf_Sign_07072026_Adset3 | N1610: E_Karan_Natuf_Sign_07072026_Adset2_Ad1 | O1610: Natuf | P1610: Facebook | Q1610: (Unassigned) | R1610: Omkar Navge | S1610: - | T1610: Nagaur | V1610: 0 | W1610: 0 | X1610: XXXXXX4151 | Y1610: 46326.52
A1611: 6ad60aa1b3384bff603d42ad | B1611: 46314.742 | C1611: 46314 | D1611: 2026-10 | E1611: Wk of 2026-10-19 | F1611: Details Shared | G1611: =IF(ISNUMBER(MATCH(F1611,QualityStatuses,0)),"Quality Lead","Non-Quality Lead") -> Quality Lead | H1611: =IFERROR(INDEX(CampTypes,MATCH(I1611,CampList,0)),"Unattributed") -> New | I1611: EBG - In House | ABO | Natuf | Leads | Unit Franchise | India | Oct26 | V1 | J1611: EBG - In House | ABO | Natuf | Leads | Unit Franchise | India | Oct26 | V1 | K1611: Direct (campaign tagged in CRM) | L1611: Natuf | Investors | Tier1 + Growth Cities | Oct26 | V1 | M1611: Natuf | Investors | Tier1 + Growth Cities | Oct26 | V1 | N1611: Natuf | Reel | Brand Ambassador | Heard Of Owning A Cafe | V1 | O1611: In House Natuf | P1611: Facebook | Q1611: Tejaswini Tarigopula | R1611: Rima Paul | S1611: - | T1611: Pune | V1611: 1 | W1611: 1 | X1611: XXXXXX0823 | Y1611: 46326.52
A1612: 6ad60a61a77e539fb03b0023 | B1612: 46314.741 | C1612: 46314 | D1612: 2026-10 | E1612: Wk of 2026-10-19 | F1612: Connected | G1612: =IF(ISNUMBER(MATCH(F1612,QualityStatuses,0)),"Quality Lead","Non-Quality Lead") -> Non-Quality Lead | H1612: =IFERROR(INDEX(CampTypes,MATCH(I1612,CampList,0)),"Unattributed") -> Old | I1612: E_Karan_Natuf_All_07072026 | J1612: E_Karan_Natuf_All_07072026 | K1612: Direct (campaign tagged in CRM) | L1612: E_Karan_Natuf_Sign_07072026_Adset3 | M1612: E_Karan_Natuf_Sign_07072026_Adset3 | N1612: E_Karan_Natuf_Sign_07072026_Adset2_Ad1 | O1612: Natuf | P1612: Facebook | Q1612: Tejaswini Tarigopula | R1612: Prabhudatta Pattanaik | S1612: - | T1612: Lucknow | V1612: 1 | W1612: 1 | X1612: XXXXXX0790 | Y1612: 46326.52
A1613: 6ad609e5efcfca93aae995bb | B1613: 46314.74 | C1613: 46314 | D1613: 2026-10 | E1613: Wk of 2026-10-19 | F1613: Lost | G1613: =IF(ISNUMBER(MATCH(F1613,QualityStatuses,0)),"Quality Lead","Non-Quality Lead") -> Non-Quality Lead | H1613: =IFERROR(INDEX(CampTypes,MATCH(I1613,CampList,0)),"Unattributed") -> New | I1613: EBG - In House | ABO | Natuf | Leads | Unit Franchise | India | Oct26 | V1 | J1613: EBG - In House | ABO | Natuf | Leads | Unit Franchise | India | Oct26 | V1 | K1613: Direct (campaign tagged in CRM) | L1613: Natuf | Broad | Tier1 + Growth Cities | Oct26 | V1 | M1613: Natuf | Broad | Tier1 + Growth Cities | Oct26 | V1 | N1613: Natuf | Reel | Brand Ambassador | Heard Of Owning A Cafe | V1 | O1613: In House Natuf | P1613: Facebook | Q1613: Tejaswini Tarigopula | R1613: Arjuman Vidya Sagar | S1613: DNP - Did Not Pick Up | T1613: ARIYALUR | V1613: 6 | W1613: 0 | X1613: XXXXXX6921 | Y1613: 46326.52
A1614: 6ad609533ef01080d7dac41a | B1614: 46314.738 | C1614: 46314 | D1614: 2026-10 | E1614: Wk of 2026-10-19 | F1614: New Lead | G1614: =IF(ISNUMBER(MATCH(F1614,QualityStatuses,0)),"Quality Lead","Non-Quality Lead") -> Non-Quality Lead | H1614: =IFERROR(INDEX(CampTypes,MATCH(I1614,CampList,0)),"Unattributed") -> Old | I1614: E_Suresh_Natuf_Kiosk_07072026 | J1614: E_Suresh_Natuf_Kiosk_07072026 | K1614: Direct (campaign tagged in CRM) | L1614: E_Suresh_Natuf_Kiosk_07072026_Adset5 | M1614: E_Suresh_Natuf_Kiosk_07072026_Adset5 | N1614: E_Hindi_Suresh_Natuf_Kiosk_07072026_Adset5_ad3 – Copy 2 | O1614: Natuf | P1614: Facebook | Q1614: (Unassigned) | R1614: Omkar Navge | S1614: - | T1614: fujairah | V1614: 0 | W1614: 0 | X1614: XXXXXX9765 | Y1614: 46326.52
A1615: 6ad60944efcfca93aae99480 | B1615: 46314.738 | C1615: 46314 | D1615: 2026-10 | E1615: Wk of 2026-10-19 | F1615: Lost | G1615: =IF(ISNUMBER(MATCH(F1615,QualityStatuses,0)),"Quality Lead","Non-Quality Lead") -> Non-Quality Lead | H1615: =IFERROR(INDEX(CampTypes,MATCH(I1615,CampList,0)),"Unattributed") -> Old | I1615: E_Natuf_MF_05092026 | J1615: E_Natuf_MF_05092026 | K1615: Direct (campaign tagged in CRM) | L1615: E_Natuf_MF_05092026_ Ad Set1 | M1615: E_Natuf_MF_05092026_ Ad Set1 | N1615: E_Natuf_MF_05092026_ Ad Set1_Ad1 | O1615: Natuf_MF | P1615: Facebook | Q1615: Marshal Malbari | R1615: Aisha Rasalkar | S1615: DNP - Did Not Pick Up | T1615: Nagpur | V1615: 6 | W1615: 0 | X1615: XXXXXX8183 | Y1615: 46326.52
A1616: 6ad60859f3c7c431dbfa1323 | B1616: 46314.735 | C1616: 46314 | D1616: 2026-10 | E1616: Wk of 2026-10-19 | F1616: New Lead | G1616: =IF(ISNUMBER(MATCH(F1616,QualityStatuses,0)),"Quality Lead","Non-Quality Lead") -> Non-Quality Lead | H1616: =IFERROR(INDEX(CampTypes,MATCH(I1616,CampList,0)),"Unattributed") -> New | I1616: Natuf | In House | ABO | | WhatsApp | Unit Franchise | India | Oct26 | V1 | J1616: Natuf | In House | ABO | | WhatsApp | Unit Franchise | India | Oct26 | V1 | K1616: Direct (campaign tagged in CRM) | L1616: _ | M1616: _ | N1616: _ | O1616: In House Natuf | P1616: Whatsapp Cloud API | Q1616: (Unassigned) | R1616: (Unassigned) | S1616: - | T1616: - | U1616: - | V1616: 0 | W1616: 0 | X1616: XXXXXX0822 | Y1616: 46315.072
A1617: 6ad607b03bbc124c3c8a9f01 | B1617: 46314.733 | C1617: 46314 | D1617: 2026-10 | E1617: Wk of 2026-10-19 | F1617: New Lead | G1617: =IF(ISNUMBER(MATCH(F1617,QualityStatuses,0)),"Quality Lead","Non-Quality Lead") -> Non-Quality Lead | H1617: =IFERROR(INDEX(CampTypes,MATCH(I1617,CampList,0)),"Unattributed") -> New | I1617: Natuf | In House | ABO | | WhatsApp | Unit Franchise | India | Oct26 | V1 | J1617: Natuf | In House | ABO | | WhatsApp | Unit Franchise | India | Oct26 | V1 | K1617: Direct (campaign tagged in CRM) | L1617: _ | M1617: _ | N1617: _ | O1617: In House Natuf | P1617: Whatsapp Cloud API | Q1617: (Unassigned) | R1617: (Unassigned) | S1617: - | T1617: - | U1617: - | V1617: 0 | W1617: 0 | X1617: XXXXXX0263 | Y1617: 46314.734
A1618: 6ad6054bdc4f6939e2750f29 | B1618: 46314.726 | C1618: 46314 | D1618: 2026-10 | E1618: Wk of 2026-10-19 | F1618: Connected | G1618: =IF(ISNUMBER(MATCH(F1618,QualityStatuses,0)),"Quality Lead","Non-Quality Lead") -> Non-Quality Lead | H1618: =IFERROR(INDEX(CampTypes,MATCH(I1618,CampList,0)),"Unattributed") -> New | I1618: EBG - In House | ABO | Natuf | Leads | Unit Franchise | India | Oct26 | V1 | J1618: EBG - In House | ABO | Natuf | Leads | Unit Franchise | India | Oct26 | V1 | K1618: Direct (campaign tagged in CRM) | L1618: Natuf | Investors | Tier1 + Growth Cities | Oct26 | V1 | M1618: Natuf | Investors | Tier1 + Growth Cities | Oct26 | V1 | N1618: Natuf | Reel | Brand Ambassador | Heard Of Owning A Cafe | V1 | O1618: In House Natuf | P1618: Facebook | Q1618: Tejaswini Tarigopula | R1618: Sai Charan | S1618: - | T1618: Belguam | V1618: 2 | W1618: 1 | X1618: XXXXXX1734 | Y1618: 46326.52
A1619: 6ad6052dde4d726cefbc5d31 | B1619: 46314.726 | C1619: 46314 | D1619: 2026-10 | E1619: Wk of 2026-10-19 | F1619: Attempt 1 | G1619: =IF(ISNUMBER(MATCH(F1619,QualityStatuses,0)),"Quality Lead","Non-Quality Lead") -> Non-Quality Lead | H1619: =IFERROR(INDEX(CampTypes,MATCH(I1619,CampList,0)),"Unattributed") -> New | I1619: EBG - In House | ABO | Natuf | Leads | Unit Franchise | India | Oct26 | V1 | J1619: EBG - In House | ABO | Natuf | Leads | Unit Franchise | India | Oct26 | V1 | K1619: Direct (campaign tagged in CRM) | L1619: Natuf | Business Owners | Tier1 + Growth Cities | Oct26 | V1 | M1619: Natuf | Business Owners | Tier1 + Growth Cities | Oct26 | V1 | N1619: Natuf | Reel | Brand Ambassador | Heard Of Owning A Cafe | V1 | O1619: In House Natuf | P1619: Facebook | Q1619: Tejaswini Tarigopula | R1619: Shivani Sharma | S1619: - | T1619: Patna | V1619: 1 | W1619: 0 | X1619: XXXXXX4611 | Y1619: 46326.52
A1620: 6ad60203883f93a21756e981 | B1620: 46314.717 | C1620: 46314 | D1620: 2026-10 | E1620: Wk of 2026-10-19 | F1620: Attempt 2 | G1620: =IF(ISNUMBER(MATCH(F1620,QualityStatuses,0)),"Quality Lead","Non-Quality Lead") -> Non-Quality Lead | H1620: =IFERROR(INDEX(CampTypes,MATCH(I1620,CampList,0)),"Unattributed") -> Old | I1620: E_Natuf_Generic_13082026 | J1620: E_Natuf_Generic_13082026 | K1620: Direct (campaign tagged in CRM) | L1620: E_Natuf_Generic_13082026_Adset1 | M1620: E_Natuf_Generic_13082026_Adset1 | N1620: E_Natuf_Generic_13082026_Adset1_Ad1 | O1620: Natuf | P1620: Facebook | Q1620: Tejaswini Tarigopula | R1620: Rima Paul | S1620: - | T1620: Indore | V1620: 2 | W1620: 0 | X1620: XXXXXX4674 | Y1620: 46326.52
A1621: 6ad60076a8eb1a3cd008fec2 | B1621: 46314.712 | C1621: 46314 | D1621: 2026-10 | E1621: Wk of 2026-10-19 | F1621: New Lead | G1621: =IF(ISNUMBER(MATCH(F1621,QualityStatuses,0)),"Quality Lead","Non-Quality Lead") -> Non-Quality Lead | H1621: =IFERROR(INDEX(CampTypes,MATCH(I1621,CampList,0)),"Unattributed") -> Old | I1621: E_Karan_Natuf_All_07072026 | J1621: E_Karan_Natuf_All_07072026 | K1621: Direct (campaign tagged in CRM) | L1621: E_Karan_Natuf_Sign_07072026_Adset3 | M1621: E_Karan_Natuf_Sign_07072026_Adset3 | N1621: E_Karan_Natuf_Sign_07072026_Adset2_Ad1 | O1621: Natuf | P1621: Facebook | Q1621: (Unassigned) | R1621: Omkar Navge | S1621: - | T1621: gdjg | V1621: 0 | W1621: 0 | X1621: XXXXXX9019 | Y1621: 46326.52
A1622: 6ad5fe0d3c92990bc8d7778f | B1622: 46314.705 | C1622: 46314 | D1622: 2026-10 | E1622: Wk of 2026-10-19 | F1622: Attempt 1 | G1622: =IF(ISNUMBER(MATCH(F1622,QualityStatuses,0)),"Quality Lead","Non-Quality Lead") -> Non-Quality Lead | H1622: =IFERROR(INDEX(CampTypes,MATCH(I1622,CampList,0)),"Unattributed") -> New | I1622: EBG - In House | ABO | Natuf | Leads | Unit Franchise | India | Oct26 | V1 | J1622: EBG - In House | ABO | Natuf | Leads | Unit Franchise | India | Oct26 | V1 | K1622: Direct (campaign tagged in CRM) | L1622: Natuf | Business Owners | Tier1 + Growth Cities | Oct26 | V1 | M1622: Natuf | Business Owners | Tier1 + Growth Cities | Oct26 | V1 | N1622: Natuf | Reel | Brand Ambassador | Heard Of Owning A Cafe | V1 | O1622: In House Natuf | P1622: Facebook | Q1622: Tejaswini Tarigopula | R1622: Shivamani | S1622: - | T1622: Chennai | V1622: 1 | W1622: 1 | X1622: XXXXXX6171 | Y1622: 46326.52
A1623: 6ad5fdd55ca0edd800da5157 | B1623: 46314.704 | C1623: 46314 | D1623: 2026-10 | E1623: Wk of 2026-10-19 | F1623: Attempt 1 | G1623: =IF(ISNUMBER(MATCH(F1623,QualityStatuses,0)),"Quality Lead","Non-Quality Lead") -> Non-Quality Lead | H1623: =IFERROR(INDEX(CampTypes,MATCH(I1623,CampList,0)),"Unattributed") -> New | I1623: EBG - In House | ABO | Natuf | Leads | Unit Franchise | India | Oct26 | V1 | J1623: EBG - In House | ABO | Natuf | Leads | Unit Franchise | India | Oct26 | V1 | K1623: Direct (campaign tagged in CRM) | L1623: Natuf | Broad | Tier1 + Growth Cities | Oct26 | V1 | M1623: Natuf | Broad | Tier1 + Growth Cities | Oct26 | V1 | N1623: Natuf | Reel | Brand Ambassador | Heard Of Owning A Cafe | V1 | O1623: In House Natuf | P1623: Facebook | Q1623: Tejaswini Tarigopula | R1623: Rima Paul | S1623: - | T1623: Raipur | V1623: 3 | W1623: 0 | X1623: XXXXXX0091 | Y1623: 46326.52
A1624: 6ad5fda45ca0edd800da50b4 | B1624: 46314.704 | C1624: 46314 | D1624: 2026-10 | E1624: Wk of 2026-10-19 | F1624: Details Shared | G1624: =IF(ISNUMBER(MATCH(F1624,QualityStatuses,0)),"Quality Lead","Non-Quality Lead") -> Quality Lead | H1624: =IFERROR(INDEX(CampTypes,MATCH(I1624,CampList,0)),"Unattributed") -> Old | I1624: E_Karan_Natuf_All_07072026 | J1624: E_Karan_Natuf_All_07072026 | K1624: Direct (campaign tagged in CRM) | L1624: E_Karan_Natuf_Sign_07072026_Adset3 | M1624: E_Karan_Natuf_Sign_07072026_Adset3 | N1624: E_Karan_Natuf_Sign_07072026_Adset2_Ad1 | O1624: Natuf | P1624: Facebook | Q1624: Tejaswini Tarigopula | R1624: Prabhudatta Pattanaik | S1624: - | T1624: Coimbatore | V1624: 2 | W1624: 1 | X1624: XXXXXX4440 | Y1624: 46326.52
A1625: 6ad5fd72b3d6713ffa62a755 | B1625: 46314.703 | C1625: 46314 | D1625: 2026-10 | E1625: Wk of 2026-10-19 | F1625: Details Shared | G1625: =IF(ISNUMBER(MATCH(F1625,QualityStatuses,0)),"Quality Lead","Non-Quality Lead") -> Quality Lead | H1625: =IFERROR(INDEX(CampTypes,MATCH(I1625,CampList,0)),"Unattributed") -> New | I1625: EBG - In House | ABO | Natuf | Leads | Unit Franchise | India | Oct26 | V1 | J1625: EBG - In House | ABO | Natuf | Leads | Unit Franchise | India | Oct26 | V1 | K1625: Direct (campaign tagged in CRM) | L1625: Natuf | Investors | Tier1 + Growth Cities | Oct26 | V1 | M1625: Natuf | Investors | Tier1 + Growth Cities | Oct26 | V1 | N1625: Natuf | Reel | Brand Ambassador | Heard Of Owning A Cafe | V1 | O1625: In House Natuf | P1625: Facebook | Q1625: Tejaswini Tarigopula | R1625: Rima Paul | S1625: - | T1625: Aurangabad | V1625: 1 | W1625: 1 | X1625: XXXXXX1406 | Y1625: 46326.52
A1626: 6ad5fab35d1df9241727a348 | B1626: 46314.695 | C1626: 46314 | D1626: 2026-10 | E1626: Wk of 2026-10-19 | F1626: New Lead | G1626: =IF(ISNUMBER(MATCH(F1626,QualityStatuses,0)),"Quality Lead","Non-Quality Lead") -> Non-Quality Lead | H1626: =IFERROR(INDEX(CampTypes,MATCH(I1626,CampList,0)),"Unattributed") -> Old | I1626: E_Karan_Natuf_All_07072026 | J1626: E_Karan_Natuf_All_07072026 | K1626: Direct (campaign tagged in CRM) | L1626: E_Karan_Natuf_Sign_07072026_Adset3 | M1626: E_Karan_Natuf_Sign_07072026_Adset3 | N1626: E_Karan_Natuf_Sign_07072026_Adset2_Ad1 – Copy | O1626: Natuf | P1626: Facebook | Q1626: (Unassigned) | R1626: Omkar Navge | S1626: - | T1626: Ahmedabad | V1626: 0 | W1626: 0 | X1626: XXXXXX5545 | Y1626: 46326.52
A1627: 6ad5f77d5eea62e8903e7464 | B1627: 46314.685 | C1627: 46314 | D1627: 2026-10 | E1627: Wk of 2026-10-19 | F1627: Details Shared | G1627: =IF(ISNUMBER(MATCH(F1627,QualityStatuses,0)),"Quality Lead","Non-Quality Lead") -> Quality Lead | H1627: =IFERROR(INDEX(CampTypes,MATCH(I1627,CampList,0)),"Unattributed") -> Old | I1627: E_Karan_Natuf_All_07072026 | J1627: E_Karan_Natuf_All_07072026 | K1627: Direct (campaign tagged in CRM) | L1627: E_Karan_Natuf_Sign_07072026_Adset3 | M1627: E_Karan_Natuf_Sign_07072026_Adset3 | N1627: E_Karan_Natuf_Sign_07072026_Adset2_Ad1 | O1627: Natuf | P1627: Facebook | Q1627: Tejaswini Tarigopula | R1627: Rima Paul | S1627: - | T1627: muzaffarnagar | V1627: 6 | W1627: 4 | X1627: XXXXXX5000 | Y1627: 46326.52
A1628: 6ad5f6f1e6b91fba1a288a8c | B1628: 46314.684 | C1628: 46314 | D1628: 2026-10 | E1628: Wk of 2026-10-19 | F1628: New Lead | G1628: =IF(ISNUMBER(MATCH(F1628,QualityStatuses,0)),"Quality Lead","Non-Quality Lead") -> Non-Quality Lead | H1628: =IFERROR(INDEX(CampTypes,MATCH(I1628,CampList,0)),"Unattributed") -> Old | I1628: natuf_Kiosk_14072026_Hindi | J1628: natuf_Kiosk_14072026_Hindi | K1628: Direct (campaign tagged in CRM) | L1628: natuf_Kiosk_09102026 | M1628: natuf_Kiosk_09102026 | N1628: natuf_Kiosk_14072026_ad set_ad1 | O1628: Natuf | P1628: Facebook | Q1628: Tejaswini Tarigopula | R1628: Shivamani | S1628: - | T1628: Dehra Dun | V1628: 6 | W1628: 4 | X1628: XXXXXX1157 | Y1628: 46326.52
A1629: 6ad5f64cec875969a7aaab66 | B1629: 46314.682 | C1629: 46314 | D1629: 2026-10 | E1629: Wk of 2026-10-19 | F1629: New Lead | G1629: =IF(ISNUMBER(MATCH(F1629,QualityStatuses,0)),"Quality Lead","Non-Quality Lead") -> Non-Quality Lead | H1629: =IFERROR(INDEX(CampTypes,MATCH(I1629,CampList,0)),"Unattributed") -> New | I1629: Natuf | In House | ABO | | WhatsApp | Unit Franchise | India | Oct26 | V1 | J1629: Natuf | In House | ABO | | WhatsApp | Unit Franchise | India | Oct26 | V1 | K1629: Direct (campaign tagged in CRM) | L1629: _ | M1629: _ | N1629: _ | O1629: In House Natuf | P1629: Whatsapp Cloud API | Q1629: (Unassigned) | R1629: (Unassigned) | S1629: - | T1629: - | U1629: - | V1629: 0 | W1629: 0 | X1629: XXXXXX7366 | Y1629: 46314.683
A1630: 6ad5f5d8d85ebcd58f819754 | B1630: 46314.681 | C1630: 46314 | D1630: 2026-10 | E1630: Wk of 2026-10-19 | F1630: Lost | G1630: =IF(ISNUMBER(MATCH(F1630,QualityStatuses,0)),"Quality Lead","Non-Quality Lead") -> Non-Quality Lead | H1630: =IFERROR(INDEX(CampTypes,MATCH(I1630,CampList,0)),"Unattributed") -> New | I1630: EBG - In House | ABO | Natuf | Leads | Unit Franchise | India | Oct26 | V1 | J1630: EBG - In House | ABO | Natuf | Leads | Unit Franchise | India | Oct26 | V1 | K1630: Direct (campaign tagged in CRM) | L1630: Natuf | Investors | Tier1 + Growth Cities | Oct26 | V1 | M1630: Natuf | Investors | Tier1 + Growth Cities | Oct26 | V1 | N1630: Natuf | Reel | Brand Ambassador | Heard Of Owning A Cafe | V1 | O1630: In House Natuf | P1630: Facebook | Q1630: Tejaswini Tarigopula | R1630: Arjuman Vidya Sagar | S1630: DNP - Did Not Pick Up | T1630: Khandwa | V1630: 8 | W1630: 6 | X1630: XXXXXX3190 | Y1630: 46326.52
A1631: 6ad5f2a7a9694241d22e7514 | B1631: 46314.671 | C1631: 46314 | D1631: 2026-10 | E1631: Wk of 2026-10-19 | F1631: New Lead | G1631: =IF(ISNUMBER(MATCH(F1631,QualityStatuses,0)),"Quality Lead","Non-Quality Lead") -> Non-Quality Lead | H1631: =IFERROR(INDEX(CampTypes,MATCH(I1631,CampList,0)),"Unattributed") -> New | I1631: Natuf | In House | ABO | | WhatsApp | Unit Franchise | India | Oct26 | V1 | J1631: Natuf | In House | ABO | | WhatsApp | Unit Franchise | India | Oct26 | V1 | K1631: Direct (campaign tagged in CRM) | L1631: _ | M1631: _ | N1631: _ | O1631: In House Natuf | P1631: Whatsapp Cloud API | Q1631: (Unassigned) | R1631: (Unassigned) | S1631: - | T1631: - | U1631: - | V1631: 0 | W1631: 0 | X1631: XXXXXX0041 | Y1631: 46314.672
A1632: 6ad5f1a8a13582b503d85193 | B1632: 46314.668 | C1632: 46314 | D1632: 2026-10 | E1632: Wk of 2026-10-19 | F1632: Attempt 2 | G1632: =IF(ISNUMBER(MATCH(F1632,QualityStatuses,0)),"Quality Lead","Non-Quality Lead") -> Non-Quality Lead | H1632: =IFERROR(INDEX(CampTypes,MATCH(I1632,CampList,0)),"Unattributed") -> New | I1632: EBG - In House | ABO | Natuf | Leads | Unit Franchise | India | Oct26 | V1 | J1632: EBG - In House | ABO | Natuf | Leads | Unit Franchise | India | Oct26 | V1 | K1632: Direct (campaign tagged in CRM) | L1632: Natuf | Broad | Tier1 + Growth Cities | Oct26 | V1 | M1632: Natuf | Broad | Tier1 + Growth Cities | Oct26 | V1 | N1632: Natuf | Reel | Brand Ambassador | Heard Of Owning A Cafe | V1 | O1632: In House Natuf | P1632: Facebook | Q1632: Tejaswini Tarigopula | R1632: Prabhudatta Pattanaik | S1632: - | T1632: Nashik | V1632: 2 | W1632: 0 | X1632: XXXXXX1861 | Y1632: 46326.52
A1633: 6ad5f003674aa294e28efc10 | B1633: 46314.663 | C1633: 46314 | D1633: 2026-10 | E1633: Wk of 2026-10-19 | F1633: New Lead | G1633: =IF(ISNUMBER(MATCH(F1633,QualityStatuses,0)),"Quality Lead","Non-Quality Lead") -> Non-Quality Lead | H1633: =IFERROR(INDEX(CampTypes,MATCH(I1633,CampList,0)),"Unattributed") -> New | I1633: Natuf | In House | ABO | | WhatsApp | Unit Franchise | India | Oct26 | V1 | J1633: Natuf | In House | ABO | | WhatsApp | Unit Franchise | India | Oct26 | V1 | K1633: Direct (campaign tagged in CRM) | L1633: _ | M1633: _ | N1633: _ | O1633: In House Natuf | P1633: Whatsapp Cloud API | Q1633: (Unassigned) | R1633: (Unassigned) | S1633: - | T1633: - | U1633: - | V1633: 0 | W1633: 0 | X1633: XXXXXX5555 | Y1633: 46314.664
A1634: 6ad5ee621be729df36b05781 | B1634: 46314.658 | C1634: 46314 | D1634: 2026-10 | E1634: Wk of 2026-10-19 | F1634: New Lead | G1634: =IF(ISNUMBER(MATCH(F1634,QualityStatuses,0)),"Quality Lead","Non-Quality Lead") -> Non-Quality Lead | H1634: =IFERROR(INDEX(CampTypes,MATCH(I1634,CampList,0)),"Unattributed") -> Old | I1634: natuf_Kiosk_14072026_Hindi | J1634: natuf_Kiosk_14072026_Hindi | K1634: Direct (campaign tagged in CRM) | L1634: natuf_Kiosk_23092026_ad set3 | M1634: natuf_Kiosk_23092026_ad set3 | N1634: natuf_Kiosk_23092026_ad set3_ad1 | O1634: Natuf | P1634: Facebook | Q1634: (Unassigned) | R1634: Omkar Navge | S1634: - | T1634: Beed Maharashtra | V1634: 0 | W1634: 0 | X1634: XXXXXX3131 | Y1634: 46326.52
A1635: 6ad5ea20ade0845b047b2ad4 | B1635: 46314.646 | C1635: 46314 | D1635: 2026-10 | E1635: Wk of 2026-10-19 | F1635: Connected | G1635: =IF(ISNUMBER(MATCH(F1635,QualityStatuses,0)),"Quality Lead","Non-Quality Lead") -> Non-Quality Lead | H1635: =IFERROR(INDEX(CampTypes,MATCH(I1635,CampList,0)),"Unattributed") -> New | I1635: EBG - In House | ABO | Natuf | Leads | Unit Franchise | India | Oct26 | V1 | J1635: EBG - In House | ABO | Natuf | Leads | Unit Franchise | India | Oct26 | V1 | K1635: Direct (campaign tagged in CRM) | L1635: Natuf | Business Owners | Tier1 + Growth Cities | Oct26 | V1 | M1635: Natuf | Business Owners | Tier1 + Growth Cities | Oct26 | V1 | N1635: Natuf | Reel | Brand Ambassador | Heard Of Owning A Cafe | V1 | O1635: In House Natuf | P1635: Facebook | Q1635: Tejaswini Tarigopula | R1635: Shivani Sharma | S1635: - | T1635: New Delhi | V1635: 8 | W1635: 4 | X1635: XXXXXX7525 | Y1635: 46326.52
A1636: 6ad5e9e23a1624548e54d349 | B1636: 46314.645 | C1636: 46314 | D1636: 2026-10 | E1636: Wk of 2026-10-19 | F1636: New Lead | G1636: =IF(ISNUMBER(MATCH(F1636,QualityStatuses,0)),"Quality Lead","Non-Quality Lead") -> Non-Quality Lead | H1636: =IFERROR(INDEX(CampTypes,MATCH(I1636,CampList,0)),"Unattributed") -> New | I1636: EBG - In House | ABO | Natuf | Leads | Unit Franchise | India | Oct26 | V1 | J1636: EBG - In House | ABO | Natuf | Leads | Unit Franchise | India | Oct26 | V1 | K1636: Direct (campaign tagged in CRM) | L1636: Natuf | Broad | Tier1 + Growth Cities | Oct26 | V1 | M1636: Natuf | Broad | Tier1 + Growth Cities | Oct26 | V1 | N1636: Natuf | Reel | Brand Ambassador | Heard Of Owning A Cafe | V1 | O1636: In House Natuf | P1636: Facebook | Q1636: Tejaswini Tarigopula | R1636: Shivamani | S1636: - | T1636: Bangalore | V1636: 1 | W1636: 1 | X1636: XXXXXX2358 | Y1636: 46326.52
...

Sheet Excluded_Leads
A1: Lead ID | B1: Created On | C1: CRM Brand (as tagged) | D1: Campaign (as in CRM) | E1: Ad Set (as in CRM) | F1: Ad (as in CRM) | G1: Status | H1: Quality status? | I1: Exclusion reason
A2: 6ae2e7617c04024dab0b778d | B2: 46324.498 | C2: In House Natuf | D2: AAC | Whatsapp| Unit Franchise | India | Aug26 | V4 | E2: _ | F2: _ | G2: Lost | H2: No | I2: Tagged to a Natuf brand in CRM but the campaign belongs to another brand / is not a Natuf campaign
A3: 6adf49e4ab443717580ea488 | B3: 46321.756 | C3: FW-Natuf | D3: _ | E3: _ | F3: _ | G3: Attempt 1 | H3: No | I3: No campaign and no ad set in CRM; lead source = Excel (bulk/manual upload, not a campaign lead)
A4: 6adf49e5b67450d3ba8405bc | B4: 46321.756 | C4: FW-Shayreen by Natuf | D4: _ | E4: _ | F4: _ | G4: Attempt 1 | H4: No | I4: No campaign and no ad set in CRM; lead source = Excel (bulk/manual upload, not a campaign lead)
A5: 6adf49e5dd44a4c03693d9e0 | B5: 46321.756 | C5: FW-Shayreen by Natuf | D5: _ | E5: _ | F5: _ | G5: Attempt 2 | H5: No | I5: No campaign and no ad set in CRM; lead source = Excel (bulk/manual upload, not a campaign lead)
A6: 6adf49e53a2bb1785af6704c | B6: 46321.756 | C6: FW-Natuf | D6: _ | E6: _ | F6: _ | G6: Connected | H6: No | I6: No campaign and no ad set in CRM; lead source = Excel (bulk/manual upload, not a campaign lead)
A7: 6adf49e27801830101282533 | B7: 46321.756 | C7: FW-Natuf | D7: _ | E7: _ | F7: _ | G7: Lost | H7: No | I7: No campaign and no ad set in CRM; lead source = Excel (bulk/manual upload, not a campaign lead)
A8: 6adf49e5a0a145b5e597ace5 | B8: 46321.756 | C8: FW-Shayreen by Natuf | D8: _ | E8: _ | F8: _ | G8: Connected | H8: No | I8: No campaign and no ad set in CRM; lead source = Excel (bulk/manual upload, not a campaign lead)
A9: 6adf49e5d21eabe5bac4242c | B9: 46321.756 | C9: FW-Natuf | D9: _ | E9: _ | F9: _ | G9: Attempt 1 | H9: No | I9: No campaign and no ad set in CRM; lead source = Excel (bulk/manual upload, not a campaign lead)
A10: 6adf49e5627a368fbe80b1be | B10: 46321.756 | C10: FW-Natuf | D10: _ | E10: _ | F10: _ | G10: Attempt 1 | H10: No | I10: No campaign and no ad set in CRM; lead source = Excel (bulk/manual upload, not a campaign lead)
A11: 6adf49e51de63f094504b9a6 | B11: 46321.756 | C11: FW-Natuf | D11: _ | E11: _ | F11: _ | G11: Connected | H11: No | I11: No campaign and no ad set in CRM; lead source = Excel (bulk/manual upload, not a campaign lead)
A12: 6adf49e49bf73c7226cd91be | B12: 46321.756 | C12: FW-Natuf | D12: _ | E12: _ | F12: _ | G12: Attempt 1 | H12: No | I12: No campaign and no ad set in CRM; lead source = Excel (bulk/manual upload, not a campaign lead)
A13: 6adf49e5c48b833ddb7cb6ce | B13: 46321.756 | C13: FW-Natuf | D13: _ | E13: _ | F13: _ | G13: Lost | H13: No | I13: No campaign and no ad set in CRM; lead source = Excel (bulk/manual upload, not a campaign lead)
... A36: 6adb5498cc9958ee9bd99841 | B36: 46318.754 | C36: FW-Natuf | D36: _ | E36: _ | F36: _ | G36: New Lead | H36: No | I36: No campaign and no ad set in CRM; lead source = Excel (bulk/manual upload, not a campaign lead)

Sheet XBrand_Leads
A1: Lead ID | B1: Created On | C1: CRM Brand (other brand) | D1: Natuf campaign | E1: Attribution | F1: Ad Set (as in CRM) | G1: Status (in other brand pipeline) | H1: Quality status? | I1: Campaign Type
A2: 6ae4ee4ae72cb66154cc5d06 | B2: 46326.036 | C2: Adhira & Appa Coffee | D2: EBG - In House | ABO | Natuf | Leads | Unit Franchise | India | Oct26 | V1 | E2: Direct (campaign tagged in CRM) | F2: Natuf | Investors | Tier1 + Growth Cities | Oct26 | V1 | G2: Attempt 1 | H2: No | I2: New
A3: 6ae4b192b7d3fac3ae9e1f4f | B3: 46325.856 | C3: Adhira & Appa Coffee FOFO | D3: ABO | Natuf | Leads | Master Franchise | India | Oct26 | V1 | E3: Direct (campaign tagged in CRM) | F3: Natuf | LAL 1% | India | Jul26 | V1 | G3: Attempt 1 | H3: No | I3: New
A4: 6ae4a874d6ac4e915341efb3 | B4: 46325.829 | C4: Adhira & Appa Coffee | D4: ABO | Natuf | Leads | Master Franchise | India | Oct26 | V1 | E4: Direct (campaign tagged in CRM) | F4: Natuf | LAL 1% | India | Jul26 | V1 | G4: Attempt 1 | H4: No | I4: New
A5: 6ae4a6d727122f92468b3bf7 | B5: 46325.824 | C5: Adhira & Appa Coffee | D5: ABO | Natuf | Leads | Master Franchise | India | Oct26 | V1 | E5: Direct (campaign tagged in CRM) | F5: Natuf | Broad | Tier1 + Growth Cities | Oct26 | V1 | G5: New Lead | H5: No | I5: New
A6: 6ae4845edc73ce122c042c3c | B6: 46325.722 | C6: Adhira & Appa Coffee FOFO | D6: ABO | Natuf | Leads | Master Franchise | India | Oct26 | V1 | E6: Direct (campaign tagged in CRM) | F6: Natuf | Business Owners | Tier1 + Growth Cities | Oct26 | V1 | G6: Attempt 1 | H6: No | I6: New
A7: 6ae4725821c9b407dba56f06 | B7: 46325.669 | C7: Adhira & Appa Coffee FOFO | D7: E_Karan_Natuf_All_07072026 | E7: Direct (campaign tagged in CRM) | F7: E_Karan_Natuf_Sign_07072026_Adset3 | G7: Attempt 2 | H7: No | I7: Old
A8: 6ae36cf4e4ec56502ef9b94d | B8: 46324.894 | C8: Adhira & Appa Coffee FOFO | D8: ABO | Natuf | Leads | Unit Franchise | India | Oct26 | V1 | E8: Direct (campaign tagged in CRM) | F8: Natuf | LAL 1% | India | Jul26 | V1 | G8: Attempt 2 | H8: No | I8: New
A9: 6ae2eee59461cd372fe401bd | B9: 46324.521 | C9: Adhira & Appa Coffee FOFO | D9: ABO | Natuf | Leads | Master Franchise | India | Oct26 | V1 | E9: Direct (campaign tagged in CRM) | F9: Natuf | Broad | Tier1 + Growth Cities | Oct26 | V1 | G9: Attempt 2 | H9: No | I9: New
A10: 6ae1f8b17f0dd021b091c8a0 | B10: 46323.791 | C10: Adhira & Appa Coffee FOFO | D10: EBG - In House | ABO | Natuf | Leads | Master Franchise | India | Oct26 | V1 | E10: Direct (campaign tagged in CRM) | F10: Natuf | Broad | Tier1 + Growth Cities | Oct26 | V1 | G10: Attempt 2 | H10: No | I10: New
A11: 6ae1cb41e842e6c7966c0ad6 | B11: 46323.657 | C11: Adhira & Appa Coffee | D11: E_Karan_Natuf_All_07072026 | E11: Direct (campaign tagged in CRM) | F11: E_Karan_Natuf_Sign_07072026_Adset3 | G11: Attempt 2 | H11: No | I11: Old
A12: 6ae15f22b30f57af8e0b6f78 | B12: 46323.336 | C12: Adhira & Appa Coffee FOFO | D12: E_Karan_Natuf_All_07072026 | E12: Direct (campaign tagged in CRM) | F12: E_Karan_Natuf_Sign_07072026_Adset3 | G12: Attempt 2 | H12: No | I12: Old
A13: 6ae13fc3c737643fe50a344a | B13: 46323.243 | C13: Adhira & Appa Coffee | D13: EBG - In House | ABO | Natuf | Leads | Unit Franchise | India | Oct26 | V1 | E13: Direct (campaign tagged in CRM) | F13: Natuf | LAL 1% | India | Jul26 | V1 | G13: Attempt 1 | H13: No | I13: New
... A58: 6abe0fba21c38bcfea2fb79c | B58: 46296.553 | C58: Adhira & Appa Coffee | D58: E_Selva_Natuf_All_07072026 | E58: Direct (campaign tagged in CRM) | F58: E_Selva_Natuf_Sign_07072026_Adset3 | G58: Connected | H58: No | I58: Old

Sheet Meta_Campaigns
A1: Campaign | B1: Delivery | C1: Result indicator | D1: Results (as reported) | E1: Reach | F1: Impressions | G1: Spend (INR) | H1: Link Clicks | I1: CPC link (INR) | J1: CTR link (%) | K1: CPM (INR) | L1: Landing page views | M1: Budget | N1: Budget type | O1: Cost per result (INR) | P1: Lead-type results (excl. landing-page-views)
A2: GenY-Natuf-LeadGen-10032026 | B2: inactive | E2: 0 | F2: 0 | G2: 0 | K2: 0 | M2: Using ad set budget | N2: 0 | P2: =IF(ISNUMBER(SEARCH("landing_page_view",C2)),0,N(D2)) -> 0
A3: E_Karan_Natuf_Kiosk_07072026 | B3: inactive | C3: actions:leadgen.other | D3: 30 | E3: 25010 | F3: 37281 | G3: 54540.16 | H3: 444 | I3: 122.8382 | J3: 1.190955 | K3: 1462.9479 | M3: 5000 | N3: Daily | O3: 1818.0053 | P3: =IF(ISNUMBER(SEARCH("landing_page_view",C3)),0,N(D3)) -> 30
A4: E_Suresh_Natuf_Kiosk_07072026 | B4: inactive | C4: actions:leadgen.other | D4: 360 | E4: 136352 | F4: 210455 | G4: 232416.42 | H4: 2446 | I4: 95.018978 | J4: 1.162244 | K4: 1104.3521 | M4: 10000 | N4: Daily | O4: 645.60117 | P4: =IF(ISNUMBER(SEARCH("landing_page_view",C4)),0,N(D4)) -> 360
