Workbook

Sheet Campaign Report
A1: DAEWOO × SHOOTORDER — CAMPAIGN, AD SET & AD-WISE PERFORMANCE REPORT
A2: MTD: 01 Oct 2026 – 28 Oct 2026 | FTD: 28 Oct 2026 | Currency: INR | Attribution: LeadChain (Meta raw Lead Ads export) — ground-truth Ad / Ad Set / Campaign join
A4: OCTOBER 2026 — PERFORMANCE SNAPSHOT (MTD 1–28 Oct · FTD 28 Oct)
A5: MTD SPEND | E5: MTD LEADS / RESULTS (META) | I5: BLENDED CPL (per CRM Lead) | M5: MTD IMPRESSIONS | Q5: MTD REACH | T5: MTD CTR | W5: MTD CPQL
A6: ="₹"&TEXT($J$30,"#,##0") | E6: =$E$30 | I6: =IFERROR("₹"&TEXT($J$30/Data_CRM!$J$6,"#,##0"),"n/a") | M6: =TEXT($K$30,"#,##0") | Q6: =TEXT($L$30,"#,##0") | T6: =IFERROR(TEXT($T$30/$K$30,"0.00%"),"n/a") | W6: =IFERROR("₹"&TEXT($J$30/$P$30,"#,##0"),"n/a")
A8: TOTAL CRM LEADS (MTD) | E8: QUALIFIED LEADS (CRM, MTD) | I8: MEETINGS SCHEDULED (total) | M8: FTD (28 OCT) — CRM LEADS | T8: UNIQUE LEADS (MeetingLeads file)
A9: =Data_CRM!$J$6 | E9: =SUM(Data_CRM!$F$2:$F$1694) | I9: =Data_MeetingScheduled!$J$2 | M9: =COUNTIFS(Data_CRM!$A$2:$A$1694,">="&Data_CRM!$J$4,Data_CRM!$A$2:$A$1694,"<="&Data_CRM!$J$5) | T9: 51
A11: ℹ DATA NOTES
A19: 1. CAMPAIGN-WISE PERFORMANCE — MTD (1 Oct – 28 Oct 2026)
A20: Reporting starts | B20: Reporting ends | C20: Campaign name | D20: Campaign delivery | E20: Results | F20: Result indicator | G20: Cost per result | H20: Ad set budget | I20: Ad set budget type | J20: Amount spent (INR) | K20: Impressions | L20: Reach | M20: Ends | N20: Attribution setting | O20: CRM Leads (LeadChain) | P20: Qualified Leads | Q20: Qualified Lead % | R20: Meetings Scheduled | S20: Meeting Scheduled % | T20: Link Clicks | U20: CTR | V20: CTR % | W20: CPQL | X20: CPQL %
A21: =INDEX(Data_Campaigns!$A$2:$A$15,MATCH($C21,Data_Campaigns!$C$2:$C$15,0)) | B21: =INDEX(Data_Campaigns!$B$2:$B$15,MATCH($C21,Data_Campaigns!$C$2:$C$15,0)) | C21: Andromeda_CBO_Signature Store_FICO_Daewoo_SO | D21: =INDEX(Data_Campaigns!$D$2:$D$15,MATCH($C21,Data_Campaigns!$C$2:$C$15,0)) | E21: =IF(INDEX(Data_Campaigns!$E$2:$E$15,MATCH($C21,Data_Campaigns!$C$2:$C$15,0))=0,"",INDEX(Data_Campaigns!$E$2:$E$15,MATCH($C21,Data_Campaigns!$C$2:$C$15,0))) | F21: =INDEX(Data_Campaigns!$F$2:$F$15,MATCH($C21,Data_Campaigns!$C$2:$C$15,0)) | G21: =IFERROR(IF($E21="","n/a",$J21/$E21),"n/a") | H21: =INDEX(Data_Campaigns!$H$2:$H$15,MATCH($C21,Data_Campaigns!$C$2:$C$15,0)) | I21: =INDEX(Data_Campaigns!$I$2:$I$15,MATCH($C21,Data_Campaigns!$C$2:$C$15,0)) | J21: =INDEX(Data_Campaigns!$J$2:$J$15,MATCH($C21,Data_Campaigns!$C$2:$C$15,0)) | K21: =INDEX(Data_Campaigns!$K$2:$K$15,MATCH($C21,Data_Campaigns!$C$2:$C$15,0)) | L21: =INDEX(Data_Campaigns!$L$2:$L$15,MATCH($C21,Data_Campaigns!$C$2:$C$15,0)) | M21: =INDEX(Data_Campaigns!$M$2:$M$15,MATCH($C21,Data_Campaigns!$C$2:$C$15,0)) | N21: =INDEX(Data_Campaigns!$N$2:$N$15,MATCH($C21,Data_Campaigns!$C$2:$C$15,0)) | O21: =COUNTIFS(Data_CRM!$B$2:$B$1694,$C21,Data_CRM!$A$2:$A$1694,">="&Data_CRM!$J$2,Data_CRM!$A$2:$A$1694,"<="&Data_CRM!$J$3) | P21: =SUMIFS(Data_CRM!$F$2:$F$1694,Data_CRM!$B$2:$B$1694,$C21,Data_CRM!$A$2:$A$1694,">="&Data_CRM!$J$2,Data_CRM!$A$2:$A$1694,"<="&Data_CRM!$J$3) | Q21: =IFERROR(IF($O21=0,"n/a",$P21/$O21),"n/a") | R21: =COUNTIF(Data_MeetingScheduled!$C$2:$C$200,$C21) | S21: =IFERROR(IF($O21=0,"n/a",$R21/$O21),"n/a") | T21: =INDEX(Data_Campaigns!$O$2:$O$15,MATCH($C21,Data_Campaigns!$C$2:$C$15,0)) | U21: =IFERROR($T21/$K21,"n/a") | V21: =IFERROR($T21/$K21,"n/a") | W21: =IFERROR($J21/$P21,"n/a") | X21: =IFERROR($P21/$O21,"n/a")
A22: =INDEX(Data_Campaigns!$A$2:$A$15,MATCH($C22,Data_Campaigns!$C$2:$C$15,0)) | B22: =INDEX(Data_Campaigns!$B$2:$B$15,MATCH($C22,Data_Campaigns!$C$2:$C$15,0)) | C22: META_CustomData_MOFU_STOCKIST_Leadgen | D22: =INDEX(Data_Campaigns!$D$2:$D$15,MATCH($C22,Data_Campaigns!$C$2:$C$15,0)) | E22: =IF(INDEX(Data_Campaigns!$E$2:$E$15,MATCH($C22,Data_Campaigns!$C$2:$C$15,0))=0,"",INDEX(Data_Campaigns!$E$2:$E$15,MATCH($C22,Data_Campaigns!$C$2:$C$15,0))) | F22: =INDEX(Data_Campaigns!$F$2:$F$15,MATCH($C22,Data_Campaigns!$C$2:$C$15,0)) | G22: =IFERROR(IF($E22="","n/a",$J22/$E22),"n/a") | H22: =INDEX(Data_Campaigns!$H$2:$H$15,MATCH($C22,Data_Campaigns!$C$2:$C$15,0)) | I22: =INDEX(Data_Campaigns!$I$2:$I$15,MATCH($C22,Data_Campaigns!$C$2:$C$15,0)) | J22: =INDEX(Data_Campaigns!$J$2:$J$15,MATCH($C22,Data_Campaigns!$C$2:$C$15,0)) | K22: =INDEX(Data_Campaigns!$K$2:$K$15,MATCH($C22,Data_Campaigns!$C$2:$C$15,0)) | L22: =INDEX(Data_Campaigns!$L$2:$L$15,MATCH($C22,Data_Campaigns!$C$2:$C$15,0)) | M22: =INDEX(Data_Campaigns!$M$2:$M$15,MATCH($C22,Data_Campaigns!$C$2:$C$15,0)) | N22: =INDEX(Data_Campaigns!$N$2:$N$15,MATCH($C22,Data_Campaigns!$C$2:$C$15,0)) | O22: =COUNTIFS(Data_CRM!$B$2:$B$1694,$C22,Data_CRM!$A$2:$A$1694,">="&Data_CRM!$J$2,Data_CRM!$A$2:$A$1694,"<="&Data_CRM!$J$3) | P22: =SUMIFS(Data_CRM!$F$2:$F$1694,Data_CRM!$B$2:$B$1694,$C22,Data_CRM!$A$2:$A$1694,">="&Data_CRM!$J$2,Data_CRM!$A$2:$A$1694,"<="&Data_CRM!$J$3) | Q22: =IFERROR(IF($O22=0,"n/a",$P22/$O22),"n/a") | R22: =COUNTIF(Data_MeetingScheduled!$C$2:$C$200,$C22) | S22: =IFERROR(IF($O22=0,"n/a",$R22/$O22),"n/a") | T22: =INDEX(Data_Campaigns!$O$2:$O$15,MATCH($C22,Data_Campaigns!$C$2:$C$15,0)) | U22: =IFERROR($T22/$K22,"n/a") | V22: =IFERROR($T22/$K22,"n/a") | W22: =IFERROR($J22/$P22,"n/a") | X22: =IFERROR($P22/$O22,"n/a")
A23: =INDEX(Data_Campaigns!$A$2:$A$15,MATCH($C23,Data_Campaigns!$C$2:$C$15,0)) | B23: =INDEX(Data_Campaigns!$B$2:$B$15,MATCH($C23,Data_Campaigns!$C$2:$C$15,0)) | C23: Andromeda_ABO_Stockist_Daewoo_SO | D23: =INDEX(Data_Campaigns!$D$2:$D$15,MATCH($C23,Data_Campaigns!$C$2:$C$15,0)) | E23: =IF(INDEX(Data_Campaigns!$E$2:$E$15,MATCH($C23,Data_Campaigns!$C$2:$C$15,0))=0,"",INDEX(Data_Campaigns!$E$2:$E$15,MATCH($C23,Data_Campaigns!$C$2:$C$15,0))) | F23: =INDEX(Data_Campaigns!$F$2:$F$15,MATCH($C23,Data_Campaigns!$C$2:$C$15,0)) | G23: =IFERROR(IF($E23="","n/a",$J23/$E23),"n/a") | H23: =INDEX(Data_Campaigns!$H$2:$H$15,MATCH($C23,Data_Campaigns!$C$2:$C$15,0)) | I23: =INDEX(Data_Campaigns!$I$2:$I$15,MATCH($C23,Data_Campaigns!$C$2:$C$15,0)) | J23: =INDEX(Data_Campaigns!$J$2:$J$15,MATCH($C23,Data_Campaigns!$C$2:$C$15,0)) | K23: =INDEX(Data_Campaigns!$K$2:$K$15,MATCH($C23,Data_Campaigns!$C$2:$C$15,0)) | L23: =INDEX(Data_Campaigns!$L$2:$L$15,MATCH($C23,Data_Campaigns!$C$2:$C$15,0)) | M23: =INDEX(Data_Campaigns!$M$2:$M$15,MATCH($C23,Data_Campaigns!$C$2:$C$15,0)) | N23: =INDEX(Data_Campaigns!$N$2:$N$15,MATCH($C23,Data_Campaigns!$C$2:$C$15,0)) | O23: =COUNTIFS(Data_CRM!$B$2:$B$1694,$C23,Data_CRM!$A$2:$A$1694,">="&Data_CRM!$J$2,Data_CRM!$A$2:$A$1694,"<="&Data_CRM!$J$3) | P23: =SUMIFS(Data_CRM!$F$2:$F$1694,Data_CRM!$B$2:$B$1694,$C23,Data_CRM!$A$2:$A$1694,">="&Data_CRM!$J$2,Data_CRM!$A$2:$A$1694,"<="&Data_CRM!$J$3) | Q23: =IFERROR(IF($O23=0,"n/a",$P23/$O23),"n/a") | R23: =COUNTIF(Data_MeetingScheduled!$C$2:$C$200,$C23) | S23: =IFERROR(IF($O23=0,"n/a",$R23/$O23),"n/a") | T23: =INDEX(Data_Campaigns!$O$2:$O$15,MATCH($C23,Data_Campaigns!$C$2:$C$15,0)) | U23: =IFERROR($T23/$K23,"n/a") | V23: =IFERROR($T23/$K23,"n/a") | W23: =IFERROR($J23/$P23,"n/a") | X23: =IFERROR($P23/$O23,"n/a")
A24: =INDEX(Data_Campaigns!$A$2:$A$15,MATCH($C24,Data_Campaigns!$C$2:$C$15,0)) | B24: =INDEX(Data_Campaigns!$B$2:$B$15,MATCH($C24,Data_Campaigns!$C$2:$C$15,0)) | C24: Andromeda_CBO__DDP_Daewoo_SO | D24: =INDEX(Data_Campaigns!$D$2:$D$15,MATCH($C24,Data_Campaigns!$C$2:$C$15,0)) | E24: =IF(INDEX(Data_Campaigns!$E$2:$E$15,MATCH($C24,Data_Campaigns!$C$2:$C$15,0))=0,"",INDEX(Data_Campaigns!$E$2:$E$15,MATCH($C24,Data_Campaigns!$C$2:$C$15,0))) | F24: =INDEX(Data_Campaigns!$F$2:$F$15,MATCH($C24,Data_Campaigns!$C$2:$C$15,0)) | G24: =IFERROR(IF($E24="","n/a",$J24/$E24),"n/a") | H24: =INDEX(Data_Campaigns!$H$2:$H$15,MATCH($C24,Data_Campaigns!$C$2:$C$15,0)) | I24: =INDEX(Data_Campaigns!$I$2:$I$15,MATCH($C24,Data_Campaigns!$C$2:$C$15,0)) | J24: =INDEX(Data_Campaigns!$J$2:$J$15,MATCH($C24,Data_Campaigns!$C$2:$C$15,0)) | K24: =INDEX(Data_Campaigns!$K$2:$K$15,MATCH($C24,Data_Campaigns!$C$2:$C$15,0)) | L24: =INDEX(Data_Campaigns!$L$2:$L$15,MATCH($C24,Data_Campaigns!$C$2:$C$15,0)) | M24: =INDEX(Data_Campaigns!$M$2:$M$15,MATCH($C24,Data_Campaigns!$C$2:$C$15,0)) | N24: =INDEX(Data_Campaigns!$N$2:$N$15,MATCH($C24,Data_Campaigns!$C$2:$C$15,0)) | O24: =COUNTIFS(Data_CRM!$B$2:$B$1694,$C24,Data_CRM!$A$2:$A$1694,">="&Data_CRM!$J$2,Data_CRM!$A$2:$A$1694,"<="&Data_CRM!$J$3) | P24: =SUMIFS(Data_CRM!$F$2:$F$1694,Data_CRM!$B$2:$B$1694,$C24,Data_CRM!$A$2:$A$1694,">="&Data_CRM!$J$2,Data_CRM!$A$2:$A$1694,"<="&Data_CRM!$J$3) | Q24: =IFERROR(IF($O24=0,"n/a",$P24/$O24),"n/a") | R24: =COUNTIF(Data_MeetingScheduled!$C$2:$C$200,$C24) | S24: =IFERROR(IF($O24=0,"n/a",$R24/$O24),"n/a") | T24: =INDEX(Data_Campaigns!$O$2:$O$15,MATCH($C24,Data_Campaigns!$C$2:$C$15,0)) | U24: =IFERROR($T24/$K24,"n/a") | V24: =IFERROR($T24/$K24,"n/a") | W24: =IFERROR($J24/$P24,"n/a") | X24: =IFERROR($P24/$O24,"n/a")
A25: =INDEX(Data_Campaigns!$A$2:$A$15,MATCH($C25,Data_Campaigns!$C$2:$C$15,0)) | B25: =INDEX(Data_Campaigns!$B$2:$B$15,MATCH($C25,Data_Campaigns!$C$2:$C$15,0)) | C25: META_CustomData_MOFU_Leadgen – DDP | D25: =INDEX(Data_Campaigns!$D$2:$D$15,MATCH($C25,Data_Campaigns!$C$2:$C$15,0)) | E25: =IF(INDEX(Data_Campaigns!$E$2:$E$15,MATCH($C25,Data_Campaigns!$C$2:$C$15,0))=0,"",INDEX(Data_Campaigns!$E$2:$E$15,MATCH($C25,Data_Campaigns!$C$2:$C$15,0))) | F25: =INDEX(Data_Campaigns!$F$2:$F$15,MATCH($C25,Data_Campaigns!$C$2:$C$15,0)) | G25: =IFERROR(IF($E25="","n/a",$J25/$E25),"n/a") | H25: =INDEX(Data_Campaigns!$H$2:$H$15,MATCH($C25,Data_Campaigns!$C$2:$C$15,0)) | I25: =INDEX(Data_Campaigns!$I$2:$I$15,MATCH($C25,Data_Campaigns!$C$2:$C$15,0)) | J25: =INDEX(Data_Campaigns!$J$2:$J$15,MATCH($C25,Data_Campaigns!$C$2:$C$15,0)) | K25: =INDEX(Data_Campaigns!$K$2:$K$15,MATCH($C25,Data_Campaigns!$C$2:$C$15,0)) | L25: =INDEX(Data_Campaigns!$L$2:$L$15,MATCH($C25,Data_Campaigns!$C$2:$C$15,0)) | M25: =INDEX(Data_Campaigns!$M$2:$M$15,MATCH($C25,Data_Campaigns!$C$2:$C$15,0)) | N25: =INDEX(Data_Campaigns!$N$2:$N$15,MATCH($C25,Data_Campaigns!$C$2:$C$15,0)) | O25: =COUNTIFS(Data_CRM!$B$2:$B$1694,$C25,Data_CRM!$A$2:$A$1694,">="&Data_CRM!$J$2,Data_CRM!$A$2:$A$1694,"<="&Data_CRM!$J$3) | P25: =SUMIFS(Data_CRM!$F$2:$F$1694,Data_CRM!$B$2:$B$1694,$C25,Data_CRM!$A$2:$A$1694,">="&Data_CRM!$J$2,Data_CRM!$A$2:$A$1694,"<="&Data_CRM!$J$3) | Q25: =IFERROR(IF($O25=0,"n/a",$P25/$O25),"n/a") | R25: =COUNTIF(Data_MeetingScheduled!$C$2:$C$200,$C25) | S25: =IFERROR(IF($O25=0,"n/a",$R25/$O25),"n/a") | T25: =INDEX(Data_Campaigns!$O$2:$O$15,MATCH($C25,Data_Campaigns!$C$2:$C$15,0)) | U25: =IFERROR($T25/$K25,"n/a") | V25: =IFERROR($T25/$K25,"n/a") | W25: =IFERROR($J25/$P25,"n/a") | X25: =IFERROR($P25/$O25,"n/a")
A26: =INDEX(Data_Campaigns!$A$2:$A$15,MATCH($C26,Data_Campaigns!$C$2:$C$15,0)) | B26: =INDEX(Data_Campaigns!$B$2:$B$15,MATCH($C26,Data_Campaigns!$C$2:$C$15,0)) | C26: META_CustomData_MOFU_Leadgen – Signature FICO | D26: =INDEX(Data_Campaigns!$D$2:$D$15,MATCH($C26,Data_Campaigns!$C$2:$C$15,0)) | E26: =IF(INDEX(Data_Campaigns!$E$2:$E$15,MATCH($C26,Data_Campaigns!$C$2:$C$15,0))=0,"",INDEX(Data_Campaigns!$E$2:$E$15,MATCH($C26,Data_Campaigns!$C$2:$C$15,0))) | F26: =INDEX(Data_Campaigns!$F$2:$F$15,MATCH($C26,Data_Campaigns!$C$2:$C$15,0)) | G26: =IFERROR(IF($E26="","n/a",$J26/$E26),"n/a") | H26: =INDEX(Data_Campaigns!$H$2:$H$15,MATCH($C26,Data_Campaigns!$C$2:$C$15,0)) | I26: =INDEX(Data_Campaigns!$I$2:$I$15,MATCH($C26,Data_Campaigns!$C$2:$C$15,0)) | J26: =INDEX(Data_Campaigns!$J$2:$J$15,MATCH($C26,Data_Campaigns!$C$2:$C$15,0)) | K26: =INDEX(Data_Campaigns!$K$2:$K$15,MATCH($C26,Data_Campaigns!$C$2:$C$15,0)) | L26: =INDEX(Data_Campaigns!$L$2:$L$15,MATCH($C26,Data_Campaigns!$C$2:$C$15,0)) | M26: =INDEX(Data_Campaigns!$M$2:$M$15,MATCH($C26,Data_Campaigns!$C$2:$C$15,0)) | N26: =INDEX(Data_Campaigns!$N$2:$N$15,MATCH($C26,Data_Campaigns!$C$2:$C$15,0)) | O26: =COUNTIFS(Data_CRM!$B$2:$B$1694,$C26,Data_CRM!$A$2:$A$1694,">="&Data_CRM!$J$2,Data_CRM!$A$2:$A$1694,"<="&Data_CRM!$J$3) | P26: =SUMIFS(Data_CRM!$F$2:$F$1694,Data_CRM!$B$2:$B$1694,$C26,Data_CRM!$A$2:$A$1694,">="&Data_CRM!$J$2,Data_CRM!$A$2:$A$1694,"<="&Data_CRM!$J$3) | Q26: =IFERROR(IF($O26=0,"n/a",$P26/$O26),"n/a") | R26: =COUNTIF(Data_MeetingScheduled!$C$2:$C$200,$C26) | S26: =IFERROR(IF($O26=0,"n/a",$R26/$O26),"n/a") | T26: =INDEX(Data_Campaigns!$O$2:$O$15,MATCH($C26,Data_Campaigns!$C$2:$C$15,0)) | U26: =IFERROR($T26/$K26,"n/a") | V26: =IFERROR($T26/$K26,"n/a") | W26: =IFERROR($J26/$P26,"n/a") | X26: =IFERROR($P26/$O26,"n/a")
A27: =INDEX(Data_Campaigns!$A$2:$A$15,MATCH($C27,Data_Campaigns!$C$2:$C$15,0)) | B27: =INDEX(Data_Campaigns!$B$2:$B$15,MATCH($C27,Data_Campaigns!$C$2:$C$15,0)) | C27: META_RMKT_Engage_ABO_SO | D27: =INDEX(Data_Campaigns!$D$2:$D$15,MATCH($C27,Data_Campaigns!$C$2:$C$15,0)) | E27: =IF(INDEX(Data_Campaigns!$E$2:$E$15,MATCH($C27,Data_Campaigns!$C$2:$C$15,0))=0,"",INDEX(Data_Campaigns!$E$2:$E$15,MATCH($C27,Data_Campaigns!$C$2:$C$15,0))) | F27: =INDEX(Data_Campaigns!$F$2:$F$15,MATCH($C27,Data_Campaigns!$C$2:$C$15,0)) | G27: =IFERROR(IF($E27="","n/a",$J27/$E27),"n/a") | H27: =INDEX(Data_Campaigns!$H$2:$H$15,MATCH($C27,Data_Campaigns!$C$2:$C$15,0)) | I27: =INDEX(Data_Campaigns!$I$2:$I$15,MATCH($C27,Data_Campaigns!$C$2:$C$15,0)) | J27: =INDEX(Data_Campaigns!$J$2:$J$15,MATCH($C27,Data_Campaigns!$C$2:$C$15,0)) | K27: =INDEX(Data_Campaigns!$K$2:$K$15,MATCH($C27,Data_Campaigns!$C$2:$C$15,0)) | L27: =INDEX(Data_Campaigns!$L$2:$L$15,MATCH($C27,Data_Campaigns!$C$2:$C$15,0)) | M27: =INDEX(Data_Campaigns!$M$2:$M$15,MATCH($C27,Data_Campaigns!$C$2:$C$15,0)) | N27: =INDEX(Data_Campaigns!$N$2:$N$15,MATCH($C27,Data_Campaigns!$C$2:$C$15,0)) | O27: =COUNTIFS(Data_CRM!$B$2:$B$1694,$C27,Data_CRM!$A$2:$A$1694,">="&Data_CRM!$J$2,Data_CRM!$A$2:$A$1694,"<="&Data_CRM!$J$3) | P27: =SUMIFS(Data_CRM!$F$2:$F$1694,Data_CRM!$B$2:$B$1694,$C27,Data_CRM!$A$2:$A$1694,">="&Data_CRM!$J$2,Data_CRM!$A$2:$A$1694,"<="&Data_CRM!$J$3) | Q27: =IFERROR(IF($O27=0,"n/a",$P27/$O27),"n/a") | R27: =COUNTIF(Data_MeetingScheduled!$C$2:$C$200,$C27) | S27: =IFERROR(IF($O27=0,"n/a",$R27/$O27),"n/a") | T27: =INDEX(Data_Campaigns!$O$2:$O$15,MATCH($C27,Data_Campaigns!$C$2:$C$15,0)) | U27: =IFERROR($T27/$K27,"n/a") | V27: =IFERROR($T27/$K27,"n/a") | W27: =IFERROR($J27/$P27,"n/a") | X27: =IFERROR($P27/$O27,"n/a")
A28: =INDEX(Data_Campaigns!$A$2:$A$15,MATCH($C28,Data_Campaigns!$C$2:$C$15,0)) | B28: =INDEX(Data_Campaigns!$B$2:$B$15,MATCH($C28,Data_Campaigns!$C$2:$C$15,0)) | C28: META_RMKT_Socials Pages_CBO_SO | D28: =INDEX(Data_Campaigns!$D$2:$D$15,MATCH($C28,Data_Campaigns!$C$2:$C$15,0)) | E28: =IF(INDEX(Data_Campaigns!$E$2:$E$15,MATCH($C28,Data_Campaigns!$C$2:$C$15,0))=0,"",INDEX(Data_Campaigns!$E$2:$E$15,MATCH($C28,Data_Campaigns!$C$2:$C$15,0))) | F28: =INDEX(Data_Campaigns!$F$2:$F$15,MATCH($C28,Data_Campaigns!$C$2:$C$15,0)) | G28: =IFERROR(IF($E28="","n/a",$J28/$E28),"n/a") | H28: =INDEX(Data_Campaigns!$H$2:$H$15,MATCH($C28,Data_Campaigns!$C$2:$C$15,0)) | I28: =INDEX(Data_Campaigns!$I$2:$I$15,MATCH($C28,Data_Campaigns!$C$2:$C$15,0)) | J28: =INDEX(Data_Campaigns!$J$2:$J$15,MATCH($C28,Data_Campaigns!$C$2:$C$15,0)) | K28: =INDEX(Data_Campaigns!$K$2:$K$15,MATCH($C28,Data_Campaigns!$C$2:$C$15,0)) | L28: =INDEX(Data_Campaigns!$L$2:$L$15,MATCH($C28,Data_Campaigns!$C$2:$C$15,0)) | M28: =INDEX(Data_Campaigns!$M$2:$M$15,MATCH($C28,Data_Campaigns!$C$2:$C$15,0)) | N28: =INDEX(Data_Campaigns!$N$2:$N$15,MATCH($C28,Data_Campaigns!$C$2:$C$15,0)) | O28: =COUNTIFS(Data_CRM!$B$2:$B$1694,$C28,Data_CRM!$A$2:$A$1694,">="&Data_CRM!$J$2,Data_CRM!$A$2:$A$1694,"<="&Data_CRM!$J$3) | P28: =SUMIFS(Data_CRM!$F$2:$F$1694,Data_CRM!$B$2:$B$1694,$C28,Data_CRM!$A$2:$A$1694,">="&Data_CRM!$J$2,Data_CRM!$A$2:$A$1694,"<="&Data_CRM!$J$3) | Q28: =IFERROR(IF($O28=0,"n/a",$P28/$O28),"n/a") | R28: =COUNTIF(Data_MeetingScheduled!$C$2:$C$200,$C28) | S28: =IFERROR(IF($O28=0,"n/a",$R28/$O28),"n/a") | T28: =INDEX(Data_Campaigns!$O$2:$O$15,MATCH($C28,Data_Campaigns!$C$2:$C$15,0)) | U28: =IFERROR($T28/$K28,"n/a") | V28: =IFERROR($T28/$K28,"n/a") | W28: =IFERROR($J28/$P28,"n/a") | X28: =IFERROR($P28/$O28,"n/a")
A29: =INDEX(Data_Campaigns!$A$2:$A$15,MATCH($C29,Data_Campaigns!$C$2:$C$15,0)) | B29: =INDEX(Data_Campaigns!$B$2:$B$15,MATCH($C29,Data_Campaigns!$C$2:$C$15,0)) | C29: CRM Custom List_CBO_SO | D29: =INDEX(Data_Campaigns!$D$2:$D$15,MATCH($C29,Data_Campaigns!$C$2:$C$15,0)) | E29: =IF(INDEX(Data_Campaigns!$E$2:$E$15,MATCH($C29,Data_Campaigns!$C$2:$C$15,0))=0,"",INDEX(Data_Campaigns!$E$2:$E$15,MATCH($C29,Data_Campaigns!$C$2:$C$15,0))) | F29: =INDEX(Data_Campaigns!$F$2:$F$15,MATCH($C29,Data_Campaigns!$C$2:$C$15,0)) | G29: =IFERROR(IF($E29="","n/a",$J29/$E29),"n/a") | H29: =INDEX(Data_Campaigns!$H$2:$H$15,MATCH($C29,Data_Campaigns!$C$2:$C$15,0)) | I29: =INDEX(Data_Campaigns!$I$2:$I$15,MATCH($C29,Data_Campaigns!$C$2:$C$15,0)) | J29: =INDEX(Data_Campaigns!$J$2:$J$15,MATCH($C29,Data_Campaigns!$C$2:$C$15,0)) | K29: =INDEX(Data_Campaigns!$K$2:$K$15,MATCH($C29,Data_Campaigns!$C$2:$C$15,0)) | L29: =INDEX(Data_Campaigns!$L$2:$L$15,MATCH($C29,Data_Campaigns!$C$2:$C$15,0)) | M29: =INDEX(Data_Campaigns!$M$2:$M$15,MATCH($C29,Data_Campaigns!$C$2:$C$15,0)) | N29: =INDEX(Data_Campaigns!$N$2:$N$15,MATCH($C29,Data_Campaigns!$C$2:$C$15,0)) | O29: =COUNTIFS(Data_CRM!$B$2:$B$1694,$C29,Data_CRM!$A$2:$A$1694,">="&Data_CRM!$J$2,Data_CRM!$A$2:$A$1694,"<="&Data_CRM!$J$3) | P29: =SUMIFS(Data_CRM!$F$2:$F$1694,Data_CRM!$B$2:$B$1694,$C29,Data_CRM!$A$2:$A$1694,">="&Data_CRM!$J$2,Data_CRM!$A$2:$A$1694,"<="&Data_CRM!$J$3) | Q29: =IFERROR(IF($O29=0,"n/a",$P29/$O29),"n/a") | R29: =COUNTIF(Data_MeetingScheduled!$C$2:$C$200,$C29) | S29: =IFERROR(IF($O29=0,"n/a",$R29/$O29),"n/a") | T29: =INDEX(Data_Campaigns!$O$2:$O$15,MATCH($C29,Data_Campaigns!$C$2:$C$15,0)) | U29: =IFERROR($T29/$K29,"n/a") | V29: =IFERROR($T29/$K29,"n/a") | W29: =IFERROR($J29/$P29,"n/a") | X29: =IFERROR($P29/$O29,"n/a")
C30: TOTAL / BLENDED AVERAGE | E30: =SUM(E21:E29) | G30: =IFERROR($J30/$E30,"n/a") | J30: =SUM(J21:J29) | K30: =SUM(K21:K29) | L30: =SUM(L21:L29) | O30: =SUM(O21:O29) | P30: =SUM(P21:P29) | Q30: =IFERROR($P30/$O30,"n/a") | R30: =SUM(R21:R29) | S30: =IFERROR($R30/$O30,"n/a") | T30: =SUM(T21:T29) | U30: =IFERROR($T30/$K30,"n/a") | V30: =IFERROR($T30/$K30,"n/a") | W30: =IFERROR($J30/$P30,"n/a") | X30: =IFERROR($P30/$O30,"n/a")
A31: Total Meeting Scheduled — LeadModule + MeetingDetails, 1–28 Oct 2026, deduplicated by email (see Data Notes) | R31: =Data_MeetingScheduled!$J$2
A35: 2. CAMPAIGN-WISE PERFORMANCE — FTD 28 Oct 2026 (CRM lead data, LeadChain-mapped)
A37: Campaign name | B37: CRM Leads (FTD) | C37: Qualified Leads (FTD) | D37: Qualified Lead % (FTD) | E37: Meetings Scheduled (FTD) | F37: Meeting Scheduled % (FTD)
A38: Andromeda_CBO_Signature Store_FICO_Daewoo_SO | B38: =COUNTIFS(Data_CRM!$B$2:$B$1694,$A38,Data_CRM!$A$2:$A$1694,">="&Data_CRM!$J$4,Data_CRM!$A$2:$A$1694,"<="&Data_CRM!$J$5) | C38: =SUMIFS(Data_CRM!$F$2:$F$1694,Data_CRM!$B$2:$B$1694,$A38,Data_CRM!$A$2:$A$1694,">="&Data_CRM!$J$4,Data_CRM!$A$2:$A$1694,"<="&Data_CRM!$J$5) | D38: =IFERROR(IF($B38=0,"n/a",$C38/$B38),"n/a") | E38: =COUNTIFS(Data_MeetingScheduled!$C$2:$C$200,$A38,Data_MeetingScheduled!$G$2:$G$200,">="&Data_CRM!$J$4,Data_MeetingScheduled!$G$2:$G$200,"<="&Data_CRM!$J$5) | F38: =IFERROR(IF($B38=0,"n/a",$E38/$B38),"n/a")
A39: META_CustomData_MOFU_STOCKIST_Leadgen | B39: =COUNTIFS(Data_CRM!$B$2:$B$1694,$A39,Data_CRM!$A$2:$A$1694,">="&Data_CRM!$J$4,Data_CRM!$A$2:$A$1694,"<="&Data_CRM!$J$5) | C39: =SUMIFS(Data_CRM!$F$2:$F$1694,Data_CRM!$B$2:$B$1694,$A39,Data_CRM!$A$2:$A$1694,">="&Data_CRM!$J$4,Data_CRM!$A$2:$A$1694,"<="&Data_CRM!$J$5) | D39: =IFERROR(IF($B39=0,"n/a",$C39/$B39),"n/a") | E39: =COUNTIFS(Data_MeetingScheduled!$C$2:$C$200,$A39,Data_MeetingScheduled!$G$2:$G$200,">="&Data_CRM!$J$4,Data_MeetingScheduled!$G$2:$G$200,"<="&Data_CRM!$J$5) | F39: =IFERROR(IF($B39=0,"n/a",$E39/$B39),"n/a")
A40: Andromeda_ABO_Stockist_Daewoo_SO | B40: =COUNTIFS(Data_CRM!$B$2:$B$1694,$A40,Data_CRM!$A$2:$A$1694,">="&Data_CRM!$J$4,Data_CRM!$A$2:$A$1694,"<="&Data_CRM!$J$5) | C40: =SUMIFS(Data_CRM!$F$2:$F$1694,Data_CRM!$B$2:$B$1694,$A40,Data_CRM!$A$2:$A$1694,">="&Data_CRM!$J$4,Data_CRM!$A$2:$A$1694,"<="&Data_CRM!$J$5) | D40: =IFERROR(IF($B40=0,"n/a",$C40/$B40),"n/a") | E40: =COUNTIFS(Data_MeetingScheduled!$C$2:$C$200,$A40,Data_MeetingScheduled!$G$2:$G$200,">="&Data_CRM!$J$4,Data_MeetingScheduled!$G$2:$G$200,"<="&Data_CRM!$J$5) | F40: =IFERROR(IF($B40=0,"n/a",$E40/$B40),"n/a")
A41: Andromeda_CBO__DDP_Daewoo_SO | B41: =COUNTIFS(Data_CRM!$B$2:$B$1694,$A41,Data_CRM!$A$2:$A$1694,">="&Data_CRM!$J$4,Data_CRM!$A$2:$A$1694,"<="&Data_CRM!$J$5) | C41: =SUMIFS(Data_CRM!$F$2:$F$1694,Data_CRM!$B$2:$B$1694,$A41,Data_CRM!$A$2:$A$1694,">="&Data_CRM!$J$4,Data_CRM!$A$2:$A$1694,"<="&Data_CRM!$J$5) | D41: =IFERROR(IF($B41=0,"n/a",$C41/$B41),"n/a") | E41: =COUNTIFS(Data_MeetingScheduled!$C$2:$C$200,$A41,Data_MeetingScheduled!$G$2:$G$200,">="&Data_CRM!$J$4,Data_MeetingScheduled!$G$2:$G$200,"<="&Data_CRM!$J$5) | F41: =IFERROR(IF($B41=0,"n/a",$E41/$B41),"n/a")
A42: META_CustomData_MOFU_Leadgen – DDP | B42: =COUNTIFS(Data_CRM!$B$2:$B$1694,$A42,Data_CRM!$A$2:$A$1694,">="&Data_CRM!$J$4,Data_CRM!$A$2:$A$1694,"<="&Data_CRM!$J$5) | C42: =SUMIFS(Data_CRM!$F$2:$F$1694,Data_CRM!$B$2:$B$1694,$A42,Data_CRM!$A$2:$A$1694,">="&Data_CRM!$J$4,Data_CRM!$A$2:$A$1694,"<="&Data_CRM!$J$5) | D42: =IFERROR(IF($B42=0,"n/a",$C42/$B42),"n/a") | E42: =COUNTIFS(Data_MeetingScheduled!$C$2:$C$200,$A42,Data_MeetingScheduled!$G$2:$G$200,">="&Data_CRM!$J$4,Data_MeetingScheduled!$G$2:$G$200,"<="&Data_CRM!$J$5) | F42: =IFERROR(IF($B42=0,"n/a",$E42/$B42),"n/a")
A43: META_CustomData_MOFU_Leadgen – Signature FICO | B43: =COUNTIFS(Data_CRM!$B$2:$B$1694,$A43,Data_CRM!$A$2:$A$1694,">="&Data_CRM!$J$4,Data_CRM!$A$2:$A$1694,"<="&Data_CRM!$J$5) | C43: =SUMIFS(Data_CRM!$F$2:$F$1694,Data_CRM!$B$2:$B$1694,$A43,Data_CRM!$A$2:$A$1694,">="&Data_CRM!$J$4,Data_CRM!$A$2:$A$1694,"<="&Data_CRM!$J$5) | D43: =IFERROR(IF($B43=0,"n/a",$C43/$B43),"n/a") | E43: =COUNTIFS(Data_MeetingScheduled!$C$2:$C$200,$A43,Data_MeetingScheduled!$G$2:$G$200,">="&Data_CRM!$J$4,Data_MeetingScheduled!$G$2:$G$200,"<="&Data_CRM!$J$5) | F43: =IFERROR(IF($B43=0,"n/a",$E43/$B43),"n/a")
A44: META_RMKT_Engage_ABO_SO | B44: =COUNTIFS(Data_CRM!$B$2:$B$1694,$A44,Data_CRM!$A$2:$A$1694,">="&Data_CRM!$J$4,Data_CRM!$A$2:$A$1694,"<="&Data_CRM!$J$5) | C44: =SUMIFS(Data_CRM!$F$2:$F$1694,Data_CRM!$B$2:$B$1694,$A44,Data_CRM!$A$2:$A$1694,">="&Data_CRM!$J$4,Data_CRM!$A$2:$A$1694,"<="&Data_CRM!$J$5) | D44: =IFERROR(IF($B44=0,"n/a",$C44/$B44),"n/a") | E44: =COUNTIFS(Data_MeetingScheduled!$C$2:$C$200,$A44,Data_MeetingScheduled!$G$2:$G$200,">="&Data_CRM!$J$4,Data_MeetingScheduled!$G$2:$G$200,"<="&Data_CRM!$J$5) | F44: =IFERROR(IF($B44=0,"n/a",$E44/$B44),"n/a")
A45: META_RMKT_Socials Pages_CBO_SO | B45: =COUNTIFS(Data_CRM!$B$2:$B$1694,$A45,Data_CRM!$A$2:$A$1694,">="&Data_CRM!$J$4,Data_CRM!$A$2:$A$1694,"<="&Data_CRM!$J$5) | C45: =SUMIFS(Data_CRM!$F$2:$F$1694,Data_CRM!$B$2:$B$1694,$A45,Data_CRM!$A$2:$A$1694,">="&Data_CRM!$J$4,Data_CRM!$A$2:$A$1694,"<="&Data_CRM!$J$5) | D45: =IFERROR(IF($B45=0,"n/a",$C45/$B45),"n/a") | E45: =COUNTIFS(Data_MeetingScheduled!$C$2:$C$200,$A45,Data_MeetingScheduled!$G$2:$G$200,">="&Data_CRM!$J$4,Data_MeetingScheduled!$G$2:$G$200,"<="&Data_CRM!$J$5) | F45: =IFERROR(IF($B45=0,"n/a",$E45/$B45),"n/a")
A46: CRM Custom List_CBO_SO | B46: =COUNTIFS(Data_CRM!$B$2:$B$1694,$A46,Data_CRM!$A$2:$A$1694,">="&Data_CRM!$J$4,Data_CRM!$A$2:$A$1694,"<="&Data_CRM!$J$5) | C46: =SUMIFS(Data_CRM!$F$2:$F$1694,Data_CRM!$B$2:$B$1694,$A46,Data_CRM!$A$2:$A$1694,">="&Data_CRM!$J$4,Data_CRM!$A$2:$A$1694,"<="&Data_CRM!$J$5) | D46: =IFERROR(IF($B46=0,"n/a",$C46/$B46),"n/a") | E46: =COUNTIFS(Data_MeetingScheduled!$C$2:$C$200,$A46,Data_MeetingScheduled!$G$2:$G$200,">="&Data_CRM!$J$4,Data_MeetingScheduled!$G$2:$G$200,"<="&Data_CRM!$J$5) | F46: =IFERROR(IF($B46=0,"n/a",$E46/$B46),"n/a")
A47: Not mapped to a campaign (no LeadChain match) | B47: =COUNTIFS(Data_CRM!$B$2:$B$1694,"Not mapped to a campaign",Data_CRM!$A$2:$A$1694,">="&Data_CRM!$J$4,Data_CRM!$A$2:$A$1694,"<="&Data_CRM!$J$5) | C47: =SUMIFS(Data_CRM!$F$2:$F$1694,Data_CRM!$B$2:$B$1694,"Not mapped to a campaign",Data_CRM!$A$2:$A$1694,">="&Data_CRM!$J$4,Data_CRM!$A$2:$A$1694,"<="&Data_CRM!$J$5) | D47: =IFERROR(IF($B47=0,"n/a",$C47/$B47),"n/a") | E47: =COUNTIFS(Data_MeetingScheduled!$C$2:$C$200,"Not mapped to a campaign",Data_MeetingScheduled!$G$2:$G$200,">="&Data_CRM!$J$4,Data_MeetingScheduled!$G$2:$G$200,"<="&Data_CRM!$J$5) | F47: =IFERROR(IF($B47=0,"n/a",$E47/$B47),"n/a")
A48: TOTAL (FULL CRM EXPORT FOR THE FTD PERIOD) | B48: =COUNTIFS(Data_CRM!$A$2:$A$1694,">="&Data_CRM!$J$4,Data_CRM!$A$2:$A$1694,"<="&Data_CRM!$J$5) | C48: =SUMIFS(Data_CRM!$F$2:$F$1694,Data_CRM!$A$2:$A$1694,">="&Data_CRM!$J$4,Data_CRM!$A$2:$A$1694,"<="&Data_CRM!$J$5) | D48: =IFERROR($C48/$B48,"n/a") | E48: =COUNTIFS(Data_MeetingScheduled!$G$2:$G$200,">="&Data_CRM!$J$4,Data_MeetingScheduled!$G$2:$G$200,"<="&Data_CRM!$J$5) | F48: =IFERROR($E48/$B48,"n/a")
A50: 3. AD SET-WISE PERFORMANCE — MTD (1 Oct – 28 Oct 2026), grouped by parent campaign
A51: Parent Campaign | B51: Ad set name | C51: Ad set delivery | D51: Results | E51: Result indicator | F51: Cost per result | G51: Ad set budget | H51: Ad set budget type | I51: Amount spent (INR) | J51: Impressions | K51: Reach | L51: Ends | M51: Starts | N51: Attribution setting | O51: Bid type | P51: % of Campaign Spend | Q51: % of Campaign Results | R51: Meetings Scheduled | S51: Meeting Scheduled % | T51: Link Clicks | U51: CTR | V51: CTR % | W51: CRM Leads (LeadChain) | X51: Qualified Leads | Y51: CPQL | Z51: CPQL %
A52: Andromeda_CBO_Signature Store_FICO_Daewoo_SO | B52: Business Interest Signature Stores_FICO | C52: active | D52: 351 | E52: actions:leadgen.other | F52: =IFERROR($I52/$D52,"n/a") | G52: Using campaign budget | H52: 0 | I52: 229018.3 | J52: 1577811 | K52: 790322 | L52: Ongoing | M52: 2026-02-27 | N52: 7-day click or 1-day view | O52: ABSOLUTE_OCPM | P52: =IFERROR($I52/INDEX($J$21:$J$29,MATCH($A52,$C$21:$C$29,0)),"n/a") | Q52: =IFERROR(IF(INDEX($E$21:$E$29,MATCH($A52,$C$21:$C$29,0))="","n/a",$D52/INDEX($E$21:$E$29,MATCH($A52,$C$21:$C$29,0))),"n/a") | R52: =COUNTIFS(Data_MeetingScheduled!$C$2:$C$200,$A52,Data_MeetingScheduled!$D$2:$D$200,$B52) | S52: =IFERROR($R52/Data_MeetingScheduled!$J$2,"n/a") | T52: 7499 | U52: =IFERROR($T52/$J52,"n/a") | V52: =IFERROR($T52/$J52,"n/a") | W52: =COUNTIFS(Data_CRM!$B$2:$B$1694,$A52,Data_CRM!$C$2:$C$1694,$B52) | X52: =COUNTIFS(Data_CRM!$B$2:$B$1694,$A52,Data_CRM!$C$2:$C$1694,$B52,Data_CRM!$F$2:$F$1694,1) | Y52: =IFERROR($I52/$X52,"n/a") | Z52: =IFERROR(IF($W52=0,"n/a",$X52/$W52),"n/a")
A53: Andromeda_CBO_Signature Store_FICO_Daewoo_SO | B53: HHI Pan India With Exclusions Signature Stores_FICO | C53: active | D53: 868 | E53: actions:leadgen.other | F53: =IFERROR($I53/$D53,"n/a") | G53: Using campaign budget | H53: 0 | I53: 443840.57 | J53: 2999156 | K53: 1180535 | L53: Ongoing | M53: 2026-10-17 | N53: 7-day click or 1-day view | O53: ABSOLUTE_OCPM | P53: =IFERROR($I53/INDEX($J$21:$J$29,MATCH($A53,$C$21:$C$29,0)),"n/a") | Q53: =IFERROR(IF(INDEX($E$21:$E$29,MATCH($A53,$C$21:$C$29,0))="","n/a",$D53/INDEX($E$21:$E$29,MATCH($A53,$C$21:$C$29,0))),"n/a") | R53: =COUNTIFS(Data_MeetingScheduled!$C$2:$C$200,$A53,Data_MeetingScheduled!$D$2:$D$200,$B53) | S53: =IFERROR($R53/Data_MeetingScheduled!$J$2,"n/a") | T53: 15324 | U53: =IFERROR($T53/$J53,"n/a") | V53: =IFERROR($T53/$J53,"n/a") | W53: =COUNTIFS(Data_CRM!$B$2:$B$1694,$A53,Data_CRM!$C$2:$C$1694,$B53) | X53: =COUNTIFS(Data_CRM!$B$2:$B$1694,$A53,Data_CRM!$C$2:$C$1694,$B53,Data_CRM!$F$2:$F$1694,1) | Y53: =IFERROR($I53/$X53,"n/a") | Z53: =IFERROR(IF($W53=0,"n/a",$X53/$W53),"n/a")
A54: Subtotal — Andromeda_CBO_Signature Store_FICO_Daewoo_SO | D54: =SUM(D52:D53) | F54: =IFERROR($I54/$D54,"n/a") | I54: =SUM(I52:I53) | J54: =SUM(J52:J53) | K54: =SUM(K52:K53) | P54: =SUM(P52:P53) | R54: =SUM(R52:R53) | S54: =IFERROR($R54/Data_MeetingScheduled!$J$2,"n/a") | T54: =SUM(T52:T53) | U54: =IFERROR($T54/$J54,"n/a") | V54: =IFERROR($T54/$J54,"n/a") | W54: =SUM(W52:W53) | X54: =SUM(X52:X53) | Y54: =IFERROR($I54/$X54,"n/a") | Z54: =IFERROR(IF($W54=0,"n/a",$X54/$W54),"n/a")
A55: META_CustomData_MOFU_STOCKIST_Leadgen | B55: Client Custom Data_Stockist | C55: active | D55: 15 | E55: actions:leadgen.other | F55: =IFERROR($I55/$D55,"n/a") | G55: Using campaign budget | H55: 0 | I55: 7962.14 | J55: 6301 | K55: 2549 | L55: Ongoing | M55: 2026-03-11 | N55: 7-day click or 1-day view | O55: ABSOLUTE_OCPM | P55: =IFERROR($I55/INDEX($J$21:$J$29,MATCH($A55,$C$21:$C$29,0)),"n/a") | Q55: =IFERROR(IF(INDEX($E$21:$E$29,MATCH($A55,$C$21:$C$29,0))="","n/a",$D55/INDEX($E$21:$E$29,MATCH($A55,$C$21:$C$29,0))),"n/a") | R55: =COUNTIFS(Data_MeetingScheduled!$C$2:$C$200,$A55,Data_MeetingScheduled!$D$2:$D$200,$B55) | S55: =IFERROR($R55/Data_MeetingScheduled!$J$2,"n/a") | T55: 60 | U55: =IFERROR($T55/$J55,"n/a") | V55: =IFERROR($T55/$J55,"n/a") | W55: =COUNTIFS(Data_CRM!$B$2:$B$1694,$A55,Data_CRM!$C$2:$C$1694,$B55) | X55: =COUNTIFS(Data_CRM!$B$2:$B$1694,$A55,Data_CRM!$C$2:$C$1694,$B55,Data_CRM!$F$2:$F$1694,1) | Y55: =IFERROR($I55/$X55,"n/a") | Z55: =IFERROR(IF($W55=0,"n/a",$X55/$W55),"n/a")
A56: META_CustomData_MOFU_STOCKIST_Leadgen | B56: LAL_1%_Client Data_Stockist | C56: active | D56: 330 | E56: actions:leadgen.other | F56: =IFERROR($I56/$D56,"n/a") | G56: Using campaign budget | H56: 0 | I56: 330784.95 | J56: 856408 | K56: 366715 | L56: Ongoing | M56: 2026-03-12 | N56: 7-day click or 1-day view | O56: ABSOLUTE_OCPM | P56: =IFERROR($I56/INDEX($J$21:$J$29,MATCH($A56,$C$21:$C$29,0)),"n/a") | Q56: =IFERROR(IF(INDEX($E$21:$E$29,MATCH($A56,$C$21:$C$29,0))="","n/a",$D56/INDEX($E$21:$E$29,MATCH($A56,$C$21:$C$29,0))),"n/a") | R56: =COUNTIFS(Data_MeetingScheduled!$C$2:$C$200,$A56,Data_MeetingScheduled!$D$2:$D$200,$B56) | S56: =IFERROR($R56/Data_MeetingScheduled!$J$2,"n/a") | T56: 5006 | U56: =IFERROR($T56/$J56,"n/a") | V56: =IFERROR($T56/$J56,"n/a") | W56: =COUNTIFS(Data_CRM!$B$2:$B$1694,$A56,Data_CRM!$C$2:$C$1694,$B56) | X56: =COUNTIFS(Data_CRM!$B$2:$B$1694,$A56,Data_CRM!$C$2:$C$1694,$B56,Data_CRM!$F$2:$F$1694,1) | Y56: =IFERROR($I56/$X56,"n/a") | Z56: =IFERROR(IF($W56=0,"n/a",$X56/$W56),"n/a")
A57: Subtotal — META_CustomData_MOFU_STOCKIST_Leadgen | D57: =SUM(D55:D56) | F57: =IFERROR($I57/$D57,"n/a") | I57: =SUM(I55:I56) | J57: =SUM(J55:J56) | K57: =SUM(K55:K56) | P57: =SUM(P55:P56) | R57: =SUM(R55:R56) | S57: =IFERROR($R57/Data_MeetingScheduled!$J$2,"n/a") | T57: =SUM(T55:T56) | U57: =IFERROR($T57/$J57,"n/a") | V57: =IFERROR($T57/$J57,"n/a") | W57: =SUM(W55:W56) | X57: =SUM(X55:X56) | Y57: =IFERROR($I57/$X57,"n/a") | Z57: =IFERROR(IF($W57=0,"n/a",$X57/$W57),"n/a")
A58: Andromeda_ABO_Stockist_Daewoo_SO | B58: Business Interest | C58: inactive | D58: 0 | F58: =IFERROR($I58/$D58,"n/a") | G58: 10014.36 | H58: Daily | I58: 0 | J58: 0 | K58: 0 | L58: Ongoing | M58: 2026-03-26 | N58: - | O58: ABSOLUTE_OCPM | P58: =IFERROR($I58/INDEX($J$21:$J$29,MATCH($A58,$C$21:$C$29,0)),"n/a") | Q58: =IFERROR(IF(INDEX($E$21:$E$29,MATCH($A58,$C$21:$C$29,0))="","n/a",$D58/INDEX($E$21:$E$29,MATCH($A58,$C$21:$C$29,0))),"n/a") | R58: =COUNTIFS(Data_MeetingScheduled!$C$2:$C$200,$A58,Data_MeetingScheduled!$D$2:$D$200,$B58) | S58: =IFERROR($R58/Data_MeetingScheduled!$J$2,"n/a") | T58: 0 | U58: =IFERROR($T58/$J58,"n/a") | V58: =IFERROR($T58/$J58,"n/a") | W58: =COUNTIFS(Data_CRM!$B$2:$B$1694,$A58,Data_CRM!$C$2:$C$1694,$B58) | X58: =COUNTIFS(Data_CRM!$B$2:$B$1694,$A58,Data_CRM!$C$2:$C$1694,$B58,Data_CRM!$F$2:$F$1694,1) | Y58: =IFERROR($I58/$X58,"n/a") | Z58: =IFERROR(IF($W58=0,"n/a",$X58/$W58),"n/a")
A59: Andromeda_ABO_Stockist_Daewoo_SO | B59: New Stockist Audience Owners | C59: not_delivering | D59: 0 | F59: =IFERROR($I59/$D59,"n/a") | G59: 2157.6 | H59: Daily | I59: 0 | J59: 0 | K59: 0 | L59: Ongoing | M59: 2026-06-04 | N59: - | O59: ABSOLUTE_OCPM | P59: =IFERROR($I59/INDEX($J$21:$J$29,MATCH($A59,$C$21:$C$29,0)),"n/a") | Q59: =IFERROR(IF(INDEX($E$21:$E$29,MATCH($A59,$C$21:$C$29,0))="","n/a",$D59/INDEX($E$21:$E$29,MATCH($A59,$C$21:$C$29,0))),"n/a") | R59: =COUNTIFS(Data_MeetingScheduled!$C$2:$C$200,$A59,Data_MeetingScheduled!$D$2:$D$200,$B59) | S59: =IFERROR($R59/Data_MeetingScheduled!$J$2,"n/a") | T59: 0 | U59: =IFERROR($T59/$J59,"n/a") | V59: =IFERROR($T59/$J59,"n/a") | W59: =COUNTIFS(Data_CRM!$B$2:$B$1694,$A59,Data_CRM!$C$2:$C$1694,$B59) | X59: =COUNTIFS(Data_CRM!$B$2:$B$1694,$A59,Data_CRM!$C$2:$C$1694,$B59,Data_CRM!$F$2:$F$1694,1) | Y59: =IFERROR($I59/$X59,"n/a") | Z59: =IFERROR(IF($W59=0,"n/a",$X59/$W59),"n/a")
A60: Andromeda_ABO_Stockist_Daewoo_SO | B60: Stockists_High_Income_and_Premium_Interest_SO | C60: inactive | D60: 0 | F60: =IFERROR($I60/$D60,"n/a") | G60: 10014.36 | H60: Daily | I60: 0 | J60: 0 | K60: 0 | L60: Ongoing | M60: 2026-03-26 | N60: - | O60: ABSOLUTE_OCPM | P60: =IFERROR($I60/INDEX($J$21:$J$29,MATCH($A60,$C$21:$C$29,0)),"n/a") | Q60: =IFERROR(IF(INDEX($E$21:$E$29,MATCH($A60,$C$21:$C$29,0))="","n/a",$D60/INDEX($E$21:$E$29,MATCH($A60,$C$21:$C$29,0))),"n/a") | R60: =COUNTIFS(Data_MeetingScheduled!$C$2:$C$200,$A60,Data_MeetingScheduled!$D$2:$D$200,$B60) | S60: =IFERROR($R60/Data_MeetingScheduled!$J$2,"n/a") | T60: 0 | U60: =IFERROR($T60/$J60,"n/a") | V60: =IFERROR($T60/$J60,"n/a") | W60: =COUNTIFS(Data_CRM!$B$2:$B$1694,$A60,Data_CRM!$C$2:$C$1694,$B60) | X60: =COUNTIFS(Data_CRM!$B$2:$B$1694,$A60,Data_CRM!$C$2:$C$1694,$B60,Data_CRM!$F$2:$F$1694,1) | Y60: =IFERROR($I60/$X60,"n/a") | Z60: =IFERROR(IF($W60=0,"n/a",$X60/$W60),"n/a")
A61: Subtotal — Andromeda_ABO_Stockist_Daewoo_SO | D61: =SUM(D58:D60) | F61: =IFERROR($I61/$D61,"n/a") | I61: =SUM(I58:I60) | J61: =SUM(J58:J60) | K61: =SUM(K58:K60) | P61: =SUM(P58:P60) | R61: =SUM(R58:R60) | S61: =IFERROR($R61/Data_MeetingScheduled!$J$2,"n/a") | T61: =SUM(T58:T60) | U61: =IFERROR($T61/$J61,"n/a") | V61: =IFERROR($T61/$J61,"n/a") | W61: =SUM(W58:W60) | X61: =SUM(X58:X60) | Y61: =IFERROR($I61/$X61,"n/a") | Z61: =IFERROR(IF($W61=0,"n/a",$X61/$W61),"n/a")
A62: Andromeda_CBO__DDP_Daewoo_SO | B62: Business Interest DDP Partnerships | C62: inactive | D62: 0 | F62: =IFERROR($I62/$D62,"n/a") | G62: Using campaign budget | H62: 0 | I62: 0 | J62: 0 | K62: 0 | L62: Ongoing | M62: 2026-05-08 | N62: - | O62: ABSOLUTE_OCPM | P62: =IFERROR($I62/INDEX($J$21:$J$29,MATCH($A62,$C$21:$C$29,0)),"n/a") | Q62: =IFERROR(IF(INDEX($E$21:$E$29,MATCH($A62,$C$21:$C$29,0))="","n/a",$D62/INDEX($E$21:$E$29,MATCH($A62,$C$21:$C$29,0))),"n/a") | R62: =COUNTIFS(Data_MeetingScheduled!$C$2:$C$200,$A62,Data_MeetingScheduled!$D$2:$D$200,$B62) | S62: =IFERROR($R62/Data_MeetingScheduled!$J$2,"n/a") | T62: 0 | U62: =IFERROR($T62/$J62,"n/a") | V62: =IFERROR($T62/$J62,"n/a") | W62: =COUNTIFS(Data_CRM!$B$2:$B$1694,$A62,Data_CRM!$C$2:$C$1694,$B62) | X62: =COUNTIFS(Data_CRM!$B$2:$B$1694,$A62,Data_CRM!$C$2:$C$1694,$B62,Data_CRM!$F$2:$F$1694,1) | Y62: =IFERROR($I62/$X62,"n/a") | Z62: =IFERROR(IF($W62=0,"n/a",$X62/$W62),"n/a")
A63: Subtotal — Andromeda_CBO__DDP_Daewoo_SO | D63: =SUM(D62:D62) | F63: =IFERROR($I63/$D63,"n/a") | I63: =SUM(I62:I62) | J63: =SUM(J62:J62) | K63: =SUM(K62:K62) | P63: =SUM(P62:P62) | R63: =SUM(R62:R62) | S63: =IFERROR($R63/Data_MeetingScheduled!$J$2,"n/a") | T63: =SUM(T62:T62) | U63: =IFERROR($T63/$J63,"n/a") | V63: =IFERROR($T63/$J63,"n/a") | W63: =SUM(W62:W62) | X63: =SUM(X62:X62) | Y63: =IFERROR($I63/$X63,"n/a") | Z63: =IFERROR(IF($W63=0,"n/a",$X63/$W63),"n/a")
A64: META_CustomData_MOFU_Leadgen – DDP | B64: Business Interest DDP Partnerships | C64: not_delivering | D64: 0 | F64: =IFERROR($I64/$D64,"n/a") | G64: Using campaign budget | H64: 0 | I64: 0 | J64: 0 | K64: 0 | L64: Ongoing | M64: 2026-05-21 | N64: - | O64: ABSOLUTE_OCPM | P64: =IFERROR($I64/INDEX($J$21:$J$29,MATCH($A64,$C$21:$C$29,0)),"n/a") | Q64: =IFERROR(IF(INDEX($E$21:$E$29,MATCH($A64,$C$21:$C$29,0))="","n/a",$D64/INDEX($E$21:$E$29,MATCH($A64,$C$21:$C$29,0))),"n/a") | R64: =COUNTIFS(Data_MeetingScheduled!$C$2:$C$200,$A64,Data_MeetingScheduled!$D$2:$D$200,$B64) | S64: =IFERROR($R64/Data_MeetingScheduled!$J$2,"n/a") | T64: 0 | U64: =IFERROR($T64/$J64,"n/a") | V64: =IFERROR($T64/$J64,"n/a") | W64: =COUNTIFS(Data_CRM!$B$2:$B$1694,$A64,Data_CRM!$C$2:$C$1694,$B64) | X64: =COUNTIFS(Data_CRM!$B$2:$B$1694,$A64,Data_CRM!$C$2:$C$1694,$B64,Data_CRM!$F$2:$F$1694,1) | Y64: =IFERROR($I64/$X64,"n/a") | Z64: =IFERROR(IF($W64=0,"n/a",$X64/$W64),"n/a")
A65: META_CustomData_MOFU_Leadgen – DDP | B65: Client Custom Data_DDP | C65: not_delivering | D65: 0 | F65: =IFERROR($I65/$D65,"n/a") | G65: Using campaign budget | H65: 0 | I65: 0 | J65: 0 | K65: 0 | L65: Ongoing | M65: 2026-05-21 | N65: - | O65: ABSOLUTE_OCPM | P65: =IFERROR($I65/INDEX($J$21:$J$29,MATCH($A65,$C$21:$C$29,0)),"n/a") | Q65: =IFERROR(IF(INDEX($E$21:$E$29,MATCH($A65,$C$21:$C$29,0))="","n/a",$D65/INDEX($E$21:$E$29,MATCH($A65,$C$21:$C$29,0))),"n/a") | R65: =COUNTIFS(Data_MeetingScheduled!$C$2:$C$200,$A65,Data_MeetingScheduled!$D$2:$D$200,$B65) | S65: =IFERROR($R65/Data_MeetingScheduled!$J$2,"n/a") | T65: 0 | U65: =IFERROR($T65/$J65,"n/a") | V65: =IFERROR($T65/$J65,"n/a") | W65: =COUNTIFS(Data_CRM!$B$2:$B$1694,$A65,Data_CRM!$C$2:$C$1694,$B65) | X65: =COUNTIFS(Data_CRM!$B$2:$B$1694,$A65,Data_CRM!$C$2:$C$1694,$B65,Data_CRM!$F$2:$F$1694,1) | Y65: =IFERROR($I65/$X65,"n/a") | Z65: =IFERROR(IF($W65=0,"n/a",$X65/$W65),"n/a")
A66: META_CustomData_MOFU_Leadgen – DDP | B66: LAL_1%_Client Data_DDP | C66: not_delivering | D66: 0 | F66: =IFERROR($I66/$D66,"n/a") | G66: Using campaign budget | H66: 0 | I66: 0 | J66: 0 | K66: 0 | L66: Ongoing | M66: 2026-05-21 | N66: - | O66: ABSOLUTE_OCPM | P66: =IFERROR($I66/INDEX($J$21:$J$29,MATCH($A66,$C$21:$C$29,0)),"n/a") | Q66: =IFERROR(IF(INDEX($E$21:$E$29,MATCH($A66,$C$21:$C$29,0))="","n/a",$D66/INDEX($E$21:$E$29,MATCH($A66,$C$21:$C$29,0))),"n/a") | R66: =COUNTIFS(Data_MeetingScheduled!$C$2:$C$200,$A66,Data_MeetingScheduled!$D$2:$D$200,$B66) | S66: =IFERROR($R66/Data_MeetingScheduled!$J$2,"n/a") | T66: 0 | U66: =IFERROR($T66/$J66,"n/a") | V66: =IFERROR($T66/$J66,"n/a") | W66: =COUNTIFS(Data_CRM!$B$2:$B$1694,$A66,Data_CRM!$C$2:$C$1694,$B66) | X66: =COUNTIFS(Data_CRM!$B$2:$B$1694,$A66,Data_CRM!$C$2:$C$1694,$B66,Data_CRM!$F$2:$F$1694,1) | Y66: =IFERROR($I66/$X66,"n/a") | Z66: =IFERROR(IF($W66=0,"n/a",$X66/$W66),"n/a")
A67: Subtotal — META_CustomData_MOFU_Leadgen – DDP | D67: =SUM(D64:D66) | F67: =IFERROR($I67/$D67,"n/a") | I67: =SUM(I64:I66) | J67: =SUM(J64:J66) | K67: =SUM(K64:K66) | P67: =SUM(P64:P66) | R67: =SUM(R64:R66) | S67: =IFERROR($R67/Data_MeetingScheduled!$J$2,"n/a") | T67: =SUM(T64:T66) | U67: =IFERROR($T67/$J67,"n/a") | V67: =IFERROR($T67/$J67,"n/a") | W67: =SUM(W64:W66) | X67: =SUM(X64:X66) | Y67: =IFERROR($I67/$X67,"n/a") | Z67: =IFERROR(IF($W67=0,"n/a",$X67/$W67),"n/a")
A68: META_CustomData_MOFU_Leadgen – Signature FICO | B68: Client Custom Data_Signature Store FICO | C68: inactive | D68: 0 | F68: =IFERROR($I68/$D68,"n/a") | G68: Using campaign budget | H68: 0 | I68: 0 | J68: 0 | K68: 0 | L68: Ongoing | M68: 2026-05-21 | N68: - | O68: ABSOLUTE_OCPM | P68: =IFERROR($I68/INDEX($J$21:$J$29,MATCH($A68,$C$21:$C$29,0)),"n/a") | Q68: =IFERROR(IF(INDEX($E$21:$E$29,MATCH($A68,$C$21:$C$29,0))="","n/a",$D68/INDEX($E$21:$E$29,MATCH($A68,$C$21:$C$29,0))),"n/a") | R68: =COUNTIFS(Data_MeetingScheduled!$C$2:$C$200,$A68,Data_MeetingScheduled!$D$2:$D$200,$B68) | S68: =IFERROR($R68/Data_MeetingScheduled!$J$2,"n/a") | T68: 0 | U68: =IFERROR($T68/$J68,"n/a") | V68: =IFERROR($T68/$J68,"n/a") | W68: =COUNTIFS(Data_CRM!$B$2:$B$1694,$A68,Data_CRM!$C$2:$C$1694,$B68) | X68: =COUNTIFS(Data_CRM!$B$2:$B$1694,$A68,Data_CRM!$C$2:$C$1694,$B68,Data_CRM!$F$2:$F$1694,1) | Y68: =IFERROR($I68/$X68,"n/a") | Z68: =IFERROR(IF($W68=0,"n/a",$X68/$W68),"n/a")
A69: META_CustomData_MOFU_Leadgen – Signature FICO | B69: LAL_1%_Client Data_Signature Store FICO | C69: active | D69: 141 | E69: actions:leadgen.other | F69: =IFERROR($I69/$D69,"n/a") | G69: Using campaign budget | H69: 0 | I69: 194123.34 | J69: 390794 | K69: 221625 | L69: Ongoing | M69: 2026-05-21 | N69: 7-day click or 1-day view | O69: ABSOLUTE_OCPM | P69: =IFERROR($I69/INDEX($J$21:$J$29,MATCH($A69,$C$21:$C$29,0)),"n/a") | Q69: =IFERROR(IF(INDEX($E$21:$E$29,MATCH($A69,$C$21:$C$29,0))="","n/a",$D69/INDEX($E$21:$E$29,MATCH($A69,$C$21:$C$29,0))),"n/a") | R69: =COUNTIFS(Data_MeetingScheduled!$C$2:$C$200,$A69,Data_MeetingScheduled!$D$2:$D$200,$B69) | S69: =IFERROR($R69/Data_MeetingScheduled!$J$2,"n/a") | T69: 2781 | U69: =IFERROR($T69/$J69,"n/a") | V69: =IFERROR($T69/$J69,"n/a") | W69: =COUNTIFS(Data_CRM!$B$2:$B$1694,$A69,Data_CRM!$C$2:$C$1694,$B69) | X69: =COUNTIFS(Data_CRM!$B$2:$B$1694,$A69,Data_CRM!$C$2:$C$1694,$B69,Data_CRM!$F$2:$F$1694,1) | Y69: =IFERROR($I69/$X69,"n/a") | Z69: =IFERROR(IF($W69=0,"n/a",$X69/$W69),"n/a")
A70: Subtotal — META_CustomData_MOFU_Leadgen – Signature FICO | D70: =SUM(D68:D69) | F70: =IFERROR($I70/$D70,"n/a") | I70: =SUM(I68:I69) | J70: =SUM(J68:J69) | K70: =SUM(K68:K69) | P70: =SUM(P68:P69) | R70: =SUM(R68:R69) | S70: =IFERROR($R70/Data_MeetingScheduled!$J$2,"n/a") | T70: =SUM(T68:T69) | U70: =IFERROR($T70/$J70,"n/a") | V70: =IFERROR($T70/$J70,"n/a") | W70: =SUM(W68:W69) | X70: =SUM(X68:X69) | Y70: =IFERROR($I70/$X70,"n/a") | Z70: =IFERROR(IF($W70=0,"n/a",$X70/$W70),"n/a")
A71: META_RMKT_Engage_ABO_SO | B71: CRM_Engagements_Positive | C71: active | D71: 5 | E71: total_profile_visits | F71: =IFERROR($I71/$D71,"n/a") | G71: 100 | H71: Daily | I71: 1618.94 | J71: 1767 | K71: 104 | L71: Ongoing | M71: 2026-06-22 | N71: 1-day click | O71: ABSOLUTE_OCPM | P71: =IFERROR($I71/INDEX($J$21:$J$29,MATCH($A71,$C$21:$C$29,0)),"n/a") | Q71: =IFERROR(IF(INDEX($E$21:$E$29,MATCH($A71,$C$21:$C$29,0))="","n/a",$D71/INDEX($E$21:$E$29,MATCH($A71,$C$21:$C$29,0))),"n/a") | R71: =COUNTIFS(Data_MeetingScheduled!$C$2:$C$200,$A71,Data_MeetingScheduled!$D$2:$D$200,$B71) | S71: =IFERROR($R71/Data_MeetingScheduled!$J$2,"n/a") | T71: 5 | U71: =IFERROR($T71/$J71,"n/a") | V71: =IFERROR($T71/$J71,"n/a") | W71: =COUNTIFS(Data_CRM!$B$2:$B$1694,$A71,Data_CRM!$C$2:$C$1694,$B71) | X71: =COUNTIFS(Data_CRM!$B$2:$B$1694,$A71,Data_CRM!$C$2:$C$1694,$B71,Data_CRM!$F$2:$F$1694,1) | Y71: =IFERROR($I71/$X71,"n/a") | Z71: =IFERROR(IF($W71=0,"n/a",$X71/$W71),"n/a")
A72: META_RMKT_Engage_ABO_SO | B72: FB Page Engagements | C72: active | D72: 59 | E72: page_visit_view | F72: =IFERROR($I72/$D72,"n/a") | G72: 100 | H72: Daily | I72: 2793.17 | J72: 10146 | K72: 1442 | L72: Ongoing | M72: 2026-05-31 | N72: 1-day click | O72: ABSOLUTE_OCPM | P72: =IFERROR($I72/INDEX($J$21:$J$29,MATCH($A72,$C$21:$C$29,0)),"n/a") | Q72: =IFERROR(IF(INDEX($E$21:$E$29,MATCH($A72,$C$21:$C$29,0))="","n/a",$D72/INDEX($E$21:$E$29,MATCH($A72,$C$21:$C$29,0))),"n/a") | R72: =COUNTIFS(Data_MeetingScheduled!$C$2:$C$200,$A72,Data_MeetingScheduled!$D$2:$D$200,$B72) | S72: =IFERROR($R72/Data_MeetingScheduled!$J$2,"n/a") | T72: 31 | U72: =IFERROR($T72/$J72,"n/a") | V72: =IFERROR($T72/$J72,"n/a") | W72: =COUNTIFS(Data_CRM!$B$2:$B$1694,$A72,Data_CRM!$C$2:$C$1694,$B72) | X72: =COUNTIFS(Data_CRM!$B$2:$B$1694,$A72,Data_CRM!$C$2:$C$1694,$B72,Data_CRM!$F$2:$F$1694,1) | Y72: =IFERROR($I72/$X72,"n/a") | Z72: =IFERROR(IF($W72=0,"n/a",$X72/$W72),"n/a")
A73: META_RMKT_Engage_ABO_SO | B73: IG Page Engagements | C73: active | D73: 49 | E73: profile_visit_view | F73: =IFERROR($I73/$D73,"n/a") | G73: 100 | H73: Daily | I73: 2801.24 | J73: 7539 | K73: 1185 | L73: Ongoing | M73: 2026-05-31 | N73: 1-day click | O73: ABSOLUTE_OCPM | P73: =IFERROR($I73/INDEX($J$21:$J$29,MATCH($A73,$C$21:$C$29,0)),"n/a") | Q73: =IFERROR(IF(INDEX($E$21:$E$29,MATCH($A73,$C$21:$C$29,0))="","n/a",$D73/INDEX($E$21:$E$29,MATCH($A73,$C$21:$C$29,0))),"n/a") | R73: =COUNTIFS(Data_MeetingScheduled!$C$2:$C$200,$A73,Data_MeetingScheduled!$D$2:$D$200,$B73) | S73: =IFERROR($R73/Data_MeetingScheduled!$J$2,"n/a") | T73: 48 | U73: =IFERROR($T73/$J73,"n/a") | V73: =IFERROR($T73/$J73,"n/a") | W73: =COUNTIFS(Data_CRM!$B$2:$B$1694,$A73,Data_CRM!$C$2:$C$1694,$B73) | X73: =COUNTIFS(Data_CRM!$B$2:$B$1694,$A73,Data_CRM!$C$2:$C$1694,$B73,Data_CRM!$F$2:$F$1694,1) | Y73: =IFERROR($I73/$X73,"n/a") | Z73: =IFERROR(IF($W73=0,"n/a",$X73/$W73),"n/a")
A74: Subtotal — META_RMKT_Engage_ABO_SO | D74: =SUM(D71:D73) | F74: =IFERROR($I74/$D74,"n/a") | I74: =SUM(I71:I73) | J74: =SUM(J71:J73) | K74: =SUM(K71:K73) | P74: =SUM(P71:P73) | R74: =SUM(R71:R73) | S74: =IFERROR($R74/Data_MeetingScheduled!$J$2,"n/a") | T74: =SUM(T71:T73) | U74: =IFERROR($T74/$J74,"n/a") | V74: =IFERROR($T74/$J74,"n/a") | W74: =SUM(W71:W73) | X74: =SUM(X71:X73) | Y74: =IFERROR($I74/$X74,"n/a") | Z74: =IFERROR(IF($W74=0,"n/a",$X74/$W74),"n/a")
A75: META_RMKT_Socials Pages_CBO_SO | B75: Socials Pages FB_ABO – Stockist | C75: inactive | D75: 0 | F75: =IFERROR($I75/$D75,"n/a") | G75: 200 | H75: Daily | I75: 0 | J75: 0 | K75: 0 | L75: Ongoing | M75: 2026-05-22 | N75: - | O75: ABSOLUTE_OCPM | P75: =IFERROR($I75/INDEX($J$21:$J$29,MATCH($A75,$C$21:$C$29,0)),"n/a") | Q75: =IFERROR(IF(INDEX($E$21:$E$29,MATCH($A75,$C$21:$C$29,0))="","n/a",$D75/INDEX($E$21:$E$29,MATCH($A75,$C$21:$C$29,0))),"n/a") | R75: =COUNTIFS(Data_MeetingScheduled!$C$2:$C$200,$A75,Data_MeetingScheduled!$D$2:$D$200,$B75) | S75: =IFERROR($R75/Data_MeetingScheduled!$J$2,"n/a") | T75: 0 | U75: =IFERROR($T75/$J75,"n/a") | V75: =IFERROR($T75/$J75,"n/a") | W75: =COUNTIFS(Data_CRM!$B$2:$B$1694,$A75,Data_CRM!$C$2:$C$1694,$B75) | X75: =COUNTIFS(Data_CRM!$B$2:$B$1694,$A75,Data_CRM!$C$2:$C$1694,$B75,Data_CRM!$F$2:$F$1694,1) | Y75: =IFERROR($I75/$X75,"n/a") | Z75: =IFERROR(IF($W75=0,"n/a",$X75/$W75),"n/a")
A76: META_RMKT_Socials Pages_CBO_SO | B76: Socials Pages IG_ABO – Stockist | C76: inactive | D76: 0 | F76: =IFERROR($I76/$D76,"n/a") | G76: 200 | H76: Daily | I76: 0 | J76: 0 | K76: 0 | L76: Ongoing | M76: 2026-05-22 | N76: - | O76: ABSOLUTE_OCPM | P76: =IFERROR($I76/INDEX($J$21:$J$29,MATCH($A76,$C$21:$C$29,0)),"n/a") | Q76: =IFERROR(IF(INDEX($E$21:$E$29,MATCH($A76,$C$21:$C$29,0))="","n/a",$D76/INDEX($E$21:$E$29,MATCH($A76,$C$21:$C$29,0))),"n/a") | R76: =COUNTIFS(Data_MeetingScheduled!$C$2:$C$200,$A76,Data_MeetingScheduled!$D$2:$D$200,$B76) | S76: =IFERROR($R76/Data_MeetingScheduled!$J$2,"n/a") | T76: 0 | U76: =IFERROR($T76/$J76,"n/a") | V76: =IFERROR($T76/$J76,"n/a") | W76: =COUNTIFS(Data_CRM!$B$2:$B$1694,$A76,Data_CRM!$C$2:$C$1694,$B76) | X76: =COUNTIFS(Data_CRM!$B$2:$B$1694,$A76,Data_CRM!$C$2:$C$1694,$B76,Data_CRM!$F$2:$F$1694,1) | Y76: =IFERROR($I76/$X76,"n/a") | Z76: =IFERROR(IF($W76=0,"n/a",$X76/$W76),"n/a")
A77: META_RMKT_Socials Pages_CBO_SO | B77: Socials Pages_SO | C77: active | D77: 6 | E77: actions:leadgen.other | F77: =IFERROR($I77/$D77,"n/a") | G77: Using campaign budget | H77: 0 | I77: 2821.62 | J77: 10131 | K77: 4306 | L77: Ongoing | M77: 2026-06-04 | N77: 7-day click or 1-day view | O77: ABSOLUTE_OCPM | P77: =IFERROR($I77/INDEX($J$21:$J$29,MATCH($A77,$C$21:$C$29,0)),"n/a") | Q77: =IFERROR(IF(INDEX($E$21:$E$29,MATCH($A77,$C$21:$C$29,0))="","n/a",$D77/INDEX($E$21:$E$29,MATCH($A77,$C$21:$C$29,0))),"n/a") | R77: =COUNTIFS(Data_MeetingScheduled!$C$2:$C$200,$A77,Data_MeetingScheduled!$D$2:$D$200,$B77) | S77: =IFERROR($R77/Data_MeetingScheduled!$J$2,"n/a") | T77: 116 | U77: =IFERROR($T77/$J77,"n/a") | V77: =IFERROR($T77/$J77,"n/a") | W77: =COUNTIFS(Data_CRM!$B$2:$B$1694,$A77,Data_CRM!$C$2:$C$1694,$B77) | X77: =COUNTIFS(Data_CRM!$B$2:$B$1694,$A77,Data_CRM!$C$2:$C$1694,$B77,Data_CRM!$F$2:$F$1694,1) | Y77: =IFERROR($I77/$X77,"n/a") | Z77: =IFERROR(IF($W77=0,"n/a",$X77/$W77),"n/a")
A78: Subtotal — META_RMKT_Socials Pages_CBO_SO | D78: =SUM(D75:D77) | F78: =IFERROR($I78/$D78,"n/a") | I78: =SUM(I75:I77) | J78: =SUM(J75:J77) | K78: =SUM(K75:K77) | P78: =SUM(P75:P77) | R78: =SUM(R75:R77) | S78: =IFERROR($R78/Data_MeetingScheduled!$J$2,"n/a") | T78: =SUM(T75:T77) | U78: =IFERROR($T78/$J78,"n/a") | V78: =IFERROR($T78/$J78,"n/a") | W78: =SUM(W75:W77) | X78: =SUM(X75:X77) | Y78: =IFERROR($I78/$X78,"n/a") | Z78: =IFERROR(IF($W78=0,"n/a",$X78/$W78),"n/a")
A79: CRM Custom List_CBO_SO | B79: Qualified LAL All Models | C79: not_delivering | D79: 1 | E79: conversion_leads:conversion_lead | F79: =IFERROR($I79/$D79,"n/a") | G79: Using campaign budget | H79: 0 | I79: 0 | J79: 0 | K79: 0 | L79: Ongoing | M79: 2026-06-20 | N79: 7-day click or 1-day view | O79: ABSOLUTE_OCPM | P79: =IFERROR($I79/INDEX($J$21:$J$29,MATCH($A79,$C$21:$C$29,0)),"n/a") | Q79: =IFERROR(IF(INDEX($E$21:$E$29,MATCH($A79,$C$21:$C$29,0))="","n/a",$D79/INDEX($E$21:$E$29,MATCH($A79,$C$21:$C$29,0))),"n/a") | R79: =COUNTIFS(Data_MeetingScheduled!$C$2:$C$200,$A79,Data_MeetingScheduled!$D$2:$D$200,$B79) | S79: =IFERROR($R79/Data_MeetingScheduled!$J$2,"n/a") | T79: 0 | U79: =IFERROR($T79/$J79,"n/a") | V79: =IFERROR($T79/$J79,"n/a") | W79: =COUNTIFS(Data_CRM!$B$2:$B$1694,$A79,Data_CRM!$C$2:$C$1694,$B79) | X79: =COUNTIFS(Data_CRM!$B$2:$B$1694,$A79,Data_CRM!$C$2:$C$1694,$B79,Data_CRM!$F$2:$F$1694,1) | Y79: =IFERROR($I79/$X79,"n/a") | Z79: =IFERROR(IF($W79=0,"n/a",$X79/$W79),"n/a")
A80: Subtotal — CRM Custom List_CBO_SO | D80: =SUM(D79:D79) | F80: =IFERROR($I80/$D80,"n/a") | I80: =SUM(I79:I79) | J80: =SUM(J79:J79) | K80: =SUM(K79:K79) | P80: =SUM(P79:P79) | R80: =SUM(R79:R79) | S80: =IFERROR($R80/Data_MeetingScheduled!$J$2,"n/a") | T80: =SUM(T79:T79) | U80: =IFERROR($T80/$J80,"n/a") | V80: =IFERROR($T80/$J80,"n/a") | W80: =SUM(W79:W79) | X80: =SUM(X79:X79) | Y80: =IFERROR($I80/$X80,"n/a") | Z80: =IFERROR(IF($W80=0,"n/a",$X80/$W80),"n/a")
A81: GRAND TOTAL — ALL AD SETS (this export) | D81: =SUM(D52,D53,D55,D56,D58,D59,D60,D62,D64,D65,D66,D68,D69,D71,D72,D73,D75,D76,D77,D79) | I81: =SUM(I52,I53,I55,I56,I58,I59,I60,I62,I64,I65,I66,I68,I69,I71,I72,I73,I75,I76,I77,I79) | J81: =SUM(J52,J53,J55,J56,J58,J59,J60,J62,J64,J65,J66,J68,J69,J71,J72,J73,J75,J76,J77,J79) | R81: =SUM(R52,R53,R55,R56,R58,R59,R60,R62,R64,R65,R66,R68,R69,R71,R72,R73,R75,R76,R77,R79) | S81: =IFERROR($R81/Data_MeetingScheduled!$J$2,"n/a") | T81: =SUM(T52,T53,T55,T56,T58,T59,T60,T62,T64,T65,T66,T68,T69,T71,T72,T73,T75,T76,T77,T79) | U81: =IFERROR($T81/$J81,"n/a") | V81: =IFERROR($T81/$J81,"n/a") | W81: =SUM(W52,W53,W55,W56,W58,W59,W60,W62,W64,W65,W66,W68,W69,W71,W72,W73,W75,W76,W77,W79) | X81: =SUM(X52,X53,X55,X56,X58,X59,X60,X62,X64,X65,X66,X68,X69,X71,X72,X73,X75,X76,X77,X79) | Y81: =IFERROR($I81/$X81,"n/a") | Z81: =IFERROR(IF($W81=0,"n/a",$X81/$W81),"n/a")
A84: 4. AD-WISE PERFORMANCE — MTD (1 Oct – 28 Oct 2026), grouped by ad set and parent campaign
A85: Parent Campaign | B85: Ad set name | C85: Ad name | D85: Ad delivery | E85: Results | F85: Result indicator | G85: Cost per result | H85: Amount spent (INR) | I85: Impressions | J85: Reach | K85: Attribution setting | L85: Quality ranking | M85: Engagement rate ranking | N85: Conversion rate ranking | O85: % of Ad Set Spend | P85: Meetings Scheduled | Q85: Meeting Scheduled % | R85: Link Clicks | S85: CTR | T85: CTR % | U85: CRM Leads (LeadChain) | V85: Qualified Leads | W85: CPQL | X85: CPQL %
A86: Andromeda_CBO_Signature Store_FICO_Daewoo_SO | B86: Business Interest Signature Stores_FICO | C86: Reel – V1_Signature_Store_FICO | D86: active | E86: 24 | F86: actions:leadgen.other | G86: =IFERROR($H86/$E86,"n/a") | H86: 18325.06 | I86: 64699 | J86: 43290 | K86: 7-day click or 1-day view | L86: Above average | M86: Below average – bottom 20% of ads | N86: Below average – bottom 10% of ads | O86: =IFERROR($H86/$I$52,"n/a") | P86: =COUNTIFS(Data_MeetingScheduled!$C$2:$C$200,$A86,Data_MeetingScheduled!$D$2:$D$200,$B86,Data_MeetingScheduled!$E$2:$E$200,$C86) | Q86: =IFERROR($P86/Data_MeetingScheduled!$J$2,"n/a") | R86: 532 | S86: =IFERROR($R86/$I86,"n/a") | T86: =IFERROR($R86/$I86,"n/a") | U86: =COUNTIFS(Data_CRM!$B$2:$B$1694,$A86,Data_CRM!$C$2:$C$1694,$B86,Data_CRM!$D$2:$D$1694,$C86) | V86: =COUNTIFS(Data_CRM!$B$2:$B$1694,$A86,Data_CRM!$C$2:$C$1694,$B86,Data_CRM!$D$2:$D$1694,$C86,Data_CRM!$F$2:$F$1694,1) | W86: =IFERROR($H86/$V86,"n/a") | X86: =IFERROR(IF($U86=0,"n/a",$V86/$U86),"n/a")
A87: Andromeda_CBO_Signature Store_FICO_Daewoo_SO | B87: Business Interest Signature Stores_FICO | C87: Signature_Store Launch | D87: inactive | G87: =IFERROR($H87/$E87,"n/a") | H87: 0 | I87: 0 | J87: 0 | K87: - | L87: - | M87: - | N87: - | O87: =IFERROR($H87/$I$52,"n/a") | P87: =COUNTIFS(Data_MeetingScheduled!$C$2:$C$200,$A87,Data_MeetingScheduled!$D$2:$D$200,$B87,Data_MeetingScheduled!$E$2:$E$200,$C87) | Q87: =IFERROR($P87/Data_MeetingScheduled!$J$2,"n/a") | S87: =IFERROR($R87/$I87,"n/a") | T87: =IFERROR($R87/$I87,"n/a") | U87: =COUNTIFS(Data_CRM!$B$2:$B$1694,$A87,Data_CRM!$C$2:$C$1694,$B87,Data_CRM!$D$2:$D$1694,$C87) | V87: =COUNTIFS(Data_CRM!$B$2:$B$1694,$A87,Data_CRM!$C$2:$C$1694,$B87,Data_CRM!$D$2:$D$1694,$C87,Data_CRM!$F$2:$F$1694,1) | W87: =IFERROR($H87/$V87,"n/a") | X87: =IFERROR(IF($U87=0,"n/a",$V87/$U87),"n/a")
A88: Andromeda_CBO_Signature Store_FICO_Daewoo_SO | B88: Business Interest Signature Stores_FICO | C88: Signature_Store Franchise V2 | D88: inactive | G88: =IFERROR($H88/$E88,"n/a") | H88: 0 | I88: 0 | J88: 0 | K88: - | L88: - | M88: - | N88: - | O88: =IFERROR($H88/$I$52,"n/a") | P88: =COUNTIFS(Data_MeetingScheduled!$C$2:$C$200,$A88,Data_MeetingScheduled!$D$2:$D$200,$B88,Data_MeetingScheduled!$E$2:$E$200,$C88) | Q88: =IFERROR($P88/Data_MeetingScheduled!$J$2,"n/a") | S88: =IFERROR($R88/$I88,"n/a") | T88: =IFERROR($R88/$I88,"n/a") | U88: =COUNTIFS(Data_CRM!$B$2:$B$1694,$A88,Data_CRM!$C$2:$C$1694,$B88,Data_CRM!$D$2:$D$1694,$C88) | V88: =COUNTIFS(Data_CRM!$B$2:$B$1694,$A88,Data_CRM!$C$2:$C$1694,$B88,Data_CRM!$D$2:$D$1694,$C88,Data_CRM!$F$2:$F$1694,1) | W88: =IFERROR($H88/$V88,"n/a") | X88: =IFERROR(IF($U88=0,"n/a",$V88/$U88),"n/a")
A89: Andromeda_CBO_Signature Store_FICO_Daewoo_SO | B89: Business Interest Signature Stores_FICO | C89: Signature_Store Command | D89: inactive | G89: =IFERROR($H89/$E89,"n/a") | H89: 0 | I89: 0 | J89: 0 | K89: - | L89: - | M89: - | N89: - | O89: =IFERROR($H89/$I$52,"n/a") | P89: =COUNTIFS(Data_MeetingScheduled!$C$2:$C$200,$A89,Data_MeetingScheduled!$D$2:$D$200,$B89,Data_MeetingScheduled!$E$2:$E$200,$C89) | Q89: =IFERROR($P89/Data_MeetingScheduled!$J$2,"n/a") | S89: =IFERROR($R89/$I89,"n/a") | T89: =IFERROR($R89/$I89,"n/a") | U89: =COUNTIFS(Data_CRM!$B$2:$B$1694,$A89,Data_CRM!$C$2:$C$1694,$B89,Data_CRM!$D$2:$D$1694,$C89) | V89: =COUNTIFS(Data_CRM!$B$2:$B$1694,$A89,Data_CRM!$C$2:$C$1694,$B89,Data_CRM!$D$2:$D$1694,$C89,Data_CRM!$F$2:$F$1694,1) | W89: =IFERROR($H89/$V89,"n/a") | X89: =IFERROR(IF($U89=0,"n/a",$V89/$U89),"n/a")
A90: Andromeda_CBO_Signature Store_FICO_Daewoo_SO | B90: Business Interest Signature Stores_FICO | C90: Home Appliance Franchise V1_Signature_Store | D90: inactive | G90: =IFERROR($H90/$E90,"n/a") | H90: 0 | I90: 0 | J90: 0 | K90: - | L90: - | M90: - | N90: - | O90: =IFERROR($H90/$I$52,"n/a") | P90: =COUNTIFS(Data_MeetingScheduled!$C$2:$C$200,$A90,Data_MeetingScheduled!$D$2:$D$200,$B90,Data_MeetingScheduled!$E$2:$E$200,$C90) | Q90: =IFERROR($P90/Data_MeetingScheduled!$J$2,"n/a") | S90: =IFERROR($R90/$I90,"n/a") | T90: =IFERROR($R90/$I90,"n/a") | U90: =COUNTIFS(Data_CRM!$B$2:$B$1694,$A90,Data_CRM!$C$2:$C$1694,$B90,Data_CRM!$D$2:$D$1694,$C90) | V90: =COUNTIFS(Data_CRM!$B$2:$B$1694,$A90,Data_CRM!$C$2:$C$1694,$B90,Data_CRM!$D$2:$D$1694,$C90,Data_CRM!$F$2:$F$1694,1) | W90: =IFERROR($H90/$V90,"n/a") | X90: =IFERROR(IF($U90=0,"n/a",$V90/$U90),"n/a")
A91: Andromeda_CBO_Signature Store_FICO_Daewoo_SO | B91: Business Interest Signature Stores_FICO | C91: Signature_Store_24 percent v2_ | D91: inactive | G91: =IFERROR($H91/$E91,"n/a") | H91: 0 | I91: 0 | J91: 0 | K91: - | L91: - | M91: - | N91: - | O91: =IFERROR($H91/$I$52,"n/a") | P91: =COUNTIFS(Data_MeetingScheduled!$C$2:$C$200,$A91,Data_MeetingScheduled!$D$2:$D$200,$B91,Data_MeetingScheduled!$E$2:$E$200,$C91) | Q91: =IFERROR($P91/Data_MeetingScheduled!$J$2,"n/a") | S91: =IFERROR($R91/$I91,"n/a") | T91: =IFERROR($R91/$I91,"n/a") | U91: =COUNTIFS(Data_CRM!$B$2:$B$1694,$A91,Data_CRM!$C$2:$C$1694,$B91,Data_CRM!$D$2:$D$1694,$C91) | V91: =COUNTIFS(Data_CRM!$B$2:$B$1694,$A91,Data_CRM!$C$2:$C$1694,$B91,Data_CRM!$D$2:$D$1694,$C91,Data_CRM!$F$2:$F$1694,1) | W91: =IFERROR($H91/$V91,"n/a") | X91: =IFERROR(IF($U91=0,"n/a",$V91/$U91),"n/a")
A92: Andromeda_CBO_Signature Store_FICO_Daewoo_SO | B92: Business Interest Signature Stores_FICO | C92: Signature_Store 24 percent | D92: inactive | G92: =IFERROR($H92/$E92,"n/a") | H92: 0 | I92: 0 | J92: 0 | K92: - | L92: - | M92: - | N92: - | O92: =IFERROR($H92/$I$52,"n/a") | P92: =COUNTIFS(Data_MeetingScheduled!$C$2:$C$200,$A92,Data_MeetingScheduled!$D$2:$D$200,$B92,Data_MeetingScheduled!$E$2:$E$200,$C92) | Q92: =IFERROR($P92/Data_MeetingScheduled!$J$2,"n/a") | S92: =IFERROR($R92/$I92,"n/a") | T92: =IFERROR($R92/$I92,"n/a") | U92: =COUNTIFS(Data_CRM!$B$2:$B$1694,$A92,Data_CRM!$C$2:$C$1694,$B92,Data_CRM!$D$2:$D$1694,$C92) | V92: =COUNTIFS(Data_CRM!$B$2:$B$1694,$A92,Data_CRM!$C$2:$C$1694,$B92,Data_CRM!$D$2:$D$1694,$C92,Data_CRM!$F$2:$F$1694,1) | W92: =IFERROR($H92/$V92,"n/a") | X92: =IFERROR(IF($U92=0,"n/a",$V92/$U92),"n/a")
A93: Andromeda_CBO_Signature Store_FICO_Daewoo_SO | B93: Business Interest Signature Stores_FICO | C93: 24 percent new building_Signature_Store | D93: inactive | G93: =IFERROR($H93/$E93,"n/a") | H93: 0 | I93: 0 | J93: 0 | K93: - | L93: - | M93: - | N93: - | O93: =IFERROR($H93/$I$52,"n/a") | P93: =COUNTIFS(Data_MeetingScheduled!$C$2:$C$200,$A93,Data_MeetingScheduled!$D$2:$D$200,$B93,Data_MeetingScheduled!$E$2:$E$200,$C93) | Q93: =IFERROR($P93/Data_MeetingScheduled!$J$2,"n/a") | S93: =IFERROR($R93/$I93,"n/a") | T93: =IFERROR($R93/$I93,"n/a") | U93: =COUNTIFS(Data_CRM!$B$2:$B$1694,$A93,Data_CRM!$C$2:$C$1694,$B93,Data_CRM!$D$2:$D$1694,$C93) | V93: =COUNTIFS(Data_CRM!$B$2:$B$1694,$A93,Data_CRM!$C$2:$C$1694,$B93,Data_CRM!$D$2:$D$1694,$C93,Data_CRM!$F$2:$F$1694,1) | W93: =IFERROR($H93/$V93,"n/a") | X93: =IFERROR(IF($U93=0,"n/a",$V93/$U93),"n/a")
A94: Andromeda_CBO_Signature Store_FICO_Daewoo_SO | B94: Business Interest Signature Stores_FICO | C94: Upto 24 percent model G_Signature_Store_SO | D94: inactive | G94: =IFERROR($H94/$E94,"n/a") | H94: 0 | I94: 0 | J94: 0 | K94: - | L94: - | M94: - | N94: - | O94: =IFERROR($H94/$I$52,"n/a") | P94: =COUNTIFS(Data_MeetingScheduled!$C$2:$C$200,$A94,Data_MeetingScheduled!$D$2:$D$200,$B94,Data_MeetingScheduled!$E$2:$E$200,$C94) | Q94: =IFERROR($P94/Data_MeetingScheduled!$J$2,"n/a") | S94: =IFERROR($R94/$I94,"n/a") | T94: =IFERROR($R94/$I94,"n/a") | U94: =COUNTIFS(Data_CRM!$B$2:$B$1694,$A94,Data_CRM!$C$2:$C$1694,$B94,Data_CRM!$D$2:$D$1694,$C94) | V94: =COUNTIFS(Data_CRM!$B$2:$B$1694,$A94,Data_CRM!$C$2:$C$1694,$B94,Data_CRM!$D$2:$D$1694,$C94,Data_CRM!$F$2:$F$1694,1) | W94: =IFERROR($H94/$V94,"n/a") | X94: =IFERROR(IF($U94=0,"n/a",$V94/$U94),"n/a")
A95: Andromeda_CBO_Signature Store_FICO_Daewoo_SO | B95: Business Interest Signature Stores_FICO | C95: Premium_Signature_Store_Large | D95: inactive | G95: =IFERROR($H95/$E95,"n/a") | H95: 0 | I95: 0 | J95: 0 | K95: - | L95: - | M95: - | N95: - | O95: =IFERROR($H95/$I$52,"n/a") | P95: =COUNTIFS(Data_MeetingScheduled!$C$2:$C$200,$A95,Data_MeetingScheduled!$D$2:$D$200,$B95,Data_MeetingScheduled!$E$2:$E$200,$C95) | Q95: =IFERROR($P95/Data_MeetingScheduled!$J$2,"n/a") | S95: =IFERROR($R95/$I95,"n/a") | T95: =IFERROR($R95/$I95,"n/a") | U95: =COUNTIFS(Data_CRM!$B$2:$B$1694,$A95,Data_CRM!$C$2:$C$1694,$B95,Data_CRM!$D$2:$D$1694,$C95) | V95: =COUNTIFS(Data_CRM!$B$2:$B$1694,$A95,Data_CRM!$C$2:$C$1694,$B95,Data_CRM!$D$2:$D$1694,$C95,Data_CRM!$F$2:$F$1694,1) | W95: =IFERROR($H95/$V95,"n/a") | X95: =IFERROR(IF($U95=0,"n/a",$V95/$U95),"n/a")
A96: Andromeda_CBO_Signature Store_FICO_Daewoo_SO | B96: Business Interest Signature Stores_FICO | C96: Signature_Store_24_Large_SO | D96: inactive | G96: =IFERROR($H96/$E96,"n/a") | H96: 0 | I96: 0 | J96: 0 | K96: - | L96: - | M96: - | N96: - | O96: =IFERROR($H96/$I$52,"n/a") | P96: =COUNTIFS(Data_MeetingScheduled!$C$2:$C$200,$A96,Data_MeetingScheduled!$D$2:$D$200,$B96,Data_MeetingScheduled!$E$2:$E$200,$C96) | Q96: =IFERROR($P96/Data_MeetingScheduled!$J$2,"n/a") | S96: =IFERROR($R96/$I96,"n/a") | T96: =IFERROR($R96/$I96,"n/a") | U96: =COUNTIFS(Data_CRM!$B$2:$B$1694,$A96,Data_CRM!$C$2:$C$1694,$B96,Data_CRM!$D$2:$D$1694,$C96) | V96: =COUNTIFS(Data_CRM!$B$2:$B$1694,$A96,Data_CRM!$C$2:$C$1694,$B96,Data_CRM!$D$2:$D$1694,$C96,Data_CRM!$F$2:$F$1694,1) | W96: =IFERROR($H96/$V96,"n/a") | X96: =IFERROR(IF($U96=0,"n/a",$V96/$U96),"n/a")
A97: Andromeda_CBO_Signature Store_FICO_Daewoo_SO | B97: Business Interest Signature Stores_FICO | C97: Signature_Store_24_Blu_Large_SO_ | D97: inactive | G97: =IFERROR($H97/$E97,"n/a") | H97: 0 | I97: 0 | J97: 0 | K97: - | L97: - | M97: - | N97: - | O97: =IFERROR($H97/$I$52,"n/a") | P97: =COUNTIFS(Data_MeetingScheduled!$C$2:$C$200,$A97,Data_MeetingScheduled!$D$2:$D$200,$B97,Data_MeetingScheduled!$E$2:$E$200,$C97) | Q97: =IFERROR($P97/Data_MeetingScheduled!$J$2,"n/a") | S97: =IFERROR($R97/$I97,"n/a") | T97: =IFERROR($R97/$I97,"n/a") | U97: =COUNTIFS(Data_CRM!$B$2:$B$1694,$A97,Data_CRM!$C$2:$C$1694,$B97,Data_CRM!$D$2:$D$1694,$C97) | V97: =COUNTIFS(Data_CRM!$B$2:$B$1694,$A97,Data_CRM!$C$2:$C$1694,$B97,Data_CRM!$D$2:$D$1694,$C97,Data_CRM!$F$2:$F$1694,1) | W97: =IFERROR($H97/$V97,"n/a") | X97: =IFERROR(IF($U97=0,"n/a",$V97/$U97),"n/a")
A98: Andromeda_CBO_Signature Store_FICO_Daewoo_SO | B98: Business Interest Signature Stores_FICO | C98: Reel_All_Signature_Store_FICO_SO | D98: inactive | G98: =IFERROR($H98/$E98,"n/a") | H98: 0 | I98: 0 | J98: 0 | K98: - | L98: - | M98: - | N98: - | O98: =IFERROR($H98/$I$52,"n/a") | P98: =COUNTIFS(Data_MeetingScheduled!$C$2:$C$200,$A98,Data_MeetingScheduled!$D$2:$D$200,$B98,Data_MeetingScheduled!$E$2:$E$200,$C98) | Q98: =IFERROR($P98/Data_MeetingScheduled!$J$2,"n/a") | S98: =IFERROR($R98/$I98,"n/a") | T98: =IFERROR($R98/$I98,"n/a") | U98: =COUNTIFS(Data_CRM!$B$2:$B$1694,$A98,Data_CRM!$C$2:$C$1694,$B98,Data_CRM!$D$2:$D$1694,$C98) | V98: =COUNTIFS(Data_CRM!$B$2:$B$1694,$A98,Data_CRM!$C$2:$C$1694,$B98,Data_CRM!$D$2:$D$1694,$C98,Data_CRM!$F$2:$F$1694,1) | W98: =IFERROR($H98/$V98,"n/a") | X98: =IFERROR(IF($U98=0,"n/a",$V98/$U98),"n/a")
... A100: Andromeda_CBO_Signature Store_FICO_Daewoo_SO | B100: Business Interest Signature Stores_FICO | C100: Signature_Store_Large Factory_Type_SO | D100: inactive | G100: =IFERROR($H100/$E100,"n/a") | H100: 0 | I100: 0 | J100: 0 | K100: - | L100: - | M100: - | N100: - | O100: =IFERROR($H100/$I$52,"n/a") | P100: =COUNTIFS(Data_MeetingScheduled!$C$2:$C$200,$A100,Data_MeetingScheduled!$D$2:$D$200,$B100,Data_MeetingScheduled!$E$2:$E$200,$C100) | Q100: =IFERROR($P100/Data_MeetingScheduled!$J$2,"n/a") | S100: =IFERROR($R100/$I100,"n/a") | T100: =IFERROR($R100/$I100,"n/a") | U100: =COUNTIFS(Data_CRM!$B$2:$B$1694,$A100,Data_CRM!$C$2:$C$1694,$B100,Data_CRM!$D$2:$D$1694,$C100) | V100: =COUNTIFS(Data_CRM!$B$2:$B$1694,$A100,Data_CRM!$C$2:$C$1694,$B100,Data_CRM!$D$2:$D$1694,$C100,Data_CRM!$F$2:$F$1694,1) | W100: =IFERROR($H100/$V100,"n/a") | X100: =IFERROR(IF($U100=0,"n/a",$V100/$U100),"n/a")
A101: Andromeda_CBO_Signature Store_FICO_Daewoo_SO | B101: Business Interest Signature Stores_FICO | C101: Signature_Store_160_Glass_SO | D101: active | E101: 171 | F101: actions:leadgen.other | G101: =IFERROR($H101/$E101,"n/a") | H101: 115776.82 | I101: 924764 | J101: 527548 | K101: 7-day click or 1-day view | L101: - | M101: - | N101: - | O101: =IFERROR($H101/$I$52,"n/a") | P101: =COUNTIFS(Data_MeetingScheduled!$C$2:$C$200,$A101,Data_MeetingScheduled!$D$2:$D$200,$B101,Data_MeetingScheduled!$E$2:$E$200,$C101) | Q101: =IFERROR($P101/Data_MeetingScheduled!$J$2,"n/a") | R101: 3622 | S101: =IFERROR($R101/$I101,"n/a") | T101: =IFERROR($R101/$I101,"n/a") | U101: =COUNTIFS(Data_CRM!$B$2:$B$1694,$A101,Data_CRM!$C$2:$C$1694,$B101,Data_CRM!$D$2:$D$1694,$C101) | V101: =COUNTIFS(Data_CRM!$B$2:$B$1694,$A101,Data_CRM!$C$2:$C$1694,$B101,Data_CRM!$D$2:$D$1694,$C101,Data_CRM!$F$2:$F$1694,1) | W101: =IFERROR($H101/$V101,"n/a") | X101: =IFERROR(IF($U101=0,"n/a",$V101/$U101),"n/a")
A102: Andromeda_CBO_Signature Store_FICO_Daewoo_SO | B102: Business Interest Signature Stores_FICO | C102: Signature Store_SO | D102: active | E102: 156 | F102: actions:leadgen.other | G102: =IFERROR($H102/$E102,"n/a") | H102: 94722.89 | I102: 587574 | J102: 320523 | K102: 7-day click or 1-day view | L102: - | M102: - | N102: - | O102: =IFERROR($H102/$I$52,"n/a") | P102: =COUNTIFS(Data_MeetingScheduled!$C$2:$C$200,$A102,Data_MeetingScheduled!$D$2:$D$200,$B102,Data_MeetingScheduled!$E$2:$E$200,$C102) | Q102: =IFERROR($P102/Data_MeetingScheduled!$J$2,"n/a") | R102: 3342 | S102: =IFERROR($R102/$I102,"n/a") | T102: =IFERROR($R102/$I102,"n/a") | U102: =COUNTIFS(Data_CRM!$B$2:$B$1694,$A102,Data_CRM!$C$2:$C$1694,$B102,Data_CRM!$D$2:$D$1694,$C102) | V102: =COUNTIFS(Data_CRM!$B$2:$B$1694,$A102,Data_CRM!$C$2:$C$1694,$B102,Data_CRM!$D$2:$D$1694,$C102,Data_CRM!$F$2:$F$1694,1) | W102: =IFERROR($H102/$V102,"n/a") | X102: =IFERROR(IF($U102=0,"n/a",$V102/$U102),"n/a")
A103: Andromeda_CBO_Signature Store_FICO_Daewoo_SO | B103: Business Interest Signature Stores_FICO | C103: Signature_Store_OCT_SO | D103: active | G103: =IFERROR($H103/$E103,"n/a") | H103: 193.53 | I103: 774 | J103: 662 | K103: 7-day click or 1-day view | L103: - | M103: - | N103: - | O103: =IFERROR($H103/$I$52,"n/a") | P103: =COUNTIFS(Data_MeetingScheduled!$C$2:$C$200,$A103,Data_MeetingScheduled!$D$2:$D$200,$B103,Data_MeetingScheduled!$E$2:$E$200,$C103) | Q103: =IFERROR($P103/Data_MeetingScheduled!$J$2,"n/a") | R103: 3 | S103: =IFERROR($R103/$I103,"n/a") | T103: =IFERROR($R103/$I103,"n/a") | U103: =COUNTIFS(Data_CRM!$B$2:$B$1694,$A103,Data_CRM!$C$2:$C$1694,$B103,Data_CRM!$D$2:$D$1694,$C103) | V103: =COUNTIFS(Data_CRM!$B$2:$B$1694,$A103,Data_CRM!$C$2:$C$1694,$B103,Data_CRM!$D$2:$D$1694,$C103,Data_CRM!$F$2:$F$1694,1) | W103: =IFERROR($H103/$V103,"n/a") | X103: =IFERROR(IF($U103=0,"n/a",$V103/$U103),"n/a")
A104: Subtotal — Business Interest Signature Stores_FICO | E104: =SUM(E86:E103) | H104: =SUM(H86:H103) | I104: =SUM(I86:I103) | J104: =SUM(J86:J103) | O104: =SUM(O86:O103) | P104: =SUM(P86:P103) | Q104: =IFERROR($P104/Data_MeetingScheduled!$J$2,"n/a") | R104: =SUM(R86:R103) | S104: =IFERROR($R104/$I104,"n/a") | T104: =IFERROR($R104/$I104,"n/a") | U104: =SUM(U86:U103) | V104: =SUM(V86:V103) | W104: =IFERROR($H104/$V104,"n/a") | X104: =IFERROR(IF($U104=0,"n/a",$V104/$U104),"n/a")
A105: Andromeda_CBO_Signature Store_FICO_Daewoo_SO | B105: HHI Pan India With Exclusions Signature Stores_FICO | C105: Signature_Store_OCT_SO | D105: active | E105: 31 | F105: actions:leadgen.other | G105: =IFERROR($H105/$E105,"n/a") | H105: 16371.59 | I105: 63960 | J105: 44687 | K105: 7-day click or 1-day view | L105: - | M105: - | N105: - | O105: =IFERROR($H105/$I$53,"n/a") | P105: =COUNTIFS(Data_MeetingScheduled!$C$2:$C$200,$A105,Data_MeetingScheduled!$D$2:$D$200,$B105,Data_MeetingScheduled!$E$2:$E$200,$C105) | Q105: =IFERROR($P105/Data_MeetingScheduled!$J$2,"n/a") | R105: 382 | S105: =IFERROR($R105/$I105,"n/a") | T105: =IFERROR($R105/$I105,"n/a") | U105: =COUNTIFS(Data_CRM!$B$2:$B$1694,$A105,Data_CRM!$C$2:$C$1694,$B105,Data_CRM!$D$2:$D$1694,$C105) | V105: =COUNTIFS(Data_CRM!$B$2:$B$1694,$A105,Data_CRM!$C$2:$C$1694,$B105,Data_CRM!$D$2:$D$1694,$C105,Data_CRM!$F$2:$F$1694,1) | W105: =IFERROR($H105/$V105,"n/a") | X105: =IFERROR(IF($U105=0,"n/a",$V105/$U105),"n/a")
A106: Andromeda_CBO_Signature Store_FICO_Daewoo_SO | B106: HHI Pan India With Exclusions Signature Stores_FICO | C106: Signature Store_SO | D106: active | E106: 364 | F106: actions:leadgen.other | G106: =IFERROR($H106/$E106,"n/a") | H106: 174808.13 | I106: 1008172 | J106: 428606 | K106: 7-day click or 1-day view | L106: - | M106: - | N106: - | O106: =IFERROR($H106/$I$53,"n/a") | P106: =COUNTIFS(Data_MeetingScheduled!$C$2:$C$200,$A106,Data_MeetingScheduled!$D$2:$D$200,$B106,Data_MeetingScheduled!$E$2:$E$200,$C106) | Q106: =IFERROR($P106/Data_MeetingScheduled!$J$2,"n/a") | R106: 6157 | S106: =IFERROR($R106/$I106,"n/a") | T106: =IFERROR($R106/$I106,"n/a") | U106: =COUNTIFS(Data_CRM!$B$2:$B$1694,$A106,Data_CRM!$C$2:$C$1694,$B106,Data_CRM!$D$2:$D$1694,$C106) | V106: =COUNTIFS(Data_CRM!$B$2:$B$1694,$A106,Data_CRM!$C$2:$C$1694,$B106,Data_CRM!$D$2:$D$1694,$C106,Data_CRM!$F$2:$F$1694,1) | W106: =IFERROR($H106/$V106,"n/a") | X106: =IFERROR(IF($U106=0,"n/a",$V106/$U106),"n/a")
A107: Andromeda_CBO_Signature Store_FICO_Daewoo_SO | B107: HHI Pan India With Exclusions Signature Stores_FICO | C107: Signature_Store_160_Glass_SO | D107: active | E107: 424 | F107: actions:leadgen.other | G107: =IFERROR($H107/$E107,"n/a") | H107: 230022.44 | I107: 1860027 | J107: 874490 | K107: 7-day click or 1-day view | L107: - | M107: - | N107: - | O107: =IFERROR($H107/$I$53,"n/a") | P107: =COUNTIFS(Data_MeetingScheduled!$C$2:$C$200,$A107,Data_MeetingScheduled!$D$2:$D$200,$B107,Data_MeetingScheduled!$E$2:$E$200,$C107) | Q107: =IFERROR($P107/Data_MeetingScheduled!$J$2,"n/a") | R107: 8247 | S107: =IFERROR($R107/$I107,"n/a") | T107: =IFERROR($R107/$I107,"n/a") | U107: =COUNTIFS(Data_CRM!$B$2:$B$1694,$A107,Data_CRM!$C$2:$C$1694,$B107,Data_CRM!$D$2:$D$1694,$C107) | V107: =COUNTIFS(Data_CRM!$B$2:$B$1694,$A107,Data_CRM!$C$2:$C$1694,$B107,Data_CRM!$D$2:$D$1694,$C107,Data_CRM!$F$2:$F$1694,1) | W107: =IFERROR($H107/$V107,"n/a") | X107: =IFERROR(IF($U107=0,"n/a",$V107/$U107),"n/a")
A108: Andromeda_CBO_Signature Store_FICO_Daewoo_SO | B108: HHI Pan India With Exclusions Signature Stores_FICO | C108: Reel – V1_Signature_Store_FICO | D108: active | E108: 49 | F108: actions:leadgen.other | G108: =IFERROR($H108/$E108,"n/a") | H108: 22638.41 | I108: 66997 | J108: 46060 | K108: 7-day click or 1-day view | L108: Average | M108: Below average – bottom 10% of ads | N108: Below average – bottom 10% of ads | O108: =IFERROR($H108/$I$53,"n/a") | P108: =COUNTIFS(Data_MeetingScheduled!$C$2:$C$200,$A108,Data_MeetingScheduled!$D$2:$D$200,$B108,Data_MeetingScheduled!$E$2:$E$200,$C108) | Q108: =IFERROR($P108/Data_MeetingScheduled!$J$2,"n/a") | R108: 538 | S108: =IFERROR($R108/$I108,"n/a") | T108: =IFERROR($R108/$I108,"n/a") | U108: =COUNTIFS(Data_CRM!$B$2:$B$1694,$A108,Data_CRM!$C$2:$C$1694,$B108,Data_CRM!$D$2:$D$1694,$C108) | V108: =COUNTIFS(Data_CRM!$B$2:$B$1694,$A108,Data_CRM!$C$2:$C$1694,$B108,Data_CRM!$D$2:$D$1694,$C108,Data_CRM!$F$2:$F$1694,1) | W108: =IFERROR($H108/$V108,"n/a") | X108: =IFERROR(IF($U108=0,"n/a",$V108/$U108),"n/a")
A109: Subtotal — HHI Pan India With Exclusions Signature Stores_FICO | E109: =SUM(E105:E108) | H109: =SUM(H105:H108) | I109: =SUM(I105:I108) | J109: =SUM(J105:J108) | O109: =SUM(O105:O108) | P109: =SUM(P105:P108) | Q109: =IFERROR($P109/Data_MeetingScheduled!$J$2,"n/a") | R109: =SUM(R105:R108) | S109: =IFERROR($R109/$I109,"n/a") | T109: =IFERROR($R109/$I109,"n/a") | U109: =SUM(U105:U108) | V109: =SUM(V105:V108) | W109: =IFERROR($H109/$V109,"n/a") | X109: =IFERROR(IF($U109=0,"n/a",$V109/$U109),"n/a")
A110: META_CustomData_MOFU_STOCKIST_Leadgen | B110: Client Custom Data_Stockist | C110: Stockist_IMG_3.5_Limited_All Large_SO | D110: active | E110: 15 | F110: actions:leadgen.other | G110: =IFERROR($H110/$E110,"n/a") | H110: 7962.14 | I110: 6301 | J110: 2549 | K110: 7-day click or 1-day view | L110: - | M110: - | N110: - | O110: =IFERROR($H110/$I$55,"n/a") | P110: =COUNTIFS(Data_MeetingScheduled!$C$2:$C$200,$A110,Data_MeetingScheduled!$D$2:$D$200,$B110,Data_MeetingScheduled!$E$2:$E$200,$C110) | Q110: =IFERROR($P110/Data_MeetingScheduled!$J$2,"n/a") | R110: 60 | S110: =IFERROR($R110/$I110,"n/a") | T110: =IFERROR($R110/$I110,"n/a") | U110: =COUNTIFS(Data_CRM!$B$2:$B$1694,$A110,Data_CRM!$C$2:$C$1694,$B110,Data_CRM!$D$2:$D$1694,$C110) | V110: =COUNTIFS(Data_CRM!$B$2:$B$1694,$A110,Data_CRM!$C$2:$C$1694,$B110,Data_CRM!$D$2:$D$1694,$C110,Data_CRM!$F$2:$F$1694,1) | W110: =IFERROR($H110/$V110,"n/a") | X110: =IFERROR(IF($U110=0,"n/a",$V110/$U110),"n/a")
A111: Subtotal — Client Custom Data_Stockist | E111: =SUM(E110:E110) | H111: =SUM(H110:H110) | I111: =SUM(I110:I110) | J111: =SUM(J110:J110) | O111: =SUM(O110:O110) | P111: =SUM(P110:P110) | Q111: =IFERROR($P111/Data_MeetingScheduled!$J$2,"n/a") | R111: =SUM(R110:R110) | S111: =IFERROR($R111/$I111,"n/a") | T111: =IFERROR($R111/$I111,"n/a") | U111: =SUM(U110:U110) | V111: =SUM(V110:V110) | W111: =IFERROR($H111/$V111,"n/a") | X111: =IFERROR(IF($U111=0,"n/a",$V111/$U111),"n/a")
A112: META_CustomData_MOFU_STOCKIST_Leadgen | B112: LAL_1%_Client Data_Stockist | C112: Stockist_Reel | D112: active | E112: 204 | F112: actions:leadgen.other | G112: =IFERROR($H112/$E112,"n/a") | H112: 191426.3 | I112: 474667 | J112: 284877 | K112: 7-day click or 1-day view | L112: Above average | M112: Below average – bottom 10% of ads | N112: Below average – bottom 10% of ads | O112: =IFERROR($H112/$I$56,"n/a") | P112: =COUNTIFS(Data_MeetingScheduled!$C$2:$C$200,$A112,Data_MeetingScheduled!$D$2:$D$200,$B112,Data_MeetingScheduled!$E$2:$E$200,$C112) | Q112: =IFERROR($P112/Data_MeetingScheduled!$J$2,"n/a") | R112: 2763 | S112: =IFERROR($R112/$I112,"n/a") | T112: =IFERROR($R112/$I112,"n/a") | U112: =COUNTIFS(Data_CRM!$B$2:$B$1694,$A112,Data_CRM!$C$2:$C$1694,$B112,Data_CRM!$D$2:$D$1694,$C112) | V112: =COUNTIFS(Data_CRM!$B$2:$B$1694,$A112,Data_CRM!$C$2:$C$1694,$B112,Data_CRM!$D$2:$D$1694,$C112,Data_CRM!$F$2:$F$1694,1) | W112: =IFERROR($H112/$V112,"n/a") | X112: =IFERROR(IF($U112=0,"n/a",$V112/$U112),"n/a")
A113: META_CustomData_MOFU_STOCKIST_Leadgen | B113: LAL_1%_Client Data_Stockist | C113: Stockist_IMG_3.5_Limited_All Large_SO | D113: active | E113: 126 | F113: actions:leadgen.other | G113: =IFERROR($H113/$E113,"n/a") | H113: 139358.65 | I113: 381741 | J113: 166773 | K113: 7-day click or 1-day view | L113: - | M113: - | N113: - | O113: =IFERROR($H113/$I$56,"n/a") | P113: =COUNTIFS(Data_MeetingScheduled!$C$2:$C$200,$A113,Data_MeetingScheduled!$D$2:$D$200,$B113,Data_MeetingScheduled!$E$2:$E$200,$C113) | Q113: =IFERROR($P113/Data_MeetingScheduled!$J$2,"n/a") | R113: 2243 | S113: =IFERROR($R113/$I113,"n/a") | T113: =IFERROR($R113/$I113,"n/a") | U113: =COUNTIFS(Data_CRM!$B$2:$B$1694,$A113,Data_CRM!$C$2:$C$1694,$B113,Data_CRM!$D$2:$D$1694,$C113) | V113: =COUNTIFS(Data_CRM!$B$2:$B$1694,$A113,Data_CRM!$C$2:$C$1694,$B113,Data_CRM!$D$2:$D$1694,$C113,Data_CRM!$F$2:$F$1694,1) | W113: =IFERROR($H113/$V113,"n/a") | X113: =IFERROR(IF($U113=0,"n/a",$V113/$U113),"n/a")
A114: Subtotal — LAL_1%_Client Data_Stockist | E114: =SUM(E112:E113) | H114: =SUM(H112:H113) | I114: =SUM(I112:I113) | J114: =SUM(J112:J113) | O114: =SUM(O112:O113) | P114: =SUM(P112:P113) | Q114: =IFERROR($P114/Data_MeetingScheduled!$J$2,"n/a") | R114: =SUM(R112:R113) | S114: =IFERROR($R114/$I114,"n/a") | T114: =IFERROR($R114/$I114,"n/a") | U114: =SUM(U112:U113) | V114: =SUM(V112:V113) | W114: =IFERROR($H114/$V114,"n/a") | X114: =IFERROR(IF($U114=0,"n/a",$V114/$U114),"n/a")
A115: META_CustomData_MOFU_Leadgen – Signature FICO | B115: Client Custom Data_Signature Store FICO | C115: Signature_Store_OCT_SO | D115: not_delivering | G115: =IFERROR($H115/$E115,"n/a") | H115: 0 | I115: 0 | J115: 0 | K115: - | L115: - | M115: - | N115: - | O115: =IFERROR($H115/$I$68,"n/a") | P115: =COUNTIFS(Data_MeetingScheduled!$C$2:$C$200,$A115,Data_MeetingScheduled!$D$2:$D$200,$B115,Data_MeetingScheduled!$E$2:$E$200,$C115) | Q115: =IFERROR($P115/Data_MeetingScheduled!$J$2,"n/a") | S115: =IFERROR($R115/$I115,"n/a") | T115: =IFERROR($R115/$I115,"n/a") | U115: =COUNTIFS(Data_CRM!$B$2:$B$1694,$A115,Data_CRM!$C$2:$C$1694,$B115,Data_CRM!$D$2:$D$1694,$C115) | V115: =COUNTIFS(Data_CRM!$B$2:$B$1694,$A115,Data_CRM!$C$2:$C$1694,$B115,Data_CRM!$D$2:$D$1694,$C115,Data_CRM!$F$2:$F$1694,1) | W115: =IFERROR($H115/$V115,"n/a") | X115: =IFERROR(IF($U115=0,"n/a",$V115/$U115),"n/a")
A116: Subtotal — Client Custom Data_Signature Store FICO | E116: =SUM(E115:E115) | H116: =SUM(H115:H115) | I116: =SUM(I115:I115) | J116: =SUM(J115:J115) | O116: =SUM(O115:O115) | P116: =SUM(P115:P115) | Q116: =IFERROR($P116/Data_MeetingScheduled!$J$2,"n/a") | R116: =SUM(R115:R115) | S116: =IFERROR($R116/$I116,"n/a") | T116: =IFERROR($R116/$I116,"n/a") | U116: =SUM(U115:U115) | V116: =SUM(V115:V115) | W116: =IFERROR($H116/$V116,"n/a") | X116: =IFERROR(IF($U116=0,"n/a",$V116/$U116),"n/a")
A117: META_CustomData_MOFU_Leadgen – Signature FICO | B117: LAL_1%_Client Data_Signature Store FICO | C117: Reel – V1_Signature_Store | D117: active | E117: 97 | F117: actions:leadgen.other | G117: =IFERROR($H117/$E117,"n/a") | H117: 142745.49 | I117: 285327 | J117: 188498 | K117: 7-day click or 1-day view | L117: Above average | M117: Below average – bottom 10% of ads | N117: Below average – bottom 10% of ads | O117: =IFERROR($H117/$I$69,"n/a") | P117: =COUNTIFS(Data_MeetingScheduled!$C$2:$C$200,$A117,Data_MeetingScheduled!$D$2:$D$200,$B117,Data_MeetingScheduled!$E$2:$E$200,$C117) | Q117: =IFERROR($P117/Data_MeetingScheduled!$J$2,"n/a") | R117: 2229 | S117: =IFERROR($R117/$I117,"n/a") | T117: =IFERROR($R117/$I117,"n/a") | U117: =COUNTIFS(Data_CRM!$B$2:$B$1694,$A117,Data_CRM!$C$2:$C$1694,$B117,Data_CRM!$D$2:$D$1694,$C117) | V117: =COUNTIFS(Data_CRM!$B$2:$B$1694,$A117,Data_CRM!$C$2:$C$1694,$B117,Data_CRM!$D$2:$D$1694,$C117,Data_CRM!$F$2:$F$1694,1) | W117: =IFERROR($H117/$V117,"n/a") | X117: =IFERROR(IF($U117=0,"n/a",$V117/$U117),"n/a")
A118: META_CustomData_MOFU_Leadgen – Signature FICO | B118: LAL_1%_Client Data_Signature Store FICO | C118: Signature_Store_OCT_SO | D118: active | E118: 44 | F118: actions:leadgen.other | G118: =IFERROR($H118/$E118,"n/a") | H118: 51377.85 | I118: 105467 | J118: 53954 | K118: 7-day click or 1-day view | L118: - | M118: - | N118: - | O118: =IFERROR($H118/$I$69,"n/a") | P118: =COUNTIFS(Data_MeetingScheduled!$C$2:$C$200,$A118,Data_MeetingScheduled!$D$2:$D$200,$B118,Data_MeetingScheduled!$E$2:$E$200,$C118) | Q118: =IFERROR($P118/Data_MeetingScheduled!$J$2,"n/a") | R118: 552 | S118: =IFERROR($R118/$I118,"n/a") | T118: =IFERROR($R118/$I118,"n/a") | U118: =COUNTIFS(Data_CRM!$B$2:$B$1694,$A118,Data_CRM!$C$2:$C$1694,$B118,Data_CRM!$D$2:$D$1694,$C118) | V118: =COUNTIFS(Data_CRM!$B$2:$B$1694,$A118,Data_CRM!$C$2:$C$1694,$B118,Data_CRM!$D$2:$D$1694,$C118,Data_CRM!$F$2:$F$1694,1) | W118: =IFERROR($H118/$V118,"n/a") | X118: =IFERROR(IF($U118=0,"n/a",$V118/$U118),"n/a")
...

Sheet Data_Campaigns
A1: Reporting starts | B1: Reporting ends | C1: Campaign name | D1: Campaign delivery | E1: Results | F1: Result indicator | G1: Cost per results | H1: Ad set budget | I1: Ad set budget type | J1: Amount spent (INR) | K1: Impressions | L1: Reach | M1: Ends | N1: Attribution setting | O1: Link clicks

Sheet Data_AdSets
A1: Reporting starts | B1: Reporting ends | C1: Ad set name | D1: Ad set delivery | E1: Results | F1: Result indicator | G1: Cost per results | H1: Ad set budget | I1: Ad set budget type | J1: Amount spent (INR) | K1: Impressions | L1: Reach | M1: Link clicks | N1: Ends | O1: Starts | P1: Attribution setting | Q1: Bid | R1: Bid type | S1: Last significant edit | T1: Parent Campaign

Sheet Data_Ads
A1: Reporting starts | B1: Reporting ends | C1: Ad name | D1: Ad delivery | E1: Results | F1: Result indicator | G1: Cost per results | H1: Ad set budget | I1: Ad set budget type | J1: Amount spent (INR) | K1: Impressions | L1: Reach | M1: Link clicks | N1: Ends | O1: Attribution setting | P1: Bid | Q1: Bid type | R1: Last significant edit | S1: Quality ranking | T1: Engagement rate ranking | U1: Conversion rate ranking | V1: Ad set name | W1: Parent Campaign | X1: Match Key

Sheet Data_CRM
A1: Lead Date | B1: Mapped Campaign (LeadChain) | C1: Mapped Ad Set (LeadChain) | D1: Mapped Ad (LeadChain) | E1: Lead Status | F1: Qualified (1/0) | G1: Meeting (1/0) | H1: Social Lead ID | I1: PARAMETERS

Sheet Data_MeetingScheduled
A1: Source File | B1: Email | C1: Mapped Campaign (LeadChain) | D1: Mapped Ad Set (LeadChain) | E1: Mapped Ad (LeadChain) | F1: Date / Created Time | G1: Meeting Date (value) | H1: Lead Status (source) | I1: PARAMETERS

Sheet Data_UnmappedMeetings
A1: Source File | B1: Email | C1: Date / Created Time | D1: Reason

Sheet Data_MeetingConducted
A1: Name | B1: Email | C1: Phone | D1: Mapped Campaign | E1: Mapped Ad Set | F1: Mapped Ad | G1: Created Time | H1: Team Head | I1: BDE | K1: NOTE: Not populated — no separate Meeting Conducted source this round. Under the reporting rule, Meeting Conducted and Meeting Follow-Up statuses are categorised as Meeting Scheduled (see Data_MeetingScheduled).
